Workbook
Name 七彩喷射: 法术大全!$M$62
Name 万事通: 图表!$CE$4
Name 万箭齐发: 法术大全!$M$342
Name 不动物件: 法术大全!$M$160
Name 不屈: 图表!$CQ$7
Name 不屈勇武: 图表!$CU$13
Name 不死生物召唤术_召唤不死灵魄: 法术大全!$M$266
Name 不灭明焰: 法术大全!$M$138
Name 不谐低语: 法术大全!$M$72
Name 丘陵矮人属性值加成: 图表!$BQ$48
Name 丝绳_50尺: 图表!$AC$83
Name 中甲: 图表!$U$48:$U$52
Name 中甲大师: 图表!$CY$25
Name 中甲运用: 图表!$CY$27
Name 乌斯伽部族成员工具熟练项: 图表!$BK$69
Name 乌斯伽部族成员技能熟练项: 图表!$BK$67
Name 乌斯伽部族成员牵绊: 图表!$BK$52:$BK$57
Name 乌斯伽部族成员特点: 图表!$BK$36:$BK$43
Name 乌斯伽部族成员理想: 图表!$BK$45:$BK$50
Name 乌斯伽部族成员缺点: 图表!$BK$59:$BK$64
Name 乌斯伽部族成员背景装备: 图表!$BK$73
Name 乌斯伽部族成员额外语言: 图表!$BK$71
Name 书: 图表!$AC$22
Name 书法工具: 图表!$AC$102
Name 云雾术: 法术大全!$M$82
Name 亚比达奇凋死术: 法术大全!$M$467
Name 亡者丧钟: 法术大全!$M$43
Name 交友术: 法术大全!$M$12
Name 人类: 图表!$BS$35:$BY$35
Name 人类定身术: 法术大全!$M$159
Name 人类属性值加成: 图表!$BQ$35
Name 以太化: 法术大全!$M$445
Name 仪式施法者: 图表!$CY$32
Name 任意门: 法术大全!$M$293
Name 休憩曲: 图表!$CE$5
Name 众星冠冕: 法术大全!$M$441
Name 传讯术: 法术大全!$M$23
Name 传送术: 法术大全!$M$462
Name 传送法阵: 法术大全!$M$383
Name 伪装术: 法术大全!$M$376
Name 低身之机敏: 图表!$CY$57
Name 侍僧工具熟练项: 图表!$AH$69
Name 侍僧技能熟练项: 图表!$AH$67
Name 侍僧牵绊: 图表!$AH$52:$AH$57
Name 侍僧特殊选项: 图表!$AH$75
Name 侍僧特点: 图表!$AH$36:$AH$43
Name 侍僧理想: 图表!$AH$45:$AH$50
Name 侍僧缺点: 图表!$AH$59:$AH$64
Name 侍僧背景装备: 图表!$AH$73
Name 侍僧额外语言: 图表!$AH$71
Name 侏儒: 图表!$BS$46:$BV$46
Name 侦测善恶: 法术大全!$M$68
Name 侦测思想: 法术大全!$M$143
Name 侦测毒性和疾病: 法术大全!$M$70
Name 侦测魔法: 法术大全!$M$69
Name 便携式攻城锤: 图表!$AC$79
Name 信仰守卫: 法术大全!$M$306
Name 修复术: 法术大全!$M$22
Name 修补工具: 图表!$AC$114
Name 借鉴才学: 法术大全!$M$205

Sheet 角色
A1: 角色 Character
B3: 角色名 | R3: 技能熟练项
B4: 玩家名 | E4: 作者：太易，熊妈妈2D6 | R4: 工具熟练项
R5: 背景语言
B6: 种族 | E6: 精灵 | J6: 阵营 | M6: 混乱邪恶 | R6: 背景装备
B7: 性别 | E7: 女 | J7: 年龄 | R7: 特殊选项
B8: 亚种 | E8: 高等 | J8: 信仰
R9: 背景特性
B10: 背景 | E10: 智者 | J10: 发色
B11: 身高 | E11: 168 | J11: 肤色
B12: 体重 | J12: 瞳色
B13: 外貌描述
B14: 角色外貌
R15: 所选特点 | W15: 聪慧，想象力强
R16: 所选理想 | W16: 求道
R17: 所选牵绊
R18: 所选缺点
B19: 角色形象 | R19: 背景故事
R20: 访仙求古，方得克苏鲁。

Sheet 主要情况
A1: 主要情况 Main Interface | AV1: 职业特性 | BM1: 种族特性
W2: 等级 | AH2: 角色形象 | AV2: LV | AW2: 名称 | BB2: 描述 | BM2: 名称 | BS2: 描述
B3: 角色名 | E3: karma | P3: 主职业 | S3: 邪术师 | W3: 5 | Z3: 熟练加值 | AC3: =IF(图表!F6<5,2,IF(图表!F6<9,3,IF(图表!F6<13,4,IF(图表!F6<17,5,6)))) -> 3 | AW3: 链之魔契
B4: 玩家名 | P4: 兼职 | Z4: 经验值 | AW4: 融身入影
P5: 兼职Ⅱ
B6: 属性 | N6: 战斗
B7: 熟练 | E7: 属性值 | G7: 调整值 | I7: 修正→ | K7: 豁免 | S7: 修正 | Y7: 现有值 | AC7: 最大值
B8: =IF(OR($S$3="战士",$S$3="武僧",$S$3="游侠",$S$3="野蛮人"),"O","X") -> X | C8: 力量 | E8: 10 | G8: =INT(E8/2-5) -> 0 | K8: =G8+IF(B8="O",$AC$3,0)+I8 -> 0 | N8: 先攻 | P8: =G10+S8+IF(COUNTIF(BN15:BR21,"警觉"),5,)+IF(OR(AND($S$3="吟游诗人",$W$3>=2),AND($S$4="吟游诗人",$W$4>=2)),INT(AC3/2),) -> 3 | R8: < | V8: HP | AB8: / | AC8: =图表!J5+W3*(AC12+图表!G5+AE12)+图表!F8+图表!F10 -> 28
B10: =IF(OR($S$3="吟游诗人",$S$3="武僧",$S$3="游荡者",$S$3="游侠"),"O","X") -> X | C10: 敏捷 | E10: 16 | G10: =INT(E10/2-5) -> 3 | K10: =G10+IF(B10="O",$AC$3,0)+I10 -> 3 | N10: AC | P10: =IF(OR(L23="重甲",L23="无甲"),AD23,SUM(AD23,IF(AG23>0,IF(AG23>G10,G10,AG23),G10)))+S10+IF(S12="是",AP23,0) -> 15 | R10: < | V10: 生命骰数量 | AB10: / | AC10: =W3+W4+W5 -> 5
V11: =图表!P14 -> 已知祈唤 | AB11: / | AC11: =图表!S14 -> 3
B12: =IF(OR($S$3="战士",$S$3="术士",$S$3="野蛮人",$S$3="奇械师"),"O","X") -> X | C12: 体质 | E12: 10 | G12: =INT(E12/2-5) -> 0 | K12: =G12+IF(B12="O",$AC$3,0)+I12 -> 0 | N12: 装备盾牌 | S12: 否 | V12: 生命值成长 | Y12: =图表!D14 -> 1d8 | AB12: + | AC12: =G12 -> 0 | AE12: =IF(角色!E8="丘陵矮人",1,)+IF(COUNTIF(主要情况!BN15:BR21,"健壮"),2,) -> 0
V13: 特殊能力数值 | BM13: 属性值提升/专长
B14: =IF(OR($S$3="德鲁伊",$S$3="法师",$S$3="游荡者",$S$3="奇械师"),"O","X") -> X | C14: 智力 | E14: 14 | G14: =INT(E14/2-5) -> 2 | K14: =G14+IF(B14="O",$AC$3,0)+I14 -> 2 | N14: DC | P14: =SUM(8+AC3+IF(R17="力量",G8,IF(R17="敏捷",G10,IF(R17="体质",G12,IF(R17="智力",G14,IF(R17="感知",G16,IF(R17="魅力",G18,0)))))))+S14 -> 14 | R14: < | V14: 特殊能力数值 | AA14: 临时HP | BM14: LV | BN14: 名称 | BS14: 描述
BM15: 4 | BN15: 幸运
B16: =IF(OR($S$3="邪术师",$S$3="德鲁伊",$S$3="法师",$S$3="牧师",$S$3="圣武士"),"O","X") -> O | C16: 感知 | E16: 12 | G16: =INT(E16/2-5) -> 1 | K16: =G16+IF(B16="O",$AC$3,0)+I16 -> 4 | BM16: 8
N17: 关键属性 | R17: =图表!D28 -> 魅力 | V17: 体型 | X17: 中型 | AA17: 速度 | AD17: 30 | AF17: 尺 | BM17: 12
B18: =IF(OR($S$3="吟游诗人",$S$3="邪术师",$S$3="牧师",$S$3="圣武士",$S$3="术士"),"O","X") -> O | C18: 魅力 | E18: 16 | G18: =INT(E18/2-5) -> 3 | K18: =G18+IF(B18="O",$AC$3,0)+I18 -> 6 | BM18: 16
N19: 被动察觉 | R19: =10+I35+IF(COUNTIF(BN15:BR21,"观察力"),5,) -> 13 | V19: 抗性/免疫 | BM19: 19
E20: 0 | BM20: 6
B21: 技能 | L21: 主要装备 | AM21: 盾牌 | BM21: 10
B22: 熟练 | C22: 技能名 | F22: 修正 | I22: 总值 | L22: 护甲 | O22: 名称 | S22: 需要同调 | V22: 特性 | AA22: 重量 | AD22: AC | AF22: 最大敏捷 | AJ22: 隐匿劣势 | AM22: 盾牌名称 | AP22: AC | AR22: 重量
B23: X | C23: 运动 | H23: > | I23: =$G$8+F23+IF(B23="O",$AC$3,(IF(B23="❂",$AC$3*2,IF(B23="〄",INT($AC$3/2),0)))) -> 0 | L23: 轻甲 | N23: > | O23: 镶钉皮甲 | T23: X | AA23: =IFERROR(VLOOKUP(O23,图表!U45:X59,4,0),"") -> 13 | AC23: > | AD23: =IFERROR(VLOOKUP(O23,图表!U45:V59,2,0),IF(L23="无甲",10+G10,10)) -> 12 | AF23: + | AG23: =IF(AND(COUNTIF(BN15:BR21,"中甲大师"),L23="中甲"),3,IF(L23="中甲",2,"")) | AJ23: =IFERROR(VLOOKUP(O23,图表!U45:W59,3,0),"") -> 否 | AP23: 2 | AR23: 6 | BM23: 特殊能力（狂暴、引导神力等）
B24: 敏捷系 | L24: 武器 | O24: 名称 | S24: 需要同调 | V24: 特性 | AA24: 使用属性 | AD24: 攻击命中加值 | AI24: 武器伤害 | AM24: 伤害类型 | AP24: 重量 | AR24: 弹药数 | BM24: LV | BN24: 名称 | BS24: 描述
B25: X | C25: 特技 | H25: > | I25: =$G$10+F25+IF(B25="O",$AC$3,(IF(B25="❂",$AC$3*2,IF(B25="〄",INT($AC$3/2),0)))) -> 3 | L25: 右手 | N25: > | O25: 扇子 | T25: X | U25: =图表!Y66 -> #N/A | AC25: > | AD25: d20+ | AF25: =IFERROR(VLOOKUP(AA25,C8:H19,5,0)+IF('BUY点计算器&武器调整栏'!A16="是",AC3,)+'BUY点计算器&武器调整栏'!B16,"-") -> - | AH25: > | AI25: =IFERROR(图表!V66,"-") -> - | AM25: =图表!W66 -> #N/A | AP25: =图表!Z66 -> #N/A | AR25: 箭 | AS25: 0 | BN25: 邪魔活力
B26: X | C26: 巧手 | H26: > | I26: =$G$10+F26+IF(B26="O",$AC$3,(IF(B26="❂",$AC$3*2,IF(B26="〄",INT($AC$3/2),0)))) -> 3 | L26: 左手 | N26: > | O26: 铁链 | T26: X | U26: =图表!Y67 -> #N/A | AC26: > | AD26: d20+ | AF26: =IFERROR(VLOOKUP(AA26,C8:H19,5,0)+IF('BUY点计算器&武器调整栏'!A19="是",AC3,)+'BUY点计算器&武器调整栏'!B19,"-") -> - | AH26: > | AI26: =IFERROR(图表!V67,"-") -> - | AM26: =图表!W67 -> #N/A | AP26: =图表!Z67 -> #N/A | AR26: 矢 | AS26: 0 | BN26: 千面之脸
B27: X | C27: 隐匿 | H27: > | I27: =$G$10+F27+IF(B27="O",$AC$3,(IF(B27="❂",$AC$3*2,IF(B27="〄",INT($AC$3/2),0)))) -> 3 | L27: 双手 | N27: > | T27: X | U27: =图表!Y68 -> - | AC27: > | AD27: d20+ | AF27: =IFERROR(VLOOKUP(AA27,C8:H19,5,0)+IF('BUY点计算器&武器调整栏'!A22="是",AC3,)+'BUY点计算器&武器调整栏'!B22,"-") -> - | AH27: > | AI27: =IFERROR(图表!V68,"-") -> - | AM27: =图表!W68 -> - | AP27: =图表!Z68 -> - | AR27: 弹 | AS27: 0
B28: 智力系 | L28: X | N28: > | T28: X | U28: - | AC28: > | AD28: d20+ | AF28: - | AH28: > | AI28: - | AM28: - | AP28: - | AR28: 投 | AS28: 0
B29: X | C29: 调查 | H29: > | I29: =$G$14+F29+IF(B29="O",$AC$3,(IF(B29="❂",$AC$3*2,IF(B29="〄",INT($AC$3/2),0)))) -> 2 | L29: X | N29: > | T29: X | U29: - | AC29: > | AD29: d20+ | AF29: - | AH29: > | AI29: - | AM29: - | AP29: - | AR29: 它 | AS29: 0
B30: X | C30: 奥秘 | F30: 2 | H30: > | I30: =$G$14+F30+IF(B30="O",$AC$3,(IF(B30="❂",$AC$3*2,IF(B30="〄",INT($AC$3/2),0)))) -> 4 | L30: 其他 | O30: 名称 | S30: 需要同调 | V30: 特性 | AA30: 重量
B31: X | C31: 历史 | F31: 2 | H31: > | I31: =$G$14+F31+IF(B31="O",$AC$3,(IF(B31="❂",$AC$3*2,IF(B31="〄",INT($AC$3/2),0)))) -> 4 | L31: 头部 | N31: > | T31: X | AD31: 常用法术 | AV31: 武器及护甲熟练
B32: X | C32: 自然 | H32: > | I32: =$G$14+F32+IF(B32="O",$AC$3,(IF(B32="❂",$AC$3*2,IF(B32="〄",INT($AC$3/2),0)))) -> 2 | L32: 颈部 | N32: > | T32: X | AD32: 法术名称 | AI32: 法术攻击加值 | AN32: 伤害 | AQ32: 伤害类型 | AV32: 武器
B33: X | C33: 宗教 | F33: 2 | H33: > | I33: =$G$14+F33+IF(B33="O",$AC$3,(IF(B33="❂",$AC$3*2,IF(B33="〄",INT($AC$3/2),0)))) -> 4 | L33: 肩部 | N33: > | T33: X | AI33: > | AJ33: =施法!V2 -> 6 | AL33: > | AV33: 护甲
B34: 感知系 | L34: 背部 | N34: > | O34: 自然斗篷 | T34: X | AI34: > | AJ34: =施法!V2 -> 6 | AL34: > | AV34: 其他特性 | BM34: 职业装备、豁免熟练与技能熟练
B35: X | C35: 察觉 | F35: 2 | H35: > | I35: =$G$16+F35+IF(B35="O",$AC$3,(IF(B35="❂",$AC$3*2,IF(B35="〄",INT($AC$3/2),0)))) -> 3 | L35: 胸部 | N35: > | T35: X | AM35: 环阶 | AO35: 法术位 | AV35: 语言 | AZ35: 通用语，精灵语，古神语
B36: X | C36: 洞悉 | H36: > | I36: =$G$16+F36+IF(B36="O",$AC$3,(IF(B36="❂",$AC$3*2,IF(B36="〄",INT($AC$3/2),0)))) -> 1 | L36: 腕部 | N36: > | T36: X | AD36: 关键属性 | AI36: =施法!H2 -> 魅力 | AM36: 1 | AO36: =施法!AX5 -> 0 | AQ36: / | AR36: =施法!BA5 -> 0 | AV36: 工具
B37: X | C37: 驯兽 | H37: > | I37: =$G$16+F37+IF(B37="O",$AC$3,(IF(B37="❂",$AC$3*2,IF(B37="〄",INT($AC$3/2),0)))) -> 1 | L37: 手部 | N37: > | O37: 戒指 | T37: X | AD37: 法术DC | AI37: =施法!O2 -> 14 | AM37: 2 | AO37: =施法!AX6 -> 0 | AQ37: / | AR37: =施法!BA6 -> 0 | AV37: 物品同调 | AZ37: 0 | BC37: / | BE37: 3
B38: X | C38: 医药 | H38: > | I38: =$G$16+F38+IF(B38="O",$AC$3,(IF(B38="❂",$AC$3*2,IF(B38="〄",INT($AC$3/2),0)))) -> 1 | L38: 腰部 | N38: > | T38: X | AM38: 3 | AO38: =施法!AX7 -> 0 | AQ38: / | AR38: =施法!BA7 -> 0 | AV38: 激励 | AZ38: 0 | BC38: / | BE38: 1
B39: X | C39: 求生 | H39: > | I39: =$G$16+F39+IF(B39="O",$AC$3,(IF(B39="❂",$AC$3*2,IF(B39="〄",INT($AC$3/2),0)))) -> 1 | L39: 腿部 | N39: > | O39: 飞行靴 | T39: X | AM39: 4 | AO39: =施法!AX8 -> 0 | AQ39: / | AR39: =施法!BA8 -> 0 | AV39: 伤患
B40: 魅力系 | L40: 脚部 | N40: > | T40: X | AD40: 铂金币 | AM40: 5 | AO40: =施法!AX9 -> 0 | AQ40: / | AR40: =施法!BA9 -> 0 | AV40: 声望
B41: X | C41: 游说 | H41: > | I41: =$G$18+F41+IF(B41="O",$AC$3,(IF(B41="❂",$AC$3*2,IF(B41="〄",INT($AC$3/2),0)))) -> 3 | L41: 装备 | O41: =背包!B3 -> 速查 | R41: =背包!Y3 -> 自述 | U41: 总负重 | W41: 总财富 | Z41: 钱包 | AD41: 银金币 | AM41: 6 | AO41: =施法!AX10 -> 0 | AQ41: / | AR41: =施法!BA10 -> 0 | AV41: 献力
B42: X | C42: 欺瞒 | F42: 2 | H42: > | I42: =$G$18+F42+IF(B42="O",$AC$3,(IF(B42="❂",$AC$3*2,IF(B42="〄",INT($AC$3/2),0)))) -> 5 | L42: =SUM(AA31:AB40,AA25:AB29,AA23,IF(S12="是",AR23,)) -> 13 | O42: =背包!V3 -> 0 | R42: =背包!AS3 -> 0 | U42: =SUM(L42:T42)+Z42+Z44 -> 13 | W42: =AG40*10+AG41*0.5+AG42+AG43*0.1+AG44*0.01 -> 0 | Z42: =SUM(AG40:AK44)/50 -> 0 | AD42: 金币 | AM42: 7 | AO42: =施法!AX11 -> 0 | AQ42: / | AR42: =施法!BA11 -> 0 | AV42: 祝福
B43: X | C43: 威吓 | H43: > | I43: =$G$18+F43+IF(B43="O",$AC$3,(IF(B43="❂",$AC$3*2,IF(B43="〄",INT($AC$3/2),0)))) -> 3 | L43: 轻载 | O43: 重载 | R43: 超载 | U43: 最大载重 | Z43: 次元袋 | AD43: 银币 | AM43: 8 | AO43: =施法!AX12 -> 0 | AQ43: / | AR43: =施法!BA12 -> 0 | AV43: 护咒
B44: X | C44: 表演 | H44: > | I44: =$G$18++F44+IF(B44="O",$AC$3,(IF(B44="❂",$AC$3*2,IF(B44="〄",INT($AC$3/2),0)))) -> 3 | L44: 0 | O44: =E8*5 -> 50 | R44: =E8*10 -> 100 | U44: =IF(U43="最大载重",E8*15,_xlfn.IFS(U42<=O44,"轻载",U42<=R44,"重载",U42>R44,"超载",TRUE(),)) -> 150 | Z44: =IF(背包!V27="无",0,背包!J51) -> 0 | AD44: 铜币 | AM44: 9 | AO44: =施法!AX13 -> 0 | AQ44: / | AR44: =施法!BA13 -> 0 | AV44: 传奇恩惠

Sheet 背包
A1: 背包 Backpack
B3: 速查 | V3: =SUM(AX16:AX25,AX5:AX14) -> 0 | Y3: 自述 | AS3: =SUM(AY5:AY14,AY16:AY25) -> 0
B4: 名称 | I4: 描述 | S4: 磅 | V4: 数量 | Y4: 名称 | AF4: 描述 | AP4: 磅 | AS4: 数量
S5: =图表!AE145 -> 0 | U5: x | AR5: x | AX5: =S5*V5 -> 0 | AY5: =AP5*AS5 -> 0
S6: =图表!AE146 -> 0 | U6: x | AR6: x | AX6: =S6*V6 -> 0 | AY6: =AP6*AS6 -> 0
S7: =图表!AE147 -> 0 | U7: x | AR7: x | AX7: =S7*V7 -> 0 | AY7: =AP7*AS7 -> 0
S8: =图表!AE148 -> 0 | U8: x | AR8: x | AX8: =S8*V8 -> 0 | AY8: =AP8*AS8 -> 0
S9: =图表!AE149 -> 0 | U9: x | AR9: x | AX9: =S9*V9 -> 0 | AY9: =AP9*AS9 -> 0
S10: =图表!AE150 -> 0 | U10: x | AR10: x | AX10: =S10*V10 -> 0 | AY10: =AP10*AS10 -> 0
S11: =图表!AE151 -> 0 | U11: x | AR11: x | AX11: =S11*V11 -> 0 | AY11: =AP11*AS11 -> 0
S12: =图表!AE152 -> 0 | U12: x | AR12: x | AX12: =S12*V12 -> 0 | AY12: =AP12*AS12 -> 0
S13: =图表!AE153 -> 0 | U13: x | AR13: x | AX13: =S13*V13 -> 0 | AY13: =AP13*AS13 -> 0
S14: =图表!AE154 -> 0 | U14: x | AR14: x | AX14: =S14*V14 -> 0 | AY14: =AP14*AS14 -> 0
S16: =图表!AE156 -> 0 | U16: x | AR16: x | AX16: =S16*V16 -> 0 | AY16: =AP16*AS16 -> 0
S17: =图表!AE157 -> 0 | U17: x | AR17: x | AX17: =S17*V17 -> 0 | AY17: =AP17*AS17 -> 0
... S25: =图表!AE165 -> 0 | U25: x | AR25: x | AX25: =S25*V25 -> 0 | AY25: =AP25*AS25 -> 0
B27: 次元袋/载具 | V27: 有 | Y27: 账本笔记
B28: 名称 | I28: 描述 | S28: 磅 | V28: 数量
U29: x | BF29: =S29*V29 -> 0
U30: x | BF30: =S30*V30 -> 0
U31: x | BF31: =S31*V31 -> 0
U32: x | BF32: =S32*V32 -> 0
U33: x | BF33: =S33*V33 -> 0
U34: x | BF34: =S34*V34 -> 0
U35: x | BF35: =S35*V35 -> 0
U36: x | BF36: =S36*V36 -> 0
U37: x | BF37: =S37*V37 -> 0
U38: x | BF38: =S38*V38 -> 0
A39: .
U40: x | BF40: =S40*V40 -> 0
U41: x | BF41: =S41*V41 -> 0
U42: x | BF42: =S42*V42 -> 0
U43: x | BF43: =S43*V43 -> 0
U44: x | BF44: =S44*V44 -> 0
U45: x | BF45: =S45*V45 -> 0
U46: x | BF46: =S46*V46 -> 0
U47: x | BF47: =S47*V47 -> 0
U48: x | BF48: =S48*V48 -> 0
U49: x | BF49: =S49*V49 -> 0
B51: 次元袋/载具重量 | P51: 次元袋/载具负重（收纳） | U51: =SUM(BF29:BF38,BF40:BF49,BF54:BF63) -> 0

Sheet 施法
A1: 施法 Spellcasting
D2: 关键属性 | H2: 魅力 | K2: 法术豁免DC | O2: =SUM(8+主要情况!AC3+IF(H2="力量",主要情况!G8,IF(H2="敏捷",主要情况!G10,IF(H2="体质",主要情况!G12,IF(H2="智力",主要情况!G14,IF(H2="感知",主要情况!G16,IF(H2="魅力",主要情况!G18,0)))))))+BB17 -> 14 | R2: 法术命中 | V2: =(O2-BB17)-8+BB18 -> 6 | Y2: 已知戏法 | AC2: =图表!D61 -> 3 | AF2: 主职业已知法术 | AI2: =图表!E61 -> 6 | AK2: 主职业可准备法术数量 | AP2: =图表!F28 -> ∞
A3: 列表0 | D3: LV | E3: 学派 | H3: 仪式 | J3: 法术名 | P3: 施法时间 | R3: 施法距离 | U3: 持续时间 | AA3: V | AB3: S | AC3: M | AD3: 具体施法材料 | AL3: 法术效果 | AV3: 环阶 | AX3: 法术位 | BC3: 法术值消耗
B4: 准备 | C4: ╳ | D4: =法术大全!C561 -> 0 | E4: =法术大全!D561 -> 塑能 | H4: =法术大全!E561 -> x | J4: 魔能爆 | O4: > | P4: =法术大全!F561 -> 1动作 | R4: =法术大全!G561 -> 120尺 | U4: =法术大全!L561 -> 立即 | Z4: > | AA4: =法术大全!H561 -> V | AB4: =法术大全!I561 -> S | AC4: =法术大全!J561 -> × | AD4: =法术大全!K561 -> × | AK4: > | AV4: 0 | AX4: ∞ | AZ4: / | BA4: ∞ | BC4: 0
B5: 准备 | C5: ╳ | D5: =法术大全!C562 -> 0 | E5: =法术大全!D562 -> 幻术 | H5: =法术大全!E562 -> x | J5: 次级幻影 | O5: > | P5: =法术大全!F562 -> 1动作 | R5: =法术大全!G562 -> 30尺 | U5: =法术大全!L562 -> 1分钟 | Z5: > | AA5: =法术大全!H562 -> × | AB5: =法术大全!I562 -> S | AC5: =法术大全!J562 -> M | AD5: =法术大全!K562 -> 一小块羊毛 | AK5: > | AV5: 1 | AX5: 0 | AZ5: / | BA5: 0 | BC5: 2
B6: 准备 | C6: ╳ | D6: =法术大全!C563 -> 0 | E6: =法术大全!D563 -> 咒法 | H6: =法术大全!E563 -> x | J6: 法师之手 | O6: > | P6: =法术大全!F563 -> 1动作 | R6: =法术大全!G563 -> 30尺 | U6: =法术大全!L563 -> 1分钟 | Z6: > | AA6: =法术大全!H563 -> V | AB6: =法术大全!I563 -> S | AC6: =法术大全!J563 -> × | AD6: =法术大全!K563 -> × | AK6: > | AV6: 2 | AX6: 0 | AZ6: / | BA6: 0 | BC6: 3
B7: 准备 | C7: ╳ | D7: =法术大全!C564 -> 2 | E7: =法术大全!D564 -> 咒法 | H7: =法术大全!E564 -> x | J7: 迷踪步 | O7: > | P7: =法术大全!F564 -> 1附赠动作 | R7: =法术大全!G564 -> 自身 | U7: =法术大全!L564 -> 立即 | Z7: > | AA7: =法术大全!H564 -> V | AB7: =法术大全!I564 -> × | AC7: =法术大全!J564 -> × | AD7: =法术大全!K564 -> × | AK7: > | AV7: 3 | AX7: 0 | AZ7: / | BA7: 0 | BC7: 5
B8: 准备 | C8: ╳ | D8: =法术大全!C565 -> 2 | E8: =法术大全!D565 -> 惑控 | H8: =法术大全!E565 -> x | J8: 暗示术 | O8: > | P8: =法术大全!F565 -> 1动作 | R8: =法术大全!G565 -> 30尺 | U8: =法术大全!L565 -> 专注,至多8小时 | Z8: > | AA8: =法术大全!H565 -> V | AB8: =法术大全!I565 -> × | AC8: =法术大全!J565 -> M | AD8: =法术大全!K565 -> 一条蛇舌，加上一小块蜂巢或一滴甜油 | AK8: > | AV8: 4 | AX8: 0 | AZ8: / | BA8: 0 | BC8: 6
B9: 准备 | C9: ╳ | D9: =法术大全!C566 -> 2 | E9: =法术大全!D566 -> 幻术 | H9: =法术大全!E566 -> x | J9: 隐形术 | O9: > | P9: =法术大全!F566 -> 1动作 | R9: =法术大全!G566 -> 触及 | U9: =法术大全!L566 -> 专注,至多1小时 | Z9: > | AA9: =法术大全!H566 -> V | AB9: =法术大全!I566 -> S | AC9: =法术大全!J566 -> M | AD9: =法术大全!K566 -> 一根包裹在阿拉伯胶中的睫毛 | AK9: > | AV9: 5 | AX9: 0 | AZ9: / | BA9: 0 | BC9: 7
B10: 准备 | C10: ╳ | D10: =法术大全!C567 -> 2 | E10: =法术大全!D567 -> 惑控 | H10: =法术大全!E567 -> x | J10: 人类定身术 | O10: > | P10: =法术大全!F567 -> 1动作 | R10: =法术大全!G567 -> 60尺 | U10: =法术大全!L567 -> 专注,至多1分钟 | Z10: > | AA10: =法术大全!H567 -> V | AB10: =法术大全!I567 -> S | AC10: =法术大全!J567 -> M | AD10: =法术大全!K567 -> 一片直的小铁片 | AK10: > | AV10: 6 | AX10: 0 | AZ10: / | BA10: 0 | BC10: 9
B11: 准备 | C11: ╳ | D11: =法术大全!C568 -> 1 | E11: =法术大全!D568 -> 咒法 | H11: =法术大全!E568 -> √ | J11: 隐形仆役 | O11: > | P11: =法术大全!F568 -> 1动作 | R11: =法术大全!G568 -> 60尺 | U11: =法术大全!L568 -> 1小时 | Z11: > | AA11: =法术大全!H568 -> V | AB11: =法术大全!I568 -> S | AC11: =法术大全!J568 -> M | AD11: =法术大全!K568 -> 一根线和一块木头 | AK11: > | AV11: 7 | AX11: 0 | AZ11: / | BA11: 0 | BC11: 10
B12: 准备 | C12: ╳ | D12: =法术大全!C569 -> 0 | E12: =法术大全!D569 -> 变化 | H12: =法术大全!E569 -> x | J12: 修复术 | O12: > | P12: =法术大全!F569 -> 1分钟 | R12: =法术大全!G569 -> 触及 | U12: =法术大全!L569 -> 立即 | Z12: > | AA12: =法术大全!H569 -> V | AB12: =法术大全!I569 -> S | AC12: =法术大全!J569 -> M | AD12: =法术大全!K569 -> 两块天然磁石 | AK12: > | AV12: 8 | AX12: 0 | AZ12: / | BA12: 0 | BC12: 11
B13: 准备 | C13: ╳ | D13: 3 | E13: =法术大全!D570 -> #N/A | H13: =法术大全!E570 -> #N/A | J13: 亡灵召唤术 | O13: > | P13: =法术大全!F570 -> #N/A | R13: =法术大全!G570 -> #N/A | U13: =法术大全!L570 -> #N/A | Z13: > | AA13: =法术大全!H570 -> #N/A | AB13: =法术大全!I570 -> #N/A | AC13: =法术大全!J570 -> #N/A | AD13: =法术大全!K570 -> #N/A | AK13: > | AV13: 9 | AX13: 0 | AZ13: / | BA13: 0 | BC13: 13
A14: 列表1 | D14: LV | E14: 学派 | H14: 仪式 | J14: 法术名 | P14: 施法时间 | R14: 施法距离 | U14: 持续时间 | AA14: V | AB14: S | AC14: M | AD14: 具体施法材料 | AL14: 法术效果 | AV14: 环位合计法术值 | BE14: =SUM((BA5*2),(BA6*3),(BA7*5),(BA8*6),(BA9*7),(BA10*9),(BA11*10),(BA12*11),(BA13*13)) -> 0
B15: 准备 | C15: ╳ | D15: =法术大全!C572 -> - | E15: =法术大全!D572 -> - | H15: =法术大全!E572 -> - | O15: > | P15: =法术大全!F572 -> - | R15: =法术大全!G572 -> - | U15: =法术大全!L572 -> - | Z15: > | AA15: =法术大全!H572 -> - | AB15: =法术大全!I572 -> - | AC15: =法术大全!J572 -> - | AD15: =法术大全!K572 -> - | AK15: >
B16: 准备 | C16: ╳ | D16: =法术大全!C573 -> - | E16: =法术大全!D573 -> - | H16: =法术大全!E573 -> - | O16: > | P16: =法术大全!F573 -> - | R16: =法术大全!G573 -> - | U16: =法术大全!L573 -> - | Z16: > | AA16: =法术大全!H573 -> - | AB16: =法术大全!I573 -> - | AC16: =法术大全!J573 -> - | AD16: =法术大全!K573 -> - | AK16: > | AV16: 额外法术加值
B17: 准备 | C17: ╳ | D17: =法术大全!C574 -> - | E17: =法术大全!D574 -> - | H17: =法术大全!E574 -> - | O17: > | P17: =法术大全!F574 -> - | R17: =法术大全!G574 -> - | U17: =法术大全!L574 -> - | Z17: > | AA17: =法术大全!H574 -> - | AB17: =法术大全!I574 -> - | AC17: =法术大全!J574 -> - | AD17: =法术大全!K574 -> - | AK17: > | AV17: DC加值
B18: 准备 | C18: ╳ | D18: =法术大全!C575 -> - | E18: =法术大全!D575 -> - | H18: =法术大全!E575 -> - | O18: > | P18: =法术大全!F575 -> - | R18: =法术大全!G575 -> - | U18: =法术大全!L575 -> - | Z18: > | AA18: =法术大全!H575 -> - | AB18: =法术大全!I575 -> - | AC18: =法术大全!J575 -> - | AD18: =法术大全!K575 -> - | AK18: > | AV18: 命中加值
B19: 准备 | C19: ╳ | D19: =法术大全!C576 -> - | E19: =法术大全!D576 -> - | H19: =法术大全!E576 -> - | O19: > | P19: =法术大全!F576 -> - | R19: =法术大全!G576 -> - | U19: =法术大全!L576 -> - | Z19: > | AA19: =法术大全!H576 -> - | AB19: =法术大全!I576 -> - | AC19: =法术大全!J576 -> - | AD19: =法术大全!K576 -> - | AK19: >
B20: 准备 | C20: ╳ | D20: =法术大全!C577 -> - | E20: =法术大全!D577 -> - | H20: =法术大全!E577 -> - | O20: > | P20: =法术大全!F577 -> - | R20: =法术大全!G577 -> - | U20: =法术大全!L577 -> - | Z20: > | AA20: =法术大全!H577 -> - | AB20: =法术大全!I577 -> - | AC20: =法术大全!J577 -> - | AD20: =法术大全!K577 -> - | AK20: > | AV20: 等级 | AX20: 法术值 | BB20: 最大法术环阶
B21: 准备 | C21: ╳ | D21: =法术大全!C578 -> - | E21: =法术大全!D578 -> - | H21: =法术大全!E578 -> - | O21: > | P21: =法术大全!F578 -> - | R21: =法术大全!G578 -> - | U21: =法术大全!L578 -> - | Z21: > | AA21: =法术大全!H578 -> - | AB21: =法术大全!I578 -> - | AC21: =法术大全!J578 -> - | AD21: =法术大全!K578 -> - | AK21: > | AV21: 0 | AX21: 0 | BB21: 0
B22: 准备 | C22: ╳ | D22: =法术大全!C579 -> - | E22: =法术大全!D579 -> - | H22: =法术大全!E579 -> - | O22: > | P22: =法术大全!F579 -> - | R22: =法术大全!G579 -> - | U22: =法术大全!L579 -> - | Z22: > | AA22: =法术大全!H579 -> - | AB22: =法术大全!I579 -> - | AC22: =法术大全!J579 -> - | AD22: =法术大全!K579 -> - | AK22: > | AV22: 1 | AX22: 4 | BB22: 1
B23: 准备 | C23: ╳ | D23: =法术大全!C580 -> - | E23: =法术大全!D580 -> - | H23: =法术大全!E580 -> - | O23: > | P23: =法术大全!F580 -> - | R23: =法术大全!G580 -> - | U23: =法术大全!L580 -> - | Z23: > | AA23: =法术大全!H580 -> - | AB23: =法术大全!I580 -> - | AC23: =法术大全!J580 -> - | AD23: =法术大全!K580 -> - | AK23: > | AV23: 2 | AX23: 6 | BB23: 1
B24: 准备 | C24: ╳ | D24: =法术大全!C581 -> - | E24: =法术大全!D581 -> - | H24: =法术大全!E581 -> - | O24: > | P24: =法术大全!F581 -> - | R24: =法术大全!G581 -> - | U24: =法术大全!L581 -> - | Z24: > | AA24: =法术大全!H581 -> - | AB24: =法术大全!I581 -> - | AC24: =法术大全!J581 -> - | AD24: =法术大全!K581 -> - | AK24: > | AV24: 3 | AX24: 14 | BB24: 2
A25: 列表2 | D25: LV | E25: 学派 | H25: 仪式 | J25: 法术名 | P25: 施法时间 | R25: 施法距离 | U25: 持续时间 | AA25: V | AB25: S | AC25: M | AD25: 具体施法材料 | AL25: 法术效果 | AV25: 4 | AX25: 17 | BB25: 2
B26: 准备 | C26: ╳ | D26: =法术大全!C583 -> - | E26: =法术大全!D583 -> - | H26: =法术大全!E583 -> - | O26: > | P26: =法术大全!F583 -> - | R26: =法术大全!G583 -> - | U26: =法术大全!L583 -> - | Z26: > | AA26: =法术大全!H583 -> - | AB26: =法术大全!I583 -> - | AC26: =法术大全!J583 -> - | AD26: =法术大全!K583 -> - | AK26: > | AV26: 5 | AX26: 27 | BB26: 3
B27: 准备 | C27: ╳ | D27: =法术大全!C584 -> - | E27: =法术大全!D584 -> - | H27: =法术大全!E584 -> - | O27: > | P27: =法术大全!F584 -> - | R27: =法术大全!G584 -> - | U27: =法术大全!L584 -> - | Z27: > | AA27: =法术大全!H584 -> - | AB27: =法术大全!I584 -> - | AC27: =法术大全!J584 -> - | AD27: =法术大全!K584 -> - | AK27: > | AV27: 6 | AX27: 32 | BB27: 3
B28: 准备 | C28: ╳ | D28: =法术大全!C585 -> - | E28: =法术大全!D585 -> - | H28: =法术大全!E585 -> - | O28: > | P28: =法术大全!F585 -> - | R28: =法术大全!G585 -> - | U28: =法术大全!L585 -> - | Z28: > | AA28: =法术大全!H585 -> - | AB28: =法术大全!I585 -> - | AC28: =法术大全!J585 -> - | AD28: =法术大全!K585 -> - | AK28: > | AV28: 7 | AX28: 38 | BB28: 4
B29: 准备 | C29: ╳ | D29: =法术大全!C586 -> - | E29: =法术大全!D586 -> - | H29: =法术大全!E586 -> - | O29: > | P29: =法术大全!F586 -> - | R29: =法术大全!G586 -> - | U29: =法术大全!L586 -> - | Z29: > | AA29: =法术大全!H586 -> - | AB29: =法术大全!I586 -> - | AC29: =法术大全!J586 -> - | AD29: =法术大全!K586 -> - | AK29: > | AV29: 8 | AX29: 44 | BB29: 4
B30: 准备 | C30: ╳ | D30: =法术大全!C587 -> - | E30: =法术大全!D587 -> - | H30: =法术大全!E587 -> - | O30: > | P30: =法术大全!F587 -> - | R30: =法术大全!G587 -> - | U30: =法术大全!L587 -> - | Z30: > | AA30: =法术大全!H587 -> - | AB30: =法术大全!I587 -> - | AC30: =法术大全!J587 -> - | AD30: =法术大全!K587 -> - | AK30: > | AV30: 9 | AX30: 57 | BB30: 5
B31: 准备 | C31: ╳ | D31: =法术大全!C588 -> - | E31: =法术大全!D588 -> - | H31: =法术大全!E588 -> - | O31: > | P31: =法术大全!F588 -> - | R31: =法术大全!G588 -> - | U31: =法术大全!L588 -> - | Z31: > | AA31: =法术大全!H588 -> - | AB31: =法术大全!I588 -> - | AC31: =法术大全!J588 -> - | AD31: =法术大全!K588 -> - | AK31: > | AV31: 10 | AX31: 64 | BB31: 5
B32: 准备 | C32: ╳ | D32: =法术大全!C589 -> - | E32: =法术大全!D589 -> - | H32: =法术大全!E589 -> - | O32: > | P32: =法术大全!F589 -> - | R32: =法术大全!G589 -> - | U32: =法术大全!L589 -> - | Z32: > | AA32: =法术大全!H589 -> - | AB32: =法术大全!I589 -> - | AC32: =法术大全!J589 -> - | AD32: =法术大全!K589 -> - | AK32: > | AV32: 11 | AX32: 73 | BB32: 6
B33: 准备 | C33: ╳ | D33: =法术大全!C590 -> - | E33: =法术大全!D590 -> - | H33: =法术大全!E590 -> - | O33: > | P33: =法术大全!F590 -> - | R33: =法术大全!G590 -> - | U33: =法术大全!L590 -> - | Z33: > | AA33: =法术大全!H590 -> - | AB33: =法术大全!I590 -> - | AC33: =法术大全!J590 -> - | AD33: =法术大全!K590 -> - | AK33: > | AV33: 12 | AX33: 73 | BB33: 6
B34: 准备 | C34: ╳ | D34: =法术大全!C591 -> - | E34: =法术大全!D591 -> - | H34: =法术大全!E591 -> - | O34: > | P34: =法术大全!F591 -> - | R34: =法术大全!G591 -> - | U34: =法术大全!L591 -> - | Z34: > | AA34: =法术大全!H591 -> - | AB34: =法术大全!I591 -> - | AC34: =法术大全!J591 -> - | AD34: =法术大全!K591 -> - | AK34: > | AV34: 13 | AX34: 83 | BB34: 7
B35: 准备 | C35: ╳ | D35: =法术大全!C592 -> - | E35: =法术大全!D592 -> - | H35: =法术大全!E592 -> - | O35: > | P35: =法术大全!F592 -> - | R35: =法术大全!G592 -> - | U35: =法术大全!L592 -> - | Z35: > | AA35: =法术大全!H592 -> - | AB35: =法术大全!I592 -> - | AC35: =法术大全!J592 -> - | AD35: =法术大全!K592 -> - | AK35: > | AV35: 14 | AX35: 83 | BB35: 7
A36: 列表3 | D36: LV | E36: 学派 | H36: 仪式 | J36: 法术名 | P36: 施法时间 | R36: 施法距离 | U36: 持续时间 | AA36: V | AB36: S | AC36: M | AD36: 具体施法材料 | AL36: 法术效果 | AV36: 15 | AX36: 94 | BB36: 8
B37: 准备 | C37: ╳ | D37: =法术大全!C594 -> - | E37: =法术大全!D594 -> - | H37: =法术大全!E594 -> - | O37: > | P37: =法术大全!F594 -> - | R37: =法术大全!G594 -> - | U37: =法术大全!L594 -> - | Z37: > | AA37: =法术大全!H594 -> - | AB37: =法术大全!I594 -> - | AC37: =法术大全!J594 -> - | AD37: =法术大全!K594 -> - | AK37: > | AV37: 16 | AX37: 94 | BB37: 8
B38: 准备 | C38: ╳ | D38: =法术大全!C595 -> - | E38: =法术大全!D595 -> - | H38: =法术大全!E595 -> - | O38: > | P38: =法术大全!F595 -> - | R38: =法术大全!G595 -> - | U38: =法术大全!L595 -> - | Z38: > | AA38: =法术大全!H595 -> - | AB38: =法术大全!I595 -> - | AC38: =法术大全!J595 -> - | AD38: =法术大全!K595 -> - | AK38: > | AV38: 17 | AX38: 107 | BB38: 9
B39: 准备 | C39: ╳ | D39: =法术大全!C596 -> - | E39: =法术大全!D596 -> - | H39: =法术大全!E596 -> - | O39: > | P39: =法术大全!F596 -> - | R39: =法术大全!G596 -> - | U39: =法术大全!L596 -> - | Z39: > | AA39: =法术大全!H596 -> - | AB39: =法术大全!I596 -> - | AC39: =法术大全!J596 -> - | AD39: =法术大全!K596 -> - | AK39: > | AV39: 18 | AX39: 114 | BB39: 9
B40: 准备 | C40: ╳ | D40: =法术大全!C597 -> - | E40: =法术大全!D597 -> - | H40: =法术大全!E597 -> - | O40: > | P40: =法术大全!F597 -> - | R40: =法术大全!G597 -> - | U40: =法术大全!L597 -> - | Z40: > | AA40: =法术大全!H597 -> - | AB40: =法术大全!I597 -> - | AC40: =法术大全!J597 -> - | AD40: =法术大全!K597 -> - | AK40: > | AV40: 19 | AX40: 123 | BB40: 9
B41: 准备 | C41: ╳ | D41: =法术大全!C598 -> - | E41: =法术大全!D598 -> - | H41: =法术大全!E598 -> - | O41: > | P41: =法术大全!F598 -> - | R41: =法术大全!G598 -> - | U41: =法术大全!L598 -> - | Z41: > | AA41: =法术大全!H598 -> - | AB41: =法术大全!I598 -> - | AC41: =法术大全!J598 -> - | AD41: =法术大全!K598 -> - | AK41: > | AV41: 20 | AX41: 133 | BB41: 9
B42: 准备 | C42: ╳ | D42: =法术大全!C599 -> - | E42: =法术大全!D599 -> - | H42: =法术大全!E599 -> - | O42: > | P42: =法术大全!F599 -> - | R42: =法术大全!G599 -> - | U42: =法术大全!L599 -> - | Z42: > | AA42: =法术大全!H599 -> - | AB42: =法术大全!I599 -> - | AC42: =法术大全!J599 -> - | AD42: =法术大全!K599 -> - | AK42: >
B43: 准备 | C43: ╳ | D43: =法术大全!C600 -> - | E43: =法术大全!D600 -> - | H43: =法术大全!E600 -> - | O43: > | P43: =法术大全!F600 -> - | R43: =法术大全!G600 -> - | U43: =法术大全!L600 -> - | Z43: > | AA43: =法术大全!H600 -> - | AB43: =法术大全!I600 -> - | AC43: =法术大全!J600 -> - | AD43: =法术大全!K600 -> - | AK43: >
B44: 准备 | C44: ╳ | D44: =法术大全!C601 -> - | E44: =法术大全!D601 -> - | H44: =法术大全!E601 -> - | O44: > | P44: =法术大全!F601 -> - | R44: =法术大全!G601 -> - | U44: =法术大全!L601 -> - | Z44: > | AA44: =法术大全!H601 -> - | AB44: =法术大全!I601 -> - | AC44: =法术大全!J601 -> - | AD44: =法术大全!K601 -> - | AK44: >
B45: 准备 | C45: ╳ | D45: =法术大全!C602 -> - | E45: =法术大全!D602 -> - | H45: =法术大全!E602 -> - | O45: > | P45: =法术大全!F602 -> - | R45: =法术大全!G602 -> - | U45: =法术大全!L602 -> - | Z45: > | AA45: =法术大全!H602 -> - | AB45: =法术大全!I602 -> - | AC45: =法术大全!J602 -> - | AD45: =法术大全!K602 -> - | AK45: >
B46: 准备 | C46: ╳ | D46: =法术大全!C603 -> - | E46: =法术大全!D603 -> - | H46: =法术大全!E603 -> - | O46: > | P46: =法术大全!F603 -> - | R46: =法术大全!G603 -> - | U46: =法术大全!L603 -> - | Z46: > | AA46: =法术大全!H603 -> - | AB46: =法术大全!I603 -> - | AC46: =法术大全!J603 -> - | AD46: =法术大全!K603 -> - | AK46: >
A47: 列表4 | D47: LV | E47: 学派 | H47: 仪式 | J47: 法术名 | P47: 施法时间 | R47: 施法距离 | U47: 持续时间 | AA47: V | AB47: S | AC47: M | AD47: 具体施法材料 | AL47: 法术效果
B48: 准备 | C48: ╳ | D48: =法术大全!C605 -> - | E48: =法术大全!D605 -> - | H48: =法术大全!E605 -> - | O48: > | P48: =法术大全!F605 -> - | R48: =法术大全!G605 -> - | U48: =法术大全!L605 -> - | Z48: > | AA48: =法术大全!H605 -> - | AB48: =法术大全!I605 -> - | AC48: =法术大全!J605 -> - | AD48: =法术大全!K605 -> - | AK48: >
B49: 准备 | C49: ╳ | D49: =法术大全!C606 -> - | E49: =法术大全!D606 -> - | H49: =法术大全!E606 -> - | O49: > | P49: =法术大全!F606 -> - | R49: =法术大全!G606 -> - | U49: =法术大全!L606 -> - | Z49: > | AA49: =法术大全!H606 -> - | AB49: =法术大全!I606 -> - | AC49: =法术大全!J606 -> - | AD49: =法术大全!K606 -> - | AK49: >
B50: 准备 | C50: ╳ | D50: =法术大全!C607 -> - | E50: =法术大全!D607 -> - | H50: =法术大全!E607 -> - | O50: > | P50: =法术大全!F607 -> - | R50: =法术大全!G607 -> - | U50: =法术大全!L607 -> - | Z50: > | AA50: =法术大全!H607 -> - | AB50: =法术大全!I607 -> - | AC50: =法术大全!J607 -> - | AD50: =法术大全!K607 -> - | AK50: >
B51: 准备 | C51: ╳ | D51: =法术大全!C608 -> - | E51: =法术大全!D608 -> - | H51: =法术大全!E608 -> - | O51: > | P51: =法术大全!F608 -> - | R51: =法术大全!G608 -> - | U51: =法术大全!L608 -> - | Z51: > | AA51: =法术大全!H608 -> - | AB51: =法术大全!I608 -> - | AC51: =法术大全!J608 -> - | AD51: =法术大全!K608 -> - | AK51: >
B52: 准备 | C52: ╳ | D52: =法术大全!C609 -> - | E52: =法术大全!D609 -> - | H52: =法术大全!E609 -> - | O52: > | P52: =法术大全!F609 -> - | R52: =法术大全!G609 -> - | U52: =法术大全!L609 -> - | Z52: > | AA52: =法术大全!H609 -> - | AB52: =法术大全!I609 -> - | AC52: =法术大全!J609 -> - | AD52: =法术大全!K609 -> - | AK52: >
B53: 准备 | C53: ╳ | D53: =法术大全!C610 -> - | E53: =法术大全!D610 -> - | H53: =法术大全!E610 -> - | O53: > | P53: =法术大全!F610 -> - | R53: =法术大全!G610 -> - | U53: =法术大全!L610 -> - | Z53: > | AA53: =法术大全!H610 -> - | AB53: =法术大全!I610 -> - | AC53: =法术大全!J610 -> - | AD53: =法术大全!K610 -> - | AK53: >
B54: 准备 | C54: ╳ | D54: =法术大全!C611 -> - | E54: =法术大全!D611 -> - | H54: =法术大全!E611 -> - | O54: > | P54: =法术大全!F611 -> - | R54: =法术大全!G611 -> - | U54: =法术大全!L611 -> - | Z54: > | AA54: =法术大全!H611 -> - | AB54: =法术大全!I611 -> - | AC54: =法术大全!J611 -> - | AD54: =法术大全!K611 -> - | AK54: >
B55: 准备 | C55: ╳ | D55: =法术大全!C612 -> - | E55: =法术大全!D612 -> - | H55: =法术大全!E612 -> - | O55: > | P55: =法术大全!F612 -> - | R55: =法术大全!G612 -> - | U55: =法术大全!L612 -> - | Z55: > | AA55: =法术大全!H612 -> - | AB55: =法术大全!I612 -> - | AC55: =法术大全!J612 -> - | AD55: =法术大全!K612 -> - | AK55: >
B56: 准备 | C56: ╳ | D56: =法术大全!C613 -> - | E56: =法术大全!D613 -> - | H56: =法术大全!E613 -> - | O56: > | P56: =法术大全!F613 -> - | R56: =法术大全!G613 -> - | U56: =法术大全!L613 -> - | Z56: > | AA56: =法术大全!H613 -> - | AB56: =法术大全!I613 -> - | AC56: =法术大全!J613 -> - | AD56: =法术大全!K613 -> - | AK56: >
B57: 准备 | C57: ╳ | D57: =法术大全!C614 -> - | E57: =法术大全!D614 -> - | H57: =法术大全!E614 -> - | O57: > | P57: =法术大全!F614 -> - | R57: =法术大全!G614 -> - | U57: =法术大全!L614 -> - | Z57: > | AA57: =法术大全!H614 -> - | AB57: =法术大全!I614 -> - | AC57: =法术大全!J614 -> - | AD57: =法术大全!K614 -> - | AK57: >
A58: 列表5 | D58: LV | E58: 学派 | H58: 仪式 | J58: 法术名 | P58: 施法时间 | R58: 施法距离 | U58: 持续时间 | AA58: V | AB58: S | AC58: M | AD58: 具体施法材料 | AL58: 法术效果
B59: 准备 | C59: ╳ | D59: =法术大全!C616 -> - | E59: =法术大全!D616 -> - | H59: =法术大全!E616 -> - | O59: > | P59: =法术大全!F616 -> - | R59: =法术大全!G616 -> - | U59: =法术大全!L616 -> - | Z59: > | AA59: =法术大全!H616 -> - | AB59: =法术大全!I616 -> - | AC59: =法术大全!J616 -> - | AD59: =法术大全!K616 -> - | AK59: >
B60: 准备 | C60: ╳ | D60: =法术大全!C617 -> - | E60: =法术大全!D617 -> - | H60: =法术大全!E617 -> - | O60: > | P60: =法术大全!F617 -> - | R60: =法术大全!G617 -> - | U60: =法术大全!L617 -> - | Z60: > | AA60: =法术大全!H617 -> - | AB60: =法术大全!I617 -> - | AC60: =法术大全!J617 -> - | AD60: =法术大全!K617 -> - | AK60: >
B61: 准备 | C61: ╳ | D61: =法术大全!C618 -> - | E61: =法术大全!D618 -> - | H61: =法术大全!E618 -> - | O61: > | P61: =法术大全!F618 -> - | R61: =法术大全!G618 -> - | U61: =法术大全!L618 -> - | Z61: > | AA61: =法术大全!H618 -> - | AB61: =法术大全!I618 -> - | AC61: =法术大全!J618 -> - | AD61: =法术大全!K618 -> - | AK61: >
B62: 准备 | C62: ╳ | D62: =法术大全!C619 -> - | E62: =法术大全!D619 -> - | H62: =法术大全!E619 -> - | O62: > | P62: =法术大全!F619 -> - | R62: =法术大全!G619 -> - | U62: =法术大全!L619 -> - | Z62: > | AA62: =法术大全!H619 -> - | AB62: =法术大全!I619 -> - | AC62: =法术大全!J619 -> - | AD62: =法术大全!K619 -> - | AK62: >
B63: 准备 | C63: ╳ | D63: =法术大全!C620 -> - | E63: =法术大全!D620 -> - | H63: =法术大全!E620 -> - | O63: > | P63: =法术大全!F620 -> - | R63: =法术大全!G620 -> - | U63: =法术大全!L620 -> - | Z63: > | AA63: =法术大全!H620 -> - | AB63: =法术大全!I620 -> - | AC63: =法术大全!J620 -> - | AD63: =法术大全!K620 -> - | AK63: >
B64: 准备 | C64: ╳ | D64: =法术大全!C621 -> - | E64: =法术大全!D621 -> - | H64: =法术大全!E621 -> - | O64: > | P64: =法术大全!F621 -> - | R64: =法术大全!G621 -> - | U64: =法术大全!L621 -> - | Z64: > | AA64: =法术大全!H621 -> - | AB64: =法术大全!I621 -> - | AC64: =法术大全!J621 -> - | AD64: =法术大全!K621 -> - | AK64: >
B65: 准备 | C65: ╳ | D65: =法术大全!C622 -> - | E65: =法术大全!D622 -> - | H65: =法术大全!E622 -> - | O65: > | P65: =法术大全!F622 -> - | R65: =法术大全!G622 -> - | U65: =法术大全!L622 -> - | Z65: > | AA65: =法术大全!H622 -> - | AB65: =法术大全!I622 -> - | AC65: =法术大全!J622 -> - | AD65: =法术大全!K622 -> - | AK65: >
B66: 准备 | C66: ╳ | D66: =法术大全!C623 -> - | E66: =法术大全!D623 -> - | H66: =法术大全!E623 -> - | O66: > | P66: =法术大全!F623 -> - | R66: =法术大全!G623 -> - | U66: =法术大全!L623 -> - | Z66: > | AA66: =法术大全!H623 -> - | AB66: =法术大全!I623 -> - | AC66: =法术大全!J623 -> - | AD66: =法术大全!K623 -> - | AK66: >
B67: 准备 | C67: ╳ | D67: =法术大全!C624 -> - | E67: =法术大全!D624 -> - | H67: =法术大全!E624 -> - | O67: > | P67: =法术大全!F624 -> - | R67: =法术大全!G624 -> - | U67: =法术大全!L624 -> - | Z67: > | AA67: =法术大全!H624 -> - | AB67: =法术大全!I624 -> - | AC67: =法术大全!J624 -> - | AD67: =法术大全!K624 -> - | AK67: >
B68: 准备 | C68: ╳ | D68: =法术大全!C625 -> - | E68: =法术大全!D625 -> - | H68: =法术大全!E625 -> - | O68: > | P68: =法术大全!F625 -> - | R68: =法术大全!G625 -> - | U68: =法术大全!L625 -> - | Z68: > | AA68: =法术大全!H625 -> - | AB68: =法术大全!I625 -> - | AC68: =法术大全!J625 -> - | AD68: =法术大全!K625 -> - | AK68: >
A69: 列表6 | D69: LV | E69: 学派 | H69: 仪式 | J69: 法术名 | P69: 施法时间 | R69: 施法距离 | U69: 持续时间 | AA69: V | AB69: S | AC69: M | AD69: 具体施法材料 | AL69: 法术效果
B70: 准备 | C70: ╳ | D70: =法术大全!C627 -> - | E70: =法术大全!D627 -> - | H70: =法术大全!E627 -> - | O70: > | P70: =法术大全!F627 -> - | R70: =法术大全!G627 -> - | U70: =法术大全!L627 -> - | Z70: > | AA70: =法术大全!H627 -> - | AB70: =法术大全!I627 -> - | AC70: =法术大全!J627 -> - | AD70: =法术大全!K627 -> - | AK70: >
B71: 准备 | C71: ╳ | D71: =法术大全!C628 -> - | E71: =法术大全!D628 -> - | H71: =法术大全!E628 -> - | O71: > | P71: =法术大全!F628 -> - | R71: =法术大全!G628 -> - | U71: =法术大全!L628 -> - | Z71: > | AA71: =法术大全!H628 -> - | AB71: =法术大全!I628 -> - | AC71: =法术大全!J628 -> - | AD71: =法术大全!K628 -> - | AK71: >
B72: 准备 | C72: ╳ | D72: =法术大全!C629 -> - | E72: =法术大全!D629 -> - | H72: =法术大全!E629 -> - | O72: > | P72: =法术大全!F629 -> - | R72: =法术大全!G629 -> - | U72: =法术大全!L629 -> - | Z72: > | AA72: =法术大全!H629 -> - | AB72: =法术大全!I629 -> - | AC72: =法术大全!J629 -> - | AD72: =法术大全!K629 -> - | AK72: >
B73: 准备 | C73: ╳ | D73: =法术大全!C630 -> - | E73: =法术大全!D630 -> - | H73: =法术大全!E630 -> - | O73: > | P73: =法术大全!F630 -> - | R73: =法术大全!G630 -> - | U73: =法术大全!L630 -> - | Z73: > | AA73: =法术大全!H630 -> - | AB73: =法术大全!I630 -> - | AC73: =法术大全!J630 -> - | AD73: =法术大全!K630 -> - | AK73: >
B74: 准备 | C74: ╳ | D74: =法术大全!C631 -> - | E74: =法术大全!D631 -> - | H74: =法术大全!E631 -> - | O74: > | P74: =法术大全!F631 -> - | R74: =法术大全!G631 -> - | U74: =法术大全!L631 -> - | Z74: > | AA74: =法术大全!H631 -> - | AB74: =法术大全!I631 -> - | AC74: =法术大全!J631 -> - | AD74: =法术大全!K631 -> - | AK74: >
B75: 准备 | C75: ╳ | D75: =法术大全!C632 -> - | E75: =法术大全!D632 -> - | H75: =法术大全!E632 -> - | O75: > | P75: =法术大全!F632 -> - | R75: =法术大全!G632 -> - | U75: =法术大全!L632 -> - | Z75: > | AA75: =法术大全!H632 -> - | AB75: =法术大全!I632 -> - | AC75: =法术大全!J632 -> - | AD75: =法术大全!K632 -> - | AK75: >
B76: 准备 | C76: ╳ | D76: =法术大全!C633 -> - | E76: =法术大全!D633 -> - | H76: =法术大全!E633 -> - | O76: > | P76: =法术大全!F633 -> - | R76: =法术大全!G633 -> - | U76: =法术大全!L633 -> - | Z76: > | AA76: =法术大全!H633 -> - | AB76: =法术大全!I633 -> - | AC76: =法术大全!J633 -> - | AD76: =法术大全!K633 -> - | AK76: >
B77: 准备 | C77: ╳ | D77: =法术大全!C634 -> - | E77: =法术大全!D634 -> - | H77: =法术大全!E634 -> - | O77: > | P77: =法术大全!F634 -> - | R77: =法术大全!G634 -> - | U77: =法术大全!L634 -> - | Z77: > | AA77: =法术大全!H634 -> - | AB77: =法术大全!I634 -> - | AC77: =法术大全!J634 -> - | AD77: =法术大全!K634 -> - | AK77: >
B78: 准备 | C78: ╳ | D78: =法术大全!C635 -> - | E78: =法术大全!D635 -> - | H78: =法术大全!E635 -> - | O78: > | P78: =法术大全!F635 -> - | R78: =法术大全!G635 -> - | U78: =法术大全!L635 -> - | Z78: > | AA78: =法术大全!H635 -> - | AB78: =法术大全!I635 -> - | AC78: =法术大全!J635 -> - | AD78: =法术大全!K635 -> - | AK78: >
B79: 准备 | C79: ╳ | D79: =法术大全!C636 -> - | E79: =法术大全!D636 -> - | H79: =法术大全!E636 -> - | O79: > | P79: =法术大全!F636 -> - | R79: =法术大全!G636 -> - | U79: =法术大全!L636 -> - | Z79: > | AA79: =法术大全!H636 -> - | AB79: =法术大全!I636 -> - | AC79: =法术大全!J636 -> - | AD79: =法术大全!K636 -> - | AK79: >
A80: 列表7 | D80: LV | E80: 学派 | H80: 仪式 | J80: 法术名 | P80: 施法时间 | R80: 施法距离 | U80: 持续时间 | AA80: V | AB80: S | AC80: M | AD80: 具体施法材料 | AL80: 法术效果
B81: 准备 | C81: ╳ | D81: =法术大全!C638 -> - | E81: =法术大全!D638 -> - | H81: =法术大全!E638 -> - | O81: > | P81: =法术大全!F638 -> - | R81: =法术大全!G638 -> - | U81: =法术大全!L638 -> - | Z81: > | AA81: =法术大全!H638 -> - | AB81: =法术大全!I638 -> - | AC81: =法术大全!J638 -> - | AD81: =法术大全!K638 -> - | AK81: >
B82: 准备 | C82: ╳ | D82: =法术大全!C639 -> - | E82: =法术大全!D639 -> - | H82: =法术大全!E639 -> - | O82: > | P82: =法术大全!F639 -> - | R82: =法术大全!G639 -> - | U82: =法术大全!L639 -> - | Z82: > | AA82: =法术大全!H639 -> - | AB82: =法术大全!I639 -> - | AC82: =法术大全!J639 -> - | AD82: =法术大全!K639 -> - | AK82: >
B83: 准备 | C83: ╳ | D83: =法术大全!C640 -> - | E83: =法术大全!D640 -> - | H83: =法术大全!E640 -> - | O83: > | P83: =法术大全!F640 -> - | R83: =法术大全!G640 -> - | U83: =法术大全!L640 -> - | Z83: > | AA83: =法术大全!H640 -> - | AB83: =法术大全!I640 -> - | AC83: =法术大全!J640 -> - | AD83: =法术大全!K640 -> - | AK83: >
B84: 准备 | C84: ╳ | D84: =法术大全!C641 -> - | E84: =法术大全!D641 -> - | H84: =法术大全!E641 -> - | O84: > | P84: =法术大全!F641 -> - | R84: =法术大全!G641 -> - | U84: =法术大全!L641 -> - | Z84: > | AA84: =法术大全!H641 -> - | AB84: =法术大全!I641 -> - | AC84: =法术大全!J641 -> - | AD84: =法术大全!K641 -> - | AK84: >
B85: 准备 | C85: ╳ | D85: =法术大全!C642 -> - | E85: =法术大全!D642 -> - | H85: =法术大全!E642 -> - | O85: > | P85: =法术大全!F642 -> - | R85: =法术大全!G642 -> - | U85: =法术大全!L642 -> - | Z85: > | AA85: =法术大全!H642 -> - | AB85: =法术大全!I642 -> - | AC85: =法术大全!J642 -> - | AD85: =法术大全!K642 -> - | AK85: >
B86: 准备 | C86: ╳ | D86: =法术大全!C643 -> - | E86: =法术大全!D643 -> - | H86: =法术大全!E643 -> - | O86: > | P86: =法术大全!F643 -> - | R86: =法术大全!G643 -> - | U86: =法术大全!L643 -> - | Z86: > | AA86: =法术大全!H643 -> - | AB86: =法术大全!I643 -> - | AC86: =法术大全!J643 -> - | AD86: =法术大全!K643 -> - | AK86: >
B87: 准备 | C87: ╳ | D87: =法术大全!C644 -> - | E87: =法术大全!D644 -> - | H87: =法术大全!E644 -> - | O87: > | P87: =法术大全!F644 -> - | R87: =法术大全!G644 -> - | U87: =法术大全!L644 -> - | Z87: > | AA87: =法术大全!H644 -> - | AB87: =法术大全!I644 -> - | AC87: =法术大全!J644 -> - | AD87: =法术大全!K644 -> - | AK87: >
B88: 准备 | C88: ╳ | D88: =法术大全!C645 -> - | E88: =法术大全!D645 -> - | H88: =法术大全!E645 -> - | O88: > | P88: =法术大全!F645 -> - | R88: =法术大全!G645 -> - | U88: =法术大全!L645 -> - | Z88: > | AA88: =法术大全!H645 -> - | AB88: =法术大全!I645 -> - | AC88: =法术大全!J645 -> - | AD88: =法术大全!K645 -> - | AK88: >
B89: 准备 | C89: ╳ | D89: =法术大全!C646 -> - | E89: =法术大全!D646 -> - | H89: =法术大全!E646 -> - | O89: > | P89: =法术大全!F646 -> - | R89: =法术大全!G646 -> - | U89: =法术大全!L646 -> - | Z89: > | AA89: =法术大全!H646 -> - | AB89: =法术大全!I646 -> - | AC89: =法术大全!J646 -> - | AD89: =法术大全!K646 -> - | AK89: >
B90: 准备 | C90: ╳ | D90: =法术大全!C647 -> - | E90: =法术大全!D647 -> - | H90: =法术大全!E647 -> - | O90: > | P90: =法术大全!F647 -> - | R90: =法术大全!G647 -> - | U90: =法术大全!L647 -> - | Z90: > | AA90: =法术大全!H647 -> - | AB90: =法术大全!I647 -> - | AC90: =法术大全!J647 -> - | AD90: =法术大全!K647 -> - | AK90: >
A91: 列表8 | D91: LV | E91: 学派 | H91: 仪式 | J91: 法术名 | P91: 施法时间 | R91: 施法距离 | U91: 持续时间 | AA91: V | AB91: S | AC91: M | AD91: 具体施法材料 | AL91: 法术效果
B92: 准备 | C92: ╳ | D92: =法术大全!C649 -> - | E92: =法术大全!D649 -> - | H92: =法术大全!E649 -> - | O92: > | P92: =法术大全!F649 -> - | R92: =法术大全!G649 -> - | U92: =法术大全!L649 -> - | Z92: > | AA92: =法术大全!H649 -> - | AB92: =法术大全!I649 -> - | AC92: =法术大全!J649 -> - | AD92: =法术大全!K649 -> - | AK92: >
B93: 准备 | C93: ╳ | D93: =法术大全!C650 -> - | E93: =法术大全!D650 -> - | H93: =法术大全!E650 -> - | O93: > | P93: =法术大全!F650 -> - | R93: =法术大全!G650 -> - | U93: =法术大全!L650 -> - | Z93: > | AA93: =法术大全!H650 -> - | AB93: =法术大全!I650 -> - | AC93: =法术大全!J650 -> - | AD93: =法术大全!K650 -> - | AK93: >
B94: 准备 | C94: ╳ | D94: =法术大全!C651 -> - | E94: =法术大全!D651 -> - | H94: =法术大全!E651 -> - | O94: > | P94: =法术大全!F651 -> - | R94: =法术大全!G651 -> - | U94: =法术大全!L651 -> - | Z94: > | AA94: =法术大全!H651 -> - | AB94: =法术大全!I651 -> - | AC94: =法术大全!J651 -> - | AD94: =法术大全!K651 -> - | AK94: >
B95: 准备 | C95: ╳ | D95: =法术大全!C652 -> - | E95: =法术大全!D652 -> - | H95: =法术大全!E652 -> - | O95: > | P95: =法术大全!F652 -> - | R95: =法术大全!G652 -> - | U95: =法术大全!L652 -> - | Z95: > | AA95: =法术大全!H652 -> - | AB95: =法术大全!I652 -> - | AC95: =法术大全!J652 -> - | AD95: =法术大全!K652 -> - | AK95: >
B96: 准备 | C96: ╳ | D96: =法术大全!C653 -> - | E96: =法术大全!D653 -> - | H96: =法术大全!E653 -> - | O96: > | P96: =法术大全!F653 -> - | R96: =法术大全!G653 -> - | U96: =法术大全!L653 -> - | Z96: > | AA96: =法术大全!H653 -> - | AB96: =法术大全!I653 -> - | AC96: =法术大全!J653 -> - | AD96: =法术大全!K653 -> - | AK96: >
B97: 准备 | C97: ╳ | D97: =法术大全!C654 -> - | E97: =法术大全!D654 -> - | H97: =法术大全!E654 -> - | O97: > | P97: =法术大全!F654 -> - | R97: =法术大全!G654 -> - | U97: =法术大全!L654 -> - | Z97: > | AA97: =法术大全!H654 -> - | AB97: =法术大全!I654 -> - | AC97: =法术大全!J654 -> - | AD97: =法术大全!K654 -> - | AK97: >
B98: 准备 | C98: ╳ | D98: =法术大全!C655 -> - | E98: =法术大全!D655 -> - | H98: =法术大全!E655 -> - | O98: > | P98: =法术大全!F655 -> - | R98: =法术大全!G655 -> - | U98: =法术大全!L655 -> - | Z98: > | AA98: =法术大全!H655 -> - | AB98: =法术大全!I655 -> - | AC98: =法术大全!J655 -> - | AD98: =法术大全!K655 -> - | AK98: >
B99: 准备 | C99: ╳ | D99: =法术大全!C656 -> - | E99: =法术大全!D656 -> - | H99: =法术大全!E656 -> - | O99: > | P99: =法术大全!F656 -> - | R99: =法术大全!G656 -> - | U99: =法术大全!L656 -> - | Z99: > | AA99: =法术大全!H656 -> - | AB99: =法术大全!I656 -> - | AC99: =法术大全!J656 -> - | AD99: =法术大全!K656 -> - | AK99: >
B100: 准备 | C100: ╳ | D100: =法术大全!C657 -> - | E100: =法术大全!D657 -> - | H100: =法术大全!E657 -> - | O100: > | P100: =法术大全!F657 -> - | R100: =法术大全!G657 -> - | U100: =法术大全!L657 -> - | Z100: > | AA100: =法术大全!H657 -> - | AB100: =法术大全!I657 -> - | AC100: =法术大全!J657 -> - | AD100: =法术大全!K657 -> - | AK100: >
...

Sheet 法术大全
A1: =施法!J3 -> 法术名 | B1: 法术名 | C1: 环阶 | D1: 学派 | E1: 仪式 | F1: 施法时间 | G1: 施法距离 | H1: V 言语 | I1: S 姿势 | J1: M 材料 | K1: 材料内容 | L1: 持续时间 | M1: 法术详述 | N1: 名字 | O1: 英文名 | P1: 吟游诗人 | Q1: 牧师 | R1: 德鲁伊 | S1: 圣武士 | T1: 游侠 | U1: 术士 | V1: 邪术师 | W1: 法师 | X1: 奇械师 | Y1: 时间法师 | Z1: 重力法师 | AA1: 出处
A2: =施法!J4 -> 魔能爆 | B2: 酸液飞溅 | C2: 0 | D2: 咒法 | E2: x | F2: 1动作 | G2: 60尺 | H2: V | I2: S | J2: × | K2: × | L2: 立即 | M2: ·你掷出一颗酸液球。在施法距离内指定一个生物，或者在距离内指定两个相距不超过5尺的生物。每个目标必须进行一次敏捷豁免，豁免失败则受到1d6点强酸伤害。 ·你到达5级时，该法术的伤害增加1d6（变为2d6）11级时再加1d6（变为3d6），17级时再加1d6（变为4d6）。 | N2: 酸液飞溅 | O2: Acid Splash | U2: √ | W2: √ | X2: √ | AA2: 玩家手册
A3: =施法!J5 -> 次级幻影 | B3: 剑刃防护 | C3: 0 | D3: 防护 | E3: x | F3: 1动作 | G3: 自身 | H3: V | I3: S | J3: × | K3: × | L3: 1轮 | M3: ·你伸手在空中勾勒出一个防护印记，以令自己在下一回合结束前对武器攻击造成的钝击、穿刺和挥砍伤害具有抗性。 | N3: 剑刃防护 | O3: Blade Ward | P3: √ | U3: √ | V3: √ | W3: √ | AA3: 玩家手册
A4: =施法!J6 -> 法师之手 | B4: 轰雷剑 | C4: 0 | D4: 塑能 | E4: x | F4: 1动作 | G4: 自身(5尺半径) | H4: × | I4: S | J4: M | K4: 一把至少价值1sp的近战武器 | L4: 1轮 | M4: ·作为施展该法术的一部分，你必须用你的武器对5尺内的一个生物进行一次近战攻击。如果攻击命中，目标受到这次攻击的正常影响，并且被包覆在爆发性的能量之中，直到你下回合开始前。如果目标在结束之前自愿移动了5尺或更多，其立即受到1d8点雷鸣伤害，并且法术结束。 ·该法术的伤害随着你的等级提升而增加。你到达5级时，这次近战攻击将造成额外1d8点雷鸣伤害，并且目标进行移动时受到的伤害提升为2d8。两个伤害骰都会在11级时增加1d8（2d8和3d8），17级时再加1d8（3d8和4d8）。 | N4: 轰雷剑 | O4: Booming Blade | U4: √ | V4: √ | W4: √ | X4: √ | AA4: 剑湾冒险者指南
A5: =施法!J7 -> 迷踪步 | B5: 冻寒之触 | C5: 0 | D5: 死灵 | E5: x | F5: 1动作 | G5: 120尺 | H5: V | I5: S | J5: × | K5: × | L5: 1轮 | M5: ·你在施法距离内某生物所在位置召唤出幽魂般的骨手，夹带着墓穴的刺骨冻寒攻击目标。并对该生物进行一次远程法术攻击，命中时，手掌抓住目标并令其受1d8点黯蚀伤害，且直至你下一回合开始前都无法恢复生命值。 ·如果你的命中目标为一个不死生物，则其在你下回合结束之前对你发动的攻击检定都具有劣势。 ·你到达5级时，该法术的伤害增加1d8（变为2d8）。11级时再加1d8（变为3d8），17级时再加1d8（变为4d8）。 | N5: 冻寒之触 | O5: Chill Touch | U5: √ | V5: √ | W5: √ | AA5: 玩家手册
A6: =施法!J8 -> 暗示术 | B6: 控火 | C6: 0 | D6: 变化 | E6: x | F6: 1动作 | G6: 60尺 | H6: × | I6: S | J6: × | K6: × | L6: 立即或1小时 | M6: ·你选择范围内你能看见的，占据5立方尺的非魔法火焰。你以下述方式之一影响此火焰： ·你立刻令火焰在一个方向上蔓延5尺，如同在新位置处有着木头或其他燃料。 ·你立刻熄灭该空间内的火焰。 、 ·你令火焰产生的明亮和微亮区域的范围加倍或减半，和/或改变其颜色。此种变化持续1个小时。 ·你令火焰产生简单的形象——例如一个生物的模糊影像，一个固定的物体，或一个地点——这样的影像出现在火焰中，如你所愿变化着。这样的形象持续1个小时 ·若你多次施放此法术，你可以令至多3个非立刻的效应同时生效，而你可以以一个动作解除上述的效果之一。 | N6: 控火 | O6: Control Flames | R6: √ | U6: √ | W6: √ | AA6: 珊娜萨的万事指南
A7: =施法!J9 -> 隐形术 | B7: 创造篝火 | C7: 0 | D7: 咒法 | E7: x | F7: 1动作 | G7: 60尺 | H7: V | I7: S | J7: × | K7: × | L7: 专注,至多1分钟 | M7: ·你在距离之内你能看到的地面上燃起一堆篝火。直到此法术终结，该魔法篝火会占满5立方尺的空间。当你施放此法术时，所有在篝火所在空间的生物必须通过一次敏捷豁免，否则受到1d8点伤害。当生物在一个回合中第一次进入篝火所在的空间，或在篝火所在的空间结束其回合时，其同样必须进行该豁免。 ·篝火可以点燃区域内未被穿戴或者携带的可燃物体。 ·你到达5级时，该法术的伤害增加1d8（变为2d8）。11级时再加1d8（变为3d8），17级时再加1d8（变为4d8）。 | N7: 创造篝火 | O7: Create Bonfire | R7: √ | U7: √ | V7: √ | W7: √ | X7: √ | AA7: 珊娜萨的万事指南
A8: =施法!J10 -> 人类定身术 | B8: 舞光术 | C8: 0 | D8: 塑能 | E8: x | F8: 1动作 | G8: 120尺 | H8: V | I8: S | J8: M | K8: 一点磷或光榆木，或者一只萤火虫 | L8: 专注,至多1分钟 | M8: ·你在施法距离内创造四个火把大小的光源。法术持续时间内，光源能够以火把，灯笼或光球的形态显现并在空中悬浮。你也可以将四个光源合为一个中型类人生物的模糊光影。无论选择哪种方式，每处光源都可以发出半径10尺的微光光照。 ·你在自己回合可以用一个附赠动作令这些光源在施法距离内移动至多60尺。每个光源必需在另一个光源周边20尺内，而离开施法距离的光源会随即熄灭。 | N8: 舞光术 | O8: Dancing Lights | P8: √ | U8: √ | W8: √ | X8: √ | AA8: 玩家手册
A9: =施法!J11 -> 隐形仆役 | B9: 德鲁伊伎俩 | C9: 0 | D9: 变化 | E9: x | F9: 1动作 | G9: 30尺 | H9: V | I9: S | J9: × | K9: × | L9: 立即 | M9: ·你向自然之魂低语，并创造以下效应之一： →你创造一个微小而无害的感官效应，并以之预报你所在地接下来24小时的天气状况。该效应可表现为一个代表晴空的金球，一朵代表雨天的云彩，代表雪日而飘飞的雪花等等。该效应将持续1轮。 →你可以立即让一朵鲜花绽放，一颗种子破壳，一片叶蕾发芽。 →你创造一个微小而无害的即时感官效应，如落叶，微风，小动物的动静或者臭鼬的微弱气味。该效应只能在5尺的立方空间内起效。 →你可以立即点亮或熄灭一根蜡烛、一把火把或一处小篝火。 | N9: 德鲁伊伎俩 | O9: Druidcraft | R9: √ | AA9: 玩家手册
A10: =施法!J12 -> 修复术 | B10: 魔能爆 | C10: 0 | D10: 塑能 | E10: x | F10: 1动作 | G10: 120尺 | H10: V | I10: S | J10: × | K10: × | L10: 立即 | M10: ·一束激烈的能量射向施法距离内一个生物。对该目标发动一次远程法术攻击，如果命中则该目标受1d10点力场伤害。 ·当你到达更高等级时，该法术还可以同时创造更多的射线：5级时两条，11级时三条，17级时四条。你可以决定这些射线攻击同一个目标或分别攻击不同的目标，且为每束射线分别进行攻击检定。 | N10: 魔能爆 | O10: Eldritch Blast | V10: √ | AA10: 玩家手册
A11: =施法!J13 -> 亡灵召唤术 | B11: 火焰箭 | C11: 0 | D11: 塑能 | E11: x | F11: 1动作 | G11: 120尺 | H11: V | I11: S | J11: × | K11: × | L11: 立即 | M11: ·你对施法距离内一个生物或物件掷出一把火焰，对目标进行一次远程法术攻击。若命中，则目标受到1d10点火焰伤害。未被着装或携带的可燃物件被该法术命中时将被点燃。 ·你到达5级时，该法术的伤害增加1d10（变为2d10）。11级时再加1d10（变为3d10），17级时再加1d10（变为4d10）。 | N11: 火焰箭 | O11: Fire Bolt | U11: √ | W11: √ | X11: √ | AA11: 玩家手册
A12: =施法!J14 -> 法术名 | B12: 交友术 | C12: 0 | D12: 惑控 | E12: x | F12: 1动作 | G12: 自身 | H12: × | I12: S | J12: M | K12: 法术施展时作用于脸部的一些化妆用品 | L12: 专注,至多1分钟 | M12: ·指定一个对你非敌对的生物，你在法术持续时间内对其进行的所有魅力检定均具有优势。当该法术终止时，该生物将意识到你曾使用魔法操弄他的情绪，从而对你的态度转为敌对。此时如果该生物有暴力倾向则会直接对你发动攻击，而非暴力倾向的生物则会寻求其他的报复形式（由DM决定），具体情况视你与其交互时的具体内容而定。 | N12: 交友术 | O12: Friend | P12: √ | U12: √ | V12: √ | W12: √ | AA12: 玩家手册
A13: =施法!J15 -> 0 | B13: 霜噬 | C13: 0 | D13: 塑能 | E13: x | F13: 1动作 | G13: 60尺 | H13: V | I13: S | J13: × | K13: × | L13: 立即 | M13: ·你令距离之内，一个你能看见的生物开始结冰。该目标必须进行一次体质豁免检定。若豁免失败，该目标受到1d6点冷冻伤害，并在其下个回合结束前进行的下一次武器攻击检定中得到劣势。 ·你到达5级时，该法术的伤害增加1d6（变为2d6）。11级时再加1d6（变为3d6），17级时再加1d6（变为4d6）。 | N13: 霜噬 | O13: Frostbite | R13: √ | U13: √ | V13: √ | W13: √ | X13: √ | AA13: 珊娜萨的万事指南
A14: =施法!J16 -> 0 | B14: 翠炎剑 | C14: 0 | D14: 塑能 | E14: x | F14: 1动作 | G14: 自身(5尺半径) | H14: × | I14: S | J14: M | K14: 一把至少价值1sp的近战武器 | L14: 立即 | M14: ·作为施展该法术的一部分，你必须用你的武器对5尺内的一个生物进行一次近战攻击。如果攻击命中，目标受到这次攻击的正常影响，并且翠绿色的火焰将从目标身上跳转至其5尺内的另一个生物。第二个生物受到等于你施法关键属性调整值点火焰伤害。 ·该法术的伤害随着你的等级提升而增加。你到达5级时，这次近战攻击将造成额外1d8火焰伤害，且第二个目标将受到的伤害提升至1d8+你的施法关键属性调整值。两个伤害骰都会在11级时增加1d8（2d8和2d8），17级时再加1d8（3d8和3d8）。 | N14: 翠炎剑 | O14: Green Flame Blade | U14: √ | V14: √ | W14: √ | X14: √ | AA14: 剑湾冒险者指南
A15: =施法!J17 -> 0 | B15: 神导术 | C15: 0 | D15: 预言 | E15: x | F15: 1动作 | G15: 触及 | H15: V | I15: S | J15: × | K15: × | L15: 专注,至多1分钟 | M15: ·你触碰一个自愿的生物。在法术终止前，目标可以选择在一次属性检定时额外掷一粒d4，并将所得数值加入检定结果中。它可以在进行属性检定之前或之后掷骰。法术随后即终止。 | N15: 神导术 | O15: Guidance | Q15: √ | R15: √ | X15: √ | AA15: 玩家手册
A16: =施法!J18 -> 0 | B16: 舞风 | C16: 0 | D16: 变化 | E16: x | F16: 1动作 | G16: 30尺 | H16: V | I16: S | J16: × | K16: × | L16: 立即 | M16: ·在距离内的，你能看到的一点上，空气被你掌握，被迫产生了下述效应之一： ·由你选择的一个中型或更小的生物必须通过一次力量豁免，否则会被你推离5尺。 ·你能制造出小小的空气爆破，足以移动一个未被持握或携带的，不超过5磅的物体。该物体被推离你10尺。以此法产生的力不足以造成伤害。 ·你利用空气制造出无害的感官感受，例如令树叶沙沙作响，令百叶窗闭合，或你的衣服在微风中摆动。 | N16: 舞风 | O16: Gust | R16: √ | U16: √ | W16: √ | AA16: 珊娜萨的万事指南
A17: =施法!J19 -> 0 | B17: 虫群孳生 | C17: 0 | D17: 咒法 | E17: x | F17: 1动作 | G17: 30尺 | H17: V | I17: S | J17: M | K17: 一只活跳蚤 | L17: 立即 | M17: ·你令一个处于距离内、你能看见的生物身上暂时性的出现螨虫、跳蚤、和其他寄生虫。目标必须通过一次体质豁免，否则受到1d6点毒素伤害并且向着一个随机的方向移动5尺，只要它可以移动并且有至少5尺的速度。投1d4决定方向：1，北；2，南；3，东；4，西。这个移动不会提供借机攻击，并且如果移动的方向被阻挡，目标将不会移动。 ·此法术的伤害在你达到5级（2d6），11级（3d6），和17级（4d6）时提高1d6点。 | N17: 虫群孳生 | O17: Infestation | R17: √ | U17: √ | V17: √ | W17: √ | AA17: 珊娜萨的万事指南
A18: =施法!J20 -> 0 | B18: 光亮术 | C18: 0 | D18: 塑能 | E18: x | F18: 1动作 | G18: 触及 | H18: V | I18: × | J18: M | K18: 一只萤火虫或一片磷光苔藓 | L18: 1小时 | M18: ·你触碰一个尺寸在任意方向上都不超过10尺的物件。在法术终止前，物件将在其20尺半径范围内发出明亮光照，并在其外20尺范围发出微光光照。光的颜色由你决定，该物件被不透明的东西完全遮盖时，其光照被遮挡。如果你再次施展该法术，或者使用一个动作解散该法术，则该法术终止。 ·如果你指定敌对生物所持握或着装的一个物件作为目标，则该生物必须进行一次敏捷豁免以尝试摆脱该法术的效应。 | N18: 光亮术 | O18: Light | P18: √ | Q18: √ | U18: √ | W18: √ | X18: √ | AA18: 玩家手册
A19: =施法!J21 -> 0 | B19: 闪电牵引 | C19: 0 | D19: 塑能 | E19: x | F19: 1动作 | G19: 15尺 | H19: V | I19: × | J19: × | K19: × | L19: 立即 | M19: ·你创造出鞭状的闪电能量袭向你15尺内可见的一个生物。目标必须进行一次力量豁免，豁免失败则其以直线被你拉近10尺。如果拉近以后目标在你周围5尺内，那么他将受到1d8点闪电伤害。 ·你到达5级时，该法术的伤害增加1d8（变为2d8）。11级时再加1d8（变为3d8），17级时再加1d8（变为4d8）。 | N19: 闪电牵引 | O19: Lightning Lure | U19: √ | V19: √ | W19: √ | X19: √ | AA19: 剑湾冒险者指南
A20: =施法!J22 -> 0 | B20: 法师之手 | C20: 0 | D20: 咒法 | E20: x | F20: 1动作 | G20: 30尺 | H20: V | I20: S | J20: × | K20: × | L20: 1分钟 | M20: ·一只漂浮的幽灵手出现在施法距离内你指定的一点。幽灵手持续存在至法术终止，或直至你以一个动作解散该法术。如果幽灵手距你的距离超过30尺，或者当你再次施展了该法术时，则现存的幽灵手消失不见。 ·你可以用动作控制幽灵手，并通过幽灵手实现一个行为：你可以操控一个物件，或者打开一扇未上锁的门或容器，或者将一件物品放入容器或从容器中取出，或者将小瓶中的内容物倾倒出来。你每次你使用幽灵手时可以令其移动至多30尺。 ·该幽灵手不能攻击，也不能激活魔法物品或承载超过10磅重的物质。 | N20: 法师之手 | O20: Mage Hand | P20: √ | U20: √ | V20: √ | W20: √ | X20: √ | AA20: 玩家手册
A21: =施法!J23 -> 0 | B21: 魔石 | C21: 0 | D21: 变化 | E21: x | F21: 1附赠动作 | G21: 触及 | H21: V | I21: S | J21: × | K21: × | L21: 1分钟 | M21: ·你接触一到三块小石块，向其中注入魔法的力量。你或其他人可以通过徒手或使用投石索来投掷小石块之一以进行一次远程法术攻击。若徒手投掷，其射程为60尺。若除你之外的其他人使用小石块进行攻击，攻击者在其攻击检定中加上你的施法属性调整值，而非攻击者的。若击中，目标受到1d6+你的施法属性调整值点数点钝击伤害。无论击中与否，在那块石块上的魔法都会消失。 ·若你再次释放此法术，此法术先前释放时，在受到影响的石块上的效果会提前结束。 | N21: 魔石 | O21: Magic Stone | R21: √ | V21: √ | X21: √ | AA21: 珊娜萨的万事指南
A22: =施法!J24 -> 0 | B22: 修复术 | C22: 0 | D22: 变化 | E22: x | F22: 1分钟 | G22: 触及 | H22: V | I22: S | J22: M | K22: 两块天然磁石 | L22: 立即 | M22: ·该法术修复你所触碰一个物件上的一处破损或裂缝，例如修复一条断裂的链条，或者一把碎成两半的钥匙、一件撕裂的斗篷、一个漏了的酒袋等。只要破损或断裂处在任意方向上都不超过1尺，你就可以不留痕迹地修复它。 ·该法术可以从物理上修复一件魔法物品或一个构装体，但不会恢复这类物件上的魔法。 | N22: 修复术 | O22: Mending | P22: √ | Q22: √ | R22: √ | U22: √ | W22: √ | X22: √ | AA22: 玩家手册
A23: =施法!J25 -> 法术名 | B23: 传讯术 | C23: 0 | D23: 变化 | E23: x | F23: 1动作 | G23: 120尺 | H23: V | I23: S | J23: M | K23: 一小段铜线 | L23: 1轮 | M23: ·你用手指指向施法距离内的一个生物并低声说出一段信息。该目标（且只有该目标）会听到这段信息并可以用只有你能听见的低语回复你。 ·你可以隔着固态物件施展该法术，但你必须熟悉法术目标并知晓其就在屏障后方。魔法的沉默，1尺厚的石头，1寸厚的普通金属，一片薄铅片，或者3尺厚的木料都可以阻挡该法术。该法术不需要直线传递信息，它可以自由地转过拐角或穿过孔洞。 | N23: 传讯术 | O23: Message | P23: √ | U23: √ | W23: √ | X23: √ | AA23: 玩家手册
A24: =施法!J26 -> 0 | B24: 心灵之楔 | C24: 0 | D24: 惑控 | E24: x | F24: 1动作 | G24: 60尺 | H24: V | I24: × | J24: × | K24: × | L24: 1轮 | M24: ·你将由灵能塑成的迷惘尖刺打入一个距离内可见生物的心智。目标必须进行一次智力豁免，豁免失败则将受到1d6点心灵伤害，且在你下回合结束前进行的下一次豁免检定中，在结果上减去1d4。 ·这道法术的伤害在你达到特定等级时增加1d6：5级（变为2d6），11级（变为3d6），17级（变为4d6）。 | N24: 心灵之楔 | O24: Mind Sliver | U24: √ | V24: √ | W24: √ | AA24: 塔莎的万象坩埚
A25: =施法!J27 -> 0 | B25: 次级幻影 | C25: 0 | D25: 幻术 | E25: x | F25: 1动作 | G25: 30尺 | H25: × | I25: S | J25: M | K25: 一小块羊毛 | L25: 1分钟 | M25: ·你在施法距离内创造一段声响或一个物件的影像，并使之维持至法术持续时间结束。你也可以用一个动作解除幻象，或者再次施展该法术来终止幻象。 ·如果你创造一段声响，其音量可以是低声耳语也可以是高声尖叫。它可以是你或其他任何人的嗓音，或者是一头狮子的咆哮、一段鼓声以及任何你指定的其它声响。声响在持续时间内不会减弱，或者你也可以于法术终止前在不同的时间段创造几段分散的声响。 ·如果你创造一个物件的影像（比如一把椅子、泥泞的脚印、一个小箱子等），则该物件大小不得大于一个边长5尺的立方体。该影像不具有声音、光亮、味道或任何其他的感官效应。由于影像可以被任何物件所穿透，因此与之进行物理互动时都会揭露其幻象的本质。 ·生物用其动作调查该声响或影像时，必须进行一次对抗该法术豁免DC的智力（调查）检定，检定成功则判断出眼前即是幻象。幻象在看穿它的生物面前会显得模糊不清。 | N25: 次级幻影 | O25: Minor Illusion | P25: √ | U25: √ | V25: √ | W25: √ | AA25: 玩家手册
A26: =施法!J28 -> 0 | B26: 塑土 | C26: 0 | D26: 变化 | E26: x | F26: 1动作 | G26: 30尺 | H26: × | I26: S | J26: × | K26: × | L26: 立即或1小时 | M26: ·你选择距离之内，你能看见的，占满5立方尺空间的一堆泥土或一块岩石。你可以用以下方式之一对其进行改变： ·若你指向一片松散的土壤，你可以立刻挖开它，令其沿着地表行进，被运离到至多5尺之外的地方。这种移动的力量不足以造成伤害。 ·你让泥土或岩石的形状，和/或颜色发生改变，写出文字，画出图案或雕出图纹。这种变化持续1个小时。 ·若你指定的泥土或岩石在地表上，你可以令其成为困难地形。作为另一种选项，你亦可以令已经是困难地形的地表区域成为正常地形。这种变化持续1个小时。 ·若你多次施放此法术，你可以同时维持至多两个非立即的效果生效，你也可以以一个动作解消上述效应之一。 | N26: 塑土 | O26: Mold Earth | R26: √ | U26: √ | W26: √ | AA26: 珊娜萨的万事指南
A27: =施法!J29 -> 0 | B27: 毒气喷溅 | C27: 0 | D27: 咒法 | E27: x | F27: 1动作 | G27: 10尺 | H27: V | I27: S | J27: × | K27: × | L27: 立即 | M27: ·你伸手向施法距离内一个你能看见的生物喷一阵毒气。目标必须进行一次体质豁免，豁免失败则受1d12毒素伤害。 ·你到达5级时，该法术的伤害增加1d12（变为2d12）。11级时再加1d12（变为3d12），17级时再加1d12（变为4d12） | N27: 毒气喷溅 | O27: Poison Spray | R27: √ | U27: √ | V27: √ | W27: √ | X27: √ | AA27: 玩家手册
A28: =施法!J30 -> 0 | B28: 魔法伎俩 | C28: 0 | D28: 变化 | E28: x | F28: 1动作 | G28: 10尺 | H28: V | I28: S | J28: × | K28: × | L28: 至多1小时 | M28: ·该法术是一个初级施法者用来练习的魔法小伎俩。你在施法距离内创造下列魔法效果中的一种： →你创造一个立即生效的，无害的感观效应，比如一束火花，一阵风，微弱音乐或古怪的臭味。 →你立即点燃或熄灭一支蜡烛，一支火把或一小型营火。 →你立即使一个不大于1立方尺的物件变得清洁或肮脏。 →你立即使一个不大于1立方尺的非活体物质变得冰冷、温暖或对其调味，其效应持续1小时。 →你在一个物件或一个表面上创造一块色斑，或者一个记号，又或者一个标志，其效应持续1小时。 →你创造一个巴掌大小的非魔法小玩意或一个虚幻图像，其效应持续到你下回合结束。 ·如果你多次施展该法术，则可以同时维持至多三个不同的非即时效应，并且可以用一个动作解散其中一种效应。 | N28: 魔法伎俩 | O28: Prestidigitation | P28: √ | U28: √ | V28: √ | W28: √ | X28: √ | AA28: 玩家手册
A29: =施法!J31 -> 0 | B29: 原初蛮击 | C29: 0 | D29: 变化 | E29: x | F29: 1动作 | G29: 自身 | H29: × | I29: S | J29: × | K29: × | L29: 立即 | M29: ·你的牙齿或指甲变得长而尖锐，从而准备好发起酸蚀性的打击。对一个处于你周围5尺内的生物进行一次近战法术攻击。命中则目标受到1d10点强酸伤害。在你进行此攻击后，你的牙齿或指甲恢复正常。 ·此法术的伤害在你达到5级（2d10），11级（3d10），和17级（4d10）时提高1d10点。 | N29: 原初蛮击 | O29: Primal Savagery | R29: √ | AA29: 珊娜萨的万事指南
A30: =施法!J32 -> 0 | B30: 燃火术 | C30: 0 | D30: 咒法 | E30: x | F30: 1动作 | G30: 自身 | H30: V | I30: S | J30: × | K30: × | L30: 10分钟 | M30: ·一朵摇曳的火焰出现在你手中。火焰在法术持续时间存在，并且不会伤害你和你的装备。火焰为其周边半径10尺范围内提供明亮光照，以及该范围外10尺的微光光照。法术将在再次施展该法术，或者以一个动作解除法术时终止。 ·此外，你还可以使用火焰发动攻击，并以此终止该法术。施展该法术时，你可以将火焰投向距你30尺内的一个生物，并对其发动一次远程法术攻击，命中时目标将受到1d8点火焰伤害。你也可以在施展法术后的随后回合里以一个动作实现该行为。 ·你到达5级时，该法术的伤害增加1d8（变为2d8）。11级时再加1d8（变为3d8），17级时再加1d8（变为4d8）。 | N30: 燃火术 | O30: Produce Flame | R30: √ | AA30: 玩家手册
A31: =施法!J33 -> 0 | B31: 冷冻射线 | C31: 0 | D31: 塑能 | E31: x | F31: 1动作 | G31: 60尺 | H31: V | I31: S | J31: × | K31: × | L31: 立即 | M31: ·一道冰冷的蓝白色光线朝施法距离内的一个生物射去。你对目标进行一次远程法术攻击。若命中，则目标受到1d8点冷冻伤害，并且在你的下一回合开始前速度减少10尺。 ·你到达5级时，该法术的伤害增加1d8（变为2d8）。11级时再加1d8（变为3d8），17级时再加1d8（变为4d8）。 | N31: 冷冻射线 | O31: Ray of Frost | U31: √ | W31: √ | X31: √ | AA31: 玩家手册
A32: =施法!J34 -> 0 | B32: 提升抗性 | C32: 0 | D32: 防护 | E32: x | F32: 1动作 | G32: 触及 | H32: V | I32: S | J32: M | K32: 一件微型斗篷 | L32: 专注,至多1分钟 | M32: ·你触碰一个自愿的生物。在法术终止前，目标可以选择在一次豁免检定时额外掷一粒d4，并将所得数值加入检定结果中。他可以在进行豁免检定之前或之后掷骰。法术随后即终止。 | N32: 提升抗性 | O32: Resistance | Q32: √ | R32: √ | X32: √ | AA32: 玩家手册
A33: =施法!J35 -> 0 | B33: 圣火术 | C33: 0 | D33: 塑能 | E33: x | F33: 1动作 | G33: 60尺 | H33: V | I33: S | J33: × | K33: × | L33: 立即 | M33: ·如同火焰般的辉光向施法距离内你能看见的一个生物倾泻而下。目标必须要进行一次敏捷豁免，豁免失败则受到1d8点光耀伤害。目标在这次豁免检定中无法获得掩护的增益。 ·你到达5级时，该法术的伤害增加1d8（变为2d8）。11级时再加1d8（变为3d8），17级时再加1d8（变为4d8）。 | N33: 圣火术 | O33: Sacred Flame | Q33: √ | AA33: 玩家手册
A34: =施法!J36 -> 法术名 | B34: 削弱芒刺 | C34: 0 | D34: 死灵 | E34: x | F34: 1动作 | G34: 30尺 | H34: V | I34: S | J34: × | K34: × | L34: 立即 | M34: ·你削弱施法距离内一个你看得见的生物的生命活力。目标必须通过一个体质豁免，否则就会受到1d4点黯蚀伤害并且倒地。 ·该法术的伤害会在你到达5级（2d4），11级（3d4）与17级（4d4）时增加1d4. | N34: 削弱芒刺 | O34: Sapping Sting | Y34: √ | Z34: √ | AA34: 荒洲探险家指南
A35: =施法!J37 -> 0 | B35: 操水 | C35: 0 | D35: 变化 | E35: x | F35: 1动作 | G35: 30尺 | H35: × | I35: S | J35: × | K35: × | L35: 立即或1小时 | M35: ·你选定距离之内，你能看见的一处占据5立方尺的水体。你能以下述方式之一来对其进行操控： ·你立即在你选定的方向上，造成或改变水的流动，至多在任意方向上改变5尺。此种运动的力量不足以造成伤害。 ·你令水体呈现出简单的形状，随你的意愿而运动。这种变化持续1个小时。 ·你改变了水体的颜色或透明度。水体必须被整体性的改变。此种变化持续1个小时。 ·你冻结了水，只要其中没有生物。水会在1小时内解冻。 ·若你多次施放此法术，你可以同时维持至多两个非立即的效果生效，你也可以以一个动作解消上述效应之一。 | N35: 操水 | O35: Shape Water | R35: √ | U35: √ | W35: √ | AA35: 珊娜萨的万事指南
A36: =施法!J38 -> 0 | B36: 橡棍术 | C36: 0 | D36: 变化 | E36: x | F36: 1附赠动作 | G36: 触及 | H36: V | I36: S | J36: M | K36: 一些槲寄生，一片三叶草的叶子和一根短棒或木杖 | L36: 1分钟 | M36: ·你将自然之力灌入手中持握的一根短棒或木杖中。你在法术持续时间内使用该武器进行近战攻击时可以用你的施法关键属性代替力量值来进行攻击检定和伤害掷骰，且该武器的伤害骰变为d8。另外，如果该武器原来不是魔法武器，则它将变成魔法武器。你再次施展该法术或丢掉该武器时，该法术将随之终止。 | N36: 橡棍术 | O36: Shillelagh | R36: √ | AA36: 玩家手册
A37: =施法!J39 -> 0 | B37: 电爪 | C37: 0 | D37: 塑能 | E37: x | F37: 1动作 | G37: 触及 | H37: V | I37: S | J37: × | K37: × | L37: 立即 | M37: ·你的手上发出闪电，并对你触碰的一个生物发动电击。对目标发动一次近战法术攻击。如果目标穿着金属护甲，则你进行该检定时具有优势。若命中，则目标受到1d8点闪电伤害，并且在其下一回合开始前不能执行任何反应。 ·你到达5级时，该法术的伤害增加1d8（变为2d8）。11级时再加1d8（变为3d8），17级时再加1d8（变为4d8）。 | N37: 电爪 | O37: Shocking Grasp | U37: √ | W37: √ | X37: √ | AA37: 玩家手册
A38: =施法!J40 -> 0 | B38: 维生术 | C38: 0 | D38: 死灵 | E38: x | F38: 1动作 | G38: 触及 | H38: V | I38: S | J38: × | K38: × | L38: 立即 | M38: ·你触碰一个生命值为0的活体生物，使该生物的伤势立刻稳定下来。该法术对不死生物和构装生物无效。 | N38: 维生术 | O38: Spare the Dying | Q38: √ | X38: √ | AA38: 玩家手册
A39: =施法!J41 -> 0 | B39: 剑刃爆发 | C39: 0 | D39: 咒法 | E39: x | F39: 1动作 | G39: 自身(5尺半径) | H39: V | I39: × | J39: × | K39: × | L39: 立即 | M39: ·你在瞬间制造出一圈半透明的利刃清扫你的周围。法术范围内除你以外的每一个生物都必须成功通过一次敏捷豁免，否则将受到1d6点力场伤害。 ·你到达5级时，该法术的伤害增加1d6（变为2d6）。11级时再加1d6（变为3d6），17级时再加1d6（变为4d6）。 | N39: 剑刃爆发 | O39: Sword Burst | U39: √ | V39: √ | W39: √ | X39: √ | AA39: 剑湾冒险者指南
A40: =施法!J42 -> 0 | B40: 奇术 | C40: 0 | D40: 变化 | E40: x | F40: 1动作 | G40: 30尺 | H40: V | I40: × | J40: × | K40: × | L40: 至多1分钟 | M40: ·你在施法距离内展示出一个低级奇观，以表现你的超自然力。你在施法距离内创造出下列魔法效应之一： →你的声音在1分钟内变得比常人响两倍。 →你在1分钟内使一团火焰闪烁，变亮，变暗或变色。 →你使地面震动1分钟（完全无害）。 →你使某种声音自施法距离内一点瞬间发出，例如雷鸣声，鸦叫声或不祥的低语声。 →你使一扇没有锁上的门或窗瞬间打开或关上。 →你在1分钟内改变自己眼睛的颜色。 ·多次施展该法术时，你可以同时维持最多三个持续1分钟的效应。你也可以用一个动作驱散其中一种效应。 | N40: 奇术 | O40: Thaumaturgy | Q40: √ | AA40: 玩家手册
A41: =施法!J43 -> 0 | B41: 荆棘之鞭 | C41: 0 | D41: 变化 | E41: x | F41: 1动作 | G41: 30尺 | H41: V | I41: S | J41: M | K41: 一根来自带刺植物的茎干 | L41: 立即 | M41: ·你创造出一条藤蔓般的带刺长鞭，并猛抽向施法距离内一个你指定的生物。对目标进行一次近战法术攻击，如果命中，则目标受到1d6点穿刺伤害，如果目标生物为大型或更小体型，则其将朝你所在位置拉近至多10尺。 ·你到达5级时，该法术的伤害增加1d6（变为2d6）。11级时再加1d6（变为3d6），17级时再加1d6（变为4d6）。 | N41: 荆棘之鞭 | O41: Thorn Whip | R41: √ | X41: √ | AA41: 玩家手册
A42: =施法!J44 -> 0 | B42: 鸣雷破 | C42: 0 | D42: 塑能 | E42: x | F42: 1动作 | G42: 5尺 | H42: × | I42: S | J42: × | K42: × | L42: 立即 | M42: ·你制造出雷鸣巨响，可以在100尺范围内被听到。除你之外，在你周围5尺范围内的生物必须进行一次体质豁免。若豁免失败，该生物受到1d6点雷鸣伤害。 ·你到达5级时，该法术的伤害增加1d6（变为2d6）。11级时再加1d6（变为3d6），17级时再加1d6（变为4d6）。 | N42: 鸣雷破 | O42: Thunderclap | P42: √ | R42: √ | U42: √ | V42: √ | W42: √ | X42: √ | AA42: 珊娜萨的万事指南
A43: =施法!J45 -> 0 | B43: 亡者丧钟 | C43: 0 | D43: 死灵 | E43: x | F43: 1动作 | G43: 60尺 | H43: V | I43: S | J43: × | K43: × | L43: 立即 | M43: ·你指向一个处于距离内、你能看见的生物，一阵哀痛的铃声在空中鸣响。目标必须通过一次感知豁免，否则受到1d8点黯蚀伤害。若目标失去了任何量的生命值，它改为受到1d12点黯蚀伤害。 ·此法术的伤害在你达到5级（2d8或2d12），11级（3d8或3d12），和17级（4d8或4d12）时提高一个伤害骰。 | N43: 亡者丧钟 | O43: Toll the Dead | Q43: √ | V43: √ | W43: √ | AA43: 珊娜萨的万事指南
A44: =施法!J46 -> 0 | B44: 克敌先机 | C44: 0 | D44: 预言 | E44: x | F44: 1动作 | G44: 30尺 | H44: × | I44: S | J44: × | K44: × | L44: 专注,至多1轮 | M44: ·你伸出手并以手指指向施法距离内的一个生物，并以魔力刹那间看穿目标的防御。如果该法术还未终止，则你在自己的下一回合里，对该目标发动的第一次攻击检定具有优势。 | N44: 克敌先机 | O44: True Strike | P44: √ | U44: √ | V44: √ | W44: √ | AA44: 玩家手册
A45: =施法!J47 -> 法术名 | B45: 恶言相加 | C45: 0 | D45: 惑控 | E45: x | F45: 1动作 | G45: 60尺 | H45: V | I45: × | J45: × | K45: × | L45: 立即 | M45: ·你对施法距离内一个你能看见的生物连珠炮式的说出一串蕴涵魔力的咒骂。如果目标能听见你说话（不一定要听懂），它就必须要进行一次感知豁免，豁免失败则将受到1d4点心灵伤害，其下一回合结束前进行第一次攻击检定具有劣势。 ·你到达5级时，该法术的伤害增加1d4（变为2d4）。11级时再加1d4（变为3d4），17级时再加1d4（变为4d4）。 | N45: 恶言相加 | O45: Vicious Mockery | P45: √ | AA45: 玩家手册
A46: =施法!J48 -> 0 | B46: 光耀祷言 | C46: 0 | D46: 塑能 | E46: x | F46: 1动作 | G46: 5尺 | H46: V | I46: × | J46: M | K46: 一块圣徽 | L46: 立即 | M46: ·你念出神圣的词语，灼热的光辉随之喷薄而出。每个你选择的、处于你周围5尺内、你能看见的生物必须通过一次体质豁免检定，否则受到1d6点光耀伤害。 ·此法术的伤害在你达到5级（2d6），11级（3d6），和17级（4d6）时提高1d6点。 | N46: 光耀祷言 | O46: Word of Radiance | Q46: √ | AA46: 珊娜萨的万事指南
A47: =施法!J49 -> 0 | B47: 吸收元素 | C47: 1 | D47: 防护 | E47: x | F47: 1反应，于你受到强酸、冷冻、火焰、闪电、或雷鸣伤害时进行 | G47: 自身 | H47: × | I47: S | J47: × | K47: × | L47: 1轮 | M47: ·此法术捕获了部分袭来的能量，减轻它对你的效果，并将之储存起来以用在你的下一次近战攻击中。在你的下个回合的开始之前，你对于触发法术的伤害类型具有抗性。此外，在你的下个回合，第一次以近战攻击命中时，目标额外受到1d6点触发法术的伤害类型的伤害，同时此法术终结。 ·升环施法效应。当你使用2环或更高的法术位施放该法术时，使用的法术位每高一环，额外伤害便增加1d6。 | N47: 吸收元素 | O47: Absorb Elements | R47: √ | T47: √ | U47: √ | W47: √ | X47: √ | AA47: 珊娜萨的万事指南
A48: =施法!J50 -> 0 | B48: 警报术 | C48: 1 | D48: 防护 | E48: √ | F48: 1分钟 | G48: 30尺 | H48: V | I48: S | J48: M | K48: 一个小铃铛和一小段银线 | L48: 8小时 | M48: ·你针对不速之客设置一个警报。在施法距离内指定一扇门窗或选择一个边长不大于20尺的立方区域。在法术持续时间内，任何触碰或进入目标区域的微型或更大体型生物都会触发警报。施法时，你可以决定哪些生物不会触发警报，还可以选择警报方式为声音警报或是精神警报。 ·如果你选择精神警报，且警报触发时你距离目标区域不超过1里，则你的意念里会传来“乒”的警报声。如果你在睡觉，则警报将使你惊醒。 ·如果你选择声音警报，则警报触发时其60尺范围内将响起持续10秒摇铃声。 | N48: 警报术 | O48: Alarm | T48: √ | W48: √ | X48: √ | AA48: 玩家手册
A49: =施法!J51 -> 0 | B49: 化兽为友 | C49: 1 | D49: 惑控 | E49: x | F49: 1动作 | G49: 30尺 | H49: V | I49: S | J49: M | K49: 一点食物 | L49: 24小时 | M49: ·该法术帮你让一只野兽相信你并无恶意。在施法距离内指定一只你能看见的野兽，而它也必须能看见你且能听到你的声音。该野兽必须进行一次感知豁免，豁免失败则将在法术持续时间内被你魅惑。如果它的智力为４或更高则法术直接失败。如果你或你的同伴对目标造成伤害，则法术终止。 ·升环施法效应。使用２环或更高法术位施展该法术时，你使用的法术位每比１环高一环，就可以多选择一个野兽作为目标。 | N49: 化兽为友 | O49: Animal Friendship | P49: √ | R49: √ | T49: √ | AA49: 玩家手册
A50: =施法!J52 -> 0 | B50: 艾嘉西斯之铠 | C50: 1 | D50: 防护 | E50: x | F50: 1动作 | G50: 自身 | H50: V | I50: S | J50: M | K50: 一杯水 | L50: 1小时 | M50: ·防护性的魔法力量环绕着你，凝聚成覆盖着你和你的装备表面上一层魅影般的凝霜。 ·你在法术持续时间内获得５点临时生命值。如果有生物在你拥有这些临时生命值时以近战攻击命中你，则该生物将受到５点冷冻伤害。 ·升环施法效应。使用２环或更高法术位施展该法术时，你使用的法术位每比１环高一环，临时生命和冷冻伤害就各增加５点。 | N50: 艾嘉西斯之铠 | O50: Armor of Agathys | V50: √ | AA50: 玩家手册
A51: =施法!J53 -> 0 | B51: 哈达之臂 | C51: 1 | D51: 咒法 | E51: x | F51: 1动作 | G51: 自身(10尺半径) | H51: V | I51: S | J51: × | K51: × | L51: 立即 | M51: ·你祈求“乌黯之饥渴 the Dark Hunger”，哈达 Hadar 的力量。黑暗能量构成的触须从你身上蔓延而出并痛击10尺内的所有生物。范围内的所有生物都必须进行一次力量豁免，豁免失败者将受到2d6点黯蚀伤害，并其下一回合前都无法执行反应。豁免成功的生物伤害减半，且不受其他效应的影响。 ·升环施法效应。使用２环或更高法术位施展该法术时，你使用的法术位每比１环高一环，法术的伤害就增加1d6。 | N51: 哈达之臂 | O51: Arms of Hadar | V51: √ | AA51: 玩家手册
A52: =施法!J54 -> 0 | B52: 灾祸术 | C52: 1 | D52: 惑控 | E52: x | F52: 1动作 | G52: 30尺 | H52: V | I52: S | J52: M | K52: 一滴血 | L52: 专注,至多1分钟 | M52: ·指定施法距离内至多三个你能看见的生物，并迫使其进行一次魅力豁免。豁免失败者直至法术终止前，在每当进行攻击检定或豁免检定时，必须从投骰结果中减去一个d4。 ·升环施法效应。使用2环或更高法术位施展该法术时，你使用的法术位每比1环高一环，就能多指定一个目标。 | N52: 灾祸术 | O52: Bane | P52: √ | Q52: √ | AA52: 玩家手册
A53: =施法!J55 -> 0 | B53: 兽之联结 | C53: 1 | D53: 预言 | E53: x | F53: 1动作 | G53: 触及 | H53: V | I53: S | J53: M | K53: 一小块被布包裹的毛皮 | L53: 专注,至多10分钟 | M53: ·你和一个你接触的，对你友好或被你魅惑的野兽建立起一道心灵链接。若该野兽的智力不低于4，则此法术失败。直到法术终结，只要你和该野兽相互处于彼此的视觉线内，此链接便处于活动状态。通过此链接，该野兽可以理解你以心灵感应传递的信息，而其也会以心灵感应向你传递其基本的情绪和意愿。只要此链接处于激活状态，该野兽在对你周围5尺，你能看见的任何生物所进行的攻击检定中获得优势。 | N53: 兽之联结 | O53: Beast Bond | R53: √ | T53: √ | AA53: 珊娜萨的万事指南
A54: =施法!J56 -> 0 | B54: 祝福术 | C54: 1 | D54: 惑控 | E54: x | F54: 1动作 | G54: 30尺 | H54: V | I54: S | J54: M | K54: 一钵圣水 | L54: 专注,至多1分钟 | M54: ·你用言语祝福施法距离内至多三个生物。在法术终止前，每当受术目标进行攻击检定或豁免检定时，可以额外掷一次d4并加在其结果上。 ·升环施法效应。使用2环或更高法术位施展该法术时，你使用的法术位每比1环高一环，就可以多指定一个目标。 | N54: 祝福术 | O54: Bless | Q54: √ | S54: √ | AA54: 玩家手册
A55: =施法!J57 -> 0 | B55: 燃烧之手 | C55: 1 | D55: 塑能 | E55: x | F55: 1动作 | G55: 自身(15尺锥状) | H55: V | I55: S | J55: × | K55: × | L55: 立即 | M55: ·你双手拇指相对，其他手指张开，一道火焰随即从手指间喷出。处于15尺锥状区域内的生物必须进行一次敏捷豁免。豁免失败者受到3d6 点火焰伤害，豁免成功则伤害减半。 ·该法术的火焰会点燃范围内未被着装或携带的可燃物。 ·升环施法效应。使用2环或更高法术位施展该法术时，你使用的法术位每比1环高一环，法术的伤害就增加1d6。 | N55: 燃烧之手 | O55: Burning Hand | U55: √ | W55: √ | AA55: 玩家手册
A56: =施法!J58 -> 法术名 | B56: 弹射 | C56: 1 | D56: 变化 | E56: x | F56: 1动作 | G56: 60尺 | H56: × | I56: S | J56: × | K56: × | L56: 立即 | M56: ·选择距离之内，一个未被穿戴或持握的，重量为1到5磅的物体。此目标在你选择的一个方向上以直线轨迹飞行，在落到地面前至多行进90尺，若其在此过程中撞击到了固体表面则会提前停止运动。若该物体将会撞击一个生物，该生物必须进行一次敏捷豁免检定，豁免失败该物体击中该生物并不再移动。目标被击中后，它与该物体各受到3d8点钝击伤害。 ·升环施法效应。当你使用2环或更高的法术位施放该法术时，使用的法术位每高一环，你可以指定的物体的重量上限便增加5磅，而造成的伤害便提高1d8。 | N56: 弹射 | O56: Catapult | U56: √ | W56: √ | X56: √ | AA56: 珊娜萨的万事指南
A57: =施法!J59 -> 0 | B57: 造成恐惧 | C57: 1 | D57: 死灵 | E57: x | F57: 1动作 | G57: 60尺 | H57: V | I57: × | J57: × | K57: × | L57: 专注,至多1分钟 | M57: ·你唤醒了一个处于距离内、你能看见的生物内心的凡性。此法术对于构装生物或不死生物无效。目标必须通过一次感知豁免检定，否则在持续时间内陷入恐慌状态。被恐惧的生物可以在它的每个回合结束时重复进行这个豁免检定，若成功将结束法术对自身的效果。 ·升环施法效应。当你使用2环或更高的法术位施放该法术时，使用的法术位每高一环，你就可以多指定一个额外生物作为目标。每个被你指定的生物相互之间的距离必须在30尺内。 | N57: 造成恐惧 | O57: Cause Fear | V57: √ | W57: √ | AA57: 珊娜萨的万事指南
A58: =施法!J60 -> 0 | B58: 典礼术 | C58: 1 | D58: 防护 | E58: √ | F58: 1小时 | G58: 触及 | H58: V | I58: S | J58: M | K58: 至少价值25gp的银粉，作为此法术的耗材 | L58: 立即 | M58: ·你进行几种宗教典礼之一。当你施展此法术时，选择下述典礼之一，其目标必须在施法过程中处于你周围10尺内。 ·赎罪Atonement：你接触一个阵营发生了改变的自愿生物，而你进行一次DC20的感知（洞悉）检定。成功则你令目标恢复其原始阵营。 ·祝福圣水Bless Water：你接触一瓶水并将它转变为圣水。 ·成人礼Coming of Age：你接触一个年龄足够成年的类人生物。在接下来的24小时内，当目标进行一次属性检定时，它可以投d4并将投出的结果加到属性检定上。一个生物只能从此仪式中获得此增益一次。 ·献身Dedication：你接触一个自愿转变为你的宗教的信仰或想要为你信奉的神明服务的类人生物。在接下来的24小时内，当目标进行一次豁免检定时，它可以投d4并将投出的结果加到检定上。一个生物只能从此仪式中获得此增益一次。 ·葬礼Funeral Rite：你祝福一具处于你周围5尺内的尸体。在接下来的7天内，目标不能被任何弱于祈愿术wish的方式变为不死生物。 ·婚礼Wedding：你接触自愿接受婚姻的束缚的成年类人生物。在接下来的7天内，每个目标若处于彼此30尺范围内，则在AC上获得+2加值。一个生物只有在丧偶时才能再次从这个仪式中受益。 | N58: 典礼术 | O58: Ceremony | Q58: √ | S58: √ | AA58: 珊娜萨的万事指南
A59: =施法!J61 -> 0 | B59: 混乱箭 | C59: 1 | D59: 塑能 | E59: x | F59: 1动作 | G59: 120尺 | H59: V | I59: S | J59: × | K59: × | L59: 立即 | M59: ·你向着距离内的一个生物掷出一团变化不定、高声尖鸣的混乱能量。对目标进行一次远程法术攻击。击中时，目标受到2d8+1d6点伤害。选择一颗d8投出的数字来决定它的伤害类型：1强酸，2冷冻，3火焰，4力场，5闪电，6毒素，7精神，8雷鸣。 ·若你的两颗d8投出了相同的数字，混乱能量将从目标跳跃到一个由你选择的、处于它周围30尺内的其他生物上。对新目标进行一次新的攻击检定，进行新的伤害检定，这次伤害检定也可能令混沌能量跳跃。 ·一个生物只能被此混乱箭选作目标一次。 ·升环施法效应。当你使用2环或更高的法术位施展此法术时，每个生物受到额外伤害，类型与投出的一致。额外伤害等于高于1环的每个等级1d6点。 | N59: 混乱箭 | O59: Chaos Bolt | U59: √ | AA59: 珊娜萨的万事指南
A60: =施法!J62 -> 0 | B60: 魅惑人类 | C60: 1 | D60: 惑控 | E60: x | F60: 1动作 | G60: 30尺 | H60: V | I60: S | J60: × | K60: × | L60: 1小时 | M60: ·你尝试魅惑施法距离内的某个你能看见的类人生物。该生物必须进行一次感知豁免。如果你或你的同伴正在和该生物战斗，则该生物进行该豁免时具有优势。如果豁免失败，则该生物被你魅惑至法术终止，或者直到你或你的同伴对他做出伤害行为为止。此间，被魅惑的生物将视你为友方且熟悉的人。法术终止后，该生物将会发觉曾被你魅惑过。 ·升环施法效应。使用2环或更高法术位施展该法术时，你使用的法术位每比1环高一环，法术就能多影响一个目标。而各目标之间距离不能超过30尺。 | N60: 魅惑人类 | O60: Charm Person | P60: √ | R60: √ | U60: √ | V60: √ | W60: √ | AA60: 玩家手册
A61: =施法!J63 -> 0 | B61: 繁彩球 | C61: 1 | D61: 塑能 | E61: x | F61: 1动作 | G61: 90尺 | H61: V | I61: S | J61: M | K61: 一枚至少价值50gp的钻石 | L61: 立即 | M61: ·你向施法距离内某个你能看见的生物掷出一颗直径4寸的能量球，并从强酸、冷冻、火焰、闪电、毒素、雷鸣中选择一种类型以对该生物发动一次远程法术攻击。攻击命中时，该生物将受到3d8点你所选类型的伤害。 ·升环施法效应。使用２环或更高法术位施展该法术时，你使用的法术位每比１环高一环，法术的伤害就增加1d8。 | N61: 繁彩球 | O61: Chromatic Orb | U61: √ | W61: √ | AA61: 玩家手册
A62: =施法!J64 -> 0 | B62: 七彩喷射 | C62: 1 | D62: 幻术 | E62: x | F62: 1动作 | G62: 自身(15尺锥状) | H62: V | I62: S | J62: M | K62: 一撮粉末或沙子，其颜色必须包含红、黄、蓝三色 | L62: 1轮 | M62: ·炫目的彩光从你指间散射而出。掷一次6d10；其结果为受该法术影响生物的生命值总数。在以你为源点的15尺锥状区域内的生物以剩余生命值由小至大的顺序受法术影响（生效时忽略昏迷生物和不能视物的生物）。 ·计算受法术影响生物时，从剩余生命值最低的生物开始逐个计算。每个受术生物均陷入目盲，直至法术终止。法术掷骰的生命值总数减去一个受术生物的生命值后，余数再用以计算生命值稍高者是否受法术影响。生物剩余生命值，必须小于等于该余数法术才能成功影响该生物。 ·升环施法效应。使用2环或更高法术位施展该法术时，你使用的法术位每比1环高一环，法术的掷骰时就增加2d10。 | N62: 七彩喷射 | O62: Color Spray | U62: √ | W62: √ | AA62: 玩家手册
A63: =施法!J65 -> 0 | B63: 命令术 | C63: 1 | D63: 惑控 | E63: x | F63: 1动作 | G63: 60尺 | H63: V | I63: × | J63: × | K63: × | L63: 1轮 | M63: ·你对施法距离内一个你能看见的生物说出一个单词的命令。目标生物必须成功通过一次感知豁免，否则必须在其自己的下一回合服从该命令行事。如果目标为不死生物或目标无法听懂你的语言，又或者你的命令对其直接构成损害，则该法术无效。 ·以下列出一些通常可用的命令单词及其效果。你也可以说出此处没有列明的单词命令，并由DM决定目标将如何行动。如果目标无法完成你的命令，则法术终止。 →过来 Approach：目标以最短最直接的路线向你移动，并在到达距你5尺时结束其回合。 →放下 Drop：目标放下手中持握物并结束其回合。 →走开 Flee：目标在其回合内以最快最有效的方式远离你。 →趴下 Grovel：目标趴下倒地并结束其回合。 →立定 Halt：目标不移动且不作任何动作。飞行生物在原地悬浮（如果它可以这么做）。如果它必须移动才能保持在空中，则其移动最小的距离以保持飞行。 ·升环施法效应。使用2环或更高法术位施展该法术时，你使用的法术位每比1环高一环，法术就能多影响一个目标。而各目标之间距离不能超过30尺。 | N63: 命令术 | O63: Command | Q63: √ | S63: √ | AA63: 玩家手册
A64: =施法!J66 -> 0 | B64: 强令对决 | C64: 1 | D64: 惑控 | E64: x | F64: 1附赠动作 | G64: 30尺 | H64: V | I64: × | J64: × | K64: × | L64: 专注,至多1分钟 | M64: ·你尝试强令一个生物与你决斗。指定施法距离内一个你能看见的生物作为法术的目标。该生物必须进行一次感知豁免，豁免失败则该生物将被你的神圣要求所吸引。在法术持续时间内，该生物对除你之外任何生物发动攻击检定时都具有劣势，并且每当其试图移动至与你相距超过30尺的距离时，都必须进行一次感知豁免。豁免成功则该目标的移动本回合内暂时不受该魔法限制。 ·当你攻击另一个生物时，或者当你对另一个敌对生物施展法术时，又或者当一个你的友方生物对该目标造成伤害或者对其施展伤害性法术时，又或者你在距离该目标超过30 尺的位置结束你的回合时，该法术终止。 | N64: 强令对决 | O64: Compelled Duel | S64: √ | AA64: 玩家手册
A65: =施法!J67 -> 0 | B65: 通晓语言 | C65: 1 | D65: 预言 | E65: √ | F65: 1动作 | G65: 自身 | H65: V | I65: S | J65: M | K65: 一撮煤灰和一撮盐 | L65: 1小时 | M65: ·你在法术持续时间内知晓你所听到所有语言的字面意义。你也可以通过触碰书写的文字来读懂其字面意义。以这种方式阅读每页文字需要花费1分钟的时间。 ·某些文字或图形的密语（比如一个奥秘符文）由于不属于书写语言一类所以无法用此法术破译。 | N65: 通晓语言 | O65: Comprehend Language | P65: √ | U65: √ | V65: √ | W65: √ | AA65: 玩家手册
A66: =施法!J68 -> 0 | B66: 造水_枯水术 | C66: 1 | D66: 变化 | E66: x | F66: 1动作 | G66: 30尺 | H66: V | I66: S | J66: M | K66: 造水为一滴水，枯水为一点谷物或沙子 | L66: 立即 | M66: ·你施法创造水或者使水枯竭。 ·造水 Create Water：你在施法距离内一个打开的容器里创造10加仑干净的水。或以降雨的方式在施法距离内一处30尺的立方区域降下等量水分并浇灭区域内不受遮盖的火苗。 ·枯水 Destroy Water：你使施法距离内一个打开的容器里的10加仑水分枯竭不见。或者使施法距离内一片30尺立方区域的浓雾消失不见。 ·升环施法效应。使用2环或更高法术位施展该法术时，你使用的法术位每比1环高一环，法术就多创造或枯竭10加仑额外的水分，或者影响的立方区域边长增加5尺。 | N66: 造水_枯水术 | O66: Create or Destroy Water | Q66: √ | R66: √ | AA66: 玩家手册
A67: =施法!J69 -> 法术名 | B67: 疗伤术 | C67: 1 | D67: 塑能 | E67: x | F67: 1动作 | G67: 触及 | H67: V | I67: S | J67: × | K67: × | L67: 立即 | M67: ·一个你触碰的生物恢复特定数值的生命值，其恢复量等于1d8＋你的施法关键属性调整值。该法术对不死生物和构装生物无效。 ·升环施法效应。使用2环或更高法术位施展该法术时，你使用的法术位每比1环高一环，恢复量就增加1d8。 | N67: 疗伤术 | O67: Cure Wounds | P67: √ | Q67: √ | R67: √ | S67: √ | T67: √ | X67: √ | AA67: 玩家手册
A68: =施法!J70 -> 0 | B68: 侦测善恶 | C68: 1 | D68: 预言 | E68: x | F68: 1动作 | G68: 自身 | H68: V | I68: S | J68: × | K68: × | L68: 专注,至多10分钟 | M68: ·你在法术持续时间内能感觉到身边30尺内出现的任一异怪、天界生物、元素生物、精类生物、邪魔或不死生物的存在，并掌握其具体位置。另外，你也可以知晓30尺内的物件或地点是否被祝福或亵渎。 ·该法术可以穿透大多障碍，但仍会被1尺厚石质或1寸厚金属质，或一层薄铅质，或3尺厚木质或泥质材料阻隔。 | N68: 侦测善恶 | O68: Detect Evil and Good | Q68: √ | S68: √ | AA68: 玩家手册
A69: =施法!J71 -> 0 | B69: 侦测魔法 | C69: 1 | D69: 预言 | E69: √ | F69: 1动作 | G69: 自身 | H69: V | I69: S | J69: × | K69: × | L69: 专注,至多10分钟 | M69: · 你在法术持续时间内能感测到30尺内存在的魔法。感测到魔法的存在后，你可以使用动作，来看到任何你能看见的生物或物件周围微弱的灵光，并分辨出其所属的魔法学派（若有）。 ·该法术可以穿透大部分障碍，但仍会被1尺厚石质，或1寸厚金属质，或一层薄铅质，或3尺厚木质或泥质材料阻隔。 | N69: 侦测魔法 | O69: Detect Magic | P69: √ | Q69: √ | R69: √ | S69: √ | T69: √ | U69: √ | W69: √ | X69: √ | AA69: 玩家手册
A70: =施法!J72 -> 0 | B70: 侦测毒性和疾病 | C70: 1 | D70: 预言 | E70: √ | F70: 1动作 | G70: 自身 | H70: V | I70: S | J70: M | K70: 一片红豆杉叶 | L70: 专注,至多10分钟 | M70: ·你在法术持续时间内可以感测并定位30尺内的毒素、有毒生物以及疾病。你还可以判断所感测毒素、毒物或疾病的具体类别。 ·该法术可以穿透大部分障碍，但仍会被1尺厚石质，或1寸厚金属质，或一层薄铅质，或3尺厚木质或泥质材料阻隔。 | N70: 侦测毒性和疾病 | O70: Detect Poison and Disease | Q70: √ | R70: √ | S70: √ | T70: √ | AA70: 玩家手册
A71: =施法!J73 -> 0 | B71: 易容术 | C71: 1 | D71: 幻术 | E71: x | F71: 1动作 | G71: 自身 | H71: V | I71: S | J71: × | K71: × | L71: 1小时 | M71: ·你改变自身以及随身的衣物、护甲、武器等所有物。该效应在法术终止或你使用动作主动解除时结束。肉眼看来你的身高可以有1尺的增减，体态可胖可瘦可匀称。但是你不能改变身体的形状，所以你变形的样子必须有四肢或类似的生理结构。此外，幻术的影响范围由你决定。 ·此法术产生的变化无法应对物理检查。比如，你用此法术添了一顶帽子，那么现实物件会从帽子穿过去，且任何触碰帽子的人将摸不到任何东西或者摸到的是你的头和头发。如果你用该法术让自己变得消瘦，而某个人用手摸到你时，他的手看起来就像摸着空气。 ·如果一个生物想要分辨你是否易容，则必须使用一个动作揭露你的伪装，并进行一次智力（调查）检定以对抗你的法术豁免DC。 | N71: 易容术 | O71: Disguise Self | P71: √ | U71: √ | W71: √ | X71: √ | AA71: 玩家手册
A72: =施法!J74 -> 0 | B72: 不谐低语 | C72: 1 | D72: 惑控 | E72: x | F72: 1动作 | G72: 60尺 | H72: V | I72: × | J72: × | K72: × | L72: 立即 | M72: ·你指定一个施法距离内能够听到你声音的生物，并对其说出只有他能听到的不谐低语，使其受强烈的痛苦折磨。目标必须进行一次感知豁免。豁免失败则受到3d6点心灵伤害，并立即执行反应往远离你的方向移动其速度所允许的距离。该生物不会进入明显危险的地域，如火堆或陷坑。豁免成功则伤害减半，且不会执行远离的反应。陷入耳聋状态的目标，进行该豁免时直接判定为成功。 ·升环施法效应。使用2环或更高法术位施展该法术，你使用的法术位每比1环高一环，伤害就提高1d6。 | N72: 不谐低语 | O72: Dissonant Whispers | P72: √ | AA72: 玩家手册
A73: =施法!J75 -> 0 | B73: 神恩 | C73: 1 | D73: 塑能 | E73: x | F73: 1附赠动作 | G73: 自身 | H73: V | I73: S | J73: × | K73: × | L73: 专注,至多1分钟 | M73: ·你的祈祷赋予你神圣的光芒。在法术持续时间结束前，你的武器攻击命中时将造成额外1d4点光耀伤害。 | N73: 神恩 | O73: Divine Favor | S73: √ | AA73: 玩家手册
A74: =施法!J76 -> 0 | B74: 地颤 | C74: 1 | D74: 塑能 | E74: x | F74: 1动作 | G74: 自身(10尺半径) | H74: V | I74: S | J74: × | K74: × | L74: 立即 | M74: ·你在施法距离内引发地面颤动。处于该区域，除你之外的其他生物必须进行一次敏捷豁免检定。若检定失败，该生物受到1d6点钝击伤害并应击倒地。若区域的地表为松软的土壤或石头，其在被清理之前成为困难地形。每5尺直径的部分都需要至少1分钟来手动清理。 ·升环施法效应。当你使用2环或更高的法术位施放该法术时，使用的法术位每高一环，伤害便增加1d6。 | N74: 地颤 | O74: Earth Tremor | P74: √ | R74: √ | U74: √ | W74: √ | AA74: 珊娜萨的万事指南
A75: =施法!J77 -> 0 | B75: 诱捕打击 | C75: 1 | D75: 咒法 | E75: x | F75: 1附赠动作 | G75: 自身 | H75: V | I75: × | J75: × | K75: × | L75: 专注,至多1分钟 | M75: ·你在法术终止前的下一次武器攻击命中一个生物时，将在攻击处出现一团扭曲的多刺藤蔓，并迫使目标进行一次力量豁免，豁免失败者将受魔法藤蔓影响而陷入束缚状态，直至法术终止。大型或更大体型的生物进行该豁免时具有优势，如果豁免成功，则藤蔓立即枯萎。 ·受该法术束缚的目标每回合开始时受到1d6点穿刺伤害。该受束缚生物或其他能触及该目标的生物可用一个动作进行一次对抗法术豁免DC的力量检定。检定成功则目标解除束缚。 ·升环施法效应。使用2环或更高法术位施展该法术时，你使用的法术位每比1环高一环，伤害就提高1d6。 | N75: 诱捕打击 | O75: Ensnaring Strike | T75: √ | AA75: 玩家手册
A76: =施法!J78 -> 0 | B76: 纠缠术 | C76: 1 | D76: 咒法 | E76: x | F76: 1动作 | G76: 90尺 | H76: V | I76: S | J76: × | K76: × | L76: 专注,至多1分钟 | M76: ·在施法距离内指定一点，并以其为源点蔓延出20尺方形区域的杂草和藤蔓。在法术持续时间内，这片被植物覆盖的区域变为困难地形。 在你施展法术时，该区域内的生物必须成功通过一此力量豁免，否则将因为这些缠绕的植物陷入束缚状态，直到法术终止。一个因此被束缚的生物可以使用其动作进行一次力量检定以对抗该法术的豁免DC，检定成功则摆脱束缚。 ·法术终止时，所召唤的植物随即枯萎。 | N76: 纠缠术 | O76: Entangle | R76: √ | AA76: 玩家手册
A77: =施法!J79 -> 0 | B77: 脚底抹油 | C77: 1 | D77: 变化 | E77: x | F77: 1附赠动作 | G77: 自身 | H77: V | I77: S | J77: × | K77: × | L77: 专注,至多10分钟 | M77: ·此法术让你以惊人的步速移动。你在施展该法术时可以执行一次“疾走 Dash ”动作。其后直至法术终止前的每个自己回合，你能以一个附赠动作执行“疾走 Dash ”动作。 | N77: 脚底抹油 | O77: Expeditious Retreat | U77: √ | V77: √ | W77: √ | X77: √ | AA77: 玩家手册
A78: =施法!J80 -> 法术名 | B78: 妖火 | C78: 1 | D78: 塑能 | E78: x | F78: 1动作 | G78: 60尺 | H78: V | I78: × | J78: × | K78: × | L78: 专注,至多1分钟 | M78: ·指定施法距离内一处20尺立方区域，其内每个物件都将被蓝色，绿色或紫色的光所包围（颜色由你指定）。区域内敏捷豁免失败的生物也会被光包围。受术物件和生物在法术持续时间内发出10尺半径的微光。 ·受术生物或物件无法受益于隐形，且任何能看见他们的攻击者对其发动攻击检定时具有优势。 | N78: 妖火 | O78: Faerie Fire | P78: √ | R78: √ | X78: √ | AA78: 玩家手册
A79: =施法!J81 -> 0 | B79: 虚假生命 | C79: 1 | D79: 死灵 | E79: x | F79: 1动作 | G79: 自身 | H79: V | I79: S | J79: M | K79: 一小瓶酒或蒸馏酒精 | L79: 1小时 | M79: ·你从死灵法术中获得了额外的生命力。在法术持续时间内，你获得1d4+4的临时生命值。 ·升环施法效应。使用2环或更高法术位施展该法术时，你使用的法术位每比1环高一环，其给予的临时生命值就增加5。 | N79: 虚假生命 | O79: False Life | U79: √ | W79: √ | X79: √ | AA79: 玩家手册
A80: =施法!J82 -> 0 | B80: 羽落术 | C80: 1 | D80: 变化 | E80: x | F80: 1反应，你60尺内有生物坠落时可用 | G80: 60尺 | H80: V | I80: × | J80: M | K80: 一小片羽毛或绒毛 | L80: 1分钟 | M80: ·在施法距离内指定至多五个正坠落的生物。受术生物的坠落速度在法术持续时间内降低至每轮60尺。如果该生物在法术终止前落地，则其不会受到任何坠落伤害，且可以安全的用脚着地。着地后法术对该生物的效应随即终止。 | N80: 羽落术 | O80: Feather Fall | P80: √ | U80: √ | W80: √ | X80: √ | AA80: 玩家手册
A81: =施法!J83 -> 0 | B81: 获得魔宠 | C81: 1 | D81: 咒法 | E81: √ | F81: 1小时 | G81: 10尺 | H81: V | I81: S | J81: M | K81: 将价值10gp的木炭、焚香以及香草，放在黄铜盆中烧尽 | L81: 立即 | M81: ·你获得一只为你服务的魔宠。以下列动物为原型选择魔宠的动物精魂外貌：蝙蝠 bat、猫 cat、螃蟹 crab、青蛙 frog（蟾蜍 toad）、鹰 hawk、蜥蜴 lizard、章鱼 octopus、猫头鹰 owl、毒蛇 poisonous snake、鱼 fish（食人鱼 quipper）、老鼠 rat、渡鸦 raven、海马 sea horse、蜘蛛 spider、鼬鼠 weasel。魔宠出现在施法距离内一处未被占据的空间，虽然有着所选的生物属性数据，但其种类为天界生物，精类生物或邪魔（由你选择）而不是野兽。 ·你的魔宠可以独立行动，不过会随时遵循你的指令。战斗时，它为自己骰先攻，并在自己的回合里行动。魔宠无法攻击，但是它能如常执行其他动作。 ·魔宠的HP降为0时自行消失，且不会留下任何物理残余，而当你重新施展该法术后它会重新出现。 ·你的魔宠在你身边100尺范围内时，你可以与其进行心灵交流。此外，你还可以用一个动作将自己的视觉和听觉切换到魔宠的感官，并一持续至你下一回合。在此期间，你同时享有该魔宠自身的特殊感官，而你本体的感官则等同于陷入耳聋以及目盲状态。 ·你可以用一个动作暂时的解散你的魔宠。此时它将进入一个小位面等待你的重新召唤。或者，你也可以选择永久解散它。暂时解散时，你可以用一个动作召唤它出现在30尺内任意未占据的空间中。 ·你不能同时拥有一只以上的魔宠，如果你在已有魔宠的状况下施展该法术，则你可以为现有的魔宠选择的新的形态（从以上列表选择）。 ·此外，当你施展施法距离为触及的法术时，你的魔宠可以帮你传递法术，其效果就如同该法术由魔宠施展一样。此时你的魔宠必须在你身边100尺范围内，且其必须可以执行反应来传递法术。如果传递的法术需要进行攻击检定，则该检定将使用你自己的攻击调整值。 | N81: 获得魔宠 | O81: Find Familiar | W81: √ | AA81: 玩家手册
A82: =施法!J84 -> 0 | B82: 云雾术 | C82: 1 | D82: 咒法 | E82: x | F82: 1动作 | G82: 120尺 | H82: V | I82: S | J82: × | K82: × | L82: 专注,至多1小时 | M82: ·你以施法距离内一点为中心创造一片半径20尺的球状浓雾。浓雾在球形内充斥所有角落，并造成重度遮蔽。浓雾持续至法术持续时间结束，但仍可被和风或更强风势（至少每小时10里）所吹散。 ·升环施法效应。使用2环或更高法术位施展该法术时，你使用的法术位每比1环高一环，浓雾的半径就增加20尺。 | N82: 云雾术 | O82: Fog Cloud | R82: √ | T82: √ | U82: √ | W82: √ | AA82: 玩家手册
A83: =施法!J85 -> 0 | B83: 灵敏之赐 | C83: 1 | D83: 预言 | E83: x | F83: 1分钟 | G83: 触及 | H83: V | I83: S | J83: × | K83: × | L83: 8小时 | M83: ·你触碰一个自愿生物，在法术持续时间内，他的先攻掷骰中可以加入一个额外的D8。 | N83: 灵敏之赐 | O83: Gift of Alacrity | Y83: √ | AA83: 荒洲探险家指南
A84: =施法!J86 -> 0 | B84: 神莓术 | C84: 1 | D84: 变化 | E84: x | F84: 1动作 | G84: 触及 | H84: V | I84: S | J84: M | K84: 一枝槲寄生 | L84: 立即 | M84: ·至多10个浆果出现在你手里。果子在法术持续时间内充满魔法，一个生物可用动作吃下其中之一并以此恢复1点生命值，且一枚浆果就可以满足该生物一整天的营养需求。 ·创造的浆果如果在法术施展后的24小时内没有被吃掉就会失去其效力。 | N84: 神莓术 | O84: Goodberry | R84: √ | T84: √ | AA84: 玩家手册
A85: =施法!J87 -> 0 | B85: 油腻术 | C85: 1 | D85: 咒法 | E85: x | F85: 1动作 | G85: 60尺 | H85: V | I85: S | J85: M | K85: 一小块猪皮或黄油 | L85: 1分钟 | M85: ·你在施法距离内指定一点，光滑的油脂以该点为中心覆盖一处10尺的方状区域。在法术持续时间内。该区域变为困难地形。 ·油脂出现时，站在其范围内的每个生物必须进行一次敏捷豁免，豁免失败则失足倒地。进入该区域或在区域内结束其回合的生物也必须进行该敏捷豁免，豁免失败则失足倒地。 | N85: 油腻术 | O85: Grease | W85: √ | X85: √ | AA85: 玩家手册
A86: =施法!J88 -> 0 | B86: 曳光弹 | C86: 1 | D86: 塑能 | E86: x | F86: 1动作 | G86: 120尺 | H86: V | I86: S | J86: × | K86: × | L86: 1轮 | M86: ·一道闪光快速飞向施法距离内你指定的一个生物，并对该目标进行一次远程法术攻击检定。命中时，目标受4d6点光耀伤害。由于目标身上闪耀着秘法的微光，在施法者下个回合结束前，对该目标发动的下一次攻击检定具有优势。 ·升环施法效应。使用2环或更高法术位施展该法术时，你使用的法术位每比1环高一环，伤害就增加1d6。 | N86: 曳光弹 | O86: Guiding Bolt | Q86: √ | AA86: 玩家手册
A87: =施法!J89 -> 0 | B87: 棘雹术 | C87: 1 | D87: 咒法 | E87: x | F87: 1附赠动作 | G87: 自身 | H87: V | I87: × | J87: × | K87: × | L87: 专注,至多1分钟 | M87: ·你在法术终止前进行的下一次远程武器攻击命中时会从你的远程武器或弹药中创造出棘刺，并形成一片棘刺之雨。除了攻击产生的正常效果外，受攻击的目标及目标身边5尺范围内的所有生物还必须进行一次敏捷豁免，豁免失败者将受到1d10点穿刺伤害，豁免成功则伤害减半。 ·升环施法效应。使用2环或更高法术位施展该法术时，你使用的法术位每比1环高一环，伤害就增加1d10（最大伤害6d10）。 | N87: 棘雹术 | O87: Hail of Thorns | T87: √ | AA87: 玩家手册
A88: =施法!J90 -> 0 | B88: 治愈真言 | C88: 1 | D88: 塑能 | E88: x | F88: 1附赠动作 | G88: 60尺 | H88: V | I88: × | J88: × | K88: × | L88: 立即 | M88: ·你指定施法距离内一个你能看见的生物并恢复其生命值，恢复量等于1d4＋你的施法关键属性调整值。该法术对构装体和不死生物无效。 ·升环施法效应。使用2环或更高法术位施展该法术时，你使用的法术位每比1环高一环，治疗量就增加1d4点。 | N88: 治愈真言 | O88: Healing Word | P88: √ | Q88: √ | R88: √ | AA88: 玩家手册
A89: =施法!J91 -> 法术名 | B89: 炼狱叱喝 | C89: 1 | D89: 塑能 | E89: x | F89: 1反应，当60尺内一个你能看见的生物对你造成伤害时执行 | G89: 60尺 | H89: V | I89: S | J89: × | K89: × | L89: 立即 | M89: ·你伸指一点，伤害你的生物立刻被炼狱的烈焰包围。该生物必须进行一次敏捷豁免，豁免失败则受到2d10点火焰伤害，豁免成功则伤害减半。 ·升环施法效应。使用2环或更高法术位施展该法术时，你使用的法术位每比1环高一环，伤害就增加1d10。 | N89: 炼狱叱喝 | O89: Hellish Rebuke | V89: √ | AA89: 玩家手册
A90: =施法!J92 -> 0 | B90: 英雄气概 | C90: 1 | D90: 惑控 | E90: x | F90: 1动作 | G90: 触及 | H90: V | I90: S | J90: × | K90: × | L90: 专注,至多1分钟 | M90: ·你触碰一个自愿生物使其充满勇气。该生物直至法术终止前免疫恐慌，且它将在其每回合开始时获得临时生命值，其数值等于你的施法关键属性调整值。法术终止时，目标失去所有来自该法术的临时生命值。 ·升环施法效应。使用2环或更高法术位施展该法术时，你使用的法术位每比1环高一环，就可以额外指定一个目标。 | N90: 英雄气概 | O90: Heroism | P90: √ | S90: √ | AA90: 玩家手册
A91: =施法!J93 -> 0 | B91: 脆弱诅咒 | C91: 1 | D91: 惑控 | E91: x | F91: 1附赠动作 | G91: 90尺 | H91: V | I91: S | J91: M | K91: 一只被石化的蝾螈眼睛 | L91: 专注,至多1小时 | M91: ·你对施法距离内一个你能看见的一个生物施加诅咒。直到法术终止前，你命中该目标的任意攻击都将额外造成1d6点黯蚀伤害。此外，你在施展该法术的同时选择一项属性，使该目标进行所选属性的属性检定时具有劣势。 ·如果目标在法术终止前HP降至0，则你可以在法术终止前后续的某一回合中使用一个附赠动作诅咒另一个生物。 ·对受术目标施展法术移除诅咒remove curse后可以提前终止该法术。 ·升环施法效应。使用3环或4环法术位施展该法术时，其专注可以维持至多8小时。使用5环或更高法术位施展该法术时，其专注可以维持至多24小时。 | N91: 脆弱诅咒 | O91: Hex | V91: √ | AA91: 玩家手册
A92: =施法!J94 -> 0 | B92: 猎人印记 | C92: 1 | D92: 预言 | E92: x | F92: 1附赠动作 | G92: 90尺 | H92: V | I92: × | J92: × | K92: × | L92: 专注,至多1小时 | M92: ·你指定施法距离内一个你能看见的生物并以魔法标记其作为你的猎物。直至法术终止前，你每次以武器攻击命中该目标时都会额外造成1d6点伤害，且每当你为寻找目标生物而进行感知（察觉）或感知（生存）检定时都具有优势。如果在法术结束前目标HP降至0，则你可以在法术结束前的后续某一个回合中用一个附赠动作标记另一个生物。 ·升环施法效应。你使用3环或4环法术位施展该法术时，该法术的专注可以至多维持8小时。你使用5环或更高法术位施展该法术时，该法术的专注可以至多维持24小时。 | N92: 猎人印记 | O92: Hunter's Mark | T92: √ | AA92: 玩家手册
A93: =施法!J95 -> 0 | B93: 冰刃 | C93: 1 | D93: 咒法 | E93: x | F93: 1动作 | G93: 60尺 | H93: × | I93: S | J93: M | K93: 一滴水或一块冰 | L93: 立即 | M93: ·你制造出一块冰晶裂片，并将它射向距离内的一个生物。你对目标进行一次远程法术攻击。若击中，目标受到1d10点穿刺伤害。无论击中与否，裂片都会在之后爆裂。目标和周围5尺范围内的每个生物必须通过一次敏捷豁免检定，否则受到2d6点冷冻伤害。 ·升环施法效应。当你使用2环或更高的法术位施放该法术时，使用的法术位每高一环，冷冻伤害便增加1d6点。 | N93: 冰刃 | O93: Ice Knife | R93: √ | U93: √ | W93: √ | AA93: 珊娜萨的万事指南
A94: =施法!J96 -> 0 | B94: 鉴定术 | C94: 1 | D94: 预言 | E94: √ | F94: 1分钟 | G94: 触及 | H94: V | I94: S | J94: M | K94: 一颗价值至少100gp的珍珠和一根猫头鹰羽毛 | L94: 立即 | M94: ·你指定一个物件，并在施法过程中一直与其保持接触。如果该物件是魔法物品或其他附有魔力的物件，则你将知晓其属性和使用方式，以及了解是否需要与之同调。若它是充能物品则你将得知它现存的可用次数。你还可以发现是否有法术正影响该物件，以及可能存在的法术效应具体来自哪项法术。如果目标由法术所创，则你将知晓具体来自哪项法术。 ·如果你施法过程中一直接触的是一生物，则你将知晓其是否受法术影响，及产生影响的法术效应具体来自哪项法术。 | N94: 鉴定术 | O94: Identity | P94: √ | W94: √ | X94: √ | AA94: 玩家手册
A95: =施法!J97 -> 0 | B95: 迷幻手稿 | C95: 1 | D95: 幻术 | E95: √ | F95: 1分钟 | G95: 触及 | H95: × | I95: S | J95: M | K95: 价值至少10gp的铅料墨水，作为法术的耗材 | L95: 10日 | M95: ·你在羊皮纸，纸张或是其他适合书写的材质上书写文字并对其施加一个强力的幻象。其效应将持续至法术终止。 ·文件对于你和你施法时所指定的生物而言是一份普通的文件，文件内容即是以你的笔迹传达你写下手稿时想要传达的一切意义。而对于所有其他阅读者而言，该文件看起来就像由难懂的未知文字或魔法文字所书写。此外，你还可以使该文件呈现出完全不同的信息，使其看起来是用另一种笔迹或者语言所书写，不过你必须懂得该语言。 ·如果法术被解除，则幻象和原始手稿一同消失不见。 ·拥有真实视觉的生物可以读出其内被隐藏的信息。 | N95: 迷幻手稿 | O95: Illusory Script | P95: √ | V95: √ | W95: √ | AA95: 玩家手册
A96: =施法!J98 -> 0 | B96: 致伤术 | C96: 1 | D96: 死灵 | E96: x | F96: 1动作 | G96: 触及 | H96: V | I96: S | J96: × | K96: × | L96: 立即 | M96: ·你对触及范围内一个生物发动一次近战法术攻击。命中时，目标受到3d10点黯蚀伤害。 ·升环施法效应。使用2环或更高法术位施展该法术时，你使用的法术位每比1环高一环，伤害就增加1d10。 | N96: 致伤术 | O96: Inflict Wounds | Q96: √ | AA96: 玩家手册
A97: =施法!J99 -> 0 | B97: 跳跃术 | C97: 1 | D97: 变化 | E97: x | F97: 1动作 | G97: 触及 | H97: V | I97: S | J97: M | K97: 一只蚱蜢的后腿 | L97: 1分钟 | M97: ·你触碰一个生物，并使该生物的跳跃距离在法术持续时间内增至三倍。 | N97: 跳跃术 | O97: Jump | R97: √ | T97: √ | U97: √ | W97: √ | X97: √ | AA97: 玩家手册
A98: =施法!J100 -> 0 | B98: 大步奔行 | C98: 1 | D98: 变化 | E98: x | F98: 1动作 | G98: 触及 | H98: V | I98: S | J98: M | K98: 一撮泥土 | L98: 1小时 | M98: ·你触碰一个生物，该目标速度在法术持续时间内增加10尺。 ·升环施法效应。使用2环或更高法术位施展该法术时，你使用的法术位每比1环高一环，你就可以额外指定一个目标。 | N98: 大步奔行 | O98: Longstrider | P98: √ | R98: √ | T98: √ | W98: √ | X98: √ | AA98: 玩家手册
A99: =施法!J101 -> 0 | B99: 法师护甲 | C99: 1 | D99: 防护 | E99: x | F99: 1动作 | G99: 触及 | H99: V | I99: S | J99: M | K99: 一块鞣制过的皮革 | L99: 8小时 | M99: ·你触碰一个未着装护甲的自愿生物，使其受一个保护性魔法力场环绕直至法术终止。目标的基础AC变为13＋它的敏捷调整值。目标着装护甲或你以一个动作解散该法术后法术随之终止。 | N99: 法师护甲 | O99: Mage Armor | U99: √ | W99: √ | AA99: 玩家手册
A100: =施法!J102 -> 法术名 | B100: 魔法飞弹 | C100: 1 | D100: 塑能 | E100: x | F100: 1动作 | G100: 120尺 | H100: V | I100: S | J100: × | K100: × | L100: 立即 | M100: ·你创造三枚由魔法力场形成的闪光飞镖，并让每发飞镖命中施法距离内你能看见的指定生物。每发飞镖对目标造成1d4+1点力场伤害。所有飞镖同将时命中目标，而你还可以指定它们击中同一个目标或是分别击中几个目标。 ·升环施法效应。使用2环或更高法术位施展该法术时，你使用的法术位每比1环高一环，该法术就会多制造出一支飞镖。 | N100: 魔法飞弹 | O100: Magic Missile | U100: √ | W100: √ | AA100: 玩家手册
...

Sheet 图表
A1: 人类 | B1: =主要情况!S3 -> 邪术师 | C1: 法师 | D1: 1d6 | E1: =D14 -> 1d8 | F1: 1d6 | G1: 4 | H1: =D14 -> 1d8 | I1: 1d6 | J1: 2 | K1: =主要情况!W3 -> 5 | L1: 0 | M1: 0 | N1: =主要情况!S3 -> 邪术师 | O1: 法师 | P1: 法术值 | Q1: =主要情况!V11 -> 已知祈唤 | R1: 法术值 | S1: =P35 -> 27 | T1: =主要情况!O25 -> 扇子 | U1: 短棒 | V1: 1d4 | W1: 钝击 | X1: 1 sp | Y1: 轻型 | Z1: 2 | AA1: =背包!B5 -> 0 | AB1: 算盘 | AC1: - | AD1: 2gp | AE1: 2 | AF1: =角色!E10 -> 智者 | AG1: 侍僧Acolyte | AH1: 信仰庇护ShelteroftheFaithful。作为一名侍僧，你与同一信仰的同志互相尊重，并且可以随时主持相应神祇的神圣仪式。当你与冒险同伴遇到你所信仰神祇的神庙，圣坛或其他机构时，你们可能会得到免费的治疗和照料，但你必须为法术提供必须的材料成分。那些与同一信仰的同志会支持你（但仅限你）最基本的生活需求。 | AI1: 侍僧理想 | AJ1: 侍僧牵绊 | AK1: 侍僧缺点 | AL1: 侍僧特点 | AM1: 侍僧技能熟练项 | AN1: 侍僧工具熟练项 | AO1: 侍僧额外语言 | AP1: 侍僧背景装备 | AQ1: 侍僧特殊选项 | BX1: 圣武士 | BZ1: 法师 | CB1: 术士 | CD1: 吟游诗人 | CF1: 牧师 | CH1: 武僧 | CJ1: 游荡者 | CL1: 邪术师 | CN1: 奇械师 | CP1: 战士 | CR1: 游侠 | CT1: 野蛮人 | CV1: 德鲁伊 | CX1: 属性值提升 | CY1: 你可以选择一项属性值提升2点，或是选择两项属性各提升1点。不过你不能通过此特性让属性值超过20。 | CZ1: 0
A2: 半身人 | C2: 术士 | D2: 1d6 | F2: 1d8 | G2: 5 | I2: 1d8 | J2: 3 | L2: 1 | M2: 4 | O2: 术士 | P2: 术法点 | R2: 术法点 | S2: =P56 -> 5 | T2: =主要情况!O26 -> 铁链 | U2: 匕首 | V2: 1d4 | W2: 穿刺 | X2: 2gp | Y2: 灵巧 轻型 投掷(射程20/60) | Z2: 1 | AA2: =背包!B6 -> 0 | AB2: 强酸_小瓶 | AC2: 你可以用一个动作将这小瓶液体泼溅到你身边 5尺内的一个生物身上，或是将小瓶投到至多 20 尺远的地方，并利用冲击打破它。两种情况都可以视为对一个生物或物件发动一次远程攻击，并将强酸视为一件临时武器。命中时，目标受到 2d6点强酸伤害。 | AD2: 25gp | AE2: 1 | AG2: 骗子Charlatan | AH2: 假身份FalseIdentity。你可以伪装成另一个身份，还附带关于该身份的相关的人证物证，并且必须先乔装打扮来让你进入角色。此外，你还可以伪造含有官方格式和私人笔迹的文书，前提是你必须曾见过此类文件以及目标的笔迹以作范本。 | AI2: 骗子理想 | AJ2: 骗子牵绊 | AK2: 骗子缺点 | AL2: 骗子特点 | AM2: 骗子技能熟练项 | AN2: 骗子工具熟练项 | AO2: 骗子额外语言 | AP2: 骗子背景装备 | AQ2: 骗子特殊选项 | BX2: 神圣感知 | BY2: 强大的邪恶存在于你有如带毒的香气，而强大的善良光环于你则如仙乐般悠扬。 你可以使用一个动作扩展你的意识，以侦测此类势力。直到你下回合结束前，你可以对身边60尺范围内进行感测，任何未对你处在全身掩护状态的天界生物、邪魔或不死生物都将被你定位。你感应到范围内生物的种类（天界生物、邪魔、不死生物），不过并不能精确指明（比如“吸血鬼伯爵施特拉德･冯･扎洛维奇 Vampire Count Strahd von Zarovich”）。 在同样的范围内，你也可以侦测任何受到圣居hallow 一类的法术祝福或亵渎的地点或物件。 该特性的可用次数等于1＋你的魅力调整值。而已消耗的特性使用次数，则可以通过完成一次长休进行恢复。 | BZ2: 法师施法 | CA2: 作为一名奥术魔法的研习者，你拥有一本自己的法术书。书中所包含的法术隐约透露着你真正的力量。参考第10章的施法规则，以及第11章的法师法术列表。 戏法 Cantrips 第1级时，你从法师法术列表中选择三个戏法作为已知法术。在获得更高的法师等级后你还可以习得其它的戏法，具体数量参见“法师职业表”中“已知戏法”一栏。 法术书 Spellbook 第1级时，你让一本法术书纪录上六个你自选的1环法师法术。你的法术书储存着你除戏法外的所有已知法术，而你的戏法则直接铭记在你脑海中。 法术的准备和施展 Preparing and Casting Spells “法师职业表”里记录了你用以施展你法师法术的1环及更高环阶法术位数量。施展一个法师法术时，你必须同时消耗其对应环阶的法术位。已消耗的法术位可在完成长休后恢复。 你可以准备一系列符合当前施法条件的法师法术。准备法术时，你从法术书中选择的准备法术总数等于你的智力调整值＋你的法师职业等级（最少为1）。另外，你只能准备已经获得相应环阶法术位的法术。已施展的法术并不会从你的准备列表中移除。 你可以在完成长休后改变你的准备法术列表。准备新的法师法术列表时，你要再花时间研读你的法术书，并重新记忆所准备法术的咒语和施展动作。准备时，你要为你列表上每个法术的每个环阶都花费至少1分钟时间。 施法关键属性 Spellcasting Ability 你的法术来自你专注的研习和记忆，因此智力是你施展法师法术的关键属性。每当你的法术需要施法关键属性时均指向你的智力值。而你法师法术的豁免DC和攻击检定，则使用你的智力调整值。 法术豁免 DC＝8＋你的熟练加值＋你的智力调整值 法术攻击调整值＝你的熟练加值＋你的智力调整值 仪式施法 Ritual Casting 如果你法术书记录了带有仪式标签的法术，则你可以用这些法术进行仪式施法。进行仪式施法时，你不需要准备相应的法术。 法器 Spellcasting Focus 你可以使用奥术法器（详见第5章）来作为施展法师法术的法器。 学习法术 Learning Spells of 1st Level and Higher 你每提升一个法师等级，可以将两项自选的法师法术加入你的法术书中。但是，你只能加入已经获得相应环阶法术位的法术。你在冒险过程中所发现的法术也可以加入到法术书中（详见“你的法术书”边栏）。 | CB2: 术士施法 | CC2: 过去的一个事件激发了你体内先辈的血脉，为你烙上了奥法力量的坚固印记。这股起源于某种存在的魔力驱动着你的法术能力。详见第10章的施法规则及第11章的术士法术列表。 戏法 Cantrips 第1级时，你从术士法术列表里选择四个戏法作为已知法术。在获得更高的术士等级后你还可以习得其它的戏法，具体数量见“术士职业表”中“已知戏法”一栏。 法术位 Spell Slots “术士职业表”中记录了你用以施展你术士法术的1环及更高环阶法术位数量。施展一个术士法术时，你必须同时消耗其对应环阶的法术位。已消耗的法术位可在完成长休后恢复。 已知法术 Spells Known of 1st Level and Higher 第1级时，你从术士法术列表里选择两个1环法术作为已知法术。 “术士职业表”中“已知法术”一栏记录了你获得更多已知法术时的相应等级。但是你只能获取已有相应环阶法术位的法术。 另外，你每提升一个术士等级，都可以从术士法术列表里选择一个新法术来代替一个已知法术列表中的旧法术。但是，你必须拥有新法术的相应环阶法术位。 施法关键属性 Spellcasting Ability 你的魔力来源于你意志的现实投影，因此魅力是你施展术士法术的关键属性。每当你的法术需要施法关键属性时均指向你的魅力值。而你术士法术的豁免DC和攻击检定，则使用你 的魅力调整值。 法术豁免 DC＝8＋你的熟练加值＋你的魅力调整值 法术攻击调整值＝你的熟练加值＋你的魅力调整值 法器 Spellcasting Focus 你可以使用奥术法器（详见第5章），作为你施展术士法术时的法器。 | CD2: 吟游诗人施法 | CE2: 你习得以音乐为媒介随意解构、分解，再重新构造现实的方法。你的法术是融入你纷繁奏乐中的音符，也是你以各种形式谱奏的魔法乐章。 参考第10章的施法规则，以及第11章的吟游诗人法术列表。 戏法 Cantrips 第1级时，你从诗人法术列表中选择两个戏法作为已知法术。在获得更高诗人等级后你还可以习得其它的戏法，具体数 量见“吟游诗人职业表”中“已知戏法”一栏。 法术位 Spell Slots “吟游诗人职业表”中记录了你可用以施展诗人法术的1环及更高环阶法术位数量。施展诗人法术时，你必须同时消耗其对应环阶的法术位。已消耗的法术位可在完成长休后恢复。 已知法术 Spell Known of 1st Level and Higher 第1级时，你从诗人法术列表中选择四个1环法术作为已知法术。 “吟游诗人职业表”中“已知法术”一栏记录了你获得更多已知法术时的相应等级。但是，你只能获取已有相应环阶法术位的法术。 另外，你每提升一个诗人等级，可以从诗人法术列表中选 择一个新法术来代替一个已知法术列表中的旧法术，不过你必须已有新法术的相应环阶法术位。 施法关键属性 Spellcasting Ability 你的魔力源于你注入音乐或演说中的心灵力量，因此魅力是你施展吟游诗人法术的关键属性。每当你的诗人法术需要施法关键属性时均指向你的魅力值。而你诗人法术的豁免DC和攻击检定，则使用你的魅力调整值。 法术豁免 DC＝8＋你的熟练加值＋你的魅力调整值 法术攻击调整值＝你的熟练加值＋你的魅力调整值 仪式施法 Ritual Casting 如果你已知法术列表中的一个法术带有仪式标签，则你可以用这些法术进行仪式施法。 法器 Spellcasting Focus 你可以使用乐器（见第5章）作为施展诗人法术的法器。 | CF2: 牧师施法 | CG2: 你作为神圣力量的导体得以施展牧师法术。参考第10章的施法规则，以及第11章的牧师法术列表。 戏法 Cantrips 第1级时，你选择三个牧师法术列表中的戏法作为已知法术。在获得更高的牧师等级后你还可以习得其它的戏法，具体数据参见“牧师职业表”中“已知戏法”一栏。 法术的准备与施展 Preparing and Casting Spells “牧师职业表”里记录了你用以施展牧师法术的1环及更高环阶法术位数量。施展一个牧师法术时，你必须同时消耗其对应环阶的法术位。已消耗的法术位可在完成长休后恢复。 你可以准备牧师法术列表中所有符合当前施展条件的法术。准备法术时，你所准备法术的总数等于你的感知调整值＋你的牧师职业等级（最少可以准备一个）。另外，你只能准备已经获得相应环阶法术位的法术。另外，已施展的法术并不会从你的准备列表中移除。 你可以在完成长休后改变你的准备法术列表。准备新的牧 师法术列表时，你要再花时间进行祈祷和冥想。准备时，你要为你列表上每个法术的每个环阶都花费至少1分钟时间。 施法关键属性 Spellcasting Ability 你的法术力量来源于你对神祇的信仰，因此感知是你施展牧师法术的关键属性。每当你的牧师法术需要施法关键属性时均指向你的感知值。而你牧师法术的豁免DC和攻击检定，则使用你的感知调整值。 法术豁免 DC＝8＋你的熟练加值＋你的感知调整值 法术攻击调整值＝你的熟练加值＋你的感知调整值 仪式施法 Ritual Casting 如果你所准备牧师法术中的一个法术有带仪式标签，则你可以用这些法术进行仪式施法。 法器 Spellcasting Focus 你可以使用圣徽（见第5章）作为施展牧师法术的法器。 | CH2: 武僧无甲防御 | CI2: 第1级起，未着装任何护甲也没持用盾牌时，你的AC值等于10＋你的敏捷调整值＋你的感知调整值。 | CJ2: 游荡者专精 | CK2: 第1级起，你选择两个已有技能熟练项，或者一个技能熟练项和盗贼工具熟练项。此后你进行该项目的检定时，可以使用双倍的熟练加值。 第6级时，你可以再选择另外两个已有的技能熟练项（或盗贼工具熟练项）从该特性中获益。 | CL2: 异界宗主 | CM2: 第1级时，你就跟某个异界的存在订下契约。你可以从至高妖精Archfey、邪 Fiend、旧日支配者Great Old One等选项中选择其一。 随后你将在第 1、第 6、第 10、第14级获得相应的职业特性。 你可以在拓展之中找到更多的邪术师异界宗主。 | CN2: 魔法工艺 | CO2: 在第1级，你将学习如何在平凡的物品中注入魔法的火花。要使用这个能力，你必须手持修补工具，或其他工匠工具。然后花费一个动作触摸一个微小的非魔法物体，从以下魔法属性中选择一个赋予它： ·该物体提供5尺半径的明亮照明，以及该范围外5尺范围的微光照明。 ·无论何时，只要该物品被生物触碰，就会发出可在10英尺外听到的录音信息。录入的信息在你将此属性赋予对象时决定，且时长不可超过6秒。 ·物品不断地发出一种气味或一种非语言的声音（风声、浪声、鸟叫或类似的声音）。这一现象最多能传播10英尺远。 ·一个静态的视觉效果出现在物体的表面上。这个效果可以是一幅图片，最多25个单词的文本，线条和形状，或者这些元素的混合，如你所愿。 所选的魔法属性持续时间无限。你能够以一个动作触摸对象来消除这一魔法属性。 你能够通过此特性将魔力赋予多个物品，每次使用该特性时都需要触摸一个物品，并且单个物品一次只能承载一种魔法属性。你能够使用该特性影响的物品的最大数量等于你的智力调整值（最少一个物品）。如果你试图超过最大值，最老的魔法属性将立即结束，然后新的魔法属性生效。 | CP2: 战士战斗风格 | CQ2: 你专精于一种战斗风格，并从下列选项中选择。另外，即使你有多次选择战斗风格的机会，也不能多次选择同一个战斗风格。[注意：不要在这里选好下拉之后就不管它了，请务必清晰记录你究竟选择了什么战斗风格] 箭术Archery 你使用远程武器进行攻击检定时具有+2加值。 防御Defense 着装护甲时，你的AC获得+1加值。 对决Dueling 单手持用一把近战武器，且并未同时持用其他武器时，你用该武器攻击的伤害掷骰获得+2加值。 巨武器战斗Great Weapon Fighting 双手持用一把近战武器发动攻击时，如果你的伤害掷骰掷出1或2，则可以选择重掷。不过哪怕其仍是1或2，你都必须接受重掷的数值。此外，该武器必须具有双手或两用属性。 守护Protection 当一个你能看见的生物攻击你身边5尺内除你之外的目标时，你可以用反应迫使该攻击的攻击检定具有劣势。此时你必须持用盾牌。 双武器战斗Two-Weapon Fighting 使用两把武器战斗时，你可以将相应属性调整值加到第二次攻击的伤害上。 | CR2: 宿敌 | CS2: 第1级起，你针对一种特定类型敌人的研究令你有着充足的经验用以追踪、狩猎乃至与之交流。 从下列种类中选择其一作为宿敌：异怪、野兽、天界生物、构装生物、龙、元素生物、精类生物、邪魔、巨人、怪兽、泥怪、植物、不死生物。或者作为另一种方案，你也可以选择两个类人生物种族（例如豺狼人gnolls 和兽人orcs）作为宿敌。 追踪宿敌时，你的感知（求生）检定，以及回想关于宿敌信息时进行的智力检定具有优势。 获得该特性时，如果你选择的宿敌具有语言能力，则你还可以学会宿敌所知晓的一门语言。 第6和第14级时，你将分别获得一个额外的宿敌以及相关语言。另外，随着等级的提升，你所选择的宿敌应该与你在冒险中所遭遇怪物的种类层次相符。 | CT2: 狂暴 | CU2: 你带着原初的狂怒作战。你可以在自己回合内以一个附赠动作进入狂暴。 狂暴持续期间，只要你未着装重甲就获得以下增益： • 你进行力量检定和力量豁免时具有优势。 • 你用力量值发动近战武器攻击时的伤害掷骰获得加值。此加值随你的野蛮人等级提升而增加，具体见“野蛮人职业表” 中“狂暴伤害”一栏。 • 你拥有钝击，穿刺和挥砍伤害的抗性。 拥有施法能力的角色无法在狂暴持续期间施展法术或进行法术专注。 你的狂暴状态维持1分钟。如果你在狂暴其间陷入昏迷，或者，如果你从自己上回合结束开始到本回合结束时都未攻击任何敌对生物也未受到伤害，则狂暴提前结束。你也可以在自己回合里以一个附赠动作主动结束狂暴状态。 “野蛮人职业表”中根据你的野蛮人等级给出了相应的狂暴次数。如果你用光了这些次数，则必须完成一次长休才能再次使用狂暴。 | CV2: 德鲁伊语 | CW2: 你习得德鲁伊语——即一种德鲁伊间的秘密语言。你可以说这门语言并用它留下隐藏的信息。 懂得这门语言的人（包括你自己）会自动注意到此信息，而不懂此语言的人通过一次DC15的感知（察觉）检定后可以注意到其存在，不过不能用非魔法手段读懂。 | CX2: 警觉 | CY2: 经常对危机保持警惕，让你获得下列增益： • 你的先攻获得+5加值。 • 你在意识清醒时无法被突袭。 • 你看不到的生物对你发动攻击检定时，无法因此获得优势。 | CZ2: 1
A3: 精灵 | C3: 吟游诗人 | D3: 1d8 | F3: 1d10 | G3: 6 | I3: 1d10 | J3: 4 | L3: 2 | M3: 6 | O3: 吟游诗人 | P3: 激励骰 | R3: 激励骰 | S3: =P77 -> 1d8 | T3: =主要情况!O27 -> 0 | U3: 巨棒 | V3: 1d8 | W3: 钝击 | X3: 2 sp | Y3: 双手 | Z3: 10 | AA3: =背包!B7 -> 0 | AB3: 炽火胶_扁瓶 | AC3: 一种粘稠的流体，其一旦接触空气就会引起自燃。你可以用一个动作将这小瓶液体投到至多20尺远的地方，并利用冲击打破它。这个动作视为对一个生物或物件发动一次远程攻击，并将炽火胶视为一件临时武器。命中时，目标在它每回合开始时受到1d4点火焰伤害。被命中生物可以使用动作进行一次DC10的敏捷检定，以扑灭火焰来结束该伤害效应。 | AD3: 50gp | AE3: 1 | AG3: 罪犯Criminal | AH3: 罪犯联络员CriminalContact。你有一个可靠可信的联络员，来帮你组织进罪犯们组成的联系网中。即使遥隔千里你也知道如何从联络人处收发信息。此外，你还知道哪些人能为你捎信，他们可能是本地的信使，可贿赂的商队主管，或是衣衫褴褛的水手。 | AI3: 罪犯理想 | AJ3: 罪犯牵绊 | AK3: 罪犯缺点 | AL3: 罪犯特点 | AM3: 罪犯技能熟练项 | AN3: 罪犯工具熟练项 | AO3: 罪犯额外语言 | AP3: 罪犯背景装备 | AQ3: 罪犯特殊选项 | BX3: 圣疗 | BY3: 你的触碰溢满祝福，可以医治伤口。你获得一个治疗能量池，其内的治疗能量在每次完成长休后自动补满。治疗能量池储备的可恢复生命值总值等于你的圣武士职业等级×5。 你可以用一个动作触碰一个生物，并抽取治疗能量池中的能量恢复该生物的生命值，其恢复量最多等于你治疗能量池中剩余的治疗量。 此外，你也可以使用 5 点治疗量治愈目标生物身上的一种疾病，或者祛除一种中毒效应。你可以在一次圣疗中治愈复数的疾病并祛除复数的毒素，但你需要为每一种疾病和毒素分别支付治疗量。 该职业特性对不死生物和构装生物无效。 | BZ3: 奥术回想 | CA3: 你学会了通过研读法术书来恢复魔法能量的办法。 你可以每日使用一次奥术回想，以在你完成一次短休后恢复若干已消耗的法术位。 所恢复的法术位环阶总和不得大于你法师等级的一半（向上取整），且任何一枚法术位的环阶都必须小于6环。 例如，作为一名4级法师时，你可恢复环阶总数最多为2的法术位。你可以选择恢复一枚2环法术位或两枚1环法术位。 | CB3: 术法起源 | CC3: 选择一个术法起源作为你天赋魔力的源泉。你可在龙族血脉Draconic Bloodline 或狂野魔法Wild Magic 中选择其一。 随后，你将在第1、第6、第14、第18级获得相应起源的职业特性。 你可以在拓展中找到更多的术法起源。 | CD3: 诗人激励 | CE3: 从第1级起，你可以用热血的话语和音乐激励他人。此时， 你可以在自己回合内用一个附赠动作指定身边60尺内一个能听到你声音的生物（不能指定你自身），并使该生物获得一个诗人激励，即一个d6的激励骰。 在接下来的10分钟内，该生物在进行单次属性检定、攻击检定、豁免检定时可以使用该激励骰，以将其结果加到掷骰结果中。该生物可以在d20结果掷出后，DM宣布结果前决定是否使用诗人激励。 而诗人激励一旦使用即被消耗掉。一个生物同一时间里只能保有一个诗人激励。 你能够使用该特性的次数等于你的魅力调整值（最低一次）。完成一次长休后，你将重获所有消耗掉的诗人激励次数。 你产生的激励骰大小可以在达到本职业的特定等级时增大。第5级时为d8，第10级时为d10，而第15级时为d12。 | CF3: 神圣领域 | CG3: 你将选择一个与你所信仰神祇的神职相关的神圣领域。你可以从知识 Knowledge、生命 Life、光明 Light、自然 Nature、 风暴 Tempest、诡术 Trickery 或者战争 War 中选择其一。 一些领域其领域法术可能并不在牧师法术列表中，此时如果你选择了该领域，则你视该领域的领域法术为你的牧师法术。 领域法术 Domain Spells 每个领域都有其相应的领域法术列表。当你获得表中所对应的牧师等级时，你将同时习得这些法术。领域法术一旦习得，将会一直在你的准备法术列表中，且不计入你的每日准备法术上限。 任何领域法术对你而言都是牧师法术，而不论其是否在牧师法术列表之上。 拓展中存在更多牧师神圣领域。 | CH3: 武艺 | CI3: 第1级时，你修行的武艺让你使用徒手打击和武僧武器时得心应手。武僧武器包括短剑和所有不含双手与重型属性的简易近战武器。 未着装任何护甲也没持用盾牌时，如果你徒手或只持用武僧武器，则你发动的攻击拥有下列增益： • 你使用徒手打击或武僧武器进行攻击时，可以用敏捷值代替力量值进行攻击检定和伤害掷骰。 • 你使用徒手打击或武僧武器进行攻击时，可以选择用d4骰代替原本的伤害掷骰。该骰子将随武僧职业等级的提升而增大，具体数据见“武僧职业表”中“武艺”一栏。 • 你使用徒手打击或武僧武器执行攻击动作时，可以在自己回合内以附赠动作发动一次徒手打击。例如，你执行攻击动作并使用长棍发动攻击时，若你本轮没有执行任何附赠动作，则可以用附赠动作来发动一次徒手打击。 一些宗派的武僧会使用一些奇异的武僧武器，比如铁链连接的两根短棒（双截棍 nunchaku），或者带直刃的镰刀（单镰kama）。无论你使用什么武器，其属性数据都参考与其相似的常规武器属性数据。具体的武器数据见第5章。 | CJ3: 偷袭 | CK3: 第1级起，你就知道如何精确地攻击分心的敌人。每当你的攻击命中一个生物时，如果该攻击的攻击检定带有优势，则可以造成额外1d6的伤害。 该伤害每回合可以产生一次，且造成伤害的攻击必须使用带灵巧属性的武器或远程武器。 如果目标生物身边5尺内还有其他与之对敌者，且该对敌者并未处于失能状态，则只要你的攻击检定没有劣势，就可以发动偷袭。 你的偷袭伤害也将会随游荡者职业等级的提升而提高，其具体数值见“游荡者职业表”。 | CL3: 契约魔法 | CM3: 你的法术力量源于你的奥秘研究和宗主的魔法馈赠。参考第10章的施法规则，以及第11章的邪术师法术列表。 戏法 Cantrips 你从邪术师法术列表中选择两个戏法作为已知法术。在获得更高的邪术师等级后你还可以习得其它的戏法，具体数据见“邪术师职业表”中“已知戏法”一栏。 法术位 Spell Slots “邪术师职业表”里记录了你可用以施展邪术师法术的1环至5环法术位数量。表格中还记录了法术位对应的法术环阶，且你所有的法术位都属于同一环阶。施展1环或更高环阶的邪术师法术时，都需要消耗一枚法术位。已消耗的法术位可在完 成长休或短休后恢复。 例如，达到第5级时，你总共具有两枚3环法术位。你施展1环法术巫术箭witch bolt 时，必须消耗消耗这些法术位其中之一，并把它作为一个3环法术施放。 已知法术 Spell Known of 1st Level and Higher 第1级时，你从邪术师法术列表里选择两个1环法术作为已知法术。 “邪术师职业表”中“已知法术”一栏记录了你获得更多法术时的相应等级。每个被选的法术都必须在当前等级拥有可用以施展该法术的法术位，具体见表。比如，当你达到第6级时，你将获得一个1环、2环或3环的新邪术师法术。 另外，当你提升本职的职业等级时，你可以从邪术师法术列表里选择一个新法术来代替一个旧的邪术师已知法术，但是你的角色必须拥有用以施展新选法术的可用法术位。 施法关键属性 Spellcasting Ability 魅力是你施展邪术师法术的关键属性。每当你的法术需要施法关键属性时均指向你的魅力值。而你邪术师法术的豁免DC和攻击检定，则使用你的魅力调整值。 法术豁免 DC＝8＋你的熟练加值＋你的魅力调整值 法术攻击调整值＝你的熟练加值＋你的魅力调整值 法器 Spellcasting Focus 你可以使用奥术法器（详见第5章）作为你施展邪术师法术的法器。 | CN3: 奇械师施法 | CO3: 你已经学习了魔法的工作原理，知道如何引导魔法进入物体，以及如何唤醒魔法。因此，你获得了有限的施法能力。在旁观者看来，你不会用传统的方式施法——你看起来好像在通过各种物品创造奇迹。 必备工具 你通过你的工具产生你的奇械师法术效果。当你使用施法特性来施展法术时，必须手持一个法器——通常是盗贼工具或工匠工具。你必须熟练这一工具才能将它作为法器使用。这些工具的描述请参见《玩家手册》第五章“装备”。 当你在第二级获得物品注法特性后，你也能使用任何你注入魔法的物品来作为法器使用。 戏法 在第1级，你从奇械师法术列表中习得两个戏法。在更高的等级，你能够根据“奇械师职业表”习得更多戏法。 当你提升一个奇械师等级时，你能够从奇械师法术列表中习得一个新的戏法来替换一个原有的已知戏法。 法术的准备和施展 “奇械师职业表”显示出你有多少能用于施法的法术位。施展某个奇械师法术时，你必须同时消耗其对应环阶的法术位。而已消耗的法术位则可以通过完成一次长休进行恢复。 你需要从奇械师法术列表中选择想要准备的法术，你能选择的准备法术总数等于你的智力调整值＋你奇械师职业等级的一半（向下取整）（最少为1）。你只能准备已经获得相应环阶法术位的法术。另外，已施展的法术并不会从你的准备列表中移除。 你可以在完成长休后改变你的准备法术列表。如需准备新的奇械师法术，你需要花时间来调整你的法器：每个法术要花费至少1分钟的时间。 施法关键属性 你对魔法理论的理解使你能够以更高超的技法来使用这些法术，因此智力是你的施法关键属性。每当你的法术需要施法关键属性时均指向你的智力值。而你奇械师法术的豁免DC和攻击检定，也使用你的智力调整值。 法术豁免DC＝8＋你的熟练加值＋你的智力调整值 法术攻击调整值＝你的熟练加值＋你的智力调整值 仪式施法 如果你准备了带有仪式标签的法术，则你可以用这些法术进行仪式施法。 | CP3: 回气 | CQ3: 你拥有少量精力储备可用来保护自己免受伤害。你可以在自己回合内用一个附赠动作恢复生命值，其总值为1d10＋你的战士职业等级。 你必须完成一次短休或长休才能再次使用该特性。 | CR3: 自然探索者 | CS3: 你对某种自然环境特别熟悉，并适应了在其中行走及生存。 从下列类别中选择一种偏爱地形：极地 arctic、海岸 coast、荒漠 desert、丛林 forest、草原 grassland、山地 mountain、沼泽swamp 或幽暗地域 Underdark。当你进行与偏好地形相关的智力或感知检定时，如果你拥有该技能的熟练项，则在检定时加入双倍熟练加值。 当你在偏好地形上移动一小时或更长时间时，你获得以下增益： • 你的队伍旅行时不会因困难地形而变慢 • 除非受魔法效应影响，否则你的队伍不会迷路 • 旅行时，即使你进行另一项活动（如觅食、导航或追踪），仍能对危险保持警觉 • 独自旅行时，你能够保持隐匿状态以正常步调移动 • 觅食时，你会发现两倍的食物 • 追踪其他生物时，你还能了解他们的确切数量、体型以及离开踪迹的时间 你在第6级和第10级时将分别获得一个额外的偏好地形。 | CT3: 野蛮人无甲防御 | CU3: 未着装任何护甲时，你的AC等于 10＋你的敏捷调整值＋你的体质调整值。使用盾牌不会影响你从此特性获益。 | CV3: 德鲁伊施法 | CW3: 你掌握自然世界的神圣本质，并依你的意志施展法术对其进行重塑。参考第10章的施法规则及第11章的德鲁伊法术列表。 戏法 Cantrips 第1级时，你选择两项德鲁伊法术列表中的戏法作为已知法术。在获得更高的德鲁伊等级后你还可以习得其它的戏法，具体数据参见“德鲁伊职业表”中“已知戏法”一栏。 法术的准备和施展 Preparing and Casting Spells “德鲁伊职业表”里记录了你用以施展德鲁伊法术的1环及更高环阶法术位数量。施展一个德鲁伊法术时，你必须同时消耗其对应环阶法术位。已消耗的法术位可在完成长休后恢复。 你可以准备德鲁伊法术列表中所有符合当前施展条件的法术。准备法术时，你所准备法术的总数等于你的感知调整值＋你的德鲁伊职业等级（最少可以准备一个）。另外，你只能准备已经获得相应环阶法术位的法术。另外，已施展的法术并不会从你的准备列表中移除。 你可以在完成长休后改变你的准备法术列表。准备新的德鲁伊法术列表时，你要再花时间进行祈祷和冥想。准备时，你要为你列表上每个法术的每个环阶都花费至少1分钟时间。 施法关键属性 Spellcasting Ability 你的法术力量源于你对自然的信仰与同调，因此感知是你施展德鲁伊法术的关键属性。每当你的德鲁伊法术需要施法关键属性时均指向你的感知值。而你德鲁伊法术的豁免DC和攻击检定，则使用你的感知调整值。 法术豁免 DC＝8＋你的熟练加值＋你的感知调整值 法术攻击调整值＝你的熟练加值＋你的感知调整值 仪式施法 Ritual Casting 如果你所准备德鲁伊法术中的一个法术有带仪式标签，则你可以用这些法术进行仪式施法。 法器 Spellcasting Focus 你可以用德鲁伊法器（详见第5章）作为你施展德鲁伊法术的法器。 | CX3: 运动员 | CY3: 你接受的全面肉体锻炼使你获得下列增益： • 你的力量或敏捷增加1，上限为20。 • 你陷入倒地状态时，起立所需要花费的移动力为5尺 • 攀爬无需额外消耗移动力 • 你在进行助跑调高或跳远时只需要移动5尺，而不是10尺。 | CZ3: 2
A4: 半精灵 | C4: 牧师 | D4: 1d8 | F4: 1d12 | G4: 7 | I4: 1d12 | J4: 5 | L4: 3 | M4: 14 | O4: 牧师 | P4: 引导神力 | R4: 引导神力 | S4: =P119 -> 1 | U4: 手斧 | V4: 1d6 | W4: 挥砍 | X4: 5gp | Y4: 轻型 投掷(射程20/60) | Z4: 2 | AA4: =背包!B8 -> 0 | AB4: 箭(20) | AC4: - | AD4: 1gp | AE4: 1 | AG4: 密探Spy | AH4: 罪犯联络员CriminalContact。你有一个可靠可信的联络员，来帮你组织进罪犯们组成的联系网中。即使遥隔千里你也知道如何从联络人处收发信息。此外，你还知道哪些人能为你捎信，他们可能是本地的信使，可贿赂的商队主管，或是衣衫褴褛的水手。 | AI4: 密探理想 | AJ4: 密探牵绊 | AK4: 密探缺点 | AL4: 密探特点 | AM4: 密探技能熟练项 | AN4: 密探工具熟练项 | AO4: 密探额外语言 | AP4: 密探背景装备 | AQ4: 密探特殊选项 | BX4: 圣武士战斗风格 | BY4: 第2级起，你将精进于一种战斗风格，从下列选项中选择其一。另外，即使你有多次选择战斗风格的机会，也不能重复选择同一个战斗风格。[注意：不要在这里选好下拉之后就不管它了，请务必清晰记录你究竟选择了什么战斗风格] 防御Defense 着装护甲时，你的AC获得 +1 加值。 对决Dueling 单手持用一把近战武器，且并未同时持用其他武器时，你使用该武器进行攻击的伤害掷骰获得+2加值。 巨武器战斗Great Weapon Fighting 双手持用一把近战武器发动攻击时，若你的伤害掷骰掷出1或2，则可以选择重掷。不过哪怕其仍是1或2，你都必须接受重掷的数值。此外，该武器必须具有双手或两用属性。 守护Protection 当一个你能看见的生物攻击你身边5尺内除你之外的目标时，你可以用反应迫使该攻击的攻击检定具有劣势。你必须持用盾牌以实现该效果。 | BZ4: 奥术传承 | CA4: 第2级时，你选择一种奥术传承以使你的训练专注于八个学派之一。从防护、咒法、预言、附魔、塑能、幻术、死灵、变化各学派中选择其一。 随后，你将在第2、第6、第10、第14级时获得所选学派相应的特性。拓展中存在更多的学派。 | CB4: 魔力泉涌 | CC4: 第2级时，你解除了体内魔力之源的封印，从中涌现的魔力体现为你的可用术法点。你可以使用术法点创造各种魔法效应。 术法点 Sorcery Points 开始时，你拥有2个术法点。此后你每提升一个术士等级，都会获得更多的术法点，详见“术士职业表”中“术法点”一栏。你的术法点永远不能超过表中所列对应你当前等级的数值。 而已消耗的术法点则可以通过完成一次长休进行恢复。 灵活施法 Flexible Casting 你可以使用术法点来获得额外的法术位，或是消耗法术位来换取额外的术法点。随着术士等级的提升，你还可以学会其他术法点的使用方法。 生成法术位 Creating Spell Slots。你可以在自己回合内以附赠动作将未使用的术法点转换为法术位。表格“生成法术位”中列出了生成各法术位所需的术法点数。另外，你无法生成高于 5 环的法术位。以此方式生成的法术位将在完成一次长休后消散。 生成法术位 Creating Spell Slots 法术位环阶 术法点消耗 1环 2 2 环 3 3 环 5 4 环 6 5 环 7 法术位转换术法 Converting a Spell Slot to Sorcery Points。你可以在自己回合内使用附赠动作将未使用的法术位转化为术法点。你消耗一枚法术位并获得等于该法术位环阶的术法点。 所有你以该特性生成的法术位，在你完成一次长休后也将随之消失。 | CD4: 万事通 | CE4: 第2级起，在你进行属性检定时，如果检定结果不包含你的熟练加值，则你可以将自身熟练加值的一半（向下取整）加入到检定结果中。 | CF4: 引导神力 | CG4: 第2级时，你获得引导神祇所授予神圣能量的能力，所引导的能量将用以实现各种魔法效应。你最初将获得两种效应： 驱散不死生物和另一个与你所选领域相关的效应。随着你在冒险中提升等级，一些领域会赋予更多额外的效应，具体信息可以参考相应领域的描述内容。 引导神力最终产生的效应由你自行选择。引导神力后，你必须完成一次短休或长休才能重新使用该特性。 一些引导神力的效应需要豁免，其豁免DC等于你的牧师法术豁免DC。 第6级起，你可以在两次休息之间使用两次引导神力，第18级后可以使用三次。完成一次短休或长休后，你将重新获得所有消耗掉的引导神力次数。 引导神力：驱散不死生物Channel Divinity: Turn Undead 你以一个动作展示你的圣徽，并说出一段谴责不死生物的祷言。你身边30尺范围内能够看到圣徽或听到你祷言的不死生物必须进行一次感知豁免，豁免失败则受到驱散，其效应持续1分钟或直到其受到任何伤害。 一个被驱散的生物必须花费其回合内的所有速度尽力远离你，而且无法主动靠近你30尺内。被驱散的生物无法使用反应，只能使用既有的疾走Dash动作或从任何妨碍他们移动的效应中挣脱。该生物无路可走时会使用“回避Dodge”动作。 | CH4: 气 | CI4: 第2级起，你掌握一股名为气的神秘能量。此后你将拥有一定数量的气作为储备。而气的储备量由你的武僧等级决定，具体数值见“武僧职业表”中“气”一栏。 你可以消耗气以行使各种特性。一开始你掌握三种特性：疾风连击，坚强防御，飞檐走壁。此后，随着等级的提升你将习得更多的特性。 消耗掉的气必须在你短休或长休时完成至少 30 分钟的冥想，才能重获所有消耗掉的气值。 一些特性需要目标进行豁免检定来抵抗你特性造成的效应。其豁免DC如下： 气豁免 DC＝8＋你的熟练加值＋你的感知调整值 疾风连击 Flurry of Blows 你在自己回合内执行攻击动作后，可立即消耗1点气并以一个附赠动作发动两次徒手打击。 坚强防御 Patient Defense 你在自己回合内，可以消耗1点气，并以一个附赠动作的形式来执行回避 Dodge 动作。 飞檐走壁 Step of the Wind 你在自己回合内，可以消耗1点气，并以一个附赠动作的形式来执行撤离 Disengage 动作或疾走 Dash 动作，同时使你该回合内的跳跃距离翻倍。 | CJ4: 盗贼黑话 | CK4: 作为一名游荡者，你在平时的练习中学会了盗贼间的黑话。盗贼黑话是一门混合了土话、术语和密语的秘密语言，掌握这门语言后，你可以在平时对话中不落痕迹的加入隐藏信息。 而只有另一个懂盗贼黑话的生物才能看懂这些隐藏信息。不过这种交流方式需要花费四倍于直接交流所需要的时间。 另外，你还习得一套用以传达简单短小信息的秘密符文和标识。 它能发布的内容诸如某个地区是否危险，是否受盗贼公会管辖，附近是否有战利品，附近的人是否好主顾或者路上是否有安全的房屋以供庇护。 | CL4: 魔能祈唤 | CM4: 你在神秘学识的研习过程中发掘出魔能祈唤的方式，这些禁忌的知识残章让你获得了持久的魔法能力。 第2级时，你获得两种自选的魔能祈唤（祈唤的具体内容见后文）。在获得更高的邪术师等级后你还可以习得其它的魔能祈唤，具体数据见“邪术师职业表”中“已知祈唤”一栏。 另外，你提升本职的等级时，可以用新的祈唤替换一个已学会的祈唤，但你的角色必须满足学习新祈唤的先决条件。 | CN4: 物品注法 | CO4: 在第2级，你获得为普通物品注入魔法的能力。使用此特性创造的魔法物品是永久性魔法物品的原型。 已知注法 当你获得这个特性时，从职业描述末尾的“奇械师注法”列表中选择选择四个奇械师注法习得。当你提升奇械师等级时，还能够根据“奇械师职业表”习得更多注法。 当你提升一个奇械师等级时，你能够习得一个新的奇械师注法来来替换一个原有的已知注法。 为物品进行注法 每当你完成一个长休后，你可以触摸一个非魔法的物体，使用奇械师注法来把它变成一个魔法物品。注法只能作用于注法描述中写明的指定类型物品。如果该物品需要调谐，你可以在为物品进行注法的那一刻调谐到它，或者你可以放弃调谐，以便其他人能够调谐到该物品。如果你决定以后与这个物品进行调谐，你必须进行通常的调谐程序（参见《地下城主指南》第136页中的“调谐”）。 你的注法持续时间无限，但当你死亡时，注法会在你智力调整值的天数后消失（至少1天）。如果你将某个注法从已知中替换掉，该注法的效果也将消失。 你能在一次长休后为复数物品进行注法；注法物品的最大数量请参见“奇械师职业表”。你必须触摸每一个物体，且一种注法在同一时间内只能存在于一个物品上。如果你试图超过你的最大注法量，则最旧的注法立即结束，然后新的注法适用。 | CP4: 动作如潮 | CQ4: 第2级起，你可以在短时间内突破极限，以使你在自己回合内执行一个额外的动作。 该特性在使用后必须完成一次短休或长休才能再使用。第17级起，你可在休息前使用两次该特性，但每一回合只能使用一次。 | CR4: 游侠战斗风格 | CS4: 第2级起，你将精进于一种战斗风格，从下列选项中选择其一。另外，即使你有多次选择战斗风格的机会，也不能重复选择同一个战斗风格。[注意：不要在这里选好下拉之后就不管它了，请务必清晰记录你究竟选择了什么战斗风格] 箭术Archery 使用远程武器进行攻击检定时具有+2加值。 防御Defense 着装护甲时，你的AC获得+1加值。 对决Dueling 单手持用一把近战武器，且并未同时持用其他武器时，你用该武器攻击的伤害掷骰获得+2加值。 双武器战斗Two-Weapon Fighting 使用两把武器战斗时，你可以将相应属性调整值加到第二次攻击的伤害上。 | CT4: 鲁莽攻击 | CU4: 第2级起，你可以抛弃一切防御的执念进行狂乱的攻击。你在自己回合内发动第一次攻击时，可以选择发动鲁莽攻击。 使用此特性后，你本回合内所有使用力量值发动的近战武器攻击具有优势。 此后，所有对你发动的攻击检定也将具有优势，且该优势持续存在至你的下个回合。 | CV4: 荒野形态 | CW4: 第2级起，你可以用动作以魔力变化为曾见识过的野兽形态。该特性可以使用两次，且在完成一次短休或长休后，你将重新获得所有消耗掉的荒野形态次数。 你的德鲁伊职业等级决定了你可以变化的野兽种类，你可以变化成任意没有飞行或游泳速度且挑战等级为1/4 或更低的野兽形态。 野兽形态 Beast Shapes 等级 最高CR 限制 范例 2nd 1/4 没有飞行或游泳速度 狼 wolf 4th 1/2 没有飞行速度 鳄鱼 crocodile 8th 1 － 巨鹰 giant eagle 你可以在数个小时里保持着野兽形态，其持续时间具体数值等于你的德鲁伊职业等级的一半（向下取整）。你可以在持续时间过后恢复原形，或者你也可以再次使用此特性来维持变形。 另外，你也可以在你的回合内用一个附赠动作来恢复原形。在你陷入昏迷、生命值为0或者死亡的时候，变形将自动解除。 你变形时必须遵从以下规则： • 你的游戏数据替换为新形态的数值，但你仍保持你的阵营、个性，以及智力值、感知值、魅力值。你保留技能与豁免的熟练项，并且获得新形态的技能和豁免熟练项。如果新形态有你已具有的的熟练项且该熟练项的加值高于你的熟练加值，则使用新形态的熟练加值。你不能使用新形态可能拥有的传奇动作或巢穴动作。 • 变形后，你使用新形态的生命值和生命骰。变回原形时，你的生命值恢复变形之前的数值。而任何让你的生命值降至0的伤害，都可以使你变回原形并承受该伤害的溢出伤害量。 例如，你在动物形态下受到了10点伤害而你只剩1点生命值，则你变回原形并受到9点伤害。只要超过的伤害没有将你原形的生命值降至0，你就不会因此陷入昏迷。 • 你不能施法，并且任何说话或者需要用手的动作，在你处于野兽形态时都将受到限制。变形不会打断你正在专注的法术，也不会妨碍你执行作为已施展法术（例如召雷术call lightning）一部分的一些动作。 • 你保持从职业、种族或其它来源特性的收益，并且可以在新形态身体能力允许下使用这些特性。不过，你无法使用任何原有的特殊感官（例如黑暗视觉），除非你的新形态也具有这种感官。 • 变形时，你可以选择将你的装备丢在所处空间，或者将其融入新形态，又或者直接着装在身上。新形态直接着装的装备可以如常起作用，但DM有权基于新形态的体型和身姿作出判断，并最终决定新形态使用该装备是否合理。装备不会改变大小来适应新形态，新形态无法着装一些装备时，该装备会掉落你所处空间或融入新形态中。融入新形态的装备失去其效应，且在你变回原形时才能恢复。 | CX4: 演员 | CY4: 精通于模仿和演戏，让你获得下列增益： • 你的魅力增加1，上限为20。 • 当你试图将自己扮演成另一个人时，你进行魅力（欺瞒）和魅力（表演）检定时具有优势。 • 你可以模仿另一个生物的说话口吻和声音。前提是你必须听过被模仿者至少1分钟的说话或发声。 对方聆听你的模仿时可以进行一次感知（洞悉）检定，并与你的魅力（欺瞒）检定进行对抗，若对方胜出便会意识到声音是模仿出来的。 | CZ4: 3
A5: 矮人 | C5: 德鲁伊 | D5: 1d8 | G5: =VLOOKUP(E1,F1:G4,2,0) -> 5 | J5: =VLOOKUP(H1,I1:J4,2,0) -> 3 | L5: 4 | M5: 17 | O5: 德鲁伊 | P5: 荒野形态 | R5: 荒野形态 | S5: =P98 -> 2 | U5: 标枪 | V5: 1d6 | W5: 穿刺 | X5: 5 sp | Y5: 投掷(射程30/120) | Z5: 2 | AA5: =背包!B9 -> 0 | AB5: 吹矢(50) | AC5: - | AD5: 1gp | AE5: 1 | AG5: 艺人Entertainer | AH5: 人见人爱ByPoularDemand。你总是能找到表演场地，通常是酒馆或者客栈，偶尔也会是马戏团、剧院，甚至是贵族厅堂。只要你每晚维持出演，就可以在表演地获得简朴或舒适水平的免费食宿（取决于表演的规模）。此外，表演生涯使你在当地获得一定名气。当你在演出的城镇被陌生人认出时，通常都会受到善待。 | AI5: 艺人理想 | AJ5: 艺人牵绊 | AK5: 艺人缺点 | AL5: 艺人特点 | AM5: 艺人技能熟练项 | AN5: 艺人工具熟练项 | AO5: 艺人额外语言 | AP5: 艺人背景装备 | AQ5: 艺人特殊选项 | BX5: 圣武士施法 | BY5: 第2级起，你学会通过冥想与祈祷引导神圣魔法，其原理与牧师相仿。参考第10章的施法规则，以及第11章的圣武士法术列表。 法术的准备与施展 Preparing and Casting Spells “圣武士职业表”里记录了你用以施展圣武士法术的1环及更高环阶法术位数量。施展一个圣武士法术时，你必须同时消耗其对应环阶的法术位。而已消耗的法术位则可以通过完成一次长休进行恢复。 你可以准备圣武士法术列表中所有符合当前施展条件的法术。准备法术时，你所准备法术的总数等于你的魅力调整值＋你圣武士职业等级的一半（最少可准备一个）。另外，你只能准备已获得相应环阶法术位的法术。 你可以在完成长休后改变你的准备法术列表。准备新的圣武士法术列表时，你要再花时间进行祈祷和冥想。准备时，你要为你列表上每个法术的每个环阶都花费至少1分钟时间。 施法关键属性 Spellcasting Ability 你的法术源自你坚定信念产生的力量，因此魅力是你施展圣武士法术的关键属性。每当你的圣武士法术需要施法关键属性是均指向你的魅力值。而你圣武士法术的豁免DC和攻击检定，则使用你的魅力调整值。 法术豁免 DC＝8＋你的熟练加值＋你的魅力调整值 法术攻击调整值＝你的熟练加值＋你的魅力调整值 法器 Spellcasting Focus 你可用圣徽（见第5章）作为施展你圣武士法术的法器。 | BZ5: 法术精通 | CA5: 第18级时，你对特定的法术精熟于心，甚至可以随意施展这些法术。 选择你法术书中的一项1环法师法术和一项2环法师法术，此后只要你准备了它们，就可以随意施展其最低环阶版本，且无需消耗法术位。你也可以消耗法术位来施展其更高环阶版本。 通过8小时的研习，你可以将这两项法术中的任一项替换为同环阶的其他法术。 | CB5: 超魔法 | CC5: 第3级起，你可以扭曲所施展的法术使其符合你的需求。从下述超魔法选项中选择其二。随后你将在第10 和第17级分别再获得其一。 除非特别说明，否则对一个法术只能应用一种超魔法项。 谨慎法术 Careful Spell 施展一个让其他生物进行豁免的法术时，你可以让其中一些生物免受法术的全额威力。实现该效应需要你使用1术法点，并指定一定数量的目标生物，其最大数量等于你的魅力调整值（至少为 1）。而被指定的生物将直接成功通过法术的豁免检定。 远程法术 Distant Spell 施展一个施法距离不小于5尺的法术时，你可以使用1术法点使该法术的施法距离翻倍。施展一个施法距离为触及的法术时，你可以使用1术法点将法术的施法距离改为30尺。 强效法术 Empowered Spell 为法术进行伤害掷骰时，你可以使用1术法点重掷其中一定数量的骰子。重掷骰子的最大数等于你的魅力调整值（至少为1），且你必须接受新的结果。 强效法术超魔可以与其他超魔法选项合用。 延效法术 Extended Spell 施展一个持续时间不短于1分钟的法术时，你可以使用 1术法点使法术的持续时间翻倍，但其最终结果不能超过24小时。 升阶法术 Heightened Spell 施展一个迫使一个生物进行豁免以抵御其效应的法术时，你可以花费3术法点使该法术所有目标中的一个首次进行对抗该法术的豁免时具有劣势。 瞬发法术 Quickened Spell 施展一个施法时间为1动作的法术时，你可以使用2术法点将其施法时间改为1附赠动作。 精妙法术 Subtle Spell 施展一个法术时，你可以使用1术法点无视该法术施法必须的言语成分或动作成分。 孪生法术 Twinned Spell 施展一个影响单一生物，且施法距离并非自身的法术时，你可以使用等于法术环阶的术法点（戏法消耗1点），并在法术施法距离内再指定另一个目标。以高环阶施展的法术，其升环施法后如果目标变为复数则无法再使用该方式增加其目标。 例如，魔法飞弹magic missile和灼热射线scorching ray 可能无法使用该超魔法项，而冷冻射线ray of frost 和繁彩球chromatic 则不会出现该问题。 适用该超魔的法术在其当前环阶时不能同时指定多个生物为目标。比如，魔法飞弹magic missile 和灼热射线scorchingray 不符合条件，而冷冻射线ray of frost 和繁彩球chromatic orb 则符合条件 | CD5: 休憩曲 | CE5: 第2级起，你可以在短休时用轻柔的音乐或话语帮助伙伴们恢复伤势。 如果你或任何友方生物可以在其短休时听到你的演奏声，且决定在此时使用生命骰恢复生命值，则其恢复量可以额外增加1d6。 该额外恢复的数值在达到特定职业等级时可以再增加。第9级时增为1d8，第13级时增为1d10，第17级时增为1d12。 | CF5: 摧毁不死生物 | CG5: 第5级起，当不死生物进行对抗你驱散特性的豁免失败时，如果其挑战等级等于或低于一个既定的下限，则该不死生物将被即时摧毁。相应的数值列举在表格“摧毁不死生物”中。 摧毁不死生物 Destory Undead 牧师等级 摧毁不死生物的挑战等级 5th 1/2 或更低 8th 1或更低 11th 2 或更低 14th 3 或更低 17th 4 或更低 | CH5: 无甲移动 | CI5: 第2级起，当未穿着任何护甲也没持用盾牌时，你的移动速度增加10尺。该加值将随着武僧职业等级的提升而增加，具体数值见“武僧职业表”中“无甲移动”一栏。 第9级起，你在自己的回合内，可以在垂直平面或水面等地形移动，但移动结束时你必须处在不会坠落的地方。 | CJ5: 灵巧动作 | CK5: 第2级起，你精妙的反应与身手使你的行动无比迅速。 你每回合有一次使用一种特殊附赠动作的机会，该附赠动作可用以执行撤离Disengage、疾走Dash 或躲藏Hide三项动作其中之一。 | CL5: 魔契恩泽 | CM5: 第3级时，你的宗主赋予你一份馈赠作为你忠诚服务的回馈。你可以从下列特性中自选其一。 链之魔契 Pact of the Chain 你习得法术获得魔宠 find familiar，并可以把它作为一个仪式施展。此法术不计入你的已知法术数量。施展该法术时，你可以选择召唤一个普通的生物，或是下列特殊生物之一：小魔鬼 imp、伪龙 pseidodragon、夸赛魔quasit、或小妖精 sprite。 此外，当你执行攻击动作时可以放弃所有攻击中的一次攻击，转而让你的魔宠使用其反应发动一次攻击。 刃之魔契 Pact of the Blade 你可以用一个动作从空着的手中创造一把契约武器。你每次创造契约武器时都可以从近战武器列表中选择它的形态（见第5章的武器选项）。当你使用该武器时，将视为拥有该武器的熟练项。在攻击对非魔法攻击或伤害具有抗性或免疫的目标时，该武器将视为魔法武器。 你的契约武器在离你5尺外的区域停留超过1分钟或更长时间，其将自然消失。当你再次创造契约武器、解散契约武器（无需动作）或是死亡的情况下，契约武器也会消失不见。 你可以通过一个特殊的仪式把持有的魔法武器变为你的契约武器。该仪式花费1小时，并且可以在短休时进行。仪式完成后，你随时可以解散该武器，以将其转移到一个异次元空间之中。而每当你再次创造契约武器时再将它召唤出来。该仪式无法对神器或智能武器起作用。如果你死亡；或是花费1小时对另外一把武器举行了仪式；或是你通过1小时的仪式打破该契约，则该武器便不再是你的契约武器。如果在它处于异次元空间时你打破契约，那么该武器将会出现在你的脚边。 书之魔契 Pact of the Tome 你的宗主给予你一本名为“影之书”的魔法书。获得该特性后，从任意职业法术列表中选择三个戏法（这三个戏法不必来自同一个列表）。该魔法书在你身上时，你可以随意施展那些法术。它们不算入你的已知戏法数量中。这些法术就算本来不属于邪术师法术列表，你也将其视为邪术师法术。 如果你丢失了自己的影之书，你可以举行一个1小时的仪式，并从你的宗主处获得一个替代品。仪式可以在短休或长休期间完成，而它会摧毁之前的魔法书。当你死亡时，该书也将化为灰烬。 | CN5: 奇械师专业 | CO5: 在第3级，你造成自己将成为哪方面的专家：炼金师、魔炮师或战地匠师，这三个专业会在职业描述的最后进行说明。你的选择将决定你在5级、9级和15级获得的特性。 | CP5: 武术范型 | CQ5: 第3级时，你选择一种范型以体现你的战斗风格和技巧。 你可以从诸如勇士Champion、战斗大师Battle Master、奥法骑士Eldritch Knight 等范型中选择其一。 随后，你将在第3、第7、第10、第15、第18级获得所选范型的相应特性。 你可以在拓展之中找到更多的战士范型。 | CR5: 游侠施法 | CS5: 第2级起，你学会运用自然世界的魔法本源进行施法，你的施法方式与德鲁伊类似。参考第10章的施法基本规则以及第11章的游侠法术列表。 法术位 Spell Slots “游侠职业表”中记录了你可用以施展你游侠法术的1环及更高环阶法术位数量。施展某个游侠法术时，你必须同时消耗其对应环阶的法术位。而已消耗的法术位则可以通过完成一 次长休进行恢复。 例如，若你已知1环法术化兽为友 animal friendship 且有一枚可用的1环法术位和一枚可用的2环法术位，则两法术位都可用来施展该法术。 已知法术 Spell Known of 1st Level and Higher 你从游侠法术列表里选两个1环法术作为自己的已知法术。 “游侠职业表”中“已知法术”一栏记录了你获得更多已知法术时的相应等级。你只能获取已有相应环阶法术位的法术。 比如，当你达到第5级时，你将获得一个1环或2环法术。 另外，你每提升一个游侠等级，还可以从游侠法术列表里选择一个新法术来代替一个已知法术列表中的旧法术。但是，你必须拥有新法术的相应环阶法术位。 施法关键属性 Spellcasting Ability 你的魔法来自你与自然的同调，因此感知是你施展游侠法术的关键属性。每当你的游侠法术需要施法关键属性时均指向你的感知值。而你游侠法术的豁免DC和攻击检定，则使用你的感知调整值。 法术豁免 DC＝8＋你的熟练加值＋你的感知调整值 法术攻击调整值＝你的熟练加值＋你的感知调整值 | CT5: 险境感知 | CU5: 第2级时，你获得对周遭异常情况超乎寻常的感测力，让你能先一步脱离危险。 在受到你能看见的效应（诸如陷阱和法术）影响时，你对其进行的敏捷豁免具有优势。 你无法在目盲、耳聋或是失能的状态下从此特性获益。 | CV5: 德鲁伊结社 | CW5: 第2级时，你将选择参与一个德鲁伊结社。你可以从大地结社Circle of the Land 或月亮结社Circle of the Moon 中选择其一。 随后，你将在第2、第6、第10、第14级时获得所选结社相应的特性。你可以在拓展中找到更多的结社。 | CX5: 冲锋手 | CY5: 当你执行疾走动作时，你可以用附赠动作发动一次近战武器攻击，或推撞一个生物。 若你在使用附赠动作前至少直线行走10尺，则该次攻击的伤害掷骰具有+5加值（若你选择近战攻击且命中），或目标被推出至多10尺（若你选择推撞且成功）。 | CZ5: 4
A6: 龙裔 | C6: 武僧 | D6: 1d8 | E6: 总等级 | F6: =主要情况!W3+主要情况!W4+主要情况!W5 -> 5 | L6: 5 | M6: 27 | O6: 武僧 | P6: 气 | R6: 气 | S6: =P56 -> 5 | U6: 轻锤 | V6: 1d4 | W6: 钝击 | X6: 2gp | Y6: 轻型 投掷(射程20/60) | Z6: 2 | AA6: =背包!B10 -> 0 | AB6: 弩矢(20) | AC6: - | AD6: 1gp | AE6: 1.5 | AG6: 角斗士Gladiator | AH6: 人见人爱ByPoularDemand。你总是能找到表演场地，通常是酒馆或者客栈，偶尔也会是马戏团、剧院，甚至是贵族厅堂。只要你每晚维持出演，就可以在表演地获得简朴或舒适水平的免费食宿（取决于表演的规模）。此外，表演生涯使你在当地获得一定名气。当你在演出的城镇被陌生人认出时，通常都会受到善待。 | AI6: 角斗士理想 | AJ6: 角斗士牵绊 | AK6: 角斗士缺点 | AL6: 角斗士特点 | AM6: 角斗士技能熟练项 | AN6: 角斗士工具熟练项 | AO6: 角斗士额外语言 | AP6: 角斗士背景装备 | AQ6: 角斗士特殊选项 | BX6: 至圣斩 | BY6: 第2级起，你使用近战武器攻击命中一个生物时，可以消耗一枚法术位，并对目标造成除武器伤害外附加的光耀伤害。 额外伤害的数值为1环法术位时的2d8，以及更高法术位时每比1环高一环就外加1d8，其最高值为5d8。如果目标是不死生物或邪魔，则该伤害将再额外增加1d8，至高提升至6d8。 | BZ6: 招牌法术 | CA6: 第20级时，你精通两个强大的法术，甚至可以用更低的成本施展这些法术。 选择你的法术书中的两个3环法师法术，作为你的招牌法术。 此后这两个法术将永远视为已准备法术，且不计入你的准备法术数量之中。你可以施展这两个法术的 3环版本各一次，且无需消耗法术位。 招牌法术使用后，需要完成一次短休或长休才能再次使用。 你也可以消耗法术位施展这两个法术的更高环阶版本。 | CB6: 术法复苏 | CC6: 第20级时，你每完成一次短休，可以恢复4术法点。 | CD6: 吟游诗人学院 | CE6: 第3级时，你将选择加入一个吟游诗人的学院协会，以探寻更精深的技艺。 你可以从逸闻学院 College of Lore 或勇气学院 College of Valor 中选择其一。 随后，你将在第 3、第 6 和第14 级时获得相应的职业特性。 你可以在拓展中找到更多的吟游诗人学院。 | CF6: 神圣干预 | CG6: 第10级起，你可以在迫切需要帮助时，召唤神祇的协助。 你需要用一个动作来请求所信仰神祇的帮助。描述你所需要的帮助，然后掷d100。如果你的结果等于或者小于你的牧师等级，你将得到神祇的回应。回应的结果由DM作出选择；此时通常请求任何牧师法术或者领域法术的效应都在可接受范围内。 如果你的神祇回应了请求，你在此后的7日内无法再次使用该特性；否则你可以在完成长休后再次使用该特性。 到达20级后，你的呼唤将自动得到神祇的回应，无需再掷d100。 | CH6: 宗派 | CI6: 第3级时，你选择投入一个宗派精进你的技艺。你可以从散打宗、暗影宗、四象宗中选择其一。 随后，你的将在第 3、第6、第 11、第17级时获得相应宗派的特性传承。 你可以在拓展中找到更多的武僧宗派。 | CJ6: 游荡者范型 | CK6: 第3级时，你选择学习一种特定的战斗范型。你可以从盗贼 Thief、刺客 Assassin 或者诡术师 Arcane Trickster 中选择其一。 随后，你将在第3，第9，第13、第17级时获得所选范型的相应特性。 你可以在拓展之中找到更多的游荡者范型。 | CL6: 玄奥秘法 | CM6: 第11级时，你的宗主赋予你一种称为秘法的魔法奥秘。 你可以选择一个6环的邪术师法术作为你的玄奥秘法。 你施展秘法时无需消耗法术位，而消耗掉的秘法可以通过完成一次长休进行恢复。 在获得更高的邪术师等级后，你将可以选择更多的邪术师法术以该方式施展：第13级时可选一个7环法术，15级时可选一个8环法术，17级时可选一个9环法术。完成一次长休后，所有消耗掉的秘法都会恢复。 | CN6: 称手工具 | CO6: 在第3级，你将学习如何精确地制作你所需要的工具：使用修补工具，你可以在离你5英尺内的未占据空间中魔法性地制作出一套工匠工具。这一制造需要1小时不间断的工作，可以在短休或长休的过程中进行。这套工具是魔法的产物，但其本身是非魔法的，当你再次使用此特性时，之前制造的工具就会消失。 | CP6: 战士额外攻击 | CQ6: 第5级起，你在自己回合内执行攻击动作时可以发动两次攻击而非一次。 第11级后，你可以攻击三次。第20级后可以攻击四次。 | CR6: 游侠范型 | CS6: 第3级时，你选择学习一种特定的战斗范型。你可以从猎人Hunter或驯兽师Beast Master中进行选择。随后，你将在 第3，第7，第11、第15级时获得所选范型的相应特性。 | CT6: 原初道途 | CU6: 第3级时，你选择一种道途来塑造你狂怒时的特质。你可以从狂战士Berserker 和图腾武者Totem Warrior 中选择其一。 随后，你将在第3、第6、第10、第14级时获得所选道途的相应特性。 拓展之中存在更多的原初道途选项。 | CV6: 德鲁伊不朽身 | CW6: 第18级起，你行使的原初荒野魔力让你的衰老速度减缓。 每经过10年的岁月，你的身体就仿佛只过了1年。 | CX6: 强弩专家 | CY6: 你凭借一系列的用弩修行，获得下列增益： • 你使用拥有熟练项的弩时，忽略其装填属性。 • 你在敌对生物５尺范围内发动远程攻击检定时，不会因此而具有劣势。 • 你执行攻击动作以单手武器攻击后，可以用附赠动作使用一把正持握的手弩发动攻击。 | CZ6: 5
A7: 机关人 | C7: 游荡者 | D7: 1d8 | E7: 每级兼职血量 | F7: =J20+主要情况!AC12+主要情况!AE12 -> 0 | L7: 6 | M7: 32 | O7: 游荡者 | P7: 偷袭 | R7: 偷袭 | S7: =P140 -> 3d6 | U7: 硬头锤 | V7: 1d6 | W7: 钝击 | X7: 5gp | Y7: - | Z7: 4 | AA7: =背包!B11 -> 0 | AB7: 投石索弹丸(20) | AC7: - | AD7: 0.04gp | AE7: 1.5 | AG7: 平民英雄FolkHero | AH7: 好客乡民RusticHospitality。你因来自平民阶层而在乡民群众中倍感舒适。除非乡民们已经认为你会带来危险，否则你总能在普通人群中找到一个地方以供躲藏，休息或复原。他们能够掩护你逃脱法办，或者逃离追杀你的人，只是他们并不会为你而牺牲自己的性命。 | AI7: 平民英雄理想 | AJ7: 平民英雄牵绊 | AK7: 平民英雄缺点 | AL7: 平民英雄特点 | AM7: 平民英雄技能熟练项 | AN7: 平民英雄工具熟练项 | AO7: 平民英雄额外语言 | AP7: 平民英雄背景装备 | AQ7: 平民英雄特殊选项 | BX7: 神佑 | BY7: 第3级起，你体内涌动的神圣魔法使你免疫疾病。 | CD7: 吟游诗人专精 | CE7: 第3级起，你选择两个已有的技能熟练项。此后你进行所选技能的属性检定时，可以使用双倍的熟练加值。 第10级后，你可以再选择另外两个已有的技能熟练项从该特性中获益。 | CH7: 拨挡飞弹 | CI7: 第3级起，你可以用你的反应拨挡或抓取一个击中你的远程武器攻击。使用本特性后，该次攻击的伤害将被削弱，其减数值等于1d10＋你的敏捷调整值＋你的武僧职业等级。 当被拨挡攻击的伤害减少至0，且实施伤害的飞弹可以被你单手抓住时，你可以用此时空闲的手去抓取该飞弹。 此时你可以消耗1点气以该“飞弹”进行一次远程攻击，而该攻击将视为本次反应的一部分。 无论你是否具有被拨挡武器的熟练项，本次攻击中你都视为进行具有熟练项的攻击，所使用的飞弹也视为武僧武器，其射程为20/60尺。 | CJ7: 直觉闪避 | CK7: 第5级起，当一个你能看见的敌人攻击命中你时，你可以用反应让此次攻击的伤害减半。 | CL7: 魔能掌控 | CM7: 第20级时，你可以利用储备的魔力祈求你的宗主为你恢复已消耗的法术位。 你可以花1分钟祈求宗主的帮助，恢复所有你已消耗的契约魔法法术位。 使用该特性恢复法术位后，你必须完成一次长休才能再次使用该特性。 | CN7: 工具专精 | CO7: 从第6级起，你在使用你熟练的工具时，能够使用双倍的熟练加值。 | CP7: 不屈 | CQ7: 第9级起，你可以重掷失败的豁免检定。不过你必须采用重掷的结果。你必须完成一次长休才能再次使用该特性。 第13级起，你可以在两次长休之间使用两次该特性。 第17级起，你可以在两次长休之间使用三次该特性。 | CR7: 原初意识 | CS7: 第3级起，你可以消耗一枚游侠法术位，并用动作将你的意识集中在身处的区域，感测1里内是否存在以下类型生物（在偏爱地形中时，扩展至6里）：异怪、天界生物、龙、精类生物、邪魔、元素生物和不死生物。 所消耗法术位每提高一环阶感测效果持续时间就多加1分钟。另外，该特性并不会知晓生物的位置或数量。 | CT7: 野蛮人额外攻击 | CU7: 第5级起，你在自己回合内执行攻击动作时可以发动两次攻击而非一次。 | CV7: 野兽施法 | CW7: 第18级起，你在荒野变形状态下可以施展大部分的德鲁伊法术。 在野兽形态时，你可以完成德鲁伊法术的姿势与言语成分，但无法完成其材料成分的使用。 | CX7: 防御式决斗 | CY7: 先决条件：敏捷13或更高 当你持用一把已具有熟练项的灵巧武器时，若另一生物对你发动的近战攻击命中你，则你可执行反应并将你的熟练加值添加到本次攻击的AC中，此举还有可能导致本次攻击变为未命中。 | CZ7: 6
A8: 兽人 | C8: 邪术师 | D8: 1d8 | E8: 兼职血量 | F8: =F7*主要情况!W4 -> 0 | L8: 7 | M8: 38 | O8: 邪术师 | P8: 已知祈唤 | R8: 已知祈唤 | S8: =P161 -> 3 | U8: 长棍 | V8: 1d6 | W8: 钝击 | X8: 2 sp | Y8: 两用（1d8） | Z8: 4 | AA8: =背包!B12 -> 0 | AB8: 抗毒剂_小瓶 | AC8: 喝下瓶内液体的生物在1小时内进行对抗对毒素的豁免检定时具有优势。它无法为不死生物或构装生物提供任何增益。 | AD8: 50gp | AE8: 0 | AG8: 公会工匠GuildArtisan | AH8: 公会成员GuildMembership。你身为公会中一名备受尊敬的正式成员，可以享受到公会所提供的一些好处。公会中的同僚会在你需要时为你提供食宿，甚至在必要时为你安排身后事。公会在某些市镇设置有会馆，你可以以此作为与同行交流的场所，也可以从中开发潜在的客户、合作伙伴或雇工。 | AI8: 公会工匠理想 | AJ8: 公会工匠牵绊 | AK8: 公会工匠缺点 | AL8: 公会工匠特点 | AM8: 公会工匠技能熟练项 | AN8: 公会工匠工具熟练项 | AO8: 公会工匠额外语言 | AP8: 公会工匠背景装备 | AQ8: 公会工匠特殊选项 | BX8: 神圣誓言 | BY8: 第3级起，你将立下神圣誓言，并永远与你的圣武士身份同在。你在此之前的圣武士修行被认为仅仅是接受了一条道路而尚未立誓遵从，你之前所躬行的行为都是为此刻作准备。神圣誓言包括奉献之誓Oath of Devotion、古贤之誓Oath of the Ancients、复仇之誓Oath of Vengeance 等，你可从中选择其一。更多誓言可在扩展之中找到。 随后，你将在第3，第7，第15 和第20级获得所选圣誓的相应特性。 圣誓法术 Oath Spells 每种誓言都有其相应的圣誓法术列表。当你达到表中所示的圣武士等级时，你将同时获得其对应的圣誓法术。圣誓法术一旦获得，将会一直在你的准备法术列表中，且不计入你的每日准备法术上限。 任何圣誓法术对你而言都是圣武士法术，而不论其是否在圣武士法术列表之上。 引导神力 Channel Divinity 你的誓言使你获得引导神祇所授神圣能量的能力，引导的能量将用以实现各种魔法效应。誓言赋予的相应效应，可以参考相关誓言的描述内容。 引导神力时，神力最终产生的效应由你自行选择。引导神力后，你必须完成一次短休或长休才能再次使用该特性。 某些引导神力的效应需要豁免，其豁免DC等于你的圣武士法术豁免DC。 | CD8: 激励之源 | CE8: 第5级起，你可以在完成短休或长休后恢复你已消耗的诗人激励次数。 | CH8: 轻身坠 | CI8: 第4级起，当你要承受坠地伤害时，你可以使用反应将伤害减少等同于五倍武僧职业等级的数值。 | CJ8: 游荡者反射闪避 | CK8: 第7级起，你可以灵巧躲过某些特定的区域效应，比如红龙的火焰吐息或是法术冰风暴Ice storm。 你在成为某一范围效应影响对象时，若该效应允许你通过成功的敏捷豁免来使伤害减半，则你在该豁免成功时不受伤害，而豁免失败时只受一半伤害。 | CN8: 灵光一闪 | CO8: 从第7级起，你获得了在压力下想出解决方案的能力。当你或距离你30英尺内的可见生物进行属性检定或豁免检定时，你能以一个反应将你的智力调整值添加到此次检定中。 你能使用此能力的次数等于你的智力调整值（最少1次）。在你完成一次长休后，将恢复所有可用次数。 | CR8: 游侠额外攻击 | CS8: 第5级起，你在自己回合内执行攻击动作时可以攻击两次而非一次。 | CT8: 快速移动 | CU8: 第5级起，你在未着装重甲时速度提升10尺。 | CV8: 大德鲁伊 | CW8: 第20级时，你可以无限次的使用荒野变形。 另外，你还可以将德鲁伊法术中的姿势和言语成分，以及非无价值且不被法术消耗的材料成分忽略。你在原形态和荒野形态下都可以从此特性获益。 | CX8: 双持客 | CY8: 你精通双持武器进行作战，并获得下列增益： • 当你两手各持用一把武器时，你的AC获得+1加值。 • 你进行双持武器战斗时所持用的单手近战武器可以不具备轻型武器属性。 • 你可以在正常只能拔出或入鞘一把武器时，同时拔出或入鞘两把单手武器。 | CZ8: 7
A9: 半兽人 | C9: 奇械师 | D9: 1d8 | E9: 每级第二兼职血量 | F9: =K20+主要情况!AC12+主要情况!AE12 -> 0 | L9: 8 | M9: 44 | O9: 战士 | P9: 动作如潮 | R9: 动作如潮 | S9: =P182 -> 1 | U9: 镰刀 | V9: 1d4 | W9: 挥砍 | X9: 1gp | Y9: 轻型 | Z9: 2 | AA9: =背包!B13 -> 0 | AB9: 水晶 | AC9: 奥术法器是一件用来引导奥术法术的特殊物品，它可以是一枚法球、一块水晶、一只权杖、一根特制法杖、一根魔杖般的长木条或是其它类似的物品。术士、邪术师或法师能将这样的物品用作施法法器。 | AD9: 10gp | AE9: 1 | AG9: 公会商人GuildMerchant | AH9: 公会成员GuildMembership。你身为公会中一名备受尊敬的正式成员，可以享受到公会所提供的一些好处。公会中的同僚会在你需要时为你提供食宿，甚至在必要时为你安排身后事。公会在某些市镇设置有会馆，你可以以此作为与同行交流的场所，也可以从中开发潜在的客户、合作伙伴或雇工。 | AI9: 公会商人理想 | AJ9: 公会商人牵绊 | AK9: 公会商人缺点 | AL9: 公会商人特点 | AM9: 公会商人技能熟练项 | AN9: 公会商人工具熟练项 | AO9: 公会商人额外语言 | AP9: 公会商人背景装备 | AQ9: 公会商人特殊选项 | BX9: 圣武士额外攻击 | BY9: 第5级起，你在自己回合内执行攻击动作时可以攻击两次而非一次。 | CD9: 反迷惑 | CE9: 第6级起，你获得用音乐或话语来打断心控效应的能力。 你可以使用一个动作开始一场持续至你的下一回合结束的演出。 在这段时间内，你与你身边30尺内的友方生物进行对抗恐慌或魅惑效应的豁免检定具有优势。该生物必须能听到你的声音才能获得此增益。 这场表演只有当你陷入失能、沉默状态，或主动终止（无需动作）时才会提前结束。 | CH9: 武僧额外攻击 | CI9: 第5级起，你在自己回合内执行攻击动作时可以发动两次攻击而非一次。 | CJ9: 可靠才能 | CK9: 第11级起，你自身技能经过精炼而更趋于完美。每当你进行的属性检定可以使用熟练加值时，你可以将d20骰中9或以下的结果都视为10。 | CN9: 魔法物品熟稔 | CO9: 当你达到10级时，你对如何使用和制作魔法物品有了深刻的理解： ·你一次最多可以调谐四个魔法物品。 ·如果你制作一件稀有度为普通或非普通的魔法物品，时间花费只需通常的四分之一，而且金钱花费只有通常的一半。 | CR9: 游侠大地行者 | CS9: 第8级起，你穿过非魔法的困难地形时不会消耗额外移动力。你穿过非魔法的植物时不会消耗额外移动力，且这类植物的荆棘、毛刺或类似的危害物也无法对你造成伤害。 另外，在抵抗魔法制造或控制的植物造成的移动障碍效应时（例如纠缠术entangle），你的豁免检定具有优势。 | CT9: 野性直觉 | CU9: 第7级时，你的直觉变的异常敏锐，从而使你骰先攻时具有优势。 此外，如果你在战斗开始时被突袭但并未陷入失能，则你仍可以在你的第一回合正常行动。不过你必须在进行任何其它行动前进入狂暴。 （假如使用。ri指令进行先攻，DM可改为先攻检定具有+5加值） | CX9: 地城探索者 | CY9: 由于对隐藏的陷阱和密门特别敏感，你获得下列增益： • 你为搜寻密门进行的感知（察觉）和智力（调查）检定具有优势。 • 为躲避或抵抗陷阱而进行的豁免检定具有优势。 • 你对陷阱所造成的任何伤害都具有抗性。 • 你以快速步调旅行时无需承受通常情况下的被动感知（察觉）值的-5减值。 | CZ9: 8
A10: 提夫林 | C10: 战士 | D10: 1d10 | E10: 第二兼职血量 | F10: =F9*主要情况!W5 -> 0 | L10: 9 | M10: 57 | O10: 圣武士 | P10: 圣疗 | R10: 圣疗 | S10: =P203 -> 25 | U10: 矛 | V10: 1d6 | W10: 穿刺 | X10: 1gp | Y10: 投掷(射程20/60) 两用(1d8) | Z10: 3 | AA10: =背包!B14 -> 0 | AB10: 法球 | AC10: 奥术法器是一件用来引导奥术法术的特殊物品，它可以是一枚法球、一块水晶、一只权杖、一根特制法杖、一根魔杖般的长木条或是其它类似的物品。术士、邪术师或法师能将这样的物品用作施法法器。 | AD10: 20gp | AE10: 3 | AG10: 隐士Hermit | AH10: 探索Discovery。你寂寥的长期隐居令你发现了某些独特而强大的秘密。这项发现的具体内容与你的隐居的理由密切相关。你或许是找到了与宇宙真相，神祇本质，异界大能或是自然之力等相关的伟大真理。你也可能是发现了某处任何人都未曾发现的地点。你可能揭露了久被遗忘的真相，或是发掘出了久远史前的遗物。或者，你也可能是发现了那些一手导致你流放的家伙们相关的情报，而那也就是你重返凡世的契机。 | AI10: 隐士理想 | AJ10: 隐士牵绊 | AK10: 隐士缺点 | AL10: 隐士特点 | AM10: 隐士技能熟练项 | AN10: 隐士工具熟练项 | AO10: 隐士额外语言 | AP10: 隐士背景装备 | AQ10: 隐士特殊选项 | BX10: 守护灵光 | BY10: 第6级起，你与友方生物在你身边10尺内进行豁免检定时，可以将你的魅力调整值作为加值加在其豁免结果上（至少为+1）。 提供该加值时你必须保持意识清醒。 第18级起，该灵光的作用范围扩展至30尺。 | CD10: 魔法奥秘 | CE10: 第10级起，你从旋律中了解了大量的魔法知识，使你可以从所有职业的法术列表里选择两个法术（包括诗人列表）加入已知法术中。 你所选择的法术必须是你当前等级可以施展的环阶法术或戏法。 所选法术对你而言视为吟游诗人法术，且包含在“诗人职业表”上“已知法术”一栏所记录的数量之内。 第14和第18级时，你可以分别使用此特性再习得两个任选法术。 | CH10: 震慑拳 | CI10: 第5级起，你能够阻碍敌人体内的气的流动。你的近战武器攻击命中时，可以消耗1点气尝试发动震慑拳。 被命中目标必须进行一次体质豁免，豁免失败则受到震慑，并持续至你的下一回合结束。 | CJ10: 听声辨位 | CK10: 第14级起，只要能听到声音，你就可以定位身边10尺内躲藏或隐形的生物。 | CN10: 储法物品 | CO10: 当你达到第11级时，你将习得如何在一个物体中储存一个法术。当你完成一次长休，你能够触摸一件简易武器、军用武器或一个你可以将其作为法器使用的物品，从奇械师法术列表中选择一个施法时间为一个动作的1环或2环法术（你不需要准备这个法术）。 任何在手中持有该物品的生物能够使用你的施法关键属性来以一个动作通过该物品产生储存法术的效果。如果该法术需要专注，则启动物品的生物必须进行专注。该法术将留存在物品中，直到使用次数用完（最大使用次数等于你智力调整值的两倍（至少两次））或直到你再次使用该特性。 | CR10: 遁术 | CS10: 第10级起，你可以花1分钟来为自己制作伪裝。你必须能取用新鲜的泥土、植物、煤烟等天然物料进行制作。 伪装完成后，你可以将自己贴上至少跟自己等高等阔的实体表面（如树干或墙壁）并尝试躲藏。如果你留在原地不移动且不执行动作，则你的敏捷（隐匿）检定获得+10加值。 一旦移动、执行动作或执行反应，你都必须重新伪装以重获该增益。 | CT10: 凶蛮重击 | CU10: 第9级起，计算近战攻击的重击伤害时，你可以额外骰一个所用武器的伤害骰。 第13级时，你可以额外骰两个；第17级时，你可以额外骰三个。 | CX10: 耐性 | CY10: 由于坚强而持久，你获得下列增益： • 你的体质加1，上限为20。 • 当你掷生命骰恢复生命值时，每粒生命骰可恢复的最小生命值等于你体质调整值的两倍（最小为２）。 | CZ10: 9
A11: 阿斯莫 | C11: 圣武士 | D11: 1d10 | L11: 10 | M11: 64 | O11: 游侠 | P11: 宿敌个数 | R11: 宿敌个数 | S11: =P224 -> 1 | U11: 轻弩 | V11: 1d8 | W11: 穿刺 | X11: 25gp | Y11: 弹药(射程80/320) 装填 双手 | Z11: 5 | AA11: =背包!B16 -> 0 | AB11: 权杖 | AC11: 奥术法器是一件用来引导奥术法术的特殊物品，它可以是一枚法球、一块水晶、一只权杖、一根特制法杖、一根魔杖般的长木条或是其它类似的物品。术士、邪术师或法师能将这样的物品用作施法法器。 | AD11: 10gp | AE11: 2 | AG11: 贵族Noble | AH11: 特权地位PositionofPrivilege。由于你的贵族血统，人们总是会予你优待。高等社会愿意接纳你，人们认同你有权去任何你想去的地方。平民们会尽力满足你的要求，避免你产生任何不快，而那些同样出身高贵的人则会视你为同一个社会圈子的人。你还可以在必要时前去拜会任何当地的贵族。 | AI11: 贵族理想 | AJ11: 贵族牵绊 | AK11: 贵族缺点 | AL11: 贵族特点 | AM11: 贵族技能熟练项 | AN11: 贵族工具熟练项 | AO11: 贵族额外语言 | AP11: 贵族背景装备 | AQ11: 贵族特殊选项 | BX11: 勇气灵光 | BY11: 第10级起，你与友方生物在你身边10尺内不会陷入恐慌。提供该增益时你必须保持意识清醒。 第18级起，该灵光的作用范围扩展至30尺。 | CD11: 先发激励 | CE11: 第20级起，你骰先攻时若没有可用的诗人激励次数，则你获得一次使用次数。 | CH11: 真气驻拳 | CI11: 第6级起，攻击对非魔法攻击或伤害具有抗性或免疫的目标时，你的徒手打击视为魔法攻击。 | CJ11: 圆滑心智 | CK11: 第15级起，你的心理素质获得了大大的加强，并因此获得感知豁免的熟练项。 | CN11: 魔法物品专家 | CO11: 当你达到14级时，你在魔法物品方面的技巧愈发精进： ·你一次最多可以调谐五个魔法物品。 ·你无视调谐或使用魔法物品所需的任何职业、种族、法术和等级条件。 | CR11: 无踪步 | CS11: 第14级起，你可以在自己回合以一个附赠动作的形式执行躲藏Hide动作。此时，你无法被非魔法手段追踪到，除非你主动留下踪迹。 | CT11: 坚韧狂暴 | CU11: 第11级起，狂暴的力量让你即使身受重伤也能持续战斗。 如果你的生命值降至0但并未立即死亡，则你可以进行一次DC10的体质豁免。豁免成功则改为你的生命值降至1。 第一次使用此特性后，每当你再次使用此特性时其体质豁免DC提高5。在你完成一次短休或长休后其DC重置为10。 | CX11: 元素导师 | CY11: 先决条件：至少可以施展一个法术 获得该专长时，你选择下列一种伤害类型：强酸、冷冻、火焰、闪电、雷鸣。 你所施展的法术将忽视你所选择伤害类型的抗性。此外，当你施展法术造成所选类型伤害时，将每粒伤害骰所有1的骰值视为2。 你可以重复多次选择该专长，但每次都必须选择一种不同的伤害类型。 | CZ11: 10
A12: 侏儒 | C12: 游侠 | D12: 1d10 | L12: 11 | M12: 73 | O12: 野蛮人 | P12: 狂暴次数 | R12: 狂暴次数 | S12: =P245 -> 3 | U12: 飞镖 | V12: 1d4 | W12: 穿刺 | X12: 5 cp | Y12: 灵巧 轻型 投掷(射程20/60) | Z12: 0.25 | AA12: =背包!B17 -> 0 | AB12: 法杖 | AC12: 奥术法器是一件用来引导奥术法术的特殊物品，它可以是一枚法球、一块水晶、一只权杖、一根特制法杖、一根魔杖般的长木条或是其它类似的物品。术士、邪术师或法师能将这样的物品用作施法法器。 | AD12: 5gp | AE12: 4 | AG12: 骑士Knight | AH12: 特权地位PositionofPrivilege。由于你的贵族血统，人们总是会予你优待。高等社会愿意接纳你，人们认同你有权去任何你想去的地方。平民们会尽力满足你的要求，避免你产生任何不快，而那些同样出身高贵的人则会视你为同一个社会圈子的人。你还可以在必要时前去拜会任何当地的贵族。 | AI12: 骑士理想 | AJ12: 骑士牵绊 | AK12: 骑士缺点 | AL12: 骑士特点 | AM12: 骑士技能熟练项 | AN12: 骑士工具熟练项 | AO12: 骑士额外语言 | AP12: 骑士背景装备 | AQ12: 骑士特殊选项 | BX12: 精通至圣斩 | BY12: 第11级起，你体内充盈的公正之力使你的近战武器打击中携带着神圣的力量。当你使用近战武器命中一个生物时，该生物将额外受到1d8点光耀伤害。 | CH12: 武僧反射闪避 | CI12: 第7级起，你敏锐的直觉让你可以躲过一些特定的区域效应，比如蓝龙的闪电吐息或是法术火球术 fireball。 你在成为某一范围效应影响对象时，若该效应允许你通过成功的敏捷豁免来使伤害减半，则你在该豁免成功时不受伤害，而豁免失败时只受一半伤害。 | CJ12: 飘忽不定 | CK12: 第18级起，你飘忽不定的身形让敌人攻击时无从下手。 除非你处于失能状态，否则以你为目标的攻击检定无法取得优势。 | CN12: 魔法物品大师 | CO12: 18级起，你一次最多可以调谐六个魔法物品。 | CR12: 野性感官 | CS12: 第18级时，你获得超自然的感官以帮助你对抗看不到的生物。此后，你攻击一个看不到的生物时不会因此承受劣势。 另外，你还能感测30尺内所有隐形敌人的位置，前提是该生物并没有针对你进行躲㯿，而你也没有陷入目盲或耳聋。 | CT12: 持久狂暴 | CU12: 第15级起，你狂暴时的情绪高涨得难以抑制，以至于只有当你昏迷或是主动终止狂暴时才能使之提前结束。 | CX12: 擒抱者 | CY12: 先决条件：力量13或更高 着重磨练过如何保持近距离擒抱的技巧后，你获得下列增益： • 你对被你擒抱的生物所发动的攻击检定具有优势。 • 你可以用动作尝试压制被你擒抱的一个生物。此时，你必须进行另外一次擒抱检定。检定成功，则你与被擒抱者同时陷入束缚状态，直至擒抱终止。 | CZ12: 11
A13: 地精 | C13: 野蛮人 | D13: 1d12 | L13: 12 | M13: 73 | O13: 奇械师 | P13: 注法数量上限 | R13: 注法数量上限 | S13: =P266 -> 2 | U13: 短弓 | V13: 1d6 | W13: 穿刺 | X13: 5 cp | Y13: 弹药(射程80/320) 双手 | Z13: 2 | AA13: =背包!B18 -> 0 | AB13: 魔杖 | AC13: 奥术法器是一件用来引导奥术法术的特殊物品，它可以是一枚法球、一块水晶、一只权杖、一根特制法杖、一根魔杖般的长木条或是其它类似的物品。术士、邪术师或法师能将这样的物品用作施法法器。 | AD13: 10gp | AE13: 1 | AG13: 化外之民Outlander | AH13: 漂泊者Wanderer。你对记忆地图和地形时能力惊人，且你总能回想起地形、定居点或者其他环境特征的大致布局。此外，你每天可以为自己以及至多五名队友获取食物和饮水，前提是你们身处的土地可以提供浆果、小野兽、水源等资源。 | AI13: 化外之民理想 | AJ13: 化外之民牵绊 | AK13: 化外之民缺点 | AL13: 化外之民特点 | AM13: 化外之民技能熟练项 | AN13: 化外之民工具熟练项 | AO13: 化外之民额外语言 | AP13: 化外之民背景装备 | AQ13: 化外之民特殊选项 | BX13: 净化之触 | BY13: 第14级起，你可以用动作触碰你自身或一个自愿生物，以中止该目标身上的一个法术效应。 该特性的可用次数等于你的魅力调整值（至少1次）。而已消耗的特性使用次数则可以通过完成一次长休进行恢复。 | CH13: 心如止水 | CI13: 第7级起，你可以用你的动作结束一个正影响你的魅惑或恐慌状态。 | CJ13: 幸运一击 | CK13: 第20级时，你掌握了一手非凡技巧，让你可以随时把握自己的成功之时。 当你的攻击未命中时，可以直接更改判定为命中。或者，当你的属性检定失败时，可以直接将d20骰的结果视为20。 你必须完成一次短休或长休后才能再次使用该特性。 | CN13: 奇械之魂 | CO13: 在20级时，你与你的魔法物品建立了一种神秘的联系，你可以利用它来保护自己。 ·你当前每有一件调谐中的魔法物品，你就在所有豁免检定中得到+1加值。 ·如果你的生命值降低到0，但没有立即死亡，你能以一个反应解除一个注法，使你的生命值降低到1而不是0。 | CR13: 屠灭众敌 | CS13: 第20级时，你成为了猎杀敌人的无双猎手。你在自己的每个回合内，都有一次机会将你的感知调整值加到你对宿敌进 行的攻击检定或伤害掷骰上。 你可以在掷骰之前或者之后决定使用该特性，但必须在该掷骰的相关效应被应用之前。 | CT13: 不屈勇武 | CU13: 第18级起，你进行力量检定的总值低于你的力量值时，可以直接使用力量值作为检定结果。 | CX13: 巨武器大师 | CY13: 你习得将武器重量作为优势的技巧，使你的攻击力大增。 你获得下列增益： • 你在自己回合内用近战武器造成重击，或将一个生物生命值降至0时，可以用附赠动作发动一次近战武器攻击。 • 你在使用具有熟练项的重型武器发动近战攻击前，可以选择让本次攻击检定承受-5减值。若本次攻击命中，则其伤害掷骰获得+10加值。 | CZ13: 12
A14: 幻身灵 | D14: =VLOOKUP(B1,C1:D13,2,0) -> 1d8 | L14: 13 | M14: 83 | N14: 法师等级 | P14: =VLOOKUP(N1,O1:P13,2,0) -> 已知祈唤 | S14: =VLOOKUP(Q1,R1:S13,2,0) -> 3 | U14: 投石索 | V14: 1d4 | W14: 钝击 | X14: 1 sp | Y14: 弹药(射程30/120) | Z14: - | AA14: =背包!B19 -> 0 | AB14: 背包 | AC14: - | AD14: 2gp | AE14: 5 | AG14: 智者Sage | AH14: 研究者Researcher。当你需要学习或是记起某段学识内容时，就算你并不清楚其具体信息，也总能知道从何处或何人身上着手获取。这些情报通常来自某个图书馆、抄写室、学院，甚至是其他某个智者或某个知道相关知识的人或生物。鉴于发掘多元宇宙最深的秘密有时会需要整趟的冒险甚至是整个的战役，你的DM可能会设定这段情报的所在是一个遥不可及的地方，或者直接将其定义为无法找到。 | AI14: 智者理想 | AJ14: 智者牵绊 | AK14: 智者缺点 | AL14: 智者特点 | AM14: 智者技能熟练项 | AN14: 智者工具熟练项 | AO14: 智者额外语言 | AP14: 智者背景装备 | AQ14: 智者特殊选项 | CH14: 百病不侵 | CI14: 第10级起，你浑身的气流动使你免疫疾病和毒素。 | CT14: 原初斗士 | CU14: 第20级时，你的存在即是野性之力的具现。你的力量和体质各提升4。并且你这两项属性的上限变为24。 | CX14: 医疗师 | CY14: 你是娴熟的医师，可以快速治疗伤口，让战友迅速重返战斗。你获得下列增益： • 你使用医疗包为生物稳定伤势时，该生物可以恢复1点生命值。 • 你可以用一个动作消耗医疗包的一次使用次数，并以此护理一个生物使其恢复1d6+4再加上角色生命骰粒数的生命值。 该生物在进行短休或长休前无法再次从该专长获取生命值。 | CZ14: 13
A15: 元素裔 | B15: =主要情况!S3 -> 邪术师 | C15: 法师 | D15: 智力 | E15: 豁免：智力、感知 技能：在奥秘、历史、洞悉、调查、医药、宗教中选择两项 •（a）一根长棍或（b）一把匕首 •（a）一个材料包或（b）一件奥术法器 •（a）一个学者套装或（b）一个探索套装 • 一本法术书 | F15: =主要情况!G14+主要情况!W3 -> 7 | G15: =主要情况!S4 -> 0 | H15: 法师 | I15: 1d6 | J15: 1d6 | K15: 4 | L15: 14 | M15: 83 | N15: =主要情况!W3 -> 5 | O15: 1 | P15: 4 | Q15: 法术值 | U15: 战斧 | V15: 1d8 | W15: 挥砍 | X15: 10gp | Y15: 两用（1d10） | Z15: 4 | AA15: =背包!B20 -> 0 | AB15: 滚珠_一包1000粒 | AC15: 你可以用一个动作将这些小金属珠从袋子中洒出，并覆盖一片边长10尺的方形区域。穿过这片区域的生物必须进行一次DC10的敏捷豁免，豁免失败则摔至倒地。以半速穿过该区域的生物不需要进行该豁免。 | AD15: 1gp | AE15: 2 | AG15: 水手Sailor | AH15: 船家路子Ship’sPassage。在必要时，你可以为团队谋得免费的顺风船进行旅行。你可能是搭上曾经效力过的船只，也可能是遇到与你交好的另一艘船（可能一位你曾经的同船水手所指挥的船只）。因为你是请求对方帮助（而非雇佣），所以你不能让行程和日程全然满足自己的要求。到达目的地的具体时间将由DM做决定。而作为免费搭乘的报酬，你和你的队友必须在航行中加入船员的行列帮忙做工。 | AI15: 水手理想 | AJ15: 水手牵绊 | AK15: 水手缺点 | AL15: 水手特点 | AM15: 水手技能熟练项 | AN15: 水手工具熟练项 | AO15: 水手额外语言 | AP15: 水手背景装备 | AQ15: 水手特殊选项 | CH15: 天语通 | CI15: 第13级起，你可以与其它生物进行心灵交流。 此后，你能够听懂所有语言，同时掌握至少一门语言的任何生物都能理解你讲的话语。 | CX15: 重甲运用 | CY15: 先决条件：中甲熟练项 你学习了重甲的使用方法，你获得下列增益： • 你的力量加1，上限为20。 • 你获得重甲的熟练项。 | CZ15: 14
A16: 蜥蜴人 | C16: 术士 | D16: 魅力 | E16: 豁免：体质、魅力 技能：从奥秘、欺瞒、洞悉、威吓、游说、宗教中选择两项 •（a）一把轻弩与 20 支弩矢或（b）任意一件简易武器 •（a）一个材料包或（b）一件奥术法器 •（a）一个地城套装或（b）一个探索套装 • 两把匕首 | F16: ∞ | G16: =主要情况!S5 -> 0 | H16: 术士 | I16: 1d6 | J16: 1d8 | K16: 5 | L16: 15 | M16: 94 | O16: 2 | P16: 6 | U16: 链枷 | V16: 1d8 | W16: 钝击 | X16: 10gp | Y16: - | Z16: 2 | AA16: =背包!B21 -> 0 | AB16: 木桶 | AC16: - | AD16: 2gp | AE16: 70 | AG16: 海盗Pirate | AH16: 船家路子Ship’sPassage。在必要时，你可以为团队谋得免费的顺风船进行旅行。你可能是搭上曾经效力过的船只，也可能是遇到与你交好的另一艘船（可能一位你曾经的同船水手所指挥的船只）。因为你是请求对方帮助（而非雇佣），所以你不能让行程和日程全然满足自己的要求。到达目的地的具体时间将由DM做决定。而作为免费搭乘的报酬，你和你的队友必须在航行中加入船员的行列帮忙做工。 | AI16: 海盗理想 | AJ16: 海盗牵绊 | AK16: 海盗缺点 | AL16: 海盗特点 | AM16: 海盗技能熟练项 | AN16: 海盗工具熟练项 | AO16: 海盗额外语言 | AP16: 海盗背景装备 | AQ16: 海盗特殊选项 | CH16: 金刚魂 | CI16: 第14级起，你对气的掌控令你所有的豁免检定都成了熟练项。 另外，当豁免失败时，你可以消耗1点气重掷豁免并使用重掷的结果。 | CX16: 重甲大师 | CY16: 先决条件：重甲熟练项 你可以用护甲偏斜大多数致命的攻击。你获得下列增益： • 你的力量加1，上限为20。 • 你着装重甲时，非魔法武器对你造成的钝击、穿刺、挥砍伤害每次减少３点。 | CZ16: 15
A17: 半人马 | C17: 吟游诗人 | D17: 魅力 | E17: 工具：自选三种乐器 豁免：敏捷、魅力 技能：自选三项技能 •（a）一把刺剑，（b）一把长剑或（c）任一把简易武器 •（a）一个大使套装或（b）一个艺人套装 •（a）一个鲁特琴或（b）其它乐器 • 皮甲和一把匕首 | F17: ∞ | H17: 吟游诗人 | I17: 1d8 | J17: 1d10 | K17: 6 | L17: 16 | M17: 94 | O17: 3 | P17: 14 | U17: 长柄刀 | V17: 1d10 | W17: 挥砍 | X17: 20gp | Y17: 重型 触及 双手 | Z17: 6 | AA17: =背包!B22 -> 0 | AB17: 篮子 | AC17: - | AD17: 0.4gp | AE17: 2 | AG17: 士兵Soldier | AH17: 军阶MilitaryRank。你作为士兵时曾获得过军阶。那些忠于你之前所在组织的士兵仍会承认你的权威与影响，而其中军阶比你低的人甚至依然会遵从你的命令。凭借军阶的影响，你可以向其他士兵临时征用简单的装备或马匹。并且还可以凭此随意通过那些承认你军阶的友方军队大营和堡垒。 | AI17: 士兵理想 | AJ17: 士兵牵绊 | AK17: 士兵缺点 | AL17: 士兵特点 | AM17: 士兵技能熟练项 | AN17: 士兵工具熟练项 | AO17: 士兵额外语言 | AP17: 士兵背景装备 | AQ17: 士兵特殊选项 | CH17: 武僧不朽身 | CI17: 第15级起，你的气充盈身体让你不受衰老的减益，并且无法被魔法变老。尽管你依然会寿终正寝，但再不需要饮食。 | CX17: 领袖之证 | CY17: 先决条件：魅力13或更高 你可以花费10分钟来激励同伴，鼓舞他们战斗的信心。 此时，你可以指定30尺内至多6名友方生物（可以包括你自己）作为目标。目标生物必须能够看见你或者能够听到你的声音的，且必须能够理解你。 被指定的生物将因你获得临时生命值，其数值等于你的等级加上你的魅力调整值。 此后直至其完成一次短休或长休前，目标生物都无法再从该专长获益。 | CZ17: 16
A18: 牛头人 | C18: 牧师 | D18: 感知 | E18: 豁免：感知、魅力 技能：从历史、洞悉、医药、游说和宗教中选择两项 •（a）一把硬头锤或（b）一把战锤（拥有熟练项时可选） •（a）鳞甲，（b）皮甲或（c）链甲（拥有熟练项时可选） •（a）一把轻弩和 20 支弩矢或（b）任意简易武器 •（a）一个祭司套装或（b）一个探索套装 • 一个盾牌和一个圣徽 | F18: =主要情况!G16+主要情况!W3 -> 6 | H18: 牧师 | I18: 1d8 | J18: 1d12 | K18: 7 | L18: 17 | M18: 107 | O18: 4 | P18: 17 | U18: 巨斧 | V18: 1d12 | W18: 挥砍 | X18: 30gp | Y18: 重型 双手 | Z18: 7 | AA18: =背包!B23 -> 0 | AB18: 铺盖 | AC18: - | AD18: 1gp | AE18: 7 | AG18: 流浪儿Urchin | AH18: 城中秘密CitySecrets。你熟知城市中的秘密小路和胡同，能够在其他人容易迷失的混乱街区中寻路。如果你们并非身处战斗状态，则你还可以在市区内引导同伴以两倍的平时速度在两个地点间穿行。 | AI18: 流浪儿理想 | AJ18: 流浪儿牵绊 | AK18: 流浪儿缺点 | AL18: 流浪儿特点 | AM18: 流浪儿技能熟练项 | AN18: 流浪儿工具熟练项 | AO18: 流浪儿额外语言 | AP18: 流浪儿背景装备 | AQ18: 流浪儿特殊选项 | CH18: 空灵体 | CI18: 第18级起，你可以消耗4点气并使用动作隐形1分钟。 此时，你对力场伤害之外的所有伤害都具有抗性。 另外，你可以消耗8点气施展法术星界投影 astral projection，以该形式施展的法术不需要材料成分，且无法捎带其他生物与你同行。 | CX18: 敏锐心灵 | CY18: 你可以单单依靠心算来记录时间和方向的变换，并且可以做到精确无比。你获得下列增益： • 你的智力加1，上限为20。 • 你始终知道北边的方位。 • 你始终知道距离下一次日出或日落还有多久。 • 你可以完美复述出一个月内你所听到或看到的任何事。 | CZ18: 17
A19: 龟人 | C19: 德鲁伊 | D19: 感知 | E19: 豁免：智力、感知 技能：从奥秘、驯兽、洞悉、医药、自然、察觉、宗教和求生中选择两项 •（a）一个木盾或（b）任意简易武器 •（a）一把弯刀或（b）任意简易近战武器 • 皮甲，一个探索套装和一件德鲁伊法器 | F19: =主要情况!G16+主要情况!W3 -> 6 | H19: 德鲁伊 | I19: 1d8 | J19: 0 | K19: 0 | L19: 18 | M19: 114 | O19: 5 | P19: 27 | U19: 巨剑 | V19: 2d6 | W19: 挥砍 | X19: 50gp | Y19: 重型 双手 | Z19: 6 | AA19: =背包!B24 -> 0 | AB19: 铃铛 | AC19: - | AD19: 1gp | AE19: 0 | AG19: 城市守卫CityWatch | AH19: 守护者之眼Watcher’sEye。你在执行法律、处理违法者的工作中积累了丰富的经验，这使你对法律和犯罪的相关事宜异常敏感。你可以轻易的找到守卫的哨站或是一些类似的机构，也能轻易的发现犯罪者们活动的窝点，同时在前者中更受欢迎而在后者中则相反。 | AI19: 城市守卫理想 | AJ19: 城市守卫牵绊 | AK19: 城市守卫缺点 | AL19: 城市守卫特点 | AM19: 城市守卫技能熟练项 | AN19: 城市守卫工具熟练项 | AO19: 城市守卫额外语言 | AP19: 城市守卫背景装备 | AQ19: 城市守卫特殊选项 | CH19: 超凡入圣 | CI19: 第20级起，若你骰先攻时身上未有储备的气，则你获得4点气。 | CX19: 轻甲运用 | CY19: 你学习了轻甲的使用方法，获得下列增益： • 你的力量或敏捷加1，上限为20。 • 你获得轻甲的熟练项。 | CZ19: 18
A20: 斑猫人 | C20: 武僧 | D20: 感知 | E20: 豁免：力量、敏捷 技能：从特技、运动、历史、洞悉、宗教、隐匿中选择两项 •（a）一把短剑或（b）任意一把简易武器 •（a）一个地城套装或（b）一个探索套装 •10支飞镖 | F20: 0 | H20: 武僧 | I20: 1d8 | J20: =VLOOKUP(H29,J15:K19,2,0) -> 0 | K20: =VLOOKUP(I29,J15:K19,2,0) -> 0 | L20: 19 | M20: 123 | O20: 6 | P20: 32 | U20: 戟 | V20: 1d10 | W20: 挥砍 | X20: 20gp | Y20: 重型 触及 双手 | Z20: 6 | AA20: =背包!B25 -> 0 | AB20: 毛毯 | AC20: - | AD20: 0.5gp | AE20: 3 | AG20: 调查员Investigator | AH20: 守护者之眼Watcher’sEye。你在执行法律、处理违法者的工作中积累了丰富的经验，这使你对法律和犯罪的相关事宜异常敏感。你可以轻易的找到守卫的哨站或是一些类似的机构，也能轻易的发现犯罪者们活动的窝点，同时在前者中更受欢迎而在后者中则相反。 | AI20: 调查员理想 | AJ20: 调查员牵绊 | AK20: 调查员缺点 | AL20: 调查员特点 | AM20: 调查员技能熟练项 | AN20: 调查员工具熟练项 | AO20: 调查员额外语言 | AP20: 调查员背景装备 | AQ20: 调查员特殊选项 | CX20: 语言学家 | CY20: 你学习了不少语言和密码，获得下列增益： • 你的智力加 1，上限为20。 • 你习得三门自选语言。 • 你可以自创密码。而未经你传授解密方法的人只有两种方法可以破译你的密码：其一是进行智力检定（DC等于你的智力值＋你的熟练加值），或是以魔法破译。 | CZ20: 19
A21: 阿兰寇拉鹰人 | C21: 游荡者 | D21: 智力 | E21: 工具：盗贼工具 豁免：敏捷、智力 技能：从特技、运动、欺瞒、洞悉、威吓、调查、察觉、表演、游说、巧手、隐匿中选择四项。 •（a）一把刺剑或（b）一把短剑 •（a）一把短弓和一袋 20 支箭或（b）一把短剑 •（a）一个窃贼套装，（b）一个地城套装或（c）一个探索套装 • 皮甲，两把匕首和盗贼工具 | F21: 0 | H21: 游荡者 | I21: 1d8 | L21: 20 | M21: 133 | O21: 7 | P21: 38 | U21: 骑枪 | V21: 1d12 | W21: 穿刺 | X21: 10gp | Y21: 触及 特殊 | Z21: 6 | AB21: 滑轮组 | AC21: 一组滑轮组，其中配有一根绳索绕过轮组中，其上还装着一个系物的钩子。滑轮组可以让你提起相当于你正常举重四倍重量的物件。 | AD21: 5gp | AE21: 5 | AG21: 氏族工匠ClanCrafter | AH21: 矮人之敬意RespectoftheStoutFolk。再没其他人会像矮人一样，会对那些作为氏族工匠的外来者给予高度尊重。你总能在盾矮人或金矮人的居住地获得免费的食宿，矮人们甚至还会争相为你提供服务（你的同胞也可能成为其服务对象），并努力给予最好的食宿和帮助。 | AI21: 氏族工匠理想 | AJ21: 氏族工匠牵绊 | AK21: 氏族工匠缺点 | AL21: 氏族工匠特点 | AM21: 氏族工匠技能熟练项 | AN21: 氏族工匠工具熟练项 | AO21: 氏族工匠额外语言 | AP21: 氏族工匠背景装备 | AQ21: 氏族工匠特殊选项 | CX21: 幸运 | CY21: 你的离奇运气让你可以在最危险的时刻化险为夷。 你获得3点幸运点。当你进行攻击检定、属性检定、豁免检定时，你可以花费1幸运点来骰一个额外的d20。你可以选择在掷骰完成后，但结果公布前花费你这1幸运点。此后，你来选择该次攻击检定、属性检定或豁免检定要使用哪粒d20的结果。 你也可以在被攻击时选择花费1点幸运点骰一次d20。然后由你决定攻击者该使用哪粒d20。 若不止一个生物决定花费幸运点影响同一个骰值，则幸运点互相抵消，即并不会有额外的d20掷骰行为。 完成一次长休后你可以恢复所有的幸运点。 | CZ21: 20
A22: 纯种蛇人 | C22: 邪术师 | D22: 魅力 | E22: 豁免：感知，魅力 技能：从奥秘、欺瞒、威吓、洞悉、历史、自然、宗教中选择两项 •（a）一把轻弩和 20 支弩矢或（b）任意一把简易武器 •（a）一个材料包或（b）一件奥术法器 •（a）一个学者套装或（b）一个地城套装 • 皮甲、任意简易武器和两把匕首 | F22: ∞ | H22: 邪术师 | I22: 1d8 | M22: =VLOOKUP(K1,L1:M21,2,0) -> 27 | O22: 8 | P22: 44 | U22: 长剑 | V22: 1d8 | W22: 挥砍 | X22: 15gp | Y22: 两用（1d10） | Z22: 3 | AB22: 书 | AC22: 一本书可能写着诗歌、故事或是其他的内容。里面可能有关于某个特定地区的学识信息，也可能有侏儒语记载的机械图和笔记，或者任何其它能够用文字或图形表达的内容。一本载有法术的书则是一本法术书（见后文详述）。 | AD22: 28gp | AE22: 5 | AG22: 隐修学者CloisteredScholar | AH22: 图书馆使用权LibraryAccess。你所在的图书馆里就算最普通的资料库，想要获得进入其中权限之人都必须成功通过漫长繁复的面试并缴纳一定的费用，而你却能轻松自如地进入图书馆的大部分区域，哪怕这些防止外人直接接触的学识都涉及到各种极珍贵、魔法或秘密的领域。你在这个隐修机构中的工作经验，让你得以通过自己的人脉或官僚手段游走其中的关系网。此外，你作为一个专业礼貌的学者，在国度中其他的图书馆里也可能会获得优惠的待遇。 | AI22: 隐修学者理想 | AJ22: 隐修学者牵绊 | AK22: 隐修学者缺点 | AL22: 隐修学者特点 | AM22: 隐修学者技能熟练项 | AN22: 隐修学者工具熟练项 | AO22: 隐修学者额外语言 | AP22: 隐修学者背景装备 | AQ22: 隐修学者特殊选项 | CX22: 巫师杀手 | CY22: 你拥有一套对付施法者的近身战法，并获得下列增益： • 你周边5尺范围内的一个生物施展法术后，你可以用你的反应对该生物发动一次近战武器攻击。 • 当你对一名正专注法术的生物造成伤害时，该生物进行维持本次专注的豁免检定时具有劣势。 • 你为抵抗身边５尺范围内生物对你施展的法术而进行的豁免检定具有优势。 | CZ22: 21
A23: 吉斯人 | C23: 奇械师 | D23: 智力 | E23: 豁免：体质、智力 技能：从奥秘、历史、调查、医药、自然、察觉、巧手中选两项 •任意二把简易武器 •一把轻弩和20支弩矢 •（a）镶钉皮甲或（b）鳞甲 •一个盗贼工具和地城套装 | F23: =主要情况!G14+INT(主要情况!W3/2) -> 4 | H23: 奇械师 | I23: 1d8 | O23: 9 | P23: 57 | U23: 巨锤 | V23: 2d6 | W23: 钝击 | X23: 10gp | Y23: 重型 双手 | Z23: 10 | AB23: 玻璃瓶 | AC23: - | AD23: 2gp | AE23: 2 | AG23: 朝臣Courtier | AH23: 官员CourtFunctionary。你掌握的官场运作知识，让你在面对任何贵族宫廷或政府时得以从中获取情报并窥见其内部操作。你了解是谁在进行幕后操纵，知道应该寻求何人支持，还清楚这些组织当前正感兴趣的阴谋。 | AI23: 朝臣理想 | AJ23: 朝臣牵绊 | AK23: 朝臣缺点 | AL23: 朝臣特点 | AM23: 朝臣技能熟练项 | AN23: 朝臣工具熟练项 | AO23: 朝臣额外语言 | AP23: 朝臣背景装备 | AQ23: 朝臣特殊选项 | CX23: 魔法学徒 | CY23: 指定一个职业：吟游诗人、牧师、德鲁伊、术士、邪术师、法师。你从指定职业法术列表里习得两个戏法。 此外，你从相同列表里选择习得一个1环法术。以该方式习得的法术只可以用其最低环法术位来施展，而以该方式施展后的该1环法术必须完成一次长休后，才能再次以该方式施展。 这些法术的施法关键属性取决于你指定的职业：吟游诗人、术士、邪术师用魅力；牧师、德鲁伊用感知；法师用智力。 | CZ23: 22
A24: 梭螺鱼人 | C24: 战士 | D24: 智力 | E24: 豁免：力量、体质 技能：从特技、驯兽、运动、历史、洞悉、威吓、察觉和求生中选择两项 •（a）链甲或（b）皮甲，长弓和 20 支箭 •（a）一把军用武器和一面盾牌或（b）两把军用武器 •（a）一把轻弩和 20 支弩矢或（b）两把手斧 •（a）一个地城套装或（b）一个探索套装 | F24: 0 | H24: 战士 | I24: 1d10 | O24: 10 | P24: 64 | U24: 钉头锤 | V24: 1d8 | W24: 穿刺 | X24: 15gp | Y24: - | Z24: 4 | AB24: 水桶 | AC24: - | AD24: 0.05gp | AE24: 2 | AG24: 派系特工FactionAgent | AH24: 避风港SafeHave。作为一名派系特工，你的权限可以让你得以组织秘密联络网中那些可为你的冒险生涯提供援助之后勤和行动组成员。你知道识别这些秘密人员的记号和密语，这些人可为你提供一个免费食宿的隐秘安全屋，或是能够协助你寻找需要的情报。但这些家伙并不会为你进行暴露自己身份或生命安全的危险工作。 | AI24: 派系特工理想 | AJ24: 派系特工牵绊 | AK24: 派系特工缺点 | AL24: 派系特工特点 | AM24: 派系特工技能熟练项 | AN24: 派系特工工具熟练项 | AO24: 派系特工额外语言 | AP24: 派系特工背景装备 | AQ24: 派系特工特殊选项 | CX24: 战技专家 | CY24: 接受战技训练后，你可以使用一些独特的战技。你获得下列增益： • 你选择习得战士战斗大师范型战技列表中的两个战技。 如果所习得的战技需要目标进行豁免检定来抵抗战技效果，则其豁免DC等于８＋你的熟练加值＋你的力量或敏捷调整值（自选）。 • 你获得一枚d6的卓越骰（该骰可加到任何你以其他方式获得的卓越骰中）。此卓越骰可用于启动你的战技。此卓越骰一经使用即消耗，并在完成短休或长休后恢复。 | CZ24: 23
A25: 歌利亚 | C25: 圣武士 | D25: 魅力 | E25: 豁免：感知、魅力 技能：在运动、洞悉、威吓、医药、游说、宗教中选择两项 •（a）一把军用武器和一面盾牌或（b）两把军用武器 •（a）五支标枪或（b）任意简易近战武器 •（a）一个祭司套装或（b）一个探索套装 • 链甲和一个圣徽 | F25: =主要情况!G18+INT(主要情况!W3/2) -> 5 | H25: 圣武士 | I25: 1d10 | O25: 11 | P25: 73 | U25: 长矛 | V25: 1d10 | W25: 穿刺 | X25: 5gp | Y25: 重型 触及 双手 | Z25: 18 | AB25: 铁蒺藜_一包20枚 | AC25: 你可以用一个动作将一包铁蒺藜撒出，并覆盖一块边长5尺的方形区域。任何进入该区域的生物必须进行一次DC15的敏捷豁免，豁免失败则该生物停止移动，并受到1点穿刺伤害。在该生物恢复至少1点生命值前，其步行速度将减少10尺。以半速穿过该区域的生物不需要进行该豁免。 | AD25: 1gp | AE25: 2 | AG25: 远行者FarTraveler | AH25: 众目焦点AllEyesonYou。你的口音，言谈举止，措辞风格甚至你的外表都表明你就是一个异乡人。无论你走到哪里，好奇的目光总会伴随着你。虽然这有些令人讨厌，但是也让你得以对那些感兴趣的学者们，和那些对远方好奇希望听你述说家乡故事之人的好感。与其他民众不同，你可以运用这种关注力为自己或旅伴们亲近想要接触之人。那些贵族领主、学者、商人望族等等可能会有兴趣听你那些有关远方故乡和人民的故事。 | AI25: 远行者理想 | AJ25: 远行者牵绊 | AK25: 远行者缺点 | AL25: 远行者特点 | AM25: 远行者技能熟练项 | AN25: 远行者工具熟练项 | AO25: 远行者额外语言 | AP25: 远行者背景装备 | AQ25: 远行者特殊选项 | CX25: 中甲大师 | CY25: 先决条件：中甲熟练项 你修习过如何在着装中甲时移动，并获得下列增益： • 着装中甲不再使你进行敏捷（隐匿）检定时具有劣势。 • 着装中甲时，若你的敏捷在16或以上，你的AC可以增加3点而非2点。 | CZ25: 24
A26: 象族 | C26: 游侠 | D26: 感知 | E26: 豁免：力量、敏捷 技能：从驯兽、运动、洞悉、调查、自然、察觉、隐匿和求生中选择三项 •（a）鳞甲或（b）皮甲 •（a）两把短剑或（b）任意两把简易武器 •（a）一个地城套装或（b）一个探索套装 • 一把长弓和一个箭袋（内含 20 支箭） | F26: ∞ | H26: 游侠 | I26: 1d10 | O26: 12 | P26: 73 | U26: 刺剑 | V26: 1d8 | W26: 穿刺 | X26: 25gp | Y26: 灵巧 | Z26: 2 | AB26: 蜡烛 | AC26: 一只蜡烛可以为其身边5尺半径范围提供明亮光照，以及该范围外5尺的微光光照。蜡烛的照明效果可以持续1小时。 | AD26: 0.01gp | AE26: 0 | AG26: 继承者Inheritor | AH26: 遗产Inheritance。从下表中自选或者随机选取一项你继承的遗产。你要和你的地下城主一起讨论决定出细节：你的遗产为何那么重要，它拥怎样的故事？你可以让DM把这部分内容加到整个游戏故事中，通过剧情让你和角色更进一步了解该遗产的故事。 | AI26: 继承者理想 | AJ26: 继承者牵绊 | AK26: 继承者缺点 | AL26: 继承者特点 | AM26: 继承者技能熟练项 | AN26: 继承者工具熟练项 | AO26: 继承者额外语言 | AP26: 继承者背景装备 | AQ26: 继承者特殊选项 | CX26: 灵活移动 | CY26: 你十分灵敏而快速。你获得下列增益： • 你的移动速度增加10尺。 • 你执行疾走动作的相应回合内，在困难地形的移动不再消耗额外的移动力。 • 你对一个生物发动近战攻击后，无论命中与否，本回合剩下时间里你都不会引发该生物的借机攻击。 | CZ26: 25
A27: 析米克杂种 | C27: 野蛮人 | D27: 体质 | E27: 豁免：力量、体质 技能：从驯兽、运动、威吓、自然、察觉和求生中选两项 •（a）一把巨斧或（b）任意一把军用近战武器 •（a）两把手斧或（b）任意一把简易武器 • 一个探索套装和四支标枪 | F27: 0 | H27: 野蛮人 | I27: 1d12 | O27: 13 | P27: 83 | U27: 弯刀 | V27: 1d6 | W27: 挥砍 | X27: 25gp | Y27: 灵巧 轻型 | Z27: 3 | AB27: 弩矢匣 | AC27: 一只木匣能装二十支弩矢。 | AD27: 1gp | AE27: 1 | AG27: 教团骑士KnightoftheOrder | AH27: 骑士的敬重KnightlyRegard。你会获得来自所属骑士团其他成员和那些与骑士团有相同目标之人的救助与庇护。如果你的教团是个宗教骑士团，则你还可以从所信仰神灵的神庙和其他宗教团体中获得帮助。服务于城市的骑士团（不管是为单独的聚居地服务还是为一个国家的人民服务）可以从其服务对象处寻求帮助。服务于某种哲念的骑士团，则可以从其自身为贯彻其理念而帮助之人，或者与其理念相同之人处获得帮助。 | AI27: 教团骑士理想 | AJ27: 教团骑士牵绊 | AK27: 教团骑士缺点 | AL27: 教团骑士特点 | AM27: 教团骑士技能熟练项 | AN27: 教团骑士工具熟练项 | AO27: 教团骑士额外语言 | AP27: 教团骑士背景装备 | AQ27: 教团骑士特殊选项 | CX27: 中甲运用 | CY27: 先决条件：轻甲熟练项 你习得如何使用中甲和盾牌，并获得下列增益： • 你的力量或敏捷加1，上限为20。 • 你获得中甲和盾牌的熟练项。 | CZ27: 26
A28: 维多肯 | D28: =VLOOKUP(B15,C15:D27,2,0) -> 魅力 | E28: =VLOOKUP(B15,C15:E27,3,0) -> 豁免：感知，魅力 技能：从奥秘、欺瞒、威吓、洞悉、历史、自然、宗教中选择两项 •（a）一把轻弩和 20 支弩矢或（b）任意一把简易武器 •（a）一个材料包或（b）一件奥术法器 •（a）一个学者套装或（b）一个地城套装 • 皮甲、任意简易武器和两把匕首 | F28: =VLOOKUP(B15,C15:F27,4,0) -> ∞ | H28: 0 | I28: 0 | O28: 14 | P28: 83 | U28: 短剑 | V28: 1d6 | W28: 穿刺 | X28: 10gp | Y28: 灵巧 轻型 | Z28: 2 | AB28: 地图或卷轴匣 | AC28: 一个圆柱形皮匣能够装上十张卷起的纸或是五张卷起的羊皮纸。 | AD28: 1gp | AE28: 1 | AG28: 老佣兵MercenaryVeteran | AH28: 佣兵生涯MercenaryLife。你拥有的生活经历，只有曾同样从事过佣兵生涯之人才能体会。你只要看到对方的徽记就能辨认出相应的佣兵团，你还知道该军团的某些情报，包括其指挥官和领导者的名字和声誉，以及最近雇佣他们的是何人。只要能说相应的语言，你在任何地方都能找到这些佣兵混迹的酒馆或宴会地。你总能在冒险中通过佣兵工作找到足够的钱来维持舒适程度的生活（见《玩家手册》第8章“修整期活动”下的“专业实践”）。 | AI28: 老佣兵理想 | AJ28: 老佣兵牵绊 | AK28: 老佣兵缺点 | AL28: 老佣兵特点 | AM28: 老佣兵技能熟练项 | AN28: 老佣兵工具熟练项 | AO28: 老佣兵额外语言 | AP28: 老佣兵背景装备 | AQ28: 老佣兵特殊选项 | CX28: 骑乘战斗 | CY28: 骑乘时的你就像一头怪兽。当正在骑乘且未处于失能状态时，你获得下列增益： • 你对比你的坐骑体型更小的未骑乘生物发动近战攻击时，所进行的攻击检定具有优势。 • 你可以强迫针对你坐骑的攻击转而针对你自己。 • 当你的坐骑受某效应影响而需要进行敏捷豁免来减半伤害时，如果豁免成功则可以不承受伤害，豁免失败则伤害减半。 | CZ28: 27
A29: 狗头人 | H29: =VLOOKUP(G15,H15:I28,2,0) -> 0 | I29: =VLOOKUP(G16,H15:I28,2,0) -> 0 | O29: 15 | P29: 94 | U29: 三叉戟 | V29: 1d6 | W29: 穿刺 | X29: 5gp | Y29: 投掷(射程20/60) 两用(1d8) | Z29: 4 | AB29: 链条_10尺 | AC29: 一根链条有10点生命值。它可以被一次成功的DC20力量检定挣断。 | AD29: 5gp | AE29: 10 | AG29: 城市猎人UrbanBountyHunter | AH29: 耳目众多EartotheGround。你经常与所选定猎物途径地区的社会人士接触。这些人可能与黑社会罪犯、街头莽汉或上流社会成员相关联。这种联系其形式为，每个你所访问的城市都存在一名相应的联络人，该人物会为你提供当地人文和地理的各种相关情报。 | AI29: 城市猎人理想 | AJ29: 城市猎人牵绊 | AK29: 城市猎人缺点 | AL29: 城市猎人特点 | AM29: 城市猎人技能熟练项 | AN29: 城市猎人工具熟练项 | AO29: 城市猎人额外语言 | AP29: 城市猎人背景装备 | AQ29: 城市猎人特殊选项 | CX29: 观察力 | CY29: 你能够迅速把握周遭环境的要点，并获得下列增益： • 你的智力或感知加1，上限为20。 • 某生物在讲话时，若你可以看见目标的嘴且你可以理解其语言，则你就可以依靠读唇来解读目标正在讲什么。 • 你的被动感知（察觉）和智力（调查）检定具有+5加值。 | CZ29: 28
A30: 离梦人 | B30: =主要情况!S3 -> 邪术师 | C30: 法师 | D30: 法师武器熟练 | E30: 法师护甲熟练 | F30: 法师武器熟练 | G30: 匕首、飞镖、投石索、长棍、轻弩 | H30: 法师护甲熟练 | I30: 无 | O30: 16 | P30: 94 | U30: 战镐 | V30: 1d8 | W30: 穿刺 | X30: 5gp | Y30: - | Z30: 2 | AB30: 粉笔_1块 | AC30: - | AD30: 0.01gp | AE30: 0 | AG30: 乌斯伽部族成员UthgardtTribeMember | AH30: 乌斯伽之传承UthgardtHeritage。你不仅彻底了解自己部族之领地，还清楚北地其他地区的地形和自然资源。你熟悉所有的野外地区，而你在那里找到的食物和水的数量是平时的两倍。另外，你可以唤起他人的好客之道。受你该影响的对象包括你的同胞，以及那些与你部族结盟之人，通常包括有德鲁伊结社、精灵游牧部族、竖琴手同盟等团体的成员，以及那些献身于“第一结社FirstCircle”众神的祭祀者。 | AI30: 乌斯伽部族成员理想 | AJ30: 乌斯伽部族成员牵绊 | AK30: 乌斯伽部族成员缺点 | AL30: 乌斯伽部族成员特点 | AM30: 乌斯伽部族成员技能熟练项 | AN30: 乌斯伽部族成员工具熟练项 | AO30: 乌斯伽部族成员额外语言 | AP30: 乌斯伽部族成员背景装备 | AQ30: 乌斯伽部族成员特殊选项 | CX30: 长柄武器大师 | CY30: 你可以用触及武器与敌人近身缠斗。你获得下列增益： • 当你只使用长柄刀、戟、长棍或矛执行攻击动作时，可以用附赠动作以武器手柄的末端发动一次近战攻击。 这次攻击与主攻击使用同样的调整值，其伤害骰为d4，伤害类型为钝击伤害。 • 当你持握长柄刀、戟、长矛、长棍或矛时，进入你触及范围的生物会引发你的借机攻击。 | CZ30: 29
A31: 化兽者 | C31: 术士 | D31: 术士武器熟练 | E31: 术士护甲熟练 | F31: 术士武器熟练 | G31: 匕首、飞镖、投石索、长棍、轻弩 | H31: 术士护甲熟练 | I31: 无 | O31: 17 | P31: 107 | U31: 战锤 | V31: 1d8 | W31: 钝击 | X31: 15gp | Y31: 两用（1d10） | Z31: 2 | AB31: 木箱 | AC31: - | AD31: 5gp | AE31: 25 | AG31: 深水人贵族WaterdhavianNoble | AH31: 保持风度KeptinStyle。在深水城或北地其他地方时，你的家族会确保你的每日的日常用度。你的名字与玺印就足以支付大部分的费用，而你经常光顾的旅店、酒馆和餐馆都很乐于记下你的债务，并将账单寄给你的家人以解决你欠下的债务。这种优势使你能过上舒适的生活，而不必每天支付2gp的费用，也可以减少富裕或奢华程度生活的成本。你不能以更低价的生活方式来将这只生活费当做收入——这种得益属于信用体系，而不是明确的货币奖励。 | AI31: 深水人贵族理想 | AJ31: 深水人贵族牵绊 | AK31: 深水人贵族缺点 | AL31: 深水人贵族特点 | AM31: 深水人贵族技能熟练项 | AN31: 深水人贵族工具熟练项 | AO31: 深水人贵族额外语言 | AP31: 深水人贵族背景装备 | AQ31: 深水人贵族特殊选项 | CX31: 强健身心 | CY31: 选择1种属性，并获得下列增益： • 所选属性加1，上限为20。 • 你进行所选属性的豁免检定时可以加上你的熟练加值。 | CZ31: 30
A32: 天狗 | C32: 吟游诗人 | D32: 吟游诗人武器熟练 | E32: 吟游诗人护甲熟练 | F32: 吟游诗人武器熟练 | G32: 简易武器、手弩、长剑、刺剑、短剑 | H32: 吟游诗人护甲熟练 | I32: 轻甲 | O32: 18 | P32: 114 | U32: 鞭 | V32: 1d4 | W32: 挥砍 | X32: 2gp | Y32: 灵巧 触及 | Z32: 3 | AB32: 攀爬工具 | AC32: 一套攀爬工具包括特制的岩钉，靴子包头，手套和系带。你可以用一个动作来运用攀爬工具锚定自己；此时你不会从锚定处摔落超过25尺，且在解除锚定前无法从锚定处向外攀爬超过25尺。 | AD32: 25gp | AE32: 12 | AG32: 家族代理人 | AH32: 家族背景。你身为你家族的代理人，总是能够在家族飞地中为自己和朋友获得食宿。当家族给你任务时，通常会为你提供必要的补给和交通。除此之外，你在家族中还有很多老朋友、导师和竞争对手，当你在为家族工作时，可能会遇到其中之一。身为一名林兰德家族代理人，你可能认识一艘飞空艇的船长；身为一名伽兰达家族的代理人，你会认识很多旅馆老板和调酒师。这些熟人会帮你多大的忙取决于你目前在家族中的地位。 | AI32: 家族代理人理想 | AJ32: 家族代理人牵绊 | AK32: 家族代理人缺点 | AL32: 家族代理人特点 | AM32: 家族代理人技能熟练项 | AN32: 家族代理人工具熟练项 | AO32: 家族代理人额外语言 | AP32: 家族代理人背景装备 | AQ32: 家族代理人特殊选项 | CX32: 仪式施法者 | CY32: 先决条件：智力或感知为13或更高 你习得一些可以用于仪式施法的法术。这些法术会记载在一本仪式书上，你进行仪式施法时必须手持这本仪式书。 当你选择该专长时，你获得一本记载了两个自选1环法术的仪式书。从吟游诗人、牧师、德鲁伊、术士、邪术师、法师中选择一个职业。你所选法术必须在所选职业的法术列表里，且所选法术必须有仪式标签。你所选的职业同样决定了这些法术的施法关键属性：吟游诗人、术士、邪术师用魅力；牧师、德鲁伊用感知；法师用智力。 当你获得了一份书写形式的法术时（比如法术卷轴 spell scroll 或法师的法术书），你可以将其法术添加进你的仪式书里。 被添加的法术必须在你所选职业的法术列表里，且该法术环阶不能高于你等级的一半（向上取整），而该法术还必须带有仪式标签。将该法术抄进你的仪式书必须消耗每环2小时时间和50gp的金钱。该消耗即是你研究掌握该法术所消耗的材料成分和抄写进仪式书所用的优质墨水等的开销。 | CZ32: 31
A33: 费尔伯格人 | C33: 牧师 | D33: 牧师武器熟练 | E33: 牧师护甲熟练 | F33: 牧师武器熟练 | G33: 简易武器 | H33: 牧师护甲熟练 | I33: 轻甲、中甲、盾牌 | O33: 19 | P33: 123 | U33: 吹箭筒 | V33: 1 | W33: 穿刺 | X33: 10gp | Y33: 弹药(射程25/100) 装填 | Z33: 1 | AB33: 普通服装 | AC33: - | AD33: 0.5gp | AE33: 3 | AG33: 0 | AH33: 请在左侧【背景】一栏，选择背景或者背景模板。删除背景请从左侧，不要删除此单元格内容。 | CX33: 凶蛮打手 | CY33: 你每回合有一次机会，在掷近战武器攻击的伤害骰时，重掷武器的伤害骰并选用新旧骰值二者之一。 | CZ33: 32
C34: 德鲁伊 | D34: 德鲁伊武器熟练 | E34: 德鲁伊护甲熟练 | F34: 德鲁伊武器熟练 | G34: 短棒、匕首、飞镖、ḷ枪、硬头锤、长棍、弯刀、镰刀、投石索、矛 | H34: 德鲁伊护甲熟练 | I34: 轻甲、中甲、盾牌（德鲁伊不能装备或使用金属质的护甲和盾） | O34: 20 | P34: 133 | U34: 手弩 | V34: 1d6 | W34: 穿刺 | X34: 75gp | Y34: 弹药(射程30/120) 轻型 装填 | Z34: 3 | AB34: 表演服装 | AC34: - | AD34: 5gp | AE34: 4 | AH34: =VLOOKUP(AF1,AG1:AH33,2,0) -> #N/A | AI34: =VLOOKUP(AF1,AG1:AI33,3,0) -> #N/A | AJ34: =VLOOKUP(AF1,AG1:AJ33,4,0) -> #N/A | AK34: =VLOOKUP(AF1,AG1:AK33,5,0) -> #N/A | AL34: =VLOOKUP(AF1,AG1:AL33,6,0) -> #N/A | AM34: =VLOOKUP(AF1,AG1:AM33,7,0) -> #N/A | AN34: =VLOOKUP(AF1,AG1:AN33,8,0) -> #N/A | AO34: =VLOOKUP(AF1,AG1:AO33,9,0) -> #N/A | AP34: =VLOOKUP(AF1,AG1:AP33,10,0) -> #N/A | AQ34: =VLOOKUP(AF1,AG1:AQ33,11,0) -> #N/A | CX34: 哨兵 | CY34: 你的掌握的技术让你在击破敌人防御时占尽优势，并获得下列增益： • 你的借机攻击命中目标时，目标在本回合剩下时间内的移动速度降至 0。 • 生物即使执行撤离动作离开你的触及范围也会引发你的借机攻击。 • 处于你周边５尺范围内的生物对除你外的目标发动攻击后（且被攻击者没有这个专长），你可以用你的反应对该攻击者发动一次近战攻击。 | CZ34: 33
C35: 武僧 | D35: 武僧武器熟练 | E35: 武僧护甲熟练 | F35: 武僧武器熟练 | G35: 简易武器、短剑 | H35: 武僧护甲熟练 | I35: 无 | N35: 术士/武僧等级 | P35: =VLOOKUP(N15,O15:P34,2,0) -> 27 | U35: 重弩 | V35: 1d10 | W35: 穿刺 | X35: 50gp | Y35: 弹药(射程100/400) 重型 装填 双手 | Z35: 18 | AB35: 高档服装 | AC35: - | AD35: 15gp | AE35: 6 | AH35: 侍僧特点 | AI35: 骗子特点 | AJ35: 罪犯特点 | AK35: 密探特点 | AL35: 艺人特点 | AM35: 角斗士特点 | AN35: 平民英雄特点 | AO35: 公会工匠特点 | AP35: 公会商人特点 | AQ35: 隐士特点 | AR35: 贵族特点 | AS35: 骑士特点 | AT35: 化外之民特点 | AU35: 智者特点 | AV35: 水手特点 | AW35: 海盗特点 | AX35: 士兵特点 | AY35: 流浪儿特点 | AZ35: 城市守卫特点 | BA35: 调查员特点 | BB35: 氏族工匠特点 | BC35: 隐修学者特点 | BD35: 朝臣特点 | BE35: 派系特工特点 | BF35: 远行者特点 | BG35: 继承者特点 | BH35: 教团骑士特点 | BI35: 老佣兵特点 | BJ35: 城市猎人特点 | BK35: 乌斯伽部族成员特点 | BL35: 深水人贵族特点 | BM35: 家族代理人特点 | BN35: =角色!E8 -> 高等 | BO35: 人类 | BP35: 人类属性值加成 | BQ35: 你的全部属性值加1。 | BR35: 人类 | BS35: 人类 | BT35: 变体人类 | BU35: 探索龙纹_艾伯伦 | BV35: 畜牧龙纹_艾伯伦 | BW35: 创造龙纹_艾伯伦 | BX35: 通行龙纹_艾伯伦 | BY35: 守护龙纹_艾伯伦 | CX35: 神射手 | CY35: 你是熟练掌握了远程武器的使用方式，使看似不可能的射击都能成功命中。你获得下列增益： • 攻击最大射程内的敌人时，你的远程武器攻击检定不会具有劣势。 • 你的远程武器攻击忽视半身掩护和四分之三掩护状态。 • 你用拥有熟练项的远程武器发动攻击前，可以选择使该次攻击的攻击检定承受-5减值。若本次攻击中，则其伤害掷骰获得+10加值。 | CZ35: 34
C36: 游荡者 | D36: 游荡者武器熟练 | E36: 游荡者护甲熟练 | F36: 游荡者武器熟练 | G36: 简易武器、手弩、长剑、刺剑、短剑 | H36: 游荡者护甲熟练 | I36: 轻甲 | N36: =主要情况!W3 -> 5 | O36: 1 | P36: 0 | Q36: 术法点/气 | U36: 长弓 | V36: 1d8 | W36: 穿刺 | X36: 50gp | Y36: 弹药(射程150/600) 重型 双手 | Z36: 2 | AB36: 旅行者服装 | AC36: - | AD36: 2gp | AE36: 4 | AH36: 我崇拜某个英雄，并时刻以其事迹作为榜样。 | AI36: 我容易招蜂引蝶，爱情生活是也不断的离离合合。 | AJ36: 我总是计划好事情变糟时的应对方法。 | AK36: 我总是计划好事情变糟时的应对方法。 | AL36: 我知道一个几乎适合所有情况的故事。 | AM36: 我知道一个几乎适合所有情况的故事。 | AN36: 我以人的行为而非言辞对其做判断。 | AO36: 我确信能做的事就要做到最好。而我必须要做到最好——我是完美主义者。 | AP36: 我确信能做的事就要做到最好。而我必须要做到最好——我是完美主义者。 | AQ36: 由于在隐居生活中鲜少说话，现在的我更偏好用肢体语言交流，或者偶尔咕哝几声。 | AR36: 我的阿谀奉能能让其他人觉得自己举世无双。 | AS36: 我的阿谀奉能能让其他人觉得自己举世无双。 | AT36: 我因旅行欲望的驱使而背井离乡。 | AU36: 我会用一些让人觉得非常博学的长词。 | AV36: 朋友们知道无论出现什么困难，我都值得依赖。 | AW36: 朋友们知道无论出现什么困难，我都值得依赖。 | AX36: 我总是表现的恭敬有礼。 | AY36: 我把食物碎屑和饰品深深地藏在口袋里。 | AZ36: 我总是表现的恭敬有礼。 | BA36: 我总是表现的恭敬有礼。 | BB36: 我确信能做的事就要做到最好。而我必须要做到最好——我是完美主义者。 | BC36: 我会用一些让人觉得非常博学的长词。 | BD36: 我确信能做的事就要做到最好。而我必须要做到最好——我是完美主义者。 | BE36: 我崇拜某个英雄，并时刻以其事迹作为榜样。 | BF36: 我有着与周围人关于私人空间的不同想法，并不觉得进入到别人私人空间是什么犯罪行为，而且也不觉得我的私人空间被别人进入也毫无所谓。 | BG36: 我以人的行为而非言辞对其做判断。 | BH36: 我总是表现的恭敬有礼。 | BI36: 我总是表现的恭敬有礼。 | BJ36: 我总是计划好事情变糟时的应对方法。 | BK36: 我因旅行欲望的驱使而背井离乡。 | BL36: 我的阿谀奉能能让其他人觉得自己举世无双。 | BM36: 我从不让感情复杂化。 | BO36: 变体人类 | BP36: 变体人类属性值加成 | BQ36: 自选两项不同属性各加1。 | BR36: 半身人 | BS36: 轻足半身人 | BT36: 敦实半身人 | BU36: 鬼智半身人_剑湾 | BV36: 莲源半身人_荒洲 | BW36: 医疗龙纹_艾伯伦 | BX36: 招待龙纹_艾伯伦 | CX36: 盾牌大师 | CY36: 你的盾牌不只可以用于防御，还可以用来攻击。你在持用盾牌时获得下列增益： • 你在自己的回合内执行攻击动作时，可以用附赠动作以盾牌尝试推撞一个在你5尺范围内的生物。 • 如果你不处于失能状态，则你为抵抗以你为唯一目标的法术或其他伤害性效应而进行敏捷豁免时，可以将你盾牌的AC添加到相应的敏捷豁免中。 • 当某个效应使让你进行豁免成功可以伤害减半的敏捷豁免检定时，你可以用你的反应将盾牌挡在你与效应原点之间，此时豁免成功则不受任何伤害。 | CZ36: 35
C37: 邪术师 | D37: 邪术师武器熟练 | E37: 邪术师护甲熟练 | F37: 邪术师武器熟练 | G37: 简易武器 | H37: 邪术师护甲熟练 | I37: 轻甲 | O37: 2 | P37: 2 | U37: 捕网 | V37: 0 | W37: - | X37: 1gp | Y37: 特殊 投掷(射程5/15) | Z37: 3 | AB37: 材料包 | AC37: 材料包是一个防水的皮质小小包，其内有间格用以放置各种材料成分以及其它你需要用以施展法术的特殊物品。某些有着特定价格的材料不包含在材料包中（详见相关法术的描述内容）。 | AD37: 25gp | AE37: 2 | AH37: 我能在最狂乱的敌人间寻找共鸣，然后感化他们一同为和平而努力。 | AI37: 我在什么情境下都会说笑，尤其在不合时宜时更是如此。 | AJ37: 无论情形如何我总能保持冷静。我从不会忽然提高音调或是让情绪影响自己。 | AK37: 无论情形如何我总能保持冷静。我从不会忽然提高音调或是让情绪影响自己。 | AL37: 到一个新地方后就会着手收集当地的流言和小道消息。 | AM37: 到一个新地方后就会着手收集当地的流言和小道消息。 | AN37: 我总是会去帮助遇到麻烦的人。 | AO37: 我瞧不起那些不懂审美的家伙。 | AP37: 我瞧不起那些不懂审美的家伙。 | AQ37: 即使泰山崩于面前，我依然心如止水。 | AR37: 平民们因我的仁慈和慷慨而喜爱我。 | AS37: 平民们因我的仁慈和慷慨而喜爱我。 | AT37: 我像照顾新生儿般照顾同伴。 | AU37: 我读过世上最大图书馆中的每一本书——或者我喜欢自夸我读过。 | AV37: 我努力工作，然后休闲时就可以尽情玩乐。 | AW37: 我努力工作，然后休闲时就可以尽情玩乐。 | AX37: 我的心中总是萦绕着战争时的记忆，那些残暴的画面总是挥之不去。 | AY37: 我会常常发问。 | AZ37: 我的心中总是萦绕着战争时的记忆，那些残暴的画面总是挥之不去。 | BA37: 我的心中总是萦绕着战争时的记忆，那些残暴的画面总是挥之不去。 | BB37: 我瞧不起那些不懂审美的家伙。 | BC37: 我读过世上最大图书馆中的每一本书——或者我喜欢自夸我读过。 | BD37: 我瞧不起那些不懂审美的家伙。 | BE37: 我能在最狂乱的敌人间寻找共鸣，然后感化他们一同为和平而努力。 | BF37: 我对哪些是或不是食物有着自己的看法，并且我觉得我周围那些人的饮食习惯真是让我向往，让人恶心或是混乱不堪。 | BG37: 我总是会去帮助遇到麻烦的人。 | BH37: 我的心中总是萦绕着战争时的记忆，那些残暴的画面总是挥之不去。 | BI37: 我的心中总是萦绕着战争时的记忆，那些残暴的画面总是挥之不去。 | BJ37: 无论情形如何我总能保持冷静。我从不会忽然提高音调或是让情绪影响自己。 | BK37: 我像照顾新生儿般照顾同伴。 | BL37: 平民们因我的仁慈和慷慨而喜爱我。 | BM37: 我总是想提高效率。 | BO37: 轻足半身人 | BP37: 轻足半身人属性值加成 | BQ37: 你的敏捷加2，你的魅力加1。 | BR37: 精灵 | BS37: 高等精灵 | BT37: 木精灵 | BU37: 卓尔精灵 | BV37: 雅灵_魔邓肯 | BW37: 海精灵_魔邓肯 | BX37: 影灵_魔邓肯 | BY37: 苍白精灵_荒洲 | BZ37: 阴影龙纹_艾伯伦 | CX37: 熟习 | CY37: 选择任意组合的三项技能或工具加入你的熟练项。 | CZ37: 36
C38: 奇械师 | D38: 奇械师武器熟练 | E38: 奇械师护甲熟练 | F38: 奇械师武器熟练 | G38: 简易武器 | H38: 奇械师护甲熟练 | I38: 轻甲、中甲、盾牌 | O38: 3 | P38: 3 | U38: 双刃弯刀 | V38: 2d4 | W38: 挥砍 | X38: 100gp | Y38: 特殊 双手 | Z38: 6 | AB38: 撬棍 | AC38: 在适当的地方使用撬棍时，可以让相应的力量检定具有优势。 | AD38: 2gp | AE38: 5 | AH38: 我在每个事件和行动中看到预兆。神试图对我们说话，我们只需要听即可。 | AI38: 我爱用逢迎的手段获取所求之物。 | AJ38: 我每到一个新地方做的第一件事就是记下每个有价值之物的位置——或是可能藏有类似东西的地点。 | AK38: 我每到一个新地方做的第一件事就是记下每个有价值之物的位置——或是可能藏有类似东西的地点。 | AL38: 我是无可救药的浪漫病，总是在找“有缘人”。 | AM38: 我是无可救药的浪漫病，总是在找“有缘人”。 | AN38: 我在专注于某件事时，会排除一切障碍坚持到底。 | AO38: 我总是想搞清楚事物如何运作，人们为何奔波。 | AP38: 我总是想搞清楚事物如何运作，人们为何奔波。 | AQ38: 修会的主持无论何时都能说出至理哲言，而我也想分享得此等睿智。 | AR38: 众所周知只要看一眼我威严的仪态，就能明白我和下层民众截然不同。 | AS38: 众所周知只要看一眼我威严的仪态，就能明白我和下层民众截然不同。 | AT38: 我曾马不停蹄地跑了二十五里以警告氏族有兽人来袭。如果有必要，我还会这么干。 | AU38: 我习惯帮助那些不像我这么聪明的人，而我有耐心对其他人解释任何事和每件事。 | AV38: 我喜欢航行到新港口，然后在那里以酒会友。 | AW38: 我喜欢航行到新港口，然后在那里以酒会友。 | AX38: 我曾失去太多的朋友，而现在已经很难交个新的朋友了。 | AY38: 我喜欢钻进别人找不到我的地方。 | AZ38: 我曾失去太多的朋友，而现在已经很难交个新的朋友了。 | BA38: 我曾失去太多的朋友，而现在已经很难交个新的朋友了。 | BB38: 我总是想搞清楚事物如何运作，人们为何奔波。 | BC38: 我习惯帮助那些不像我这么聪明的人，而我有耐心对其他人解释任何事和每件事。 | BD38: 我总是想搞清楚事物如何运作，人们为何奔波。 | BE38: 我在每个事件和行动中看到预兆。神试图对我们说话，我们只需要听即可。 | BF38: 我有着非常强烈的荣誉准则或规范，这让一些人无法理解。 | BG38: 我在专注于某件事时，会排除一切障碍坚持到底。 | BH38: 我曾失去太多的朋友，而现在已经很难交个新的朋友了。 | BI38: 我曾失去太多的朋友，而现在已经很难交个新的朋友了。 | BJ38: 我每到一个新地方做的第一件事就是记下每个有价值之物的位置——或是可能藏有类似东西的地点。 | BK38: 我曾马不停蹄地跑了二十五里以警告氏族有兽人来袭。如果有必要，我还会这么干。 | BL38: 众所周知只要看一眼我威严的仪态，就能明白我和下层民众截然不同。 | BM38: 我会告诉别人一些和自己家族业务有关的琐事（医疗、船、战俑等）。 | BO38: 敦实半身人 | BP38: 敦实半身人属性值加成 | BQ38: 你的敏捷加2，你的体质加1。 | BR38: 半精灵 | BS38: 半精灵 | BT38: 半精灵变体_剑湾 | BU38: 侦测龙纹_艾伯伦 | BV38: 暴风龙纹_艾伯伦 | CX38: 隐伏者 | CY38: 先决条件：敏捷13或更高 你是利用阴影潜伏的专家。你获得下列增益： • 你可以在轻度遮蔽的状态下尝试躲藏。 • 当你对某生物处于躲藏状态时，你对其发动的远程武器攻击如果未命中便不会暴露你的位置。 • 你在微光环境下进行依靠视觉的感知（察觉）检定时不会具有劣势。 | CZ38: 37
C39: 战士 | D39: 战士武器熟练 | E39: 战士护甲熟练 | F39: 战士武器熟练 | G39: 简易武器、军用武器 | H39: 战士护甲熟练 | I39: 所有护甲、盾牌 | O39: 4 | P39: 4 | U39: 手枪 | V39: 1d10 | W39: 穿刺 | X39: 250gp | Y39: 弹药(射程30/90) 装填 | Z39: 3 | AB39: 槲寄生枝条 | AC39: 德鲁伊法器是一件用来引导德鲁伊法术的特殊物品。它可以是一枝槲寄生或冬青，一根用紫衫木或其它特殊木材制作的魔杖或节杖，一根从活树上折下的法杖或是一个包含神圣动物身上的羽毛、毛皮、骨头和牙齿组合成的图腾。德鲁伊能将这样的物品用作其施法的法器。 | AD39: 1gp | AE39: 0 | AH39: 没有什么能动摇我的乐观态度。 | AI39: 我是天生的赌徒，一旦有回报的可能，我就会不顾风险。 | AJ39: 比起制造一个新敌人，我宁可交一个新朋友。 | AK39: 比起制造一个新敌人，我宁可交一个新朋友。 | AL39: 我周围的人都不会生气太久，因为我总能缓和紧张的气氛。 | AM39: 我周围的人都不会生气太久，因为我总能缓和紧张的气氛。 | AN39: 我对公平有着强烈的执念，并且总是试图为争端寻找最公正的解决方案。 | AO39: 我有一肚子格言警句，总是能恰到好处地掉书袋。 | AP39: 我有一肚子格言警句，总是能恰到好处地掉书袋。 | AQ39: 我对受难者抱有强烈的同情心。 | AR39: 我为了时尚和美貌忍受了很大痛苦。 | AS39: 我为了时尚和美貌忍受了很大痛苦。 | AT39: 我善于观察自然，并从中获得应对任何境况的经验。 | AU39: 没有什么能比一个有趣的谜团更令我欢心。 | AV39: 我常常会为了讲述一个好故事而夸大其词。 | AW39: 我常常会为了讲述一个好故事而夸大其词。 | AX39: 我的军事生涯曾经历过各种情况，所以我能以此讲出许多鼓舞人心而又发人深省的故事。 | AY39: 我习惯靠着墙或树睡觉，睡时把自己的东西都捆成一捆。抱在怀里。 | AZ39: 我的军事生涯曾经历过各种情况，所以我能以此讲出许多鼓舞人心而又发人深省的故事。 | BA39: 我的军事生涯曾经历过各种情况，所以我能以此讲出许多鼓舞人心而又发人深省的故事。 | BB39: 我有一肚子格言警句，总是能恰到好处地掉书袋。 | BC39: 没有什么能比一个有趣的谜团更令我欢心。 | BD39: 我有一肚子格言警句，总是能恰到好处地掉书袋。 | BE39: 没有什么能动摇我的乐观态度。 | BF39: 我表达喜爱和厌恶的方式和其他人不一样。 | BG39: 我对公平有着强烈的执念，并且总是试图为争端寻找最公正的解决方案。 | BH39: 我的军事生涯曾经历过各种情况，所以我能以此讲出许多鼓舞人心而又发人深省的故事。 | BI39: 我的军事生涯曾经历过各种情况，所以我能以此讲出许多鼓舞人心而又发人深省的故事。 | BJ39: 比起制造一个新敌人，我宁可交一个新朋友。 | BK39: 我善于观察自然，并从中获得应对任何境况的经验。 | BL39: 我为了时尚和美貌忍受了很大痛苦。 | BM39: 我对自己和任何共事者都有极高的要求。 | BO39: 鬼智半身人_剑湾 | BP39: 鬼智半身人_剑湾属性值加成 | BQ39: 你的敏捷加2，你的感知加1。 | BR39: 矮人 | BS39: 丘陵矮人 | BT39: 山地矮人 | BU39: 灰矮人_魔邓肯 | BV39: 警戒龙纹_艾伯伦 | CX39: 法术射手 | CY39: 先决条件：至少可以施展一个法术 你学会如何操控特定的法术进行攻击，并获得下列增益： • 当你施展需要进行攻击检定的法术时，则该法术的施法距离加倍。 • 你的远程法术攻击忽视半身掩护和四分之三掩护状态。 • 你习得一个需要进行攻击检定的戏法。从吟游诗人、牧师、德鲁伊、术士、邪术师、法师中选择其一，并从其相应的法术列表里选择该戏法。 你施展该戏法的施法关键属性取决于你选择的职业：吟游诗人、术士、邪术师用魅力；牧师、德鲁伊用感知；法师用智力。 | CZ39: 38
C40: 圣武士 | D40: 圣武士武器熟练 | E40: 圣武士护甲熟练 | F40: 圣武士武器熟练 | G40: 简易武器、军用武器 | H40: 圣武士护甲熟练 | I40: 所有护甲、盾牌 | O40: 5 | P40: 5 | U40: 滑膛枪 | V40: 1d12 | W40: 穿刺 | X40: 500gp | Y40: 弹药(射程40/120) 装填 双手 | Z40: 10 | AB40: 图腾 | AC40: 德鲁伊法器是一件用来引导德鲁伊法术的特殊物品。它可以是一枝槲寄生或冬青，一根用紫衫木或其它特殊木材制作的魔杖或节杖，一根从活树上折下的法杖或是一个包含神圣动物身上的羽毛、毛皮、骨头和牙齿组合成的图腾。德鲁伊能将这样的物品用作其施法的法器。 | AD40: 1gp | AE40: 0 | AH40: 我任何情况下都喜欢引用（或错引）圣典和格言。 | AI40: 我什么时候都爱说点谎话，而不论是否有必要。 | AJ40: 我极端的不易信任他人。表面上看上去越公正的人通常都藏着越多见不得光的事。 | AK40: 我极端的不易信任他人。表面上看上去越公正的人通常都藏着越多见不得光的事。 | AL40: 我喜欢精妙的讽刺，即使那是对我的讽刺也一样。 | AM40: 我喜欢精妙的讽刺，即使那是对我的讽刺也一样。 | AN40: 我信任自己的能力，并且会做任何力所能及的事以获得他人的信任。 | AO40: 我对那些不像我那样努力工作、公平竞争的人并不会以礼相待。 | AP40: 我对那些不像我那样努力工作、公平竞争的人并不会以礼相待。 | AQ40: 我对于礼仪和社会常识一无所知。 | AR40: 我不喜欢干脏活，更不会因不舒适的食宿勉强自己。 | AS40: 我不喜欢干脏活，更不会因不舒适的食宿勉强自己。 | AT40: 财富和礼貌无法帮你对抗一头饥饿枭熊，而我对看重这些东西的家伙不屑一顾。 | AU40: 我作出自己的判断前，总会乐意倾听争论双方的论点。 | AV40: 我就觉得酒馆是了解一座陌生城市的好地方。 | AW40: 我就觉得酒馆是了解一座陌生城市的好地方。 | AX40: 我能盯着一只地狱犬看而毫不畏缩。 | AY40: 我的吃相像猪一样，十分没有礼数。 | AZ40: 我能盯着一只地狱犬看而毫不畏缩。 | BA40: 我能盯着一只地狱犬看而毫不畏缩。 | BB40: 我对那些不像我那样努力工作、公平竞争的人并不会以礼相待。 | BC40: 我作出自己的判断前，总会乐意倾听争论双方的论点。 | BD40: 我对那些不像我那样努力工作、公平竞争的人并不会以礼相待。 | BE40: 我任何情况下都喜欢引用（或错引）圣典和格言。 | BF40: 我通过在这片土地上实践来敬仰我的神灵。 | BG40: 我信任自己的能力，并且会做任何力所能及的事以获得他人的信任。 | BH40: 我能盯着一只地狱犬看而毫不畏缩。 | BI40: 我能盯着一只地狱犬看而毫不畏缩。 | BJ40: 我极端的不易信任他人。表面上看上去越公正的人通常都藏着越多见不得光的事。 | BK40: 财富和礼貌无法帮你对抗一头饥饿枭熊，而我对看重这些东西的家伙不屑一顾。 | BL40: 我不喜欢干脏活，更不会因不舒适的食宿勉强自己。 | BM40: 我永远不会忘记对我自己或家族的侮辱。 | BO40: 高等精灵 | BP40: 高等精灵属性值加成 | BQ40: 你的敏捷加2，你的智力加1。 | BR40: 龙裔 | BS40: 金龙裔 | BT40: 红龙裔 | BU40: 蓝龙裔 | BV40: 黑龙裔 | BW40: 银龙裔 | BX40: 绿龙裔 | BY40: 白龙裔 | BZ40: 黄铜龙裔 | CA40: 赤铜龙裔 | CB40: 青铜龙裔 | CC40: 龙国血统_荒洲 | CD40: 瑞雯奈特_荒洲 | CX40: 斗殴高手 | CY40: 你习惯了粗暴而混乱的肉体斗殴，而随手拿个东西都能成为你的武器。你获得下列增益： • 你的力量或体质加1，上限为20。 • 你获得临时武器的熟练项。 • 你徒手打击的伤害骰变为1d4。 • 你在自己的回合内用徒手打击或临时武器命中敌人时，可以用附赠动作尝试对该敌人进行一次擒抱。 | CZ40: 39
C41: 游侠 | D41: 游侠武器熟练 | E41: 游侠护甲熟练 | F41: 游侠武器熟练 | G41: 简易武器、军用武器 | H41: 游侠护甲熟练 | I41: 轻甲、中甲、盾牌 | O41: 6 | P41: 6 | U41: 0 | V41: - | W41: - | X41: - | Y41: - | Z41: - | AB41: 木制法杖 | AC41: 德鲁伊法器是一件用来引导德鲁伊法术的特殊物品。它可以是一枝槲寄生或冬青，一根用紫衫木或其它特殊木材制作的魔杖或节杖，一根从活树上折下的法杖或是一个包含神圣动物身上的羽毛、毛皮、骨头和牙齿组合成的图腾。德鲁伊能将这样的物品用作其施法的法器。 | AD41: 5gp | AE41: 4 | AH41: 我能容忍（或无法容忍）其它信仰并且尊重（或谴责）对其他神抵的崇拜。 | AI41: 讽刺和挖苦是我的首选武器。 | AJ41: 我不会考虑某个情形中的风险。永远别跟我谈几率。 | AK41: 我不会考虑某个情形中的风险。永远别跟我谈几率。 | AL41: 我一旦不能成为众人焦点就会很难受。 | AM41: 我一旦不能成为众人焦点就会很难受。 | AN41: 其他人负责思考。我只负责行动。 | AO41: 我喜欢对我的行当高谈阔论。 | AP41: 我喜欢对我的行当高谈阔论。 | AQ41: 我将周遭发生的一切视作冥冥天意的一部分。 | AR41: 我拥有贵族的血统，但并不认为自己比平民百姓更高贵。我们流的血是相同的。 | AS41: 我拥有贵族的血统，但并不认为自己比平民百姓更高贵。我们流的血是相同的。 | AT41: 我习惯偶尔从地上捡起些东西再漫不经心地摆弄，有的时候还会弄坏它们。 | AU41: 我~跟~白痴们~讲话~时~会~放慢~语速，别~误会~我~是指~所有人~都是~ग痴。 | AV41: 我从不会放弃友好的赌局。 | AW41: 我从不会放弃友好的赌局。 | AX41: 我喜欢强壮的感觉并且乐于打坏东西。 | AY41: 我认为任何对我假仁假义的人都不安好心。 | AZ41: 我喜欢强壮的感觉并且乐于打坏东西。 | BA41: 我喜欢强壮的感觉并且乐于打坏东西。 | BB41: 我喜欢对我的行当高谈阔论。 | BC41: 我~跟~白痴们~讲话~时~会~放慢~语速，别~误会~我~是指~所有人~都是~ग痴。 | BD41: 我喜欢对我的行当高谈阔论。 | BE41: 我能容忍（或无法容忍）其它信仰并且尊重（或谴责）对其他神抵的崇拜。 | BF41: 我通过一种通常和周围人不一样的小型的仪式来开始或结束我一天的生活。 | BG41: 其他人负责思考。我只负责行动。 | BH41: 我喜欢强壮的感觉并且乐于打坏东西。 | BI41: 我喜欢强壮的感觉并且乐于打坏东西。 | BJ41: 我不会考虑某个情形中的风险。永远别跟我谈几率。 | BK41: 我习惯偶尔从地上捡起些东西再漫不经心地摆弄，有的时候还会弄坏它们。 | BL41: 我拥有贵族的血统，但并不认为自己比平民百姓更高贵。我们流的血是相同的。 | BM41: 我对我家族达成的每一件事都感到激动和兴奋。 | BO41: 木精灵 | BP41: 木精灵属性值加成 | BQ41: 你的敏捷加2，你的感知加1。 | BR41: 机关人 | BS41: 机关人 | CX41: 健壮 | CY41: 获得该专长时，你的生命值上限增加你当前等级两倍的数值。并且在你随后每次升级时，生命值上限都会额外加2。 | CZ41: 40
C42: 野蛮人 | D42: 野蛮人武器熟练 | E42: 野蛮人护甲熟练 | F42: 野蛮人武器熟练 | G42: 简易武器、军用武器 | H42: 野蛮人护甲熟练 | I42: 轻甲、中甲、盾牌 | O42: 7 | P42: 7 | AB42: 紫衫魔杖 | AC42: 德鲁伊法器是一件用来引导德鲁伊法术的特殊物品。它可以是一枝槲寄生或冬青，一根用紫衫木或其它特殊木材制作的魔杖或节杖，一根从活树上折下的法杖或是一个包含神圣动物身上的羽毛、毛皮、骨头和牙齿组合成的图腾。德鲁伊能将这样的物品用作其施法的法器。 | AD42: 10gp | AE42: 1 | AH42: 我喜爱美食、饮料以及同信仰神庙中的精英分子们的高层圈子。粗野的生活令我烦躁。 | AI42: 我身上挂着一排圣徽，随时随地都可以祈祷随便哪位神祇保佑。 | AJ42: 令我做某件事的最好手段就是跟我说不能那样做。 | AK42: 令我做某件事的最好手段就是跟我说不能那样做。 | AL42: 我是完美主义者。 | AM42: 我是完美主义者。 | AN42: 会错用长单词以试图显得更聪明些。 | AO42: 我不会轻易花钱，砍价也总是砍到最低。 | AP42: 我不会轻易花钱，砍价也总是砍到最低。 | AQ42: 我时常陷入自我冥思中无法自拔，丝毫不顾周围的事物。 | AR42: 一旦辜负我的期待，就将永远失去我的青睐。 | AS42: 一旦辜负我的期待，就将永远失去我的青睐。 | AT42: 对于与人相处，和动物在一起会让我更自在。 | AU42: 我在社交场合尴尬得特别特别厉害。 | AV42: 我的言辞脏污得好比食腐兽的窝。 | AW42: 我的言辞脏污得好比食腐兽的窝。 | AX42: 我有着粗俗的幽默感。 | AY42: 我不喜欢洗澡。 | AZ42: 我有着粗俗的幽默感。 | BA42: 我有着粗俗的幽默感。 | BB42: 我不会轻易花钱，砍价也总是砍到最低。 | BC42: 我在社交场合尴尬得特别特别厉害。 | BD42: 我不会轻易花钱，砍价也总是砍到最低。 | BE42: 我喜爱美食、饮料以及同信仰神庙中的精英分子们的高层圈子。粗野的生活令我烦躁。 | BF42: 远行者特点只有6种，你也可以自己修改或者添加。——太易 | BG42: 会错用长单词以试图显得更聪明些。 | BH42: 我有着粗俗的幽默感。 | BI42: 我有着粗俗的幽默感。 | BJ42: 令我做某件事的最好手段就是跟我说不能那样做。 | BK42: 对于与人相处，和动物在一起会让我更自在。 | BL42: 一旦辜负我的期待，就将永远失去我的青睐。 | BM42: 我是家族的颜面，同时对自己的外表拥有很高的自信。 | BO42: 卓尔精灵 | BP42: 卓尔精灵属性值加成 | BQ42: 你的敏捷加2，你的魅力加1。 | BR42: 兽人 | BS42: 兽人 | CX42: 战地施法者 | CY42: 先决条件：至少可以施展一个法术 你学会如何在混乱的战场上施展法术，并获得下列增益： • 当你受到伤害时，你为维持法术专注而进行的体质豁免具有优势。 • 你在持握武器和盾牌时依然可以满足施法所需的姿势成分。 • 当敌方生物的移动引发你的借机攻击时，你可以用你的反应对该生物施展一个法术而非发动借机攻击。 该法术的施法时间必须是1动作，且该生物必须为法术的唯一目标。 | CZ42: 41
D43: =VLOOKUP(B30,C30:D42,2,0) -> 邪术师武器熟练 | E43: =VLOOKUP(B30,C30:E42,3,0) -> 邪术师护甲熟练 | O43: 8 | P43: 8 | AB43: 渔具 | AC43: 一套渔具工具包中，装有一根木杆、丝线、软木转轴、铅坠、天鹅绒饵以及窄眼网。 | AD43: 1gp | AE43: 4 | AH43: 我在神庙中生活的太久了，以至于我在与外面世界的人们打交道时缺乏实际经验。 | AI43: 我会把任何可能有点价值的玩意儿都收集起来。 | AJ43: 最轻微的侮辱也能把我气炸了。 | AK43: 最轻微的侮辱也能把我气炸了。 | AL43: 我的情绪和思想变得和弹琴轮指一样快。 | AM43: 我的情绪和思想变得和弹琴轮指一样快。 | AN43: 我时常感到厌烦。我的天命之旅什么时候才有进展呢？ | AO43: 我在我这行鼎鼎有名，而我要确保所有人都认同这点。如果人们没听说过我，就会让我大吃一惊。 | AP43: 我在我这行鼎鼎有名，而我要确保所有人都认同这点。如果人们没听说过我，就会让我大吃一惊。 | AQ43: 我正致力完成一套哲学理论，且乐于与人分享其理念。 | AR43: 我一受到伤害就要碾碎对方，乃至辱其名声毁其土地。 | AS43: 我一受到伤害就要碾碎对方，乃至辱其名声毁其土地。 | AT43: 我实际上是个由狼养大的孩子。 | AU43: 我确信人们始终在试图偷取我的秘密。 | AV43: 我喜欢工作都好好完成的样子，如果整个过程都让别人来干就更好了。 | AW43: 我喜欢工作都好好完成的样子，如果整个过程都让别人来干就更好了。 | AX43: 我迎难而上直面问题。一个简单直接的解决方案是通往成功的最佳路径。 | AY43: 我总是直接说出其他人暗示或者想遮掩的事情。 | AZ43: 我迎难而上直面问题。一个简单直接的解决方案是通往成功的最佳路径。 | BA43: 我迎难而上直面问题。一个简单直接的解决方案是通往成功的最佳路径。 | BB43: 我在我这行鼎鼎有名，而我要确保所有人都认同这点。如果人们没听说过我，就会让我大吃一惊。 | BC43: 我确信人们始终在试图偷取我的秘密。 | BD43: 我在我这行鼎鼎有名，而我要确保所有人都认同这点。如果人们没听说过我，就会让我大吃一惊。 | BE43: 我在神庙中生活的太久了，以至于我在与外面世界的人们打交道时缺乏实际经验。 | BF43: 远行者特点只有6种，你也可以自己修改或者添加。——太易 | BG43: 我时常感到厌烦。我的天命之旅什么时候才有进展呢？ | BH43: 我迎难而上直面问题。一个简单直接的解决方案是通往成功的最佳路径。 | BI43: 我迎难而上直面问题。一个简单直接的解决方案是通往成功的最佳路径。 | BJ43: 最轻微的侮辱也能把我气炸了。 | BK43: 我实际上是个由狼养大的孩子。 | BL43: 我一受到伤害就要碾碎对方，乃至辱其名声毁其土地。 | BM43: 我对君主制和任何针对家族的限制都感到不满。 | BO43: 雅灵_魔邓肯 | BP43: 雅灵_魔邓肯属性值加成 | BQ43: 你的敏捷加2，你的魅力加1。 | BR43: 半兽人 | BS43: 半兽人 | BT43: 探索龙纹_艾伯伦 | CX43: 武器大师 | CY43: 经过大量练习后，你熟练的掌握了各种武器的使用方法，并获得下列增益： • 你的力量或敏捷加1，上限为20。 • 你从简易武器和军用武器列表中，共选择四种武器并获得其熟练项。 | CZ43: 42
O44: 9 | P44: 9 | AB44: 扁瓶或大杯 | AC44: - | AD44: 0.02gp | AE44: 1 | AH44: 侍僧理想 | AI44: 骗子理想 | AJ44: 罪犯理想 | AK44: 密探理想 | AL44: 艺人理想 | AM44: 角斗士理想 | AN44: 平民英雄理想 | AO44: 公会工匠理想 | AP44: 公会商人理想 | AQ44: 隐士理想 | AR44: 贵族理想 | AS44: 骑士理想 | AT44: 化外之民理想 | AU44: 智者理想 | AV44: 水手理想 | AW44: 海盗理想 | AX44: 士兵理想 | AY44: 流浪儿理想 | AZ44: 城市守卫理想 | BA44: 调查员理想 | BB44: 氏族工匠理想 | BC44: 隐修学者理想 | BD44: 朝臣理想 | BE44: 派系特工理想 | BF44: 远行者理想 | BG44: 继承者理想 | BH44: 教团骑士理想 | BI44: 老佣兵理想 | BJ44: 城市猎人理想 | BK44: 乌斯伽部族成员理想 | BL44: 深水人贵族理想 | BM44: 家族代理人理想 | BO44: 海精灵_魔邓肯 | BP44: 海精灵_魔邓肯属性值加成 | BQ44: 你的敏捷加2，你的体质加1。 | BR44: 提夫林 | BS44: 提夫林 | BT44: 提夫林变体_剑湾 | BU44: 提夫林亚种_魔邓肯 | CX44: 慷慨吉运 | CY44: 先决条件：半身人 你的民族有着非同寻常的好运，且你学过如何在看到同伴难堪之时将其秘密地借给他们。你也不知道你是怎么做到的。你只是想想，那就实现了，这是命运的赠礼！ 如果一个30尺内你可以看见的队友在攻击检定，属性检定或者豁免检定上扔了个1，你可以用反应让他重扔一次，队友必须接受新的结果。 当你使用这个能力，直到下回合结束你都不能再次使用。 | CZ44: 43
O45: 10 | P45: 10 | U45: 布甲 | V45: 11 | W45: 是 | X45: 8 | AB45: 爪钩 | AC45: - | AD45: 2gp | AE45: 4 | AH45: 传统Traditions。古代崇拜与献祭的传统必须被保护并维持。(守序) | AI45: 自主Independence。我的灵魂自由自在——没人能对我指手画脚。（混乱） | AJ45: 荣誉Honor。我不会偷行家的东西。(守序) | AK45: 荣誉Honor。我不会偷行家的东西。(守序) | AL45: 美好Beauty。我表演时的世界会显得更美好。（善良） | AM45: 美好Beauty。我表演时的世界会显得更美好。（善良） | AN45: 尊敬Respect。民众应该受到体面而尊敬的对待。（善良） | AO45: 团结Community。加强集体团结，保卫社区安全，是文明人应尽的义务。（守序） | AP45: 团结Community。加强集体团结，保卫社区安全，是文明人应尽的义务。（守序） | AQ45: 大义Greater Good。我的天赋注定要为所有人谋利，而非为一己之私。（善良） | AR45: 尊重Respect。人们尊敬我是因为我的地位，但任何人无论地位高低，都应该被体面地对待。（善良） | AS45: 尊重Respect。人们尊敬我是因为我的地位，但任何人无论地位高低，都应该被体面地对待。（善良） | AT45: 改变Change。生活如四季流转，变化不止，而我们必须与之一道改变。（混乱） | AU45: 知识Knowledge。知识是通往力量和自我发展的必经之路。(中立) | AV45: 尊重Respect。只有船长和船员相互尊重，船才能乘风破浪。（善良） | AW45: 尊重Respect。只有船长和船员相互尊重，船才能乘风破浪。（善良） | AX45: 大义Greater Good。我们的使命即是为保卫他人而献出自己的生命。(善良) | AY45: 尊重Respect。所有人，不论贫富都应受到尊重。（善良） | AZ45: 大义Greater Good。我们的使命即是为保卫他人而献出自己的生命。(善良) | BA45: 大义Greater Good。我们的使命即是为保卫他人而献出自己的生命。(善良) | BB45: 团结Community。加强集体团结，保卫社区安全，是文明人应尽的义务。（守序） | BC45: 知识Knowledge。知识是通往力量和自我发展的必经之路。(中立) | BD45: 团结Community。加强集体团结，保卫社区安全，是文明人应尽的义务。（守序） | BE45: 传统Traditions。古代崇拜与献祭的传统必须被保护并维持。(守序) | BF45: 开放。那些在我旅程路上遇到的人，我有很多需要向他们学习。（善良） | BG45: 尊敬Respect。民众应该受到体面而尊敬的对待。（善良） | BH45: 大义Greater Good。我们的使命即是为保卫他人而献出自己的生命。(善良) | BI45: 大义Greater Good。我们的使命即是为保卫他人而献出自己的生命。(善良) | BJ45: 荣誉Honor。我不会偷行家的东西。(守序) | BK45: 改变Change。生活如四季流转，变化不止，而我们必须与之一道改变。（混乱） | BL45: 尊重Respect。人们尊敬我是因为我的地位，但任何人无论地位高低，都应该被体面地对待。（善良） | BM45: 共同利益。我的龙纹家族在世界上举足轻重，它的繁荣能够让所有人得利。（善良） | BO45: 影灵_魔邓肯 | BP45: 影灵_魔邓肯属性值加成 | BQ45: 你的敏捷加2，你的体质加1。 | BR45: 阿斯莫 | BS45: 守护阿斯莫 | BT45: 天罚阿斯莫 | BU45: 堕落阿斯莫 | CX45: 龙族之恐怖 | CY45: 先决条件：龙裔 气愤之时，你展露威慑之力。你获得以下好处。 力量，体质或者魅力+1，不能超过20 你可以使用咆哮并消耗你的喷吐武器使三十尺内你选择的每个生物通过一个感知豁免检定（DC＝8+你的熟练加值+魅力调整值）取代喷射毁灭性能量。听不到或看不到你的目标单位自动通过此检定。如果豁免失败，目标恐慌一分钟。如果恐慌的目标受到任何伤害，他可以重投豁免检定，直到通过为止。 | CZ45: 44
O46: 11 | P46: 11 | U46: 皮甲 | V46: 11 | W46: 否 | X46: 10 | AB46: 锤子 | AC46: - | AD46: 1gp | AE46: 3 | AH46: 仁爱Charity。我总是试图帮助那些需要帮助的人，无论个人的花费如何。（善良） | AI46: 公平Fairness。我从不在那些穷得失不起钱的人身上捞钱。（守序） | AJ46: 自由Freedom。枷锁的存在即是被打破，而那些铸造枷锁的人也该受同样对待。（混乱） | AK46: 自由Freedom。枷锁的存在即是被打破，而那些铸造枷锁的人也该受同样对待。（混乱） | AL46: 传统Tradition。过去的故事、史诗以及歌谣塑造了我们，因而他们不该被遗忘。（守序） | AM46: 传统Tradition。过去的故事、史诗以及歌谣塑造了我们，因而他们不该被遗忘。（守序） | AN46: 公平Fairness。没人可以在法律中得到优待，并且没人能凌驾于法律之上。（守序） | AO46: 慷慨Generosity。既然我有天赋，我就要造福世界。（善良） | AP46: 慷慨Generosity。既然我有天赋，我就要造福世界。（善良） | AQ46: 逻辑Logic。绝对不能让情绪干扰我们对正确、真实和理智的思考。（守序） | AR46: 责任Responsibility。我将服从上级视为责任，正如我的下属也必须要服从我一样。（守序） | AS46: 责任Responsibility。我将服从上级视为责任，正如我的下属也必须要服从我一样。（守序） | AT46: 大义Greater Good。部族整体的幸福，是每个成员的义务。（善良） | AU46: 美丽Beauty。美丽的事物指引我们想着其所在的方向继续向前即是真实。（善良） | AV46: 公正Fairness。一起干的活工钱一起分。（守序） | AW46: 公正Fairness。一起干的活工钱一起分。（守序） | AX46: 责任Reponsibility。我服从权力，并且只做必须做的事。（守序） | AY46: 团结Community。外人不会帮我们，因此我们必须同舟共济。（守序） | AZ46: 责任Reponsibility。我服从权力，并且只做必须做的事。（守序） | BA46: 责任Reponsibility。我服从权力，并且只做必须做的事。（守序） | BB46: 慷慨Generosity。既然我有天赋，我就要造福世界。（善良） | BC46: 美丽Beauty。美丽的事物指引我们想着其所在的方向继续向前即是真实。（善良） | BD46: 慷慨Generosity。既然我有天赋，我就要造福世界。（善良） | BE46: 仁爱Charity。我总是试图帮助那些需要帮助的人，无论个人的花费如何。（善良） | BF46: 保守。作为这个奇怪地方的新来者，我在日常交易之中保持谨慎和礼貌的态度。（守序） | BG46: 公平Fairness。没人可以在法律中得到优待，并且没人能凌驾于法律之上。（守序） | BH46: 责任Reponsibility。我服从权力，并且只做必须做的事。（守序） | BI46: 责任Reponsibility。我服从权力，并且只做必须做的事。（守序） | BJ46: 自由Freedom。枷锁的存在即是被打破，而那些铸造枷锁的人也该受同样对待。（混乱） | BK46: 大义Greater Good。部族整体的幸福，是每个成员的义务。（善良） | BL46: 责任Responsibility。我将服从上级视为责任，正如我的下属也必须要服从我一样。（守序） | BM46: 传统。我恪守家族传统，为家庭争取荣耀。（守序） | BO46: 半精灵 | BP46: 半精灵属性值加成 | BQ46: 你的魅力加2。再选择其他两项属性值各加1。 | BR46: 侏儒 | BS46: 森林侏儒 | BT46: 岩侏儒 | BU46: 地底侏儒_魔邓肯 | BV46: 抄录龙纹_艾伯伦 | CX46: 龙族皮肤 | CY46: 先决条件：龙裔 你显出自你龙族先祖的利爪与鳞片，你获得以下好处： 你的力量，体质或者魅力+1，不能超过20。 你的皮肤硬化，如果你没穿盔甲则你的AC变为13+敏捷调整值。你可以在持握盾牌时仍获得此好处。 你的指尖长出可伸缩的利爪，伸出或缩回爪子不消耗动作，爪子是可以用来徒手打击的天生武器，如果你用他们发动攻击，你造成1d4+你的力量调整值的挥砍伤害，以代替正常徒手打击造成的钝击伤害。 | CZ46: 45
D47: 已知戏法 | E47: 已知法术 | F47: 主职业等级 | G47: 副职业等级 | O47: 12 | P47: 12 | U47: 镶钉皮甲 | V47: 12 | W47: 否 | X47: 13 | AB47: 大铁锤 | AC47: - | AD47: 2gp | AE47: 10 | AH47: 改变Change。我们必须协助引发神在世界中一直为之工作的改变。（混乱） | AI47: 仁爱Charity。我把赚来的钱分给真正需要的人。（善良） | AJ47: 仁爱Charity。我从富人处窃取财富然后帮助有需要的人。（善良） | AK47: 仁爱Charity。我从富人处窃取财富然后帮助有需要的人。（善良） | AL47: 创新Creativity。世界需要崭新的创意和大胆的行动。（混乱） | AM47: 创新Creativity。世界需要崭新的创意和大胆的行动。（混乱） | AN47: 自由Freedom。压迫人民的暴君绝不能被容忍。（混乱） | AO47: 自由Freedom。任何人都有选择营生方式的自由。（混乱） | AP47: 自由Freedom。任何人都有选择营生方式的自由。（混乱） | AQ47: 解放思想Free Thinking。探究精神和好奇心是学术进步的支柱。（混乱） | AR47: 独立Independence。我必须证明自己即使不借助家族的力量也仍可以自食其力。（混乱） | AS47: 独立Independence。我必须证明自己即使不借助家族的力量也仍可以自食其力。（混乱） | AT47: 荣誉Honor。我若玷污荣誉，便是给整个氏族蒙羞。（守序） | AU47: 逻辑Logic。情绪绝不能蒙蔽逻辑思考。（守序） | AV47: 自由Freedom。大海即是自由——随你去哪儿，随你干什么。（混乱） | AW47: 自由Freedom。大海即是自由——随你去哪儿，随你干什么。（混乱） | AX47: 独立Independence。盲目的服从命令，某种意义上就相当于接受暴君统治。（混乱） | AY47: 改变Change。下等人可能发迹，上等人可能落马，变化才是万物的本质。（混乱） | AZ47: 独立Independence。盲目的服从命令，某种意义上就相当于接受暴君统治。（混乱） | BA47: 独立Independence。盲目的服从命令，某种意义上就相当于接受暴君统治。（混乱） | BB47: 自由Freedom。任何人都有选择营生方式的自由。（混乱） | BC47: 逻辑Logic。情绪绝不能蒙蔽逻辑思考。（守序） | BD47: 自由Freedom。任何人都有选择营生方式的自由。（混乱） | BE47: 改变Change。我们必须协助引发神在世界中一直为之工作的改变。（混乱） | BF47: 冒险。我远离了我的家乡，这所有的一切真是奇怪，太棒啦！（混乱） | BG47: 自由Freedom。压迫人民的暴君绝不能被容忍。（混乱） | BH47: 独立Independence。盲目的服从命令，某种意义上就相当于接受暴君统治。（混乱） | BI47: 独立Independence。盲目的服从命令，某种意义上就相当于接受暴君统治。（混乱） | BJ47: 仁爱Charity。我从富人处窃取财富然后帮助有需要的人。（善良） | BK47: 荣誉Honor。我若玷污荣誉，便是给整个氏族蒙羞。（守序） | BL47: 独立Independence。我必须证明自己即使不借助家族的力量也仍可以自食其力。（混乱） | BM47: 创新。抛弃旧的传统，找到更好的做事方法。（混乱） | BO47: 半精灵变体_剑湾 | BP47: 半精灵变体_剑湾属性值加成 | BQ47: 你的魅力加2。再选择其他两项属性值各加1。 | BR47: 地精 | BS47: 熊地精 | BT47: 地精 | BU47: 大地精 | CX47: 高等卓尔魔法 | CY47: 先决条件：卓尔精灵 你学到了更多种类的黑暗精灵魔法。你学会侦测魔法并可以任意释放他，而不会消耗法术位。你学会解除魔法和漂浮术，你可以释放每种一次不消耗法术位。直到你完成一次长休息你才可以再度释放他们。魅力是你施放这三个法术的施法主属性。 | CZ47: 46
B48: =主要情况!S3 -> 邪术师 | C48: 法师 | D48: =D85 -> 4 | E48: × | F48: =主要情况!W3 -> 5 | G48: =主要情况!W4 -> 0 | O48: 13 | P48: 13 | U48: 兽皮甲 | V48: 12 | W48: 否 | X48: 12 | AB48: 医疗包 | AC48: 一个医疗用小皮包中，装有绷带、药膏和夹板。医疗包可以使用十次。你可以使用一个动作，并花费一次使用次数来为一个生命值为0的生物稳定伤势，而无需进行相应的感知（医药）检定。 | AD48: 5gp | AE48: 3 | AH48: 权力Power。我希望有一天能够升格到所信仰宗教中等级的最高点。（守序） | AI48: 创新Creativity。我从不玩两次同样的把戏。（混乱） | AJ48: 贪婪Greed。为了致富我愿意做任何事。（邪恶） | AK48: 贪婪Greed。为了致富我愿意做任何事。（邪恶） | AL48: 贪婪Greed。我只是为名为利罢了。（邪恶） | AM48: 贪婪Greed。我只是为名为利罢了。（邪恶） | AN48: 力量Might。如果我变得强大，我就可以理所当然的随心所欲。（邪恶） | AO48: 贪婪Greed。我干这行就只为钱。（邪恶） | AP48: 贪婪Greed。我干这行就只为钱。（邪恶） | AQ48: 力量Power。清修和冥想是通往神秘力量或魔法之力的道途。（邪恶） | AR48: 权力Power。只要我掌握了更大的权力，就没人能对我指手画脚了。（邪恶） | AS48: 权力Power。只要我掌握了更大的权力，就没人能对我指手画脚了。（邪恶） | AT48: 力量Might。最强者即是规矩本身。（邪恶） | AU48: 无拘无束No Limits。任何东西都不该束缚所有存在中潜在的无限可能。（混乱） | AV48: 统治Mastery。我是个掠夺者，海上其他船都是我的猎物。（邪恶） | AW48: 统治Mastery。我是个掠夺者，海上其他船都是我的猎物。（邪恶） | AX48: 力量Might。生活与战争一样，只有更强大的一方才能获胜。（邪恶） | AY48: 报应Retribution。富人们应该被按在水沟里尝尝濒死的感觉。（邪恶） | AZ48: 力量Might。生活与战争一样，只有更强大的一方才能获胜。（邪恶） | BA48: 力量Might。生活与战争一样，只有更强大的一方才能获胜。（邪恶） | BB48: 贪婪Greed。我干这行就只为钱。（邪恶） | BC48: 无拘无束No Limits。任何东西都不该束缚所有存在中潜在的无限可能。（混乱） | BD48: 贪婪Greed。我干这行就只为钱。（邪恶） | BE48: 权力Power。我希望有一天能够升格到所信仰宗教中等级的最高点。（守序） | BF48: 狡猾。虽然我不了解他们的处事方式，但是他们也不了解我的，这可以成为我的优势。（邪恶） | BG48: 力量Might。如果我变得强大，我就可以理所当然的随心所欲。（邪恶） | BH48: 力量Might。生活与战争一样，只有更强大的一方才能获胜。（邪恶） | BI48: 力量Might。生活与战争一样，只有更强大的一方才能获胜。（邪恶） | BJ48: 贪婪Greed。为了致富我愿意做任何事。（邪恶） | BK48: 力量Might。最强者即是规矩本身。（邪恶） | BL48: 权力Power。只要我掌握了更大的权力，就没人能对我指手画脚了。（邪恶） | BM48: 权力。我想确保家族的繁荣昌盛，以便利用家族在世间的权势。（邪恶） | BO48: 丘陵矮人 | BP48: 丘陵矮人属性值加成 | BQ48: 你的体质加2，你的感知加1。 | BR48: 幻身灵 | BS48: 幻身灵 | CX48: 矮人之坚毅 | CY48: 先决条件：矮人 你的血脉中流淌着矮人英雄的血液。你获得以下好处 你的体质+1，最大20 当你在战斗中使用回避动作时，你可以消耗一颗生命骰来治愈自己。扔一颗骰子，加上你的体质调整值，恢复那么多的生命值（最少为1）。 | CZ48: 47
C49: 术士 | D49: =E85 -> 5 | E49: =D107 -> 6 | F49: 主职业施法等级 | G49: 副职业施法等级 | H49: 总施法等级 | O49: 14 | P49: 14 | U49: 链甲衫 | V49: 13 | W49: 否 | X49: 20 | AB49: 护符 | AC49: 枚圣徽是某个神袛或神系象征。它可能是一个描绘有代表一个神袛符号的护身符，相同的符号可能作为一个徽章被仔细地雕刻或镶嵌在一面盾牌上，也可能是一个盛有一块神圣遗物碎片的小盒。附录B中列举有多元宇宙众神的代表性徵记。牧师或圣武士能将圣徽用作其施法的法器。使用这些圣徽时，施法着必须将其握在手中，戴在身上可见处，或者将其装在盾上使用。 | AD49: 5gp | AE49: 1 | AH49: 信仰Faith。我信任神祇能指引我的行为。我信奉如果自己努力工作，事情就会变得顺利。（守序） | AI49: 友谊Friendship。钱财来去如流水，友情长存如青山。（善良） | AJ49: 人民People。我忠于我的朋友而非任何理想，此外的其他人就算下到冥河Styx里也与我无关。（中立） | AK49: 人民People。我忠于我的朋友而非任何理想，此外的其他人就算下到冥河Styx里也与我无关。（中立） | AL49: 人民People。我喜欢表演时人们脸上的笑容。那就是我想要的。（中立） | AM49: 人民People。我喜欢表演时人们脸上的笑容。那就是我想要的。（中立） | AN49: 诚实Sincerity。假装自己是另一种人不会有什么好处。（中立） | AO49: 人民People。我为我在乎的人奋斗，而不是为了什么理想。（中立） | AP49: 人民People。我为我在乎的人奋斗，而不是为了什么理想。（中立） | AQ49: 自持自重Live and Let LIve。胡乱插手他人事务只会造成麻烦。（中立） | AR49: 家族Family。血浓于水。（任意） | AS49: 家族Family。血浓于水。（任意） | AT49: 自然Nature。大自然比任何文明造物都重要。（中立） | AU49: 权力Power。知识是通往权力与统治的捷径。（邪恶） | AV49: 人民People。我只为同伴们出力，而不是为了什么理想。（中立） | AW49: 人民People。我只为同伴们出力，而不是为了什么理想。（中立） | AX49: 自持自重Live and Let Live。不该以理想之名行杀戮之事，或是以其名义发动战争。（中立） | AY49: 人民People。我帮助那些帮了我的人——这正是我们存在的根本。（中立） | AZ49: 自持自重Live and Let Live。不该以理想之名行杀戮之事，或是以其名义发动战争。（中立） | BA49: 自持自重Live and Let Live。不该以理想之名行杀戮之事，或是以其名义发动战争。（中立） | BB49: 人民People。我为我在乎的人奋斗，而不是为了什么理想。（中立） | BC49: 权力Power。知识是通往权力与统治的捷径。（邪恶） | BD49: 人民People。我为我在乎的人奋斗，而不是为了什么理想。（中立） | BE49: 信仰Faith。我信任神祇能指引我的行为。我信奉如果自己努力工作，事情就会变得顺利。（守序） | BF49: 好奇。所有的一切都没见过，但是我渴望了解这些。（中立） | BG49: 诚实Sincerity。假装自己是另一种人不会有什么好处。（中立） | BH49: 自持自重Live and Let Live。不该以理想之名行杀戮之事，或是以其名义发动战争。（中立） | BI49: 自持自重Live and Let Live。不该以理想之名行杀戮之事，或是以其名义发动战争。（中立） | BJ49: 人民People。我忠于我的朋友而非任何理想，此外的其他人就算下到冥河Styx里也与我无关。（中立） | BK49: 自然Nature。大自然比任何文明造物都重要。（中立） | BL49: 家族Family。血浓于水。（任意） | BM49: 发现。为了我的家族和满足好奇心，我想尽我所能地学习。（任何） | BO49: 山地矮人 | BP49: 山地矮人属性值加成 | BQ49: 你的体质与力量加2。 | BR49: 元素裔 | BS49: 气元素裔 | BT49: 土元素裔 | BU49: 火元素裔 | BV49: 水元素裔 | CX49: 精灵之准 | CY49: 先决条件：精灵或者半精灵 精灵的准确度是一种传说，尤其以弓箭手和施法者为甚，你在依赖精确度而非蛮力的攻击检定上有着奇妙的准头，你获得以下好处： 你的敏捷，智力，感知或魅力+1，最大20 当你在依靠敏捷，智力，感知或者魅力进行的攻击检定上有优势的时候，你可以重扔其中一个骰子。 | CZ49: 48
C50: 吟游诗人 | D50: =F85 -> 3 | E50: =E107 -> 8 | O50: 15 | P50: 15 | U50: 鳞甲&钉刺甲 | V50: 14 | W50: 是 | X50: 45 | AB50: 徽章 | AC50: 枚圣徽是某个神袛或神系象征。它可能是一个描绘有代表一个神袛符号的护身符，相同的符号可能作为一个徽章被仔细地雕刻或镶嵌在一面盾牌上，也可能是一个盛有一块神圣遗物碎片的小盒。附录B中列举有多元宇宙众神的代表性徵记。牧师或圣武士能将圣徽用作其施法的法器。使用这些圣徽时，施法着必须将其握在手中，戴在身上可见处，或者将其装在盾上使用。 | AD50: 5gp | AE50: 0 | AH50: 抱负Aspiration。我将自己的行动与他或她的教导相较，求证明自己配得上吾主的喜爱。（任何） | AI50: 抱负Aspiration。我决心走向成功。（任意） | AJ50: 救赎Redemption。人人心中有善念。（善良） | AK50: 救赎Redemption。人人心中有善念。（善良） | AL50: 正直Honety。艺术展现灵魂。它应当发自内心，揭露本我。（任意） | AM50: 正直Honety。艺术展现灵魂。它应当发自内心，揭露本我。（任意） | AN50: 命运Destiny。任何人或事情都无法让我偏离我那崇高的感召。（任意） | AO50: 抱负Aspiration。我努力钻研是为了成为本行中的翘楚。（任意） | AP50: 抱负Aspiration。我努力钻研是为了成为本行中的翘楚。（任意） | AQ50: 自知Self-Knowledge。如果你能自知，那么就无所不知。（任意） | AR50: 贵族义务Noble Obligation。保护依附我的人们，是我的责任。（善良） | AS50: 贵族义务Noble Obligation。保护依附我的人们，是我的责任。（善良） | AT50: 光荣Glory。我必须在战斗中赢得荣耀，既为自己也为氏族。（任意） | AU50: 提升自我Self-Improvement。终生学习为的正是让人变得更好。（任意） | AV50: 抱负Aspiration。早晚有一天，我会拥有自己的船，掌握自己的命运。（任意） | AW50: 抱负Aspiration。早晚有一天，我会拥有自己的船，掌握自己的命运。（任意） | AX50: 国家Nation。我的城市、国家和人民是最重要的事。（任意） | AY50: 抱负Aspiration。我会证明我值得拥有更好的生活。（任意） | AZ50: 国家Nation。我的城市、国家和人民是最重要的事。（任意） | BA50: 国家Nation。我的城市、国家和人民是最重要的事。（任意） | BB50: 抱负Aspiration。我努力钻研是为了成为本行中的翘楚。（任意） | BC50: 提升自我Self-Improvement。终生学习为的正是让人变得更好。（任意） | BD50: 抱负Aspiration。我努力钻研是为了成为本行中的翘楚。（任意） | BE50: 抱负Aspiration。我将自己的行动与他或她的教导相较，求证明自己配得上吾主的喜爱。（任何） | BF50: 疑心。我必须要小心，我没有办法告诉朋友们敌人是谁。（任何） | BG50: 命运Destiny。任何人或事情都无法让我偏离我那崇高的感召。（任意） | BH50: 国家Nation。我的城市、国家和人民是最重要的事。（任意） | BI50: 国家Nation。我的城市、国家和人民是最重要的事。（任意） | BJ50: 救赎Redemption。人人心中有善念。（善良） | BK50: 光荣Glory。我必须在战斗中赢得荣耀，既为自己也为氏族。（任意） | BL50: 贵族义务Noble Obligation。保护依附我的人们，是我的责任。（善良） | BM50: 舒适。我想要确保我的我的爱人能够享受生活中最美好的东西。（任何） | BO50: 灰矮人_魔邓肯 | BP50: 灰矮人_魔邓肯属性值加成 | BQ50: 你的体质加2，你的力量加1。 | BR50: 蜥蜴人 | BS50: 蜥蜴人 | CX50: 逐渐消失 | CY50: 先决条件：侏儒 你的族人在幻术系魔法的技巧上很有天赋。你学过一种在你受到伤害时逐渐隐去的魔法技巧。你获得以下好处： 你的智力+1，最大20 当你受到伤害，你可以用一个反应来用魔法把自己变成隐形，直到你攻击，造成伤害或使别人通过豁免检定或者下个回合。你只能使用一次这个能力，直到你进行一次短休或者长休。 | CZ50: 49
C51: 牧师 | D51: =G85 -> 4 | E51: × | O51: 16 | P51: 16 | U51: 胸甲 | V51: 14 | W51: 否 | X51: 20 | AB51: 圣物匣 | AC51: 枚圣徽是某个神袛或神系象征。它可能是一个描绘有代表一个神袛符号的护身符，相同的符号可能作为一个徽章被仔细地雕刻或镶嵌在一面盾牌上，也可能是一个盛有一块神圣遗物碎片的小盒。附录B中列举有多元宇宙众神的代表性徵记。牧师或圣武士能将圣徽用作其施法的法器。使用这些圣徽时，施法着必须将其握在手中，戴在身上可见处，或者将其装在盾上使用。 | AD51: 5gp | AE51: 2 | AH51: 侍僧牵绊 | AI51: 骗子牵绊 | AJ51: 罪犯牵绊 | AK51: 密探牵绊 | AL51: 艺人牵绊 | AM51: 角斗士牵绊 | AN51: 平民英雄牵绊 | AO51: 公会工匠牵绊 | AP51: 公会商人牵绊 | AQ51: 隐士牵绊 | AR51: 贵族牵绊 | AS51: 骑士牵绊 | AT51: 化外之民牵绊 | AU51: 智者牵绊 | AV51: 水手牵绊 | AW51: 海盗牵绊 | AX51: 士兵牵绊 | AY51: 流浪儿牵绊 | AZ51: 城市守卫牵绊 | BA51: 调查员牵绊 | BB51: 氏族工匠牵绊 | BC51: 隐修学者牵绊 | BD51: 朝臣牵绊 | BE51: 派系特工牵绊 | BF51: 远行者牵绊 | BG51: 继承者牵绊 | BH51: 教团骑士牵绊 | BI51: 老佣兵牵绊 | BJ51: 城市猎人牵绊 | BK51: 乌斯伽部族成员牵绊 | BL51: 深水人贵族牵绊 | BM51: 家族代理人牵绊 | BO51: 金龙裔 | BP51: 金龙裔属性值加成 | BQ51: 你力量加2，魅力加1。 | BR51: 半人马 | BS51: 半人马 | CX51: 精类位移 | CY51: 先决条件：高等精灵 你的高等精灵学识研究已然解锁了一些其他精灵掌控的精类力量，而非你的艾拉德林表亲。利用你的精类先祖，你可以大步迈入妖精荒野来减短你从一个地方到另一个地方的道路，你获得以下好处： 你的智力或者魅力+1，最大20 你学会说读写木族语。 你学会了迷踪步并且可以不消耗法术位释放它。直到你进行一次短休或者长休你才能再度使用此能力。智力是你的施法关键属性。 | CZ51: 50
C52: 德鲁伊 | D52: =H85 -> 3 | E52: × | O52: 17 | P52: 17 | U52: 半身板甲 | V52: 15 | W52: 是 | X52: 40 | AB52: 圣水_扁瓶 | AC52: 你可以用一个动作将这小瓶液体泼溅到你身边5尺范围内的一个生物身上，或是将小瓶投到至多20尺远的地方，并利用冲击打破它。两种情况都可以视为对一个生物或物件发动一次远程攻击，并将圣水视为一件临时武器。命中时，如果目标是一只邪魔或不死生物，则目标受到2d6点光耀伤害。 一名牧师或圣武士能通过主持一种特殊的仪式来创造圣水。该仪式花费1小时进行，且需要花费价值25gp的银粉，并消耗施法者一枚1环法术位。 | AD52: 25gp | AE52: 1 | AH52: 为了找回很久前丢失的与我信仰有关的一件古代遗物，我可以付出生命。 | AI52: 我敲诈错了人，所以必须确保那家伙不和我或者任何我在意的人再度打上交道。 | AJ52: 我试图偿还一个慷慨的资助者的老债务。 | AK52: 我试图偿还一个慷慨的资助者的老债务。 | AL52: 我的乐器是我最宝贵的财富，它纪念着某个我所爱之人。 | AM52: 我的乐器是我最宝贵的财富，它纪念着某个我所爱之人。 | AN52: 我有一个家庭，但我现在不知道他们身处何处。我希望终有一日能够再次见到他们。 | AO52: 我学习技艺的厂房对我来说是世界上最重要的地方。 | AP52: 我学习技艺的厂房对我来说是世界上最重要的地方。 | AQ52: 任何事物不比我的修行同伴、修行戒律或修会本身那么重要。 | AR52: 为了获得家族的认可，我可以面对任何挑战。 | AS52: 为了获得家族的认可，我可以面对任何挑战。 | AT52: 即使与其异地相隔，我的家族，氏族或部族是我生命中最重要的事物。 | AU52: 保护我的学生是我的责任。 | AV52: 我首先忠于我的船长，任何事物都要排在后头。 | AW52: 我首先忠于我的船长，任何事物都要排在后头。 | AX52: 我依然会以性命保护曾一起共事之人。 | AY52: 这城镇就是我的家，而我必须保卫它。 | AZ52: 我依然会以性命保护曾一起共事之人。 | BA52: 我依然会以性命保护曾一起共事之人。 | BB52: 我学习技艺的厂房对我来说是世界上最重要的地方。 | BC52: 保护我的学生是我的责任。 | BD52: 我学习技艺的厂房对我来说是世界上最重要的地方。 | BE52: 为了找回很久前丢失的与我信仰有关的一件古代遗物，我可以付出生命。 | BF52: 只要我有从家乡培养出的品质，我就可以在这片陌生的土地上面对任何逆境。 | BG52: 我有一个家庭，但我现在不知道他们身处何处。我希望终有一日能够再次见到他们。 | BH52: 我依然会以性命保护曾一起共事之人。 | BI52: 我依然会以性命保护曾一起共事之人。 | BJ52: 我试图偿还一个慷慨的资助者的老债务。 | BK52: 即使与其异地相隔，我的家族，氏族或部族是我生命中最重要的事物。 | BL52: 为了获得家族的认可，我可以面对任何挑战。 | BM52: 我的龙纹家族就是我的家人，我愿意为我的家人做任何事。 | BO52: 红龙裔 | BP52: 红龙裔属性值加成 | BQ52: 你力量加2，魅力加1。 | BR52: 牛头人 | BS52: 牛头人_拉尼卡 | BT52: 牛头人_塞洛斯 | CX52: 弗莱格索斯之焰 | CY52: 先决条件：提夫林 你学会了召唤地狱火来听从你的指挥，你获得以下好处： 智力或者魅力+1，最大20 当你施展法术扔火焰伤害的伤害骰时，你可以重扔任何被扔到1的骰子，你必须接受新结果哪怕那也只是个1。 当你施展造成火焰伤害的法术时，你可以让火焰环绕于你，直到你的下个回合结束。那些火焰不会对你或者你的物品造成伤害。他们提供30尺明亮照明和额外30尺昏暗照明，只要处于火焰现形之时，任何在你五尺内对你近战攻击的生物都会受到1d4火焰伤害。 | CZ52: 51
C53: 武僧 | D53: × | E53: × | O53: 18 | P53: 18 | U53: 环甲 | V53: 14 | W53: 是 | X53: 40 | AB53: 沙漏 | AC53: - | AD53: 25gp | AE53: 1 | AH53: 终有一天我会对谴责我为异端的罪恶神庙组织复仇。 | AI53: 我的导师是个可能正在某个监牢里面烂着的糟糕人物，然而我欠他很多很多。 | AJ53: 我的非法所得是为了支持我的家庭。 | AK53: 我的非法所得是为了支持我的家庭。 | AL53: 有人偷走了我珍爱的乐器，而我一定要夺回来。 | AM53: 有人偷走了我珍爱的乐器，而我一定要夺回来。 | AN53: 我劳作于这片土地，我热爱这片土地，而且我将保卫这片土地。 | AO53: 我为某人造出了一件绝世珍品，却发现对方根本配不上它。我仍在寻找配得上它的人。 | AP53: 我为某人造出了一件绝世珍品，却发现对方根本配不上它。我仍在寻找配得上它的人。 | AQ53: 我隐居是为了躲避那些仍在搜捕我的人。而我早晚必须直接面对他们。 | AR53: 我必须不惜代价的维持住两个家族之间的联姻关系。 | AS53: 我必须不惜代价的维持住两个家族之间的联姻关系。 | AT53: 破坏家园的原始风貌即是对我的伤害。 | AU53: 我有一份载有可怕秘密的远古文献，而它绝不能落入错误的人手中。 | AV53: 船才是最重要的，无论船员还是船长都是过客。 | AW53: 船才是最重要的，无论船员还是船长都是过客。 | AX53: 有人在战场上救过我的命。因而现在我也不会丢下任何一个朋友。 | AY53: 我资助了一所孤儿院，以免其他人再遭受我的厄运。 | AZ53: 有人在战场上救过我的命。因而现在我也不会丢下任何一个朋友。 | BA53: 有人在战场上救过我的命。因而现在我也不会丢下任何一个朋友。 | BB53: 我为某人造出了一件绝世珍品，却发现对方根本配不上它。我仍在寻找配得上它的人。 | BC53: 我有一份载有可怕秘密的远古文献，而它绝不能落入错误的人手中。 | BD53: 我为某人造出了一件绝世珍品，却发现对方根本配不上它。我仍在寻找配得上它的人。 | BE53: 终有一天我会对谴责我为异端的罪恶神庙组织复仇。 | BF53: 我的人民信仰的上神是对于远离家乡的我的一种安慰。 | BG53: 我劳作于这片土地，我热爱这片土地，而且我将保卫这片土地。 | BH53: 有人在战场上救过我的命。因而现在我也不会丢下任何一个朋友。 | BI53: 有人在战场上救过我的命。因而现在我也不会丢下任何一个朋友。 | BJ53: 我的非法所得是为了支持我的家庭。 | BK53: 破坏家园的原始风貌即是对我的伤害。 | BL53: 我必须不惜代价的维持住两个家族之间的联姻关系。 | BM53: 我爱上了另一个龙纹家族的人，但是这种关系是禁忌的。 | BO53: 绿龙裔 | BP53: 绿龙裔属性值加成 | BQ53: 你力量加2，魅力加1。 | BR53: 龟人 | BS53: 龟人 | CX53: 恶魔体质 | CY53: 先决条件：提夫林 恶魔之血支撑着你，解锁一些类似恶魔领主拥有的韧性。你获得以下好处： 体质+1，不能超过20 你获得冷冻与毒素的伤害抗性。 你在对抗毒素时取优势。 | CZ53: 52
C54: 游荡者 | D54: × | E54: × | O54: 19 | P54: 19 | U54: 链甲 | V54: 16 | W54: 是 | X54: 55 | AB54: 狩猎陷阱 | AC54: 使用动作设置好该陷阱后，其形成一个锯齿钢圈，并在生物踏上其中央压板时闭合。陷阱由一根沉重的链条固定在某处，例如一棵树或是一根钉在地上的钉子。任何踩上压板的生物都必须进行一次DC13的敏捷豁免，豁免失败则受到1d4点穿刺伤害，并停止移动。在该生物从陷阱中解脱前，其移动范围都被限制在链条的长度内（通常为3尺）。一个生物可以使用动作进行一次DC13的力量检定，以解脱自己或其触及范围内的另一生物。每次豁免失败时，被困生物都将受到1点穿刺伤害。 | AD54: 5gp | AE54: 25 | AH54: 我欠那位在我的双亲死亡时收养我的教士一条命。 | AI54: 我在某个地方有个未曾见过我的孩子。我正为他改变这个世界。 | AJ54: 我有一件重要的东西被夺走了，并且我想要把它偷回来。 | AK54: 我有一件重要的东西被夺走了，并且我想要把它偷回来。 | AL54: 我要不惜一切代价让自己出名。 | AM54: 我要不惜一切代价让自己出名。 | AN54: 一名傲慢的贵族曾经死命痛打了我一顿，故而我将报复任何我遇到的恃强凌弱者。 | AO54: 公会造就了今天的我，因此我仍欠公会良多。 | AP54: 公会造就了今天的我，因此我仍欠公会良多。 | AQ54: 我一直在隐居生活中寻找启迪，然而至今仍然一无所获。 | AR54: 任何事物都不如家族血亲更重要。 | AS54: 任何事物都不如家族血亲更重要。 | AT54: 我会让那些摧毁我家乡的恶徒见识什么叫狂怒。 | AU54: 我为保护一个图书馆，学院，抄写室或修道院而工作。 | AV54: 我总是会怀念我上过的第一艘船。 | AW54: 我总是会怀念我上过的第一艘船。 | AX54: 荣誉即吾命。 | AY54: 我的幸运应归功于那位曾教会我如何在街头生存的另一位流浪儿。 | AZ54: 荣誉即吾命。 | BA54: 荣誉即吾命。 | BB54: 公会造就了今天的我，因此我仍欠公会良多。 | BC54: 我为保护一个图书馆，学院，抄写室或修道院而工作。 | BD54: 公会造就了今天的我，因此我仍欠公会良多。 | BE54: 我欠那位在我的双亲死亡时收养我的教士一条命。 | BF54: 没有比为我的人民服务更伟大的事业。 | BG54: 一名傲慢的贵族曾经死命痛打了我一顿，故而我将报复任何我遇到的恃强凌弱者。 | BH54: 荣誉即吾命。 | BI54: 荣誉即吾命。 | BJ54: 我有一件重要的东西被夺走了，并且我想要把它偷回来。 | BK54: 我会让那些摧毁我家乡的恶徒见识什么叫狂怒。 | BL54: 任何事物都不如家族血亲更重要。 | BM54: 我爱的人被自己家族中的敌对派别杀害了，我决心报仇。 | BO54: 黑龙裔 | BP54: 黑龙裔属性值加成 | BQ54: 你力量加2，魅力加1。 | BR54: 斑猫人 | BS54: 斑猫人 | CX54: 兽人式狂怒 | CY54: 先决条件：半兽人 你的狂怒爆发时不知疲倦，你获得以下好处： 你的力量或者体质+1，最高20 当你用简易或者军用武器进行一次攻击命中时，你可以再扔一个武器伤害骰并且用武器伤害同样的伤害类型将它加入额外伤害。你只能使用一次，直到你进行一次短休或者长休。 在你进行坚韧不屈特性之后，你可以立即以反应进行一次武器攻击。 | CZ54: 53
C55: 邪术师 | D55: =I85 -> 3 | E55: =F107 -> 6 | O55: 20 | P55: 20 | U55: 板条甲 | V55: 17 | W55: 是 | X55: 60 | AB55: 墨水_1盎司瓶 | AC55: - | AD55: 10gp | AE55: 0 | AH55: 我做的每一件事情都是为了普罗大众。 | AI55: 我是贵族出身，我早晚一天会从剽窃我领地和头衔的人身上把一切都抢回来。 | AJ55: 我会成为有史以来最伟大的盗贼。 | AK55: 我会成为有史以来最伟大的盗贼。 | AL55: 我崇拜古老传奇中的某位英雄，并时时以他作榜样。 | AM55: 我崇拜古老传奇中的某位英雄，并时时以他作榜样。 | AN55: 我的工具是我以往生活的符号，因而我随身携带着它们以便永远记住我的根。 | AO55: 我为了向某人求爱而攒钱。 | AP55: 我为了向某人求爱而攒钱。 | AQ55: 我隐居是因为无法得到所爱之人。 | AR55: 我爱上了家族所不齿的另一个家族的子嗣。 | AS55: 我爱上了家族所不齿的另一个家族的子嗣。 | AT55: 我是部族最后的遗孤，因而只剩我可以让部族的威名成为传奇。 | AU55: 我一生的作品就是关于某项特定学识领域的一系列书典。 | AV55: 在一个港口里住着我的情人，她的魅力几乎能让我放弃海上生活和她在一起。 | AW55: 在一个港口里住着我的情人，她的魅力几乎能让我放弃海上生活和她在一起。 | AX55: 我永远不会忘记队伍曾遭受到的惨败，以及当时的敌人。 | AY55: 我欠某位同情我的绅士一笔我还不起的债。 | AZ55: 我永远不会忘记队伍曾遭受到的惨败，以及当时的敌人。 | BA55: 我永远不会忘记队伍曾遭受到的惨败，以及当时的敌人。 | BB55: 我为了向某人求爱而攒钱。 | BC55: 我一生的作品就是关于某项特定学识领域的一系列书典。 | BD55: 我为了向某人求爱而攒钱。 | BE55: 我做的每一件事情都是为了普罗大众。 | BF55: 我的自由是我最珍贵的财宝。我不会再让任何人从我手中多去它。 | BG55: 我的工具是我以往生活的符号，因而我随身携带着它们以便永远记住我的根。 | BH55: 我永远不会忘记队伍曾遭受到的惨败，以及当时的敌人。 | BI55: 我永远不会忘记队伍曾遭受到的惨败，以及当时的敌人。 | BJ55: 我会成为有史以来最伟大的盗贼。 | BK55: 我是部族最后的遗孤，因而只剩我可以让部族的威名成为传奇。 | BL55: 我爱上了家族所不齿的另一个家族的子嗣。 | BM55: 我并不关心家族整体如何，但我愿意为我的老导师做任何事。 | BO55: 银龙裔 | BP55: 银龙裔属性值加成 | BQ55: 你力量加2，魅力加1。 | BR55: 阿兰寇拉鹰人 | BS55: 阿兰寇拉鹰人 | CX55: 奇才 | CY55: 先决条件：人类或半精灵或者半兽人 你拥有学习新鲜事物的本领，你获得以下好处： 你获得一种自选技能的熟练，一种自选工具的熟练，且娴熟于一种自选的语言。 选择一种你已经熟练于其的技能。你获得这种技能的专精，这意味着你在以其进行的任何技能检定上获得双倍熟练值。你选择的这个技能必须未在任何特性上获得双倍熟练的好处，例如专精。 | CZ55: 54
C56: 奇械师 | D56: =J85 -> 2 | E56: × | N56: 吟游诗人等级 | P56: =VLOOKUP(N36,O36:P55,2,0) -> 5 | U56: 板甲 | V56: 18 | W56: 是 | X56: 65 | AB56: 墨水笔 | AC56: - | AD56: 0.02gp | AE56: 0 | AH56: 为了保卫我曾服务的神庙我可以做任何事情。 | AI56: 一个大人物杀了我的爱人。要不了多久，我就会向他复仇。 | AJ56: 我因一桩严重罪行而内疚。并希望从中寻求自我救赎。 | AK56: 我因一桩严重罪行而内疚。并希望从中寻求自我救赎。 | AL56: 只要能证明我比那个可恨的对手强，我愿意做任何事情。 | AM56: 只要能证明我比那个可恨的对手强，我愿意做任何事情。 | AN56: 我保护那些无力自我保护的人。 | AO56: 终有一天，我会回到公会，然后证明我是其中最厉害的工匠。 | AP56: 终有一天，我会回到公会，然后证明我是其中最厉害的工匠。 | AQ56: 倘若我的发现公诸于众，世界必将天翻地覆。 | AR56: 我对主君的忠诚固若泰山。 | AS56: 我对主君的忠诚固若泰山。 | AT56: 我眼前时常浮现灾难将至的幻景，我要尽全力阻止其发生。 | AU56: 我终生寻求某个特定问题的解答。 | AV56: 我平分财宝时见到有人作弊，而我要夺回我应得的那份。 | AW56: 我平分财宝时见到有人作弊，而我要夺回我应得的那份。 | AX56: 那些与我同袍的人值得为之豁出性命。 | AY56: 我通过抢劫一位大人物而脱贫致富，但是也因此而遭到通缉。 | AZ56: 那些与我同袍的人值得为之豁出性命。 | BA56: 那些与我同袍的人值得为之豁出性命。 | BB56: 终有一天，我会回到公会，然后证明我是其中最厉害的工匠。 | BC56: 我终生寻求某个特定问题的解答。 | BD56: 终有一天，我会回到公会，然后证明我是其中最厉害的工匠。 | BE56: 为了保卫我曾服务的神庙我可以做任何事情。 | BF56: 我为这片美丽而神奇的新土地而着迷。 | BG56: 我保护那些无力自我保护的人。 | BH56: 那些与我同袍的人值得为之豁出性命。 | BI56: 那些与我同袍的人值得为之豁出性命。 | BJ56: 我因一桩严重罪行而内疚。并希望从中寻求自我救赎。 | BK56: 我眼前时常浮现灾难将至的幻景，我要尽全力阻止其发生。 | BL56: 我对主君的忠诚固若泰山。 | BM56: 我相信我的家族需要进化才能生存，而我需要引领这个变化。 | BO56: 绿龙裔 | BP56: 绿龙裔属性值加成 | BQ56: 你力量加2，魅力加1。 | BR56: 纯种蛇人 | BS56: 纯种蛇人 | CX56: 花开二度 | CY56: 先决：半身人 命运在有人想要伤害你时眷顾于你，你获得以下好处： 你的敏捷，体质或者魅力+1，最大20 当一个你可以看到的生物对你进行攻击骰命中时，你可以用一个反应让那个生物重骰。一旦你使用此能力，直到你进行一次短休或者长休你才能再度使用此能力。 | CZ56: 55
C57: 战士 | D57: × | E57: × | N57: =主要情况!W3 -> 5 | O57: 1 | P57: 1d6 | Q57: 激励骰 | U57: 野蛮人无甲防御 | V57: =10+主要情况!G10+主要情况!G12 -> 13 | W57: 否 | X57: 0 | AB57: 壶或罐 | AC57: - | AD57: 0.02gp | AE57: 4 | AH57: 我试图去保护一部神圣典籍，而我的敌人认为它是异端的并寻求摧毁它。 | AI57: 我毁了一个不该被骗的人。我试图弥补我的过失，但是可能永远不会原谅自己。 | AJ57: 我深爱的某人因我犯下的错误而死。而我决不会让这种事情再发生了。 | AK57: 我深爱的某人因我犯下的错误而死。而我决不会让这种事情再发生了。 | AL57: 我可以为老剧团的同伴做任何事。 | AM57: 我可以为老剧团的同伴做任何事。 | AN57: 我希望我的青梅竹马能伴着我一起追寻我的命运。 | AO57: 我要向那个破坏我工坊，毁掉我生活的邪恶势力复仇。 | AP57: 我要向那个破坏我工坊，毁掉我生活的邪恶势力复仇。 | AQ57: 我的苦修向我揭示了只有我能摧毁的可怖邪恶。 | AR57: 平民们将我视作人民的英雄。 | AS57: 平民们将我视作人民的英雄。 | AT57: 抚养幼童继承部族是我的责任。 | AU57: 我出卖了自己的灵魂以获得知识。并希望做一些大事将其赢回来。 | AV57: 残忍的海盗杀了我的船长和兄弟，抢走了我的船，只留下濒死的我。而我一定要复仇。 | AW57: 残忍的海盗杀了我的船长和兄弟，抢走了我的船，只留下濒死的我。而我一定要复仇。 | AX57: 我为那些无法为他们自己战斗的人而战。 | AY57: 不该再有人遭受我曾经的苦难了。 | AZ57: 我为那些无法为他们自己战斗的人而战。 | BA57: 我为那些无法为他们自己战斗的人而战。 | BB57: 我要向那个破坏我工坊，毁掉我生活的邪恶势力复仇。 | BC57: 我出卖了自己的灵魂以获得知识。并希望做一些大事将其赢回来。 | BD57: 我要向那个破坏我工坊，毁掉我生活的邪恶势力复仇。 | BE57: 我试图去保护一部神圣典籍，而我的敌人认为它是异端的并寻求摧毁它。 | BF57: 虽然我没有选择，但我还是为之前必须离开所爱之人感到悲哀。我希望在未来某一天能再次见到他们。 | BG57: 我希望我的青梅竹马能伴着我一起追寻我的命运。 | BH57: 我为那些无法为他们自己战斗的人而战。 | BI57: 我为那些无法为他们自己战斗的人而战。 | BJ57: 我深爱的某人因我犯下的错误而死。而我决不会让这种事情再发生了。 | BK57: 抚养幼童继承部族是我的责任。 | BL57: 平民们将我视作人民的英雄。 | BM57: 我决心给家族中的领导留下深刻的印象，并借此上位。 | BO57: 白龙裔 | BP57: 白龙裔属性值加成 | BQ57: 你力量加2，魅力加1。 | BR57: 吉斯人 | BS57: 吉斯洋基人 | BT57: 吉斯泽莱人 | CX57: 低身之机敏 | CY57: 先决条件：矮人或者小体型 你有这在你族群中不寻常的机敏，你获得以下好处： 你的力量或者敏捷+1，最大20 你的速度提升5尺 你获得运动或者特技之一的熟练（由你选择）。 你在你进行的脱离擒抱的力量（运动）或者敏捷（特技）的检定上获得优势。 | CZ57: 56
C58: 圣武士 | D58: × | E58: × | O58: 2 | P58: 1d6 | U58: 武僧无甲防御 | V58: =10+主要情况!G10+主要情况!G16 -> 14 | W58: 否 | X58: 0 | AB58: 爬梯_10尺 | AC58: - | AD58: 0.1gp | AE58: 25 | AH58: 侍僧缺点 | AI58: 骗子缺点 | AJ58: 罪犯缺点 | AK58: 密探缺点 | AL58: 艺人缺点 | AM58: 角斗士缺点 | AN58: 平民英雄缺点 | AO58: 公会工匠缺点 | AP58: 公会商人缺点 | AQ58: 隐士缺点 | AR58: 贵族缺点 | AS58: 骑士缺点 | AT58: 化外之民缺点 | AU58: 智者缺点 | AV58: 水手缺点 | AW58: 海盗缺点 | AX58: 士兵缺点 | AY58: 流浪儿缺点 | AZ58: 城市守卫缺点 | BA58: 调查员缺点 | BB58: 氏族工匠缺点 | BC58: 隐修学者缺点 | BD58: 朝臣缺点 | BE58: 派系特工缺点 | BF58: 远行者缺点 | BG58: 继承者缺点 | BH58: 教团骑士缺点 | BI58: 老佣兵缺点 | BJ58: 城市猎人缺点 | BK58: 乌斯伽部族成员缺点 | BL58: 深水人贵族缺点 | BM58: 家族代理人缺点 | BO58: 黄铜龙裔 | BP58: 黄铜龙裔属性值加成 | BQ58: 你力量加2，魅力加1。 | BR58: 梭螺鱼人 | BS58: 梭螺鱼人 | CX58: 木精灵魔法 | CY58: 先决条件：木精灵 你学会由你的族人保护和尊敬的原初之木的魔法。你学会一种任选的德鲁伊戏法，你同时学会大步奔行和行迹无踪法术。你可以释放他们各一次而不消耗法术位，直到一次长休或者短休，你才可以再次通过此能力施法。这三个法术的施法关键属性是感知。 | CZ58: 57
C59: 游侠 | D59: × | E59: =G107 -> 4 | O59: 3 | P59: 1d6 | U59: 法师护甲 | V59: =13+主要情况!G10 -> 16 | W59: 否 | X59: 0 | AB59: 油灯 | AC59: 一只油灯可以为其身边15尺半径范围提供明亮光照，以及该范围外30尺的微光光照。点亮的油灯每6小时消耗一扁瓶灯油（1品脱）。 | AD59: 0.5gp | AE59: 1 | AH59: 我评价他人十分严苛，并且对自己更加苛刻。 | AI59: 我对漂亮脸蛋没有抵抗力。 | AJ59: 当我看到一些有价值的东西时，就会一心只想如何偷到它。 | AK59: 当我看到一些有价值的东西时，就会一心只想如何偷到它。 | AL59: 我会不择手段的去获取声誉和名望。 | AM59: 我会不择手段的去获取声誉和名望。 | AN59: 统治我故乡的暴君会一直追杀我。 | AO59: 我会为了获得某些珍贵无价之物做任何事。 | AP59: 我会为了获得某些珍贵无价之物做任何事。 | AQ59: 我现在重返文明世界，却有点过度沉溺于享乐。 | AR59: 我暗自认为自己比所有人都高贵。 | AS59: 我暗自认为自己比所有人都高贵。 | AT59: 我过度痴迷于麦酒、葡萄酒等醉人之物。 | AU59: 以知识许诺很容易打动我。 | AV59: 我遵守命令，哪怕是那些并不正确的命令。 | AW59: 我遵守命令，哪怕是那些并不正确的命令。 | AX59: 我们曾在战场上面对的凶暴的敌人依然会令我恐惧的发抖。 | AY59: 如果敌人人多势众，我就会在打斗时溜走。 | AZ59: 我们曾在战场上面对的凶暴的敌人依然会令我恐惧的发抖。 | BA59: 我们曾在战场上面对的凶暴的敌人依然会令我恐惧的发抖。 | BB59: 我会为了获得某些珍贵无价之物做任何事。 | BC59: 以知识许诺很容易打动我。 | BD59: 我会为了获得某些珍贵无价之物做任何事。 | BE59: 我评价他人十分严苛，并且对自己更加苛刻。 | BF59: 我背地里（或者明面上就）觉得我家乡的文化风俗比这片外国土地要好的多。 | BG59: 统治我故乡的暴君会一直追杀我。 | BH59: 我们曾在战场上面对的凶暴的敌人依然会令我恐惧的发抖。 | BI59: 我们曾在战场上面对的凶暴的敌人依然会令我恐惧的发抖。 | BJ59: 当我看到一些有价值的东西时，就会一心只想如何偷到它。 | BK59: 我过度痴迷于麦酒、葡萄酒等醉人之物。 | BL59: 我暗自认为自己比所有人都高贵。 | BM59: 我过分注重遵循既定的程度和协议。 | BO59: 赤铜龙裔 | BP59: 赤铜龙裔属性值加成 | BQ59: 你力量加2，魅力加1。 | BR59: 歌利亚 | BS59: 歌利亚 | CX59: 奇械学徒 | CY59: 你已习得些许奇械师的创造力。 ·你从奇械师法术列表中选择并习得一个戏法。此外，你从该法术列表中选择并习得一个一环法术。智力是你施展这些法术的施法关键属性。 ·你可以在不消耗法术位的情况下施展一次来自此专长的一环法术。你必须在完成一次长休后才能再次这样做。你也可以正常消耗法术位来施展该法术。 ·你获得你所选的一项工匠工具熟练，并且你可以将该工具作为施展任何以智力为施法关键属性的法术的法器。 | CZ59: 58
C60: 野蛮人 | D60: × | E60: × | O60: 4 | P60: 1d6 | AB60: 牛眼提灯 | AC60: 一盏牛眼提灯可以为前方60尺的锥状区域提供明亮光照，以及该范围外60尺的微光光照。点亮的牛眼提灯每6小时消耗一扁瓶的灯油（1品脱）。 | AD60: 10gp | AE60: 2 | AH60: 我过于信任那些在我神庙的阶级中控制权势的人。 | AI60: 我总是欠债，并且把不义之财花在奢侈品上，还花得比赚得快。 | AJ60: 在面对金钱与朋友间的抉择时，我通常都选择金钱。 | AK60: 在面对金钱与朋友间的抉择时，我通常都选择金钱。 | AL60: 我对漂亮脸蛋非常着迷。 | AM60: 我对漂亮脸蛋非常着迷。 | AN60: 我深信命运的征兆，以至于看不清自己的不足或是失败的可能性。 | AO60: 我常常很急躁地认定某人正在骗我。 | AP60: 我常常很急躁地认定某人正在骗我。 | AQ60: 我怀有即使是苦修和冥想也无法抹消的阴暗、嗜血之心。 | AR60: 我努力遮掩一个会永远摧毁家族的可耻秘密。 | AS60: 我努力遮掩一个会永远摧毁家族的可耻秘密。 | AT60: 繁忙充实的生活里没有谨慎的余地。 | AU60: 一般人看到恶魔时会尖叫着逃跑，而我则会停下来对它作解剖和记录。 | AV60: 我会绞尽脑汁避免额外劳动。 | AW60: 我会绞尽脑汁避免额外劳动。 | AX60: 除那些久经沙场的武士外，任何人都不值得我尊重。 | AY60: 我觉得金子很值钱，因此我会不择手段赚很多金子。 | AZ60: 除那些久经沙场的武士外，任何人都不值得我尊重。 | BA60: 除那些久经沙场的武士外，任何人都不值得我尊重。 | BB60: 我常常很急躁地认定某人正在骗我。 | BC60: 一般人看到恶魔时会尖叫着逃跑，而我则会停下来对它作解剖和记录。 | BD60: 我常常很急躁地认定某人正在骗我。 | BE60: 我过于信任那些在我神庙的阶级中控制权势的人。 | BF60: 为了不想和这些当地人交流，我假装不懂这些人当地的语言。 | BG60: 我深信命运的征兆，以至于看不清自己的不足或是失败的可能性。 | BH60: 除那些久经沙场的武士外，任何人都不值得我尊重。 | BI60: 除那些久经沙场的武士外，任何人都不值得我尊重。 | BJ60: 在面对金钱与朋友间的抉择时，我通常都选择金钱。 | BK60: 繁忙充实的生活里没有谨慎的余地。 | BL60: 我努力遮掩一个会永远摧毁家族的可耻秘密。 | BM60: 我痴迷于阴谋论，担心秘密组织和隐藏起来的恶魔会有所动作。 | BO60: 青铜龙裔 | BP60: 青铜龙裔属性值加成 | BQ60: 你力量加2，魅力加1。 | BR60: 象族 | BS60: 象族 | CX60: 大厨 | CY60: 花费在专研厨艺上的工夫已然有了回报，使你获得了以下增益： ·你的体质或感知增加1，上限为20。 ·你获得厨师工具的熟练项，如果你还没有的话。 ·作为短休的一部分，只要你手上有原料和厨师工具，你便可以烹饪特制料理。你可以为特定数量的生物准备这种食物，其数量等同于4+你的熟练加值。在本次短休结束时，任何食用了料理并且花费了一个或更多生命骰来恢复生命值的生物恢复额外1d8点生命值。 ·在花费一小时精心制作后，或者在完成一次长休时，你可以制作等同于你熟练加值个数的餐点。这些餐点在制作完成后持续八小时。任何食用餐点的生物都能获得等同于你熟练加值的临时生命值。 | CZ60: 59
D61: =VLOOKUP(B48,C48:D60,2,0) -> 3 | E61: =VLOOKUP(B48,C48:E60,3,0) -> 6 | O61: 5 | P61: 1d8 | AB61: 附盖提灯 | AC61: 一盏附盖提灯可以为其身边30尺半径范围提供明亮光照，以及该范围外30尺的微光光照。点亮的提灯每6小时消耗一扁瓶的灯油（1品脱）。你可以使用一个动作放下盖子，使其光照减弱为5尺范围的微光照明。 | AD61: 5gp | AE61: 2 | AH61: 我的虔诚有时令我盲目信任那些声称与我信仰相同的人。 | AI61: 我确信没人能用我骗人的方式骗到我。 | AJ61: 每当要记住某个计划时，我总会忘掉。就是无法忘掉，我也会选择性无视它。 | AK61: 每当要记住某个计划时，我总会忘掉。就是无法忘掉，我也会选择性无视它。 | AL61: 某个丑闻让我背井离乡。而这麻烦依然如影随形。 | AM61: 某个丑闻让我背井离乡。而这麻烦依然如影随形。 | AN61: 自幼认识我的人知道我羞耻的秘密，所以我再也不能回家了。 | AO61: 应当没人知道我曾经从公会金库里偷过钱。 | AP61: 应当没人知道我曾经从公会金库里偷过钱。 | AQ61: 我的想法和哲学观非常死板。 | AR61: 我总会听到针对我的隐晦侮辱与威胁，且轻易就会因此而发怒。 | AS61: 我总会听到针对我的隐晦侮辱与威胁，且轻易就会因此而发怒。 | AT61: 我会记住每次侮辱，并对委屈我的人报以无声的怨恨。 | AU61: 揭示一项远古奥秘值得以一整个文明作代价。 | AV61: 一旦有人质疑惑我的勇气，我就什么都敢干。 | AW61: 一旦有人质疑惑我的勇气，我就什么都敢干。 | AX61: 我曾在战场上犯了一个严重的错并为此伤害了许多生命——而我为了能守住这个秘密愿意做任何事。 | AY61: 我从不会完全信任别人，而只相信我自己。 | AZ61: 我曾在战场上犯了一个严重的错并为此伤害了许多生命——而我为了能守住这个秘密愿意做任何事。 | BA61: 我曾在战场上犯了一个严重的错并为此伤害了许多生命——而我为了能守住这个秘密愿意做任何事。 | BB61: 应当没人知道我曾经从公会金库里偷过钱。 | BC61: 揭示一项远古奥秘值得以一整个文明作代价。 | BD61: 应当没人知道我曾经从公会金库里偷过钱。 | BE61: 我的虔诚有时令我盲目信任那些声称与我信仰相同的人。 | BF61: 我对这片土地上的新奇的令人沉醉的事物和其他趣事无法抗拒。 | BG61: 自幼认识我的人知道我羞耻的秘密，所以我再也不能回家了。 | BH61: 我曾在战场上犯了一个严重的错并为此伤害了许多生命——而我为了能守住这个秘密愿意做任何事。 | BI61: 我曾在战场上犯了一个严重的错并为此伤害了许多生命——而我为了能守住这个秘密愿意做任何事。 | BJ61: 每当要记住某个计划时，我总会忘掉。就是无法忘掉，我也会选择性无视它。 | BK61: 我会记住每次侮辱，并对委屈我的人报以无声的怨恨。 | BL61: 我总会听到针对我的隐晦侮辱与威胁，且轻易就会因此而发怒。 | BM61: 我认为我的家族和血统让我比其他人更加高贵。 | BO61: 机关人 | BP61: 机关人属性值加成 | BQ61: 你的体质加2，另一个由你选择的属性加1。 | BR61: 析米克混生体 | BS61: 析米克混生体 | CX61: 粉碎者 | CY61: 你擅长于碾碎敌人的技艺，你获得了以下增益： ·你的力量或体质增加1，上限为20。 ·每回合一次，当你用造成钝击伤害的攻击命中一个生物时，只要目标的体型并未比你大一级以上，你就可以将目标移动五尺至一个未被占据的空间。 ·当你用造成钝击伤害的攻击命中一个生物并造成重击时，直至你的下一回合开始，所有针对该生物的攻击检定具有优势。 | CZ61: 60
O62: 6 | P62: 1d8 | AB62: 锁 | AC62: 每把锁与一把钥匙相配套。不使用钥匙时，一个具有盗贼工具熟练项的生物可以通过一次成功的DC15敏捷检定撬开这把锁。你的DM可以决定是否能够用更高的价格购买更好的锁。 | AD62: 10gp | AE62: 1 | AH62: 我思想呆板僵化，不懂变通。 | AI62: 我从不满足于现有的财产，而一旦涉及钱财我就会不畏风险。 | AJ62: 我撒谎时会故意作出某些习惯动作。 | AK62: 我撒谎时会故意作出某些习惯动作。 | AL62: 我曾经讽刺过一个贵族，现在他仍然想要我的脑袋。而这错误我可能还会再犯。 | AM62: 我曾经讽刺过一个贵族，现在他仍然想要我的脑袋。而这错误我可能还会再犯。 | AN62: 我对一些城里的恶习没有抵抗力，尤其是酗酒。 | AO62: 我从未满足于自己所有之物，而总是欲壑难填。 | AP62: 我从未满足于自己所有之物，而总是欲壑难填。 | AQ62: 我对争论的求胜之心胜过了友谊与和睦之心。 | AR62: 我总是放纵自己的肉体欲望。 | AS62: 我总是放纵自己的肉体欲望。 | AT62: 我容易信任对那些来自其他种族，部族或社群的人。 | AU62: 我总是拿出极度复杂的解决方案，却忽视了那些简单易行的方法。 | AV62: 我一旦开始喝酒，就根本停不下来。 | AW62: 我一旦开始喝酒，就根本停不下来。 | AX62: 我对敌人的仇恨盲目而缺乏理性。 | AY62: 与其公平决斗，我更喜欢趁人之危偷袭。 | AZ62: 我对敌人的仇恨盲目而缺乏理性。 | BA62: 我对敌人的仇恨盲目而缺乏理性。 | BB62: 我从未满足于自己所有之物，而总是欲壑难填。 | BC62: 我总是拿出极度复杂的解决方案，却忽视了那些简单易行的方法。 | BD62: 我从未满足于自己所有之物，而总是欲壑难填。 | BE62: 我思想呆板僵化，不懂变通。 | BF62: 我并不会对这片土地上的人们抱有友善的态度，因为这帮家伙与我大不相同。 | BG62: 我对一些城里的恶习没有抵抗力，尤其是酗酒。 | BH62: 我对敌人的仇恨盲目而缺乏理性。 | BI62: 我对敌人的仇恨盲目而缺乏理性。 | BJ62: 我撒谎时会故意作出某些习惯动作。 | BK62: 我容易信任对那些来自其他种族，部族或社群的人。 | BL62: 我总是放纵自己的肉体欲望。 | BM62: 我正在隐瞒一个秘密，这个秘密可能会导致我被逐出家族。 | BO62: 兽人 | BP62: 兽人属性值加成 | BQ62: 你力量加2，你的体质加1。 | BR62: 维多肯 | BS62: 维多肯 | CX62: 魔能导师 | CY62: 先决条件：施法或契约魔法特性 对神秘学的研究使你解锁了体内的秘法能量。你从邪术师职业中选择并获得一项魔能祈唤。如果该祈唤具有任何先决条件，则仅当你是一位满足该条件的邪术师时才能选择该祈唤。 当你升级时，你可以将该祈唤更换为邪术师职业中的另一个魔能祈唤。 | CZ62: 61
O63: 7 | P63: 1d8 | AB63: 放大镜 | AC63: 一枚用以详细观察小物件的透镜。生火时，你也可以用它代替燧石与铁片。使用放大镜聚焦光来生火需要如同阳光般明亮的光照、可用的引火物质以及约5分钟的时间来完成点燃作业。进行估价或是检查某个细小或具有精细细节物件时所作的属性检定可以使用放大镜来获得优势。 | AD63: 100gp | AE63: 0 | AH63: 我会怀疑陌生人并将他们想成最坏的情况。 | AI63: 我会按捺不住冲动去欺骗远比自己强的人。 | AJ63: 当事情看起来似乎开始糟糕时，我会转身掉头就跑。 | AK63: 当事情看起来似乎开始糟糕时，我会转身掉头就跑。 | AL63: 我总是忍不住道出自己的真实感受。而我的刻薄言辞也经常带给我麻烦。 | AM63: 我总是忍不住道出自己的真实感受。而我的刻薄言辞也经常带给我麻烦。 | AN63: 我暗地里会觉得，如果我是那个统领这片土地的暴君所有事情肯定会更好。 | AO63: 我极度渴望贵族头衔。 | AP63: 我极度渴望贵族头衔。 | AQ63: 我为了追求失落的知识而不顾任何风险。 | AR63: 事实上，世界就是围着我转的。 | AS63: 事实上，世界就是围着我转的。 | AT63: 大多时候我会选择用暴力克服难题。 | AU63: 我说话时未真正考虑过自己的措辞，因而老是冒犯到他人。 | AV63: 我会忍不住收集遇到的各种硬币或小饰品等玩意儿。 | AW63: 我会忍不住收集遇到的各种硬币或小饰品等玩意儿。 | AX63: 我遵从法律，而不管其律条是否会招致不幸。 | AY63: 如果我比原主人更需要某物，那我拿走就不算偷。 | AZ63: 我遵从法律，而不管其律条是否会招致不幸。 | BA63: 我遵从法律，而不管其律条是否会招致不幸。 | BB63: 我极度渴望贵族头衔。 | BC63: 我说话时未真正考虑过自己的措辞，因而老是冒犯到他人。 | BD63: 我极度渴望贵族头衔。 | BE63: 我会怀疑陌生人并将他们想成最坏的情况。 | BF63: 我认为其他神的信徒们都是一些被欺骗蒙蔽的无辜百姓（善良），愚蠢无知的白痴（邪恶）. | BG63: 我暗地里会觉得，如果我是那个统领这片土地的暴君所有事情肯定会更好。 | BH63: 我遵从法律，而不管其律条是否会招致不幸。 | BI63: 我遵从法律，而不管其律条是否会招致不幸。 | BJ63: 当事情看起来似乎开始糟糕时，我会转身掉头就跑。 | BK63: 大多时候我会选择用暴力克服难题。 | BL63: 事实上，世界就是围着我转的。 | BM63: 我和家族中的其他人不一样，有着坚定的宗教信仰。 | BO63: 半兽人 | BP63: 半兽人属性值加成 | BQ63: 你力量加2，你的体质加1。 | BR63: 狗头人 | BS63: 狗头人 | CX63: 精类触碰 | CY63: 暴露在妖精荒野的魔法之下的经历已经改变了你，使你获得了以下增益： ·你的智力，感知或魅力提升1，上限为20。 ·你习得迷踪步以及一个由你选择的一环法术。该一环法术必须是预言系或者附魔系法术。你可以在不消耗法术位的情况下施展这些法术各一次。当你以此法施展某个法术后，你不能再次以此法施展该法术，直至你完成一次长休。你也可以消耗合适的法术位来施展这些法术。这些法术的施法关键属性是你由此专长提升的属性。 | CZ63: 62
D64: 法师已知戏法 | E64: 术士已知戏法 | F64: 吟游诗人已知戏法 | G64: 牧师已知戏法 | H64: 德鲁伊已知戏法 | I64: 邪术师已知戏法 | J64: 奇械师已知戏法 | O64: 8 | P64: 1d8 | AB64: 镣铐 | AC64: 这些金属束具可以困住一只小型或中型体型的生物。解开镣铐必须成功通过一次DC20的敏捷检定。破坏镣铐则必须成功通过一次DC20的力量检定。每套镣铐配有一把对应的钥匙。不用钥匙时，一个具有盗贼工具熟练项的生物可以通过一次成功的DC15敏捷检定撬开镣铐的锁。镣铐具有15点生命值。 | AD64: 2gp | AE64: 6 | AH64: 一旦我选择了一个目标，就会变得执迷于它以至于因此损害自己生命中的所有其它事物。 | AI64: 尽管我难以启齿且痛恨不已，但是见势不妙我会转身就逃，并且只顾把自己藏好。 | AJ64: 一名无辜者因我犯下的某桩罪行而进了监狱。这事我觉得挺好的。 | AK64: 一名无辜者因我犯下的某桩罪行而进了监狱。这事我觉得挺好的。 | AL64: 就算我尽了全力，我的朋友们还是认为我靠不住。 | AM64: 就算我尽了全力，我的朋友们还是认为我靠不住。 | AN64: 我难以信任我的盟友。 | AO64: 我妒忌任何手艺胜我一筹的人。而我无论走到哪里却都是对手环绕。 | AP64: 我妒忌任何手艺胜我一筹的人。而我无论走到哪里却都是对手环绕。 | AQ64: 我喜欢对一切保密，不爱与他人分享所知。 | AR64: 我的言行总会为家族带来耻辱。 | AS64: 我的言行总会为家族带来耻辱。 | AT64: 我不会救那些无法自救者。物竞天择，强者生生存。 | AU64: 我无法保护关乎自己或其它性命的秘密。 | AV64: 我的骄傲可能会毁了自己。 | AW64: 我的骄傲可能会毁了自己。 | AX64: 我在犯错时宁可吞掉自己的护甲也不愿承认。 | AY64: 自己顾不好自己的家伙，只能算活该。 | AZ64: 我在犯错时宁可吞掉自己的护甲也不愿承认。 | BA64: 我在犯错时宁可吞掉自己的护甲也不愿承认。 | BB64: 我妒忌任何手艺胜我一筹的人。而我无论走到哪里却都是对手环绕。 | BC64: 我无法保护关乎自己或其它性命的秘密。 | BD64: 我妒忌任何手艺胜我一筹的人。而我无论走到哪里却都是对手环绕。 | BE64: 一旦我选择了一个目标，就会变得执迷于它以至于因此损害自己生命中的所有其它事物。 | BF64: 我对这片土地上的异国美人们无法抗拒。 | BG64: 我难以信任我的盟友。 | BH64: 我在犯错时宁可吞掉自己的护甲也不愿承认。 | BI64: 我在犯错时宁可吞掉自己的护甲也不愿承认。 | BJ64: 一名无辜者因我犯下的某桩罪行而进了监狱。这事我觉得挺好的。 | BK64: 我不会救那些无法自救者。物竞天择，强者生生存。 | BL64: 我的言行总会为家族带来耻辱。 | BM64: 我在为自己家族中的一个秘密派系工作，这个派系给了我一项机密任务。 | BO64: 提夫林 | BP64: 提夫林属性值加成 | BQ64: 你的智力加1，你的魅力加2。 | BR64: 离梦人 | BS64: 离梦人 | CX64: 战斗学徒 | CY64: 先决条件：军用武器熟练 你的军事训练帮助你养成了一种特定的战术风格。因此，你可以从战士职业中选择并习得一项战斗风格。如果你已经有一项战斗风格，你不能选择相同的战斗风格。 每当你升级并达到获得属性值提升特性的等级时，你可以来自此专长的战斗风格替换为战士职业中的另一项你未习得的战斗风格。 | CZ64: 63
B65: =主要情况!W3 -> 5 | C65: 1 | D65: 3 | E65: 4 | F65: 2 | G65: 3 | H65: 2 | I65: 2 | J65: 2 | O65: 9 | P65: 1d8 | AB65: 野炊工具 | AC65: 一个野炊工具锡盒包括一只茶杯和一些简易餐具。盒子被夹在一起，并且其中一面能够被用作一只煎锅而另一面则可以作为一只碟子或是浅碗。 | AD65: 0.2gp | AE65: 1 | BO65: 提夫林变体_剑湾 | BP65: 提夫林变体_剑湾属性值加成 | BQ65: 你的智力加1，你的敏捷加2。 | BR65: 化兽者 | BS65: 兽皮化兽者 | BT65: 长牙化兽者 | BU65: 迅捷化兽者 | BV65: 猎食化兽者 | CX65: 枪手 | CY65: 你持枪时的手快眼明使你获得了以下增益： ·你的敏捷提升1，上限为20。 ·你获得枪械的熟练项（见城主指南的“枪械”栏目）。 ·你忽略枪械的装填属性。 ·你在敌对生物５尺范围内发动远程攻击检定时，不会因此而具有劣势。 | CZ65: 64
C66: 2 | D66: 3 | E66: 4 | F66: 2 | G66: 3 | H66: 2 | I66: 2 | J66: 2 | O66: 10 | P66: 1d10 | V66: =VLOOKUP(T1,U1:Z41,2,0)&"+"&VLOOKUP(主要情况!AA25,主要情况!C8:H19,5,0)+'BUY点计算器&武器调整栏'!C16 -> #N/A | W66: =VLOOKUP(T1,U1:Z64,3,0) -> #N/A | X66: =VLOOKUP(T1,U1:Z64,4,0) -> #N/A | Y66: =VLOOKUP(T1,U1:Z64,5,0) -> #N/A | Z66: =VLOOKUP(T1,U1:Z64,6,0) -> #N/A | AB66: 钢面镜 | AC66: - | AD66: 5gp | AE66: 0.5 | AH66: 侍僧技能熟练项 | AI66: 骗子技能熟练项 | AJ66: 罪犯技能熟练项 | AK66: 密探技能熟练项 | AL66: 艺人技能熟练项 | AM66: 角斗士技能熟练项 | AN66: 平民英雄技能熟练项 | AO66: 公会工匠技能熟练项 | AP66: 公会商人技能熟练项 | AQ66: 隐士技能熟练项 | AR66: 贵族技能熟练项 | AS66: 骑士技能熟练项 | AT66: 化外之民技能熟练项 | AU66: 智者技能熟练项 | AV66: 水手技能熟练项 | AW66: 海盗技能熟练项 | AX66: 士兵技能熟练项 | AY66: 流浪儿技能熟练项 | AZ66: 城市守卫技能熟练项 | BA66: 调查员技能熟练项 | BB66: 氏族工匠技能熟练项 | BC66: 隐修学者技能熟练项 | BD66: 朝臣技能熟练项 | BE66: 派系特工技能熟练项 | BF66: 远行者技能熟练项 | BG66: 继承者技能熟练项 | BH66: 教团骑士技能熟练项 | BI66: 老佣兵技能熟练项 | BJ66: 城市猎人技能熟练项 | BK66: 乌斯伽部族成员技能熟练项 | BL66: 深水人贵族技能熟练项 | BM66: 家族代理人技能熟练项 | BO66: 提夫林亚种_魔邓肯 | BP66: 提夫林亚种_魔邓肯属性值加成 | BQ66: 去找你的祖先去 | BR66: 天狗 | BS66: 天狗 | CX66: 超魔法导师 | CY66: 先决条件：施法或契约魔法特性 你习得如何往你的法术上施加你的意志，从而改变它们的功能。 ·你从术士职业中选择并习得两项超魔法选项。除非特别说明，否则一个法术施展时只能应用一种超魔法项。当你升级并达到获得属性值提升特性的等级时，你可以将其中一项超魔法选项替换为术士职业中的另一项超魔法选项。 ·你获得2点术法点，用于施展超魔法（这些术法点和任何其他来源的术法点叠加，但只能用于超魔法）。你在完成长休后重获所有已消耗的术法点。 | CZ66: 65
C67: 3 | D67: 3 | E67: 4 | F67: 2 | G67: 3 | H67: 2 | I67: 2 | J67: 2 | O67: 11 | P67: 1d10 | V67: =VLOOKUP(T2,U1:Z64,2,0)&"+"&VLOOKUP(主要情况!AA26,主要情况!C8:H19,5,0)+'BUY点计算器&武器调整栏'!C19 -> #N/A | W67: =VLOOKUP(T2,U1:Z64,3,0) -> #N/A | X67: =VLOOKUP(T2,U1:Z64,4,0) -> #N/A | Y67: =VLOOKUP(T2,U1:Z64,5,0) -> #N/A | Z67: =VLOOKUP(T2,U1:Z64,6,0) -> #N/A | AB67: 灯油_扁瓶 | AC67: 灯油通常装在一个1品脱大小的陶土扁瓶中。你可以用一个动作将扁瓶中的灯油泼溅到你身边5尺范围内的一个生物身上，或是将扁瓶投到至多20尺远的地方，并利用冲击打破它。两种情况都可以视为对一个生物或物件发动一次远程攻击，并将灯油视为一件临时武器。命中时，目标被灯油洒满全身。如果目标在灯油挥发前（1分钟后）受到任何火焰伤害，则目标因燃烧的灯油受到额外5点火焰伤害。你还可以将一扁瓶灯油泼在地面上，以覆盖一块边长5尺且保持水平的方形区域。点燃该区域后，灯油将持续燃烧2轮，并对任何进入该区域或在该区域结束其回合的生物造成5点火焰伤害。同一生物每回合只受该伤害作用一次。 | AD67: 0.1gp | AE67: 1 | AH67: 洞悉，宗教 | AI67: 欺瞒，巧手 | AJ67: 欺瞒，隐匿 | AK67: 欺瞒，隐匿 | AL67: 特技，表演 | AM67: 特技，表演 | AN67: 驯兽，求生 | AO67: 洞悉、游说 | AP67: 洞悉、游说 | AQ67: 医药，宗教 | AR67: 历史，游说 | AS67: 历史，游说 | AT67: 运动，求生 | AU67: 奥秘，历史 | AV67: 运动，察觉 | AW67: 运动，察觉 | AX67: 运动，威吓 | AY67: 巧手，隐匿 | AZ67: 运动，洞悉 | BA67: 运动，洞悉 | BB67: 历史，洞悉 | BC67: 历史，从奥秘，自然和宗教中选择一个 | BD67: 洞悉，游说 | BE67: 洞悉，一种自选的作为适合你组织的智力、感知、魅力技能 | BF67: 洞悉，察觉 | BG67: 生存，从奥秘，历史，宗教中选择一个 | BH67: 游说，从奥秘，历史和宗教中适合你教团的技能选择一个 | BI67: 运动，游说 | BJ67: 从欺瞒、洞悉、游说、隐匿中选择两项 | BK67: 运动，求生 | BL67: 历史，游说 | BM67: 调查，游说 | BO67: 守护阿斯莫 | BP67: 守护阿斯莫属性值加成 | BQ67: 你的魅力加2，你的感知加1。 | BR67: 费尔伯格人 | BS67: 费尔伯格人 | CX67: 穿刺者 | CY67: 你已经可以在战斗中造成精准的穿刺。你获得以下好处： ·你的力量或敏捷提升1，上限为20。 ·每回合一次，当你用造成穿刺伤害的攻击命中一个生物时，你可以重投其中一个伤害骰。你必须使用重投的结果。 ·当你用造成穿刺伤害的攻击命中一个生物并且造成重击时，你可以在计算重击伤害时投一个额外的伤害骰。 | CZ67: 66
C68: 4 | D68: 4 | E68: 5 | F68: 3 | G68: 4 | H68: 3 | I68: 3 | J68: 2 | O68: 12 | P68: 1d10 | V68: =VLOOKUP(T3,U1:Z64,2,0)&"+"&VLOOKUP(主要情况!AA27,主要情况!C8:H19,5,0)+'BUY点计算器&武器调整栏'!C22 -> #N/A | W68: =VLOOKUP(T3,U1:Z64,3,0) -> - | X68: =VLOOKUP(T3,U1:Z64,4,0) -> - | Y68: =VLOOKUP(T3,U1:Z64,5,0) -> - | Z68: =VLOOKUP(T3,U1:Z64,6,0) -> - | AB68: 纸_每张 | AC68: - | AD68: 0.2gp | AE68: 0 | AH68: 侍僧工具熟练项 | AI68: 骗子工具熟练项 | AJ68: 罪犯工具熟练项 | AK68: 密探工具熟练项 | AL68: 艺人工具熟练项 | AM68: 角斗士工具熟练项 | AN68: 平民英雄工具熟练项 | AO68: 公会工匠工具熟练项 | AP68: 公会商人工具熟练项 | AQ68: 隐士工具熟练项 | AR68: 贵族工具熟练项 | AS68: 骑士工具熟练项 | AT68: 化外之民工具熟练项 | AU68: 智者工具熟练项 | AV68: 水手工具熟练项 | AW68: 海盗工具熟练项 | AX68: 士兵工具熟练项 | AY68: 流浪儿工具熟练项 | AZ68: 城市守卫工具熟练项 | BA68: 调查员工具熟练项 | BB68: 氏族工匠工具熟练项 | BC68: 隐修学者工具熟练项 | BD68: 朝臣工具熟练项 | BE68: 派系特工工具熟练项 | BF68: 远行者工具熟练项 | BG68: 继承者工具熟练项 | BH68: 教团骑士工具熟练项 | BI68: 老佣兵工具熟练项 | BJ68: 城市猎人工具熟练项 | BK68: 乌斯伽部族成员工具熟练项 | BL68: 深水人贵族工具熟练项 | BM68: 家族代理人工具熟练项 | BO68: 天罚阿斯莫 | BP68: 天罚阿斯莫属性值加成 | BQ68: 你的魅力加2，你的体质加1。 | BR68: 狮族 | BS68: 狮族 | CX68: 毒师 | CY68: 你可以准备并使用致命的毒药。你获得以下好处： ·当你投造成毒素伤害的伤害骰时，无视目标的伤害抗性。 ·你可以以一个附赠动作为一把武器或一枚弹药涂毒，而不是一个动作。 ·你获得制毒工具的熟练项，如果你还没有的话。花费一小时使用制毒工具进行制作后，并且消耗价值50gp的材料后，你可以制造一定数量的猛毒，其数量等同于你的熟练加值。当被用于一把武器或一枚弹药后，猛毒的毒性持续一分钟或直至你用该武器或弹药攻击命中后。当一个生物受到来自涂毒武器或弹药的伤害后，该生物必须成功通过DC14的体质豁免，否则将受到2d8毒素伤害并陷入中毒状态，直至你的下回合结束。 | CZ68: 67
C69: 5 | D69: 4 | E69: 5 | F69: 3 | G69: 4 | H69: 3 | I69: 3 | J69: 2 | O69: 13 | P69: 1d10 | AB69: 羊皮纸_每张 | AC69: - | AD69: 0.1gp | AE69: 0 | AH69: 无 | AI69: 易容工具，文书伪造工具 | AJ69: 一种赌具，盗贼工具。 | AK69: 一种赌具，盗贼工具。 | AL69: 易容工具，一种乐器 | AM69: 易容工具，一种乐器 | AN69: 一种工匠工具，载具（陆运）。 | AO69: 一种工匠工具 | AP69: 一种工匠工具（你可以用领航工具的熟练项，或者掌握额外一门外语来替换工匠工具的熟练项） | AQ69: 草药工具 | AR69: 一种赌具 | AS69: 一种赌具 | AT69: 一种乐器 | AU69: 无 | AV69: 领航工具，载具（水运） | AW69: 领航工具，载具（水运） | AX69: 一种赌具，载具（陆运）。 | AY69: 易容工具，盗贼工具 | AZ69: 无 | BA69: 无 | BB69: 一种自选的匠人工具 | BC69: 无 | BD69: 无 | BE69: 无 | BF69: 任何一项音乐或是赌博工具，当做是你故乡本土的东西。 | BG69: 从游戏组或乐器中选择一个 | BH69: 一种游戏组或乐器 | BI69: 一种赌具，载具（陆运） | BJ69: 从一种赌具、一种乐器和盗贼工具中选择两项 | BK69: 一种乐器或工匠工具 | BL69: 一种赌具或一种乐器 | BM69: 两种，视家族决定： ·卡尼斯：炼金工具和修补工具 ·邓奈斯：一种赌博工具和载具（陆运） ·伽兰达：酿酒工具和厨师工具 ·乔拉斯克：炼金工具和草药工具 ·昆达拉克：修补工具和盗贼工具 ·林兰德：载具（空运/海运）和领航工具 ·梅丹尼：盗贼工具和易容工具 ·欧瑞恩：载具（陆运）和一种赌博工具 ·费奥兰：易容工具和一种乐器 ·西维斯：书法工具和文书伪造工具 ·萨拉释克：领航工具和一种赌博工具 ·索兰尼：制毒工具和一种乐器 ·瓦塔利斯：载具（陆运）和草药工具 | BO69: 堕落阿斯莫 | BP69: 堕落阿斯莫属性值加成 | BQ69: 你的魅力加2，你的力量加1。 | BR69: 半羊人 | BS69: 半羊人 | CX69: 影界触碰 | CY69: 暴露在堕影冥界的魔法之下的经历已经改变了你，使你获得了以下增益： ·你的智力，感知或魅力提升1，上限为20。 ·你习得隐身术以及一个由你选择的一环法术。该一环法术必须是幻术系或死灵系法术。你可以在不消耗法术位的情况下施展这些法术各一次。当你以此法施展某个法术后，你不能再次以此法施展该法术，直至你完成一次长休。你也可以消耗合适的法术位来施展这些法术。这些法术的施法关键属性是你由此专长提升的属性。 | CZ69: 68
C70: 6 | D70: 4 | E70: 5 | F70: 3 | G70: 4 | H70: 3 | I70: 3 | J70: 2 | O70: 14 | P70: 1d10 | AB70: 香水_小瓶 | AC70: - | AD70: 5gp | AE70: 0 | AH70: 侍僧额外语言 | AI70: 骗子额外语言 | AJ70: 罪犯额外语言 | AK70: 密探额外语言 | AL70: 艺人额外语言 | AM70: 角斗士额外语言 | AN70: 平民英雄额外语言 | AO70: 公会工匠额外语言 | AP70: 公会商人额外语言 | AQ70: 隐士额外语言 | AR70: 贵族额外语言 | AS70: 骑士额外语言 | AT70: 化外之民额外语言 | AU70: 智者额外语言 | AV70: 水手额外语言 | AW70: 海盗额外语言 | AX70: 士兵额外语言 | AY70: 流浪儿额外语言 | AZ70: 城市守卫额外语言 | BA70: 调查员额外语言 | BB70: 氏族工匠额外语言 | BC70: 隐修学者额外语言 | BD70: 朝臣额外语言 | BE70: 派系特工额外语言 | BF70: 远行者额外语言 | BG70: 继承者额外语言 | BH70: 教团骑士额外语言 | BI70: 老佣兵额外语言 | BJ70: 城市猎人额外语言 | BK70: 乌斯伽部族成员额外语言 | BL70: 深水人贵族额外语言 | BM70: 家族代理人额外语言 | BO70: 森林侏儒 | BP70: 森林侏儒属性值加成 | BQ70: 你的智力加2，你的敏捷加1。 | CX70: 技艺专家 | CY70: 你已磨练了自身的特定技艺，并获得了以下好处： ·你选择一项属性提升1，上限为20. ·你选择并获得一项技能的熟练项。 ·选择一项你熟练的技能，你获得该技能的专精，可以将两倍的熟练加值加到使用该技能进行的属性检定上。你选择的技能必须未受益于其他使熟练加值翻倍的特性，例如专精特性。 | CZ70: 69
C71: 7 | D71: 4 | E71: 5 | F71: 3 | G71: 4 | H71: 3 | I71: 3 | J71: 2 | O71: 15 | P71: 1d12 | AB71: 矿工镐 | AC71: - | AD71: 2gp | AE71: 10 | AH71: 任选两门语言 | AI71: 无 | AJ71: 无 | AK71: 无 | AL71: 无 | AM71: 无 | AN71: 无 | AO71: 一门自选语言 | AP71: 一门自选语言 | AQ71: 自选一门语言 | AR71: 自选一门语言 | AS71: 自选一门语言 | AT71: 自选一门语言 | AU71: 自选两门语言 | AV71: 无 | AW71: 无 | AX71: 无 | AY71: 无 | AZ71: 两种由你选择的语言 | BA71: 两种由你选择的语言 | BB71: 矮人语或者如果你已经熟悉矮人语了就自选一种语言 | BC71: 你选择的两种语言 | BD71: 两种你选择的语言 | BE71: 两种自选语言 | BF71: 任意一种你选择的语言 | BG71: 任意一种你选择的语言 | BH71: 一种你选择的语言 | BI71: 无 | BJ71: 无 | BK71: 自选一门语言 | BL71: 自选一门语言 | BM71: 无 | BO71: 岩侏儒 | BP71: 岩侏儒属性值加成 | BQ71: 你的智力加2，你的体质加1。 | CX71: 劈砍者 | CY71: 你已熟知该砍向何处以造成最重的伤害。你获得以下好处： ·你的力量或敏捷提升1，上限为20。 ·每回合一次，当你用造成挥砍伤害的攻击命中一个生物时，你可以使其速度降低10尺，直到你的下回合开始。 ·当你用造成挥砍伤害的攻击命中一个生物并造成重击时，你将其重伤，使其所作的攻击检定具有劣势，直至你的下回合开始。 | CZ71: 70
C72: 8 | D72: 4 | E72: 5 | F72: 3 | G72: 4 | H72: 3 | I72: 3 | J72: 2 | O72: 16 | P72: 1d12 | AB72: 岩钉 | AC72: - | AD72: 0.05gp | AE72: 0.25 | AH72: 侍僧背景装备 | AI72: 骗子背景装备 | AJ72: 罪犯背景装备 | AK72: 密探背景装备 | AL72: 艺人背景装备 | AM72: 角斗士背景装备 | AN72: 平民英雄背景装备 | AO72: 公会工匠背景装备 | AP72: 公会商人背景装备 | AQ72: 隐士背景装备 | AR72: 贵族背景装备 | AS72: 骑士背景装备 | AT72: 化外之民背景装备 | AU72: 智者背景装备 | AV72: 水手背景装备 | AW72: 海盗背景装备 | AX72: 士兵背景装备 | AY72: 流浪儿背景装备 | AZ72: 城市守卫背景装备 | BA72: 调查员背景装备 | BB72: 氏族工匠背景装备 | BC72: 隐修学者背景装备 | BD72: 朝臣背景装备 | BE72: 派系特工背景装备 | BF72: 远行者背景装备 | BG72: 继承者背景装备 | BH72: 教团骑士背景装备 | BI72: 老佣兵背景装备 | BJ72: 城市猎人背景装备 | BK72: 乌斯伽部族成员背景装备 | BL72: 深水人贵族背景装备 | BM72: 家族代理人背景装备 | BO72: 地底侏儒_魔邓肯 | BP72: 地底侏儒_魔邓肯属性值加成 | BQ72: 你的智力加2，你的敏捷加1。 | CX72: 念动力 | CY72: 你习得用你的意念移动物体的能力。你获得以下好处： ·你的智力，感知或魅力提升1，上限为20。 ·你习得法师之手戏法，你施展它无需语言构材或材料构材，并且你可以让该幽灵手隐形。如果你已经习得该戏法，你施展该戏法时其施法距离提升30尺。该戏法的施法关键属性是你由此专长提升的属性。 ·以一个附赠动作，你可以尝试以念动力推撞30尺内的一个你可见的生物。当你这样做时，目标必须成功通过一次力量豁免（DC为8+你的熟练加值+你由此专长提升的属性的属性调整值）否则将被你拉近或推离五尺。目标生物可以自愿放弃豁免。 | CZ72: 71
C73: 9 | D73: 4 | E73: 5 | F73: 3 | G73: 4 | H73: 3 | I73: 3 | J73: 2 | O73: 17 | P73: 1d12 | U73: X | AB73: 基础毒药_小瓶 | AC73: 你可以用一个动作将小瓶中的毒药涂于一把挥砍或穿刺武器上，或者涂在至多三发弹药上。涂毒武器或弹药命中时，被命中生物必须进行一次DC10的体质豁免，豁免失败则受到1d4的毒素伤害。涂毒后，武器的毒性效果可以维持1分钟。 | AD73: 100gp | AE73: 0 | AH73: 一枚圣徽（出任神职时的礼物），一本祷告经书或经轮，5根熏香，祭袍，一套普通服装，以及一个装着15gp的小包。 | AI73: 一套高档服装，一套易容工具，一些你自选的行骗道具（十个装满五颜六色液体的塞口瓶子，一套作弊骰子，一套暗号纸牌，或者一枚捏造的公爵玺戒），以及一个装有 15gp的小包 | AJ73: 一根撬棍，一套带兜帽的深色普通服装，一套普通服装，以及一个装有 15gp 的小包 | AK73: 一根撬棍，一套带兜帽的深色普通服装，一套普通服装，以及一个装有 15gp 的小包 | AL73: 一种乐器（由你选择），倾慕者的信物（情书、一缕头发或者饰品），一套表演服装，以及一个装有 15gp 的小包 | AM73: 一种乐器（你可以将装备选择中的乐器替换为不昂贵且不常见的武器，比如三叉戟或捕网。），倾慕者的信物（情书、一缕头发或者饰品），一套表演服装，以及一个装有 15gp 的小包 | AN73: 一套工匠工具（由你选择），一把铲子，一个铁壶，一套普通服装，以及一个装有 10gp 的小包 | AO73: 一套工匠工具（由你选择），一封公会的介绍信，一套旅行者服装，以及一个装有 15gp 的小包 | AP73: 一套工匠工具（你可以用一头骡子或者一辆二轮货车代替起始工具中的工匠工具。），一封公会的介绍信，一套旅行者服装，以及一个装有 15gp 的小包 | AQ73: 一个卷轴匣，用来装纳研究成果和祈祷词的笔记，一张冬用毯子，一套普通服装，一套草药工具，以及 5gp | AR73: 一套高档服装，一枚玺戒，一张血统证书卷轴，以及一个装有 25gp 的钱袋 | AS73: 一套高档服装，一枚玺戒，一张血统证书卷轴，以及一个装有 25gp 的钱袋 | AT73: 一根手杖，一副狩猎陷阱，一件来自你手刃的动物身上的战利品，一套旅行者服装，以及一个装有 10gp 的小包 | AU73: 一瓶黑墨水，一根羽毛笔，一把小刀，一封去世同事信件其内载有你尚不能解答的问题，一套普通服装，以及一个装有 10gp 的小包 | AV73: 一根挽缆栓（短棒），50 尺丝绳，兔脚或穿孔小石头一类的护身符（或从第5章的饰品列表中掷骰决定），一套普通服装，以及一个装有 10gp 的小包 | AW73: 一根挽缆栓（短棒），50 尺丝绳，兔脚或穿孔小石头一类的护身符（或从第5章的饰品列表中掷骰决定），一套普通服装，以及一个装有 10gp 的小包 | AX73: 一枚军衔徽记，一件从某个倒下的敌人身上得到的战利品（一把匕首，毁坏的武器或是军旗碎片），一套骨骰或一组纸牌，一套普通服装，以及一个装有 10gp 的小包 | AY73: 一把小刀，一张你所成长城市的地图，一只宠物鼠，一件纪念你父母的纪念品，一套普通服装和一个装有 10gp 的小包 | AZ73: 一件你所在组织的标示你军衔的制服，一个用来召唤帮手的号角，一副手铐，一个装有10金币的袋子 | BA73: 一件你所在组织的标示你军衔的制服，一个用来召唤帮手的号角，一副手铐，一个装有10金币的袋子 | BB73: 一种你所熟练的匠人工具，一个用来标示出你是从哪个宗族学习何种手工技艺的徽记，一件旅行者衣服，一个有5gp的小包和一块价值10gp的宝石。 | BC73: 代表你学院的学者长袍，一份书写工具（一个装着羽毛笔，墨水，折叠起来的羊皮纸，一把小拆信刀），一本从学院中借出阅读的书籍和一个装着10gp的小包。 | BD73: 一套华丽的服装和一个装有5gp的小包 | BE73: 一个标示你所属组织的徽章或标志。一份你们组织文件的手抄本（或一份你们组织使用的密文本），一套普通衣服，一个装有15gp的小包。 | BF73: 旅行者衣服，一项你熟练的音乐或者赌博工具，来自你故乡的一张精密度很差的费伦地图用以标记出你在何处，一小片价值10GP来自你家乡技艺制作的珠宝，和一个5gp的小包。 | BG73: 你继承的遗产，一套旅行衣服，任何你所熟练的物品，装着15GP的小包。 | BH73: 一件旅行衣服，一个徽记，代表你骑士团或是教团等级的旗帜或是印章，一个装有10GP的袋子。 | BI73: 所属兵团的制服（质量等同于旅行者服装），一块对应你军阶的勋章，你自选的一套赌局，装着你的上次军饷的小包（10gp） | BJ73: 适合你执勤用的一套服装和一个装着 20gp 的小包 | BK73: 狩猎陷阱，标志你忠于乌特加和你部族之图腾的图腾标志或一组纹身，一套旅行者服装和一个装着 10gp 的小袋。 | BL73: 一套高档服装，一枚玺戒或胸针，一份族谱，一皮袋的高档 “兹沙 zzar ” 或红酒，以及一个装有 20gp 的小包 | BM73: 一套高档服装，一枚家徽玺戒，一份身份证明和一个装有20枚金币的钱包。 | BO73: 熊地精 | BP73: 熊地精属性值加成 | CX73: 心电感应 | CY73: 你觉醒了用意念与其他生物交流的能力。你获得以下好处： ·你的智力，感知或魅力提升1，上限为20。 ·你可以和60尺内任何你可见的生物用心灵感应进行交流。你的心电沟通以一种你已知的语言的形式进行，该生物必须懂得该语言才能理解你。你的主动沟通并未给予该生物以心灵感应的形式回复你的能力。 ·你可以施展侦测思想法术，无需法术位和构材。以此法施法后，你在完成一次长休前不能再这样做。该法术的施法关键属性是你由此专长提升的属性。如果你拥有二环或更高的法术位，你可以消耗这些法术位施展该法术。 | CZ73: 72
C74: 10 | D74: 5 | E74: 6 | F74: 4 | G74: 5 | H74: 4 | I74: 4 | J74: 3 | O74: 18 | P74: 1d12 | U74: O | AB74: 长杆_10尺 | AC74: - | AD74: 0.05gp | AE74: 7 | AH74: 侍僧特殊选项 | AI74: 骗子特殊选项 | AJ74: 罪犯特殊选项 | AK74: 密探特殊选项 | AL74: 艺人特殊选项 | AM74: 角斗士特殊选项 | AN74: 平民英雄特殊选项 | AO74: 公会工匠特殊选项 | AP74: 公会商人特殊选项 | AQ74: 隐士特殊选项 | AR74: 贵族特殊选项 | AS74: 骑士特殊选项 | AT74: 化外之民特殊选项 | AU74: 智者特殊选项 | AV74: 水手特殊选项 | AW74: 海盗特殊选项 | AX74: 士兵特殊选项 | AY74: 流浪儿特殊选项 | AZ74: 城市守卫特殊选项 | BA74: 调查员特殊选项 | BB74: 氏族工匠特殊选项 | BC74: 隐修学者特殊选项 | BD74: 朝臣特殊选项 | BE74: 派系特工特殊选项 | BF74: 远行者特殊选项 | BG74: 继承者特殊选项 | BH74: 教团骑士特殊选项 | BI74: 老佣兵特殊选项 | BJ74: 城市猎人特殊选项 | BK74: 乌斯伽部族成员特殊选项 | BL74: 深水人贵族特殊选项 | BM74: 家族代理人特殊选项 | BO74: 地精 | BP74: 地精属性值加成
C75: 11 | D75: 5 | E75: 6 | F75: 4 | G75: 5 | H75: 4 | I75: 4 | J75: 3 | O75: 19 | P75: 1d12 | U75: ◎ | AB75: 铁壶 | AC75: - | AD75: 2gp | AE75: 10 | AH75: 你可以从附录B的表格中选择某名神祇、某个神系或其他类神存在，也可以直接由你的DM进行介绍选择。 | AI75: 偏好骗局Favorite Schemes 每个骗子都有比较偏爱的骗局手法。选择一个偏好骗局，或者掷骰随机决定。 d6 骗局 1 我在博弈游戏中作弊。 2 我造假币或者伪造文件。 3 我渗透进他人生活中，掌握其把柄，夺取他其财产。 4 我像换衣服一样换身份。 5 我在街角靠巧手耍把戏。 6 我说服别人花一大笔辛苦钱买不值钱的垃圾。 | AJ75: 作案手法Criminal Specialty 违法犯罪的行为五花八门，而在盗贼公会或类似的犯罪组织中，每个成员也有着不同的专职分工。即便是那些游离于组织之外的罪犯，也会对某些特定的罪行更为偏爱。选择你在犯罪生涯中扮演的角色，或者依据下列表格进行随机投骰。 d8 手法 1 敲诈犯Blackmail 2 盗窃犯Burglar 3 斗殴犯Enforcer 4 销赃犯Fence 5 路匪Highway robber 6 职业杀手Hired killer 7 扒窃犯Pickpocket 8 走私犯Smuggle | AK75: 作案手法Criminal Specialty 违法犯罪的行为五花八门，而在盗贼公会或类似的犯罪组织中，每个成员也有着不同的专职分工。即便是那些游离于组织之外的罪犯，也会对某些特定的罪行更为偏爱。选择你在犯罪生涯中扮演的角色，或者依据下列表格进行随机投骰。 d8 手法 1 敲诈犯Blackmail 2 盗窃犯Burglar 3 斗殴犯Enforcer 4 销赃犯Fence 5 路匪Highway robber 6 职业杀手Hired killer 7 扒窃犯Pickpocket 8 走私犯Smuggle | AL75: 演艺方向Entertainer Routines 优秀的艺人应当多才多艺，并且能够在一次表演中以多种不同套路娱乐观众。自选一到三种套路或掷骰随机决定你作为艺人的技艺。 d10 演艺方向 1 演员Actor 2 舞者Dancer 3 吞火艺人Fire-eater 4 小丑Jester 5 魔术师Juggler 6 乐师Instrumentalist 7 诗人Poet 8 歌手Singer 9 说书人Storyteller 10 杂技演员Tumbler | AM75: 演艺方向Entertainer Routines 优秀的艺人应当多才多艺，并且能够在一次表演中以多种不同套路娱乐观众。自选一到三种套路或掷骰随机决定你作为艺人的技艺。 d10 演艺方向 1 演员Actor 2 舞者Dancer 3 吞火艺人Fire-eater 4 小丑Jester 5 魔术师Juggler 6 乐师Instrumentalist 7 诗人Poet 8 歌手Singer 9 说书人Storyteller 10 杂技演员Tumbler | AN75: 命定事件Defining Event 从前你与民众一同从事某一项单纯的专职工作，你的可能是专职的农民，矿工，仆役，牧羊人，伐木工或是掘墓人等。但是由于某件事的发生，你便走上了一条不同的道路并标志着你此后的追求将更加伟大。选择或投骰随机决定一个命定事件以标志着你成为人们心中英雄的时机。 d10 命定事件 1 我挺身而出反抗某位暴君的代理人。 2 我在一起自然灾害中救了人。 3 我独自一人对抗一只可怕的怪物。 4 我偷窃了一名腐败商人的钱财再用来帮助穷人。 5 我领导一支民兵击退了一支入侵的军队。 6 我闯进某位暴君的城堡，并从中偷取武器武装民众。 7 我训练农民们以农具作武器抵抗某位暴君的士兵们。 8 为反对一项不公法令，我发起了一场象征性的抗议活动，随后当地领主就将其废止了。 9 一只天界生物，精类生物或是类似的其他生物赐我予祝福，或是揭示了我的秘密血统。 10 我被招募进一位领主的军队，期间我因自己的英雄气概而受到称赞，并被提升为领导者。 | AO75: 公会行当Guild Business 通常只有那些大到足以支持许多同行工匠的城市才能发展出公会。当然，你的公会也可能是一个较大国度中，将分散在不同村镇中的工匠们联系起来的松散网络。与DM一起决定你所在公会的类型。你可以从表中选择或掷骰随机决定你的公会行当。 d20 公会行当 1 炼金师alchemists、药剂师apothecaries 2 盔甲工匠armorers、锁匠locksmiths、镀金师finesmiths 3 酿酒师brewers、蒸馏师distillers、葡萄酒商vintners 4 抄写员calligraphers、书记员scribes、公证人scriveners 5 木匠carpenters、盖顶匠roofers、泥水匠plasterers 6 绘图员cartographers、测量员surveyors、制表员chart-makers 7 补鞋匠cobblers、制鞋匠shoemakers 8 厨师cooks、烘焙师bakers 9 玻璃吹制师glassblowers、玻璃装配师glaziers 10 珠宝匠jewlers、宝石切割师gemcutters 11 皮匠leatherworkers、剥皮师skinners、制革师tanners 12 泥瓦匠masons、石匠stonecutters 13 漆匠painters、画师limners、纹章师sign-makers 14 陶工potters、瓦匠tile-makers 15 船木工shipwrights、修帆匠sailmakers 16 铁匠smiths、冶炼匠metal-forgers 17 修补匠tinkers、锡匠pewterers、铸造师casters 18 车厢工匠wagon-makers、轮匠wheelwrights 19 织布师weavers、染布师dyers 20 木雕师woodcarvers、桶匠coopers、弓匠bowyers 作为公会一员，你熟谙用原材料制造成品所需的技术（表现为你所拥有的特定工匠工具的熟练项），并且熟悉商贸的规则，还拥有做买卖的丰富经验。你需要抉择的是彻底放弃你的家底前去冒险，还是下十二分力气同时经营好冒险和自己的行当。 | AP75: 公会行当Guild Business 通常只有那些大到足以支持许多同行工匠的城市才能发展出公会。当然，你的公会也可能是一个较大国度中，将分散在不同村镇中的工匠们联系起来的松散网络。与DM一起决定你所在公会的类型。你可以从表中选择或掷骰随机决定你的公会行当。 d20 公会行当 1 炼金师alchemists、药剂师apothecaries 2 盔甲工匠armorers、锁匠locksmiths、镀金师finesmiths 3 酿酒师brewers、蒸馏师distillers、葡萄酒商vintners 4 抄写员calligraphers、书记员scribes、公证人scriveners 5 木匠carpenters、盖顶匠roofers、泥水匠plasterers 6 绘图员cartographers、测量员surveyors、制表员chart-makers 7 补鞋匠cobblers、制鞋匠shoemakers 8 厨师cooks、烘焙师bakers 9 玻璃吹制师glassblowers、玻璃装配师glaziers 10 珠宝匠jewlers、宝石切割师gemcutters 11 皮匠leatherworkers、剥皮师skinners、制革师tanners 12 泥瓦匠masons、石匠stonecutters 13 漆匠painters、画师limners、纹章师sign-makers 14 陶工potters、瓦匠tile-makers 15 船木工shipwrights、修帆匠sailmakers 16 铁匠smiths、冶炼匠metal-forgers 17 修补匠tinkers、锡匠pewterers、铸造师casters 18 车厢工匠wagon-makers、轮匠wheelwrights 19 织布师weavers、染布师dyers 20 木雕师woodcarvers、桶匠coopers、弓匠bowyers 作为公会一员，你熟谙用原材料制造成品所需的技术（表现为你所拥有的特定工匠工具的熟练项），并且熟悉商贸的规则，还拥有做买卖的丰富经验。你需要抉择的是彻底放弃你的家底前去冒险，还是下十二分力气同时经营好冒险和自己的行当。 | AQ75: 隐居生活Life of Seclusion 为何你遗世独立，而又为何重踏尘世？你可以和DM共同商讨决定隐居的原因，也可以依下表选择或掷骰随机决定。 d8 隐居生活 1 我正在寻求灵魂的启迪。 2 我遵守修会教规，参与集体清修。 3 我因不白之冤而被流放。 4 某件事情改变我人生的大事使我弃世而去。 5 我为了能潜心于艺术、文字或音乐而去寻找一处僻静之地。 6 我要与自然沟通而远离文明世界。 7 我是一座古代遗迹或一件古代遗物的看守人。 8 我是一名追寻圣人，圣地或圣遗物的朝圣者。 | AR75: 和你的DM一起为该背景讨论一个合适的头衔，以及头衔所代表的权力。贵族的头衔并非只是孤立的概念，而是必须联系起一整个家族。无论你持有什么头衔，都有责任将其传给子孙后代。你不只要决定头衔为何，更要和DM一起设计你的家族以及家族对你的影响。 你的家族是古老而稳固，还是于近日刚刚踏入贵族圈？家族的影响力有多大，占据哪块地盘？家族在邻居贵族间名声如何？平民百姓又是如何看待他们的？ 你在家族中的地位如何？你是否属于家族头领的子嗣？你对继承头衔的义务感想如何？或者你和继承权相去甚远，以至于除非你给家族蒙羞，否则根本无人在乎？家族头领对你冒险生涯的看法如何？你的家族成员是乐于与你相处，还是唯恐避之不及？ 你的家族是否拥有盾徽？你是否需要佩戴家族的玺戒？是否需要穿着特定色系的服装？是否有一种被你的家族血脉视为象征的动物，其甚至会被视为心灵上的家族成员？ 这些细节能帮助你设计相应的家族和头衔，并将其融入战役所在的世界设定中。 | AS75: 和你的DM一起为该背景讨论一个合适的头衔，以及头衔所代表的权力。贵族的头衔并非只是孤立的概念，而是必须联系起一整个家族。无论你持有什么头衔，都有责任将其传给子孙后代。你不只要决定头衔为何，更要和DM一起设计你的家族以及家族对你的影响。 你的家族是古老而稳固，还是于近日刚刚踏入贵族圈？家族的影响力有多大，占据哪块地盘？家族在邻居贵族间名声如何？平民百姓又是如何看待他们的？ 你在家族中的地位如何？你是否属于家族头领的子嗣？你对继承头衔的义务感想如何？或者你和继承权相去甚远，以至于除非你给家族蒙羞，否则根本无人在乎？家族头领对你冒险生涯的看法如何？你的家族成员是乐于与你相处，还是唯恐避之不及？ 你的家族是否拥有盾徽？你是否需要佩戴家族的玺戒？是否需要穿着特定色系的服装？是否有一种被你的家族血脉视为象征的动物，其甚至会被视为心灵上的家族成员？ 这些细节能帮助你设计相应的家族和头衔，并将其融入战役所在的世界设定中。 | AT75: 出身Origin 你曾到达过全然陌生的地方，见识过他人未曾探索过的事物。你可以设定一些曾经造访过的遥远地区，以及这些经过如何影响了你。你可以参考下表掷骰随机决定自己身处荒野时如何维持生计，或者你也可以自选一项最适合选项。 d10 出身 1 护林员forester 2 设阱捕兽者trapper 3 自耕农homesteader 4 向导guide 5 流放者exile or outcast 6 赏金猎人bounty hunter 7 朝圣者pilgrim 8 游牧蛮族tribal nomad 9 狩猎采集者hunter-gatherer 10 劫掠蛮族tribal marauder | AU75: 专业Specialty 为决定你的学术积累的性质，投一个d8或是从下面的表格中自行选择。 d8 专业 1 炼金师alchemist 2 占星师astronomer 3 失权威学者discredited academic 4 图书馆员librarian 5 教授professor 6 研究员researcher 7 法师学徒wizard’s apprentice 8 书记员scribe | AV75: 与DM讨论设定你曾经所驾驶的船只的相关信息。那是一艘商船、军舰，亦或是探索船、海盗船？它威名远扬，还是不为人知？它航线所至之处多还是少？它如今仍在航行，还是已经失踪，或是和上面的水手一道沉入海底？ 你在船上的职位是什么——水手、船长、领航员、厨师，还是别的什么职务？船长是谁，大副又是谁？你是带着同伴们的祝福离舰，还是狼狈地从船上出逃？ | AW75: 与DM讨论设定你曾经所驾驶的船只的相关信息。那是一艘商船、军舰，亦或是探索船、海盗船？它威名远扬，还是不为人知？它航线所至之处多还是少？它如今仍在航行，还是已经失踪，或是和上面的水手一道沉入海底？ 你在船上的职位是什么——水手、船长、领航员、厨师，还是别的什么职务？船长是谁，大副又是谁？你是带着同伴们的祝福离舰，还是狼狈地从船上出逃？ | AX75: 专职Specialty 你在身为士兵的时期曾在你的小组或部队中任职一个特定的专职。参照下表投一个d8随机决定角色的专职，或是直接从表中自行选择： d8 专职 1 军官officer 2 侦察兵scout 3 步兵infantry 4 骑兵cavalry 5 医疗师healer 6 军需官quartermaster 7 旗手standard bearer 8 后勤人员support staff（铁匠blacksmith、厨子cook等） | AY75: 你在开始冒险生涯时，身上带着一笔钱可以让你过上十几天简朴水平的安稳生活。你是如何得到这笔钱的？是什么力量让你能够冲破绝望的生活环境，尝试得到更好的生活？ | BO75: 大地精 | BP75: 大地精属性值加成
C76: 12 | D76: 5 | E76: 6 | F76: 4 | G76: 5 | H76: 4 | I76: 4 | J76: 3 | O76: 20 | P76: 1d12 | U76: ◒ | AB76: 治疗药水 | AC76: 一种红色的魔力药剂，可以使饮用者恢复2d4+2的生命值。喝药或者喂人喝药需要使用一个动作。 | AD76: 50gp | AE76: 0.5 | BO76: 幻身灵 | BP76: 幻身灵属性值加成 | BQ76: 你的魅力加2，此外，你选择的一个属性加1。(注：未限制魅力）
C77: 13 | D77: 5 | E77: 6 | F77: 4 | G77: 5 | H77: 4 | I77: 4 | J77: 3 | N77: 德鲁伊等级 | P77: =VLOOKUP(N57,O57:P76,2,0) -> 1d8 | AB77: 小包 | AC77: 一个布料或皮革制成的小包可以装20发弹丸或50发吹矢，或者其他东西。用来装施法材料成分的小包则成为材料包（详见前文）。 | AD77: 0.5gp | AE77: 1 | BO77: 元素裔 | BP77: 元素裔属性值加成
